Workbook

Sheet Sheet1
D6: 一般見積価格
D8: 価格改定 | F8: 2025・3
F11: ﾈﾎﾟﾝ製品原価修正
G12: '08 04 25
G13: '08 05 30
G14: '08 12 02 | H14: BTU金額改定
G15: '09 04 01 | H15: 仕入製品価格改訂
G16: '10 12 17 | H16: 製品価格改訂
G17: '11 05 24 | H17: 管材・バルブ・樹脂管等の価格UP（20％）およびネポン原価改訂
G18: '14 08 18 | H18: 製品価格改訂
G19: '15 07 29 | H19: 製品価格改訂
G20: '19 05 08 | H20: 製品価格改訂
G21: '19 08 01 | H21: 製品価格・工事原価・管材及び部材価格改訂
G22: '20 04 16 | H22: 製品原価・部材価格改訂
G23: '21 05 31 | H23: 製品価格・管材及び部材価格改訂
G24: 22 03 28 | H24: 製品価格改訂
G25: 23 03 10 | H25: 製品・部材価格、人工単価改訂
... G27: 25 03 25 | H27: 製品・部材・管材価格改訂
F29: 塩ビ管原価修正
G30: '11 05 24
G31: '19 08 01
G32: '25 03 25
F34: ST熱交換器原価修正
G35: '07 07 17
F37: 標準項修正
G38: '19 11 06
G39: 22 07 14

Sheet 項目表
A1: 項目表 | E1: E3 | F1: E4
B2: 主項目 | E2: 工単価 | F2: 工原価 | G2: G3 | H2: G4 | J2: G6
A3: b3 | B3: ボイラ及びボイラ回り設備工事 | E3: 47500 | F3: 29400 | G3: 式 | H3: 機材運搬費 | J3: 井関農機株式会社
B4: ボイラ室内設備工事 | G4: ｾｯﾄ | H4: 試運転調整費 | J4: 渡辺パイプ株式会社
B5: ボイラ回り設備工事 | G5: 組 | H5: 現場諸経費 | J5: 東海物産株式会社
B6: 機械室内設備工事 | G6: ﾕﾆｯﾄ | H6: 機材小運搬費 | J6: イノチオアグリ株式会社
B7: 地中メイン配管設備工事 | G7: ﾀﾞｰｽ | H7: 現場立会い検査費 | J7: カネコ種苗株式会社
B8: メイン配管設備工事 | G8: 基 | H8: 消防関連打合せ費用 | J8: イワタニアグリグリーン株式会社
B9: 主要機器機材設備工事 | G9: 台 | H9: 大気汚染防止法関連打合せ費用 | J9: タキイ種苗株式会社
B10: CO2施用設備工事 | G10: 個 | H10: 消防立会い検査費 | J10: トヨタネ株式会社
B11: --------------- | G11: 本 | H11: タンク水張り検査費 | J11: 佐藤商事株式会社 神奈川支店
B12: 温室内暖房設備工事 | G12: 巻 | H12: 防油堤・基礎工事費 | J12: ﾔﾝﾏｰｸﾞﾘｰﾝｼｽﾃﾑ株式会社
B13: 温室内配管設備工事 | G13: 缶 | H13: 油水分離槽工事 | J13: サンキンB&G株式会社
B14: 温室内設備工事 | G14: m | H14: 道路横断補強工事 | J14: 株式会社誠和。
B15: 温室内温風暖房設備工事 | G15: ㎡ | H15: 塗装補修工事 | J15: ｼｰｱｲﾏﾃｯｸｽ株式会社
... B20: グリーンパッケージ設備工事 | G20: ﾄﾝ | H20: 消耗品雑材 | J20: 株式会社大仙関東支社
B21: 誰でもヒーポン設備工事 | J21: 株式会社大仙中部支社
B22: アグリネット設備工事 | J22: 株式会社大仙関西支社
B23: 土壌蒸気殺菌装置 | J23: 株式会社大仙四国支店
B24: 圃場蒸気殺菌装置 | J24: 株式会社大仙九州支社
B25: --------------- | F25: G25 | G25: ㎡ | J25: ---------------
B26: 地中放熱管設備工事 | G26: a | J26: 明友機工株式会社
B27: ベット配管設備工事 | G27: ha | J27: 富国工業株式会社
B28: 養液加温設備工事 | J28: 日之出産業株式会社
B29: 養液冷暖設備工事 | J29: 株式会社松本産業
B30: 温室空間冷房設備工事 | J30: 住栄農材株式会社
B31: --------------- | J31: 八江ｸﾞﾘｰﾝﾎﾟｰﾄ株式会社
B32: 天窓関連設備機器 | J32: 未来のｱｸﾞﾘ株式会社
B33: 温度制御設備機器 | J33: 株式会社タカミヤ
B34: 複合環境制御機器
B35: アグリネット設備機器
B36: ---------------
B37: オイルタンク及びオイル配管設備工事
B38: オイルタンク設備工事
B39: オイル配管設備工事
B40: 地下オイルタンク設備工事 | G40: G40 | H40: お打ち合わせ願います
B41: 消火器・標識設備工事 | H41: ご注文後1週間でお渡しできます
B42: 諸 経 費 | H42: ご注文後2週間でお渡しできます
B43: --------------- | H43: ご注文後3週間でお渡しできます
H44: ご注文後1ヶ月でお渡しできます
H45: ご注文後2ヶ月でお渡しできます
H46: ご注文後3ヶ月でお渡しできます
H47: ご注文後半年でお渡しできます
G50: G50 | H50: 搬入・設置・試運転渡し
H51: お打ち合わせ願います
H52: 現場館側渡し
H53: ご指定地車上渡し
G60: G60 | H60: お打ち合わせ願います
H61: 月末〆翌月現金支払い
H62: 月末〆の出来高払い（現金支払い）
H63: 契約時1/3、中間1/3、完成時1/3（現金払い）
H64: 月末〆翌月支払い（90日手形）
H65: 月末〆翌月支払い（120日手形）
A80: B80 | B80: 見積外工事
B81: ﾎﾞｲﾗ室建屋工事
B82: ﾎﾞｲﾗ室の給排水･給排気設備工事
B83: ﾎﾞｲﾗ付近までの給排水工事
B84: 機械室までの給排水工事
B85: 膨張ﾀﾝｸへの給水配管工事
B86: 燃料設備全ての工事
B87: 機器設備全ての工事
B88: LPG燃料設備 全ての工事
B89: 油ﾀﾝｸ設備工事
B90: 油配管設備工事
B91: 防油堤及びﾀﾝｸ基礎工事
B92: 機器関係の基礎工事
... B133: 消費税及び地方税

Sheet 機器表
K1: 品番 | L1: 品名 | M1: 型式 | O1: 小売価格 | P1: 原価 | Q1: 歩単 | S1: 品番 | T1: 品名 | U1: 型式 | W1: 小売価格 | X1: 原価 | Y1: 歩単 | AA1: 品番 | AB1: 品名 | AC1: 型式 | AE1: 小売価格 | AF1: 原価 | AG1: 歩単 | AI1: 品番 | AJ1: 品名 | AK1: 型式 | AM1: 小売価格 | AN1: 原価 | AO1: 歩単 | AQ1: 品番 | AR1: 品名 | AS1: 型式 | AU1: 小売価格 | AV1: 原価 | AW1: 歩単 | AY1: 品番 | AZ1: 品名 | BA1: 型式 | BC1: 小売価格 | BD1: 原価 | BE1: 歩単 | BG1: 品番 | BH1: 品名 | BI1: 型式 | BK1: 小売価格 | BL1: 原価 | BM1: 歩単 | BO1: 品番 | BP1: 品名 | BQ1: 型式 | BS1: 小売価格 | BT1: 原価 | BU1: 歩単 | BW1: 品番 | BX1: 品名 | BY1: 型式 | CA1: 小売価格 | CB1: 原価 | CC1: 歩単 | CE1: 品番 | CF1: 品名 | CG1: 型式 | CI1: 小売価格 | CJ1: 原価 | CK1: 歩単 | CM1: 品番 | CN1: 品名 | CO1: 型式 | CQ1: 小売価格 | CR1: 原価 | CS1: 歩単 | CU1: 品番 | CV1: 品名 | CW1: 型式 | CY1: 小売価格 | CZ1: 原価 | DA1: 歩単 | DC1: 品番 | DD1: 品名 | DE1: 型式 | DG1: 小売価格 | DH1: 原価 | DI1: 歩単 | DK1: 品番 | DL1: 品名 | DM1: 型式 | DO1: 小売価格 | DP1: 原価 | DQ1: 歩単 | DS1: 品番 | DT1: 品名 | DU1: 型式 | DW1: 小売価格 | DX1: 原価 | DY1: 歩単 | EA1: 品番 | EB1: 品名 | EC1: 型式 | EE1: 小売価格 | EF1: 原価 | EG1: 歩単 | EI1: 品番 | EJ1: 品名 | EK1: 型式 | EM1: 小売価格 | EN1: 原価 | EO1: 歩単 | EQ1: 品番 | ER1: 品名 | ES1: 型式 | EU1: 小売価格 | EV1: 原価 | EW1: 歩単 | EY1: 品番 | EZ1: 品名 | FA1: 型式 | FC1: 小売価格 | FD1: 原価 | FE1: 歩単 | FG1: 品番 | FH1: 品名 | FI1: 型式 | FK1: 小売価格 | FL1: 原価 | FM1: 歩単 | FO1: 品番 | FP1: 品名 | FQ1: 型式 | FS1: 小売価格 | FT1: 原価 | FU1: 歩単 | FW1: 品番 | FX1: 品名 | FY1: 型式 | GA1: 小売価格 | GB1: 原価 | GC1: 歩単 | GE1: 品番 | GF1: 品名 | GG1: 型式 | GI1: 小売価格 | GJ1: 原価 | GK1: 歩単 | GM1: 品番 | GN1: 品名 | GO1: 型式 | GQ1: 小売価格 | GR1: 原価 | GS1: 歩単 | GU1: 品番 | GV1: 品名 | GW1: 型式 | GY1: 小売価格 | GZ1: 原価 | HA1: 歩単
BL2: 0.43 | BP2: STKｴﾛﾌｨﾝﾁｭｰﾌﾞ | DP2: 0.15 | DU2: ホーコス株式会社 | DX2: 0.55 | EC2: ｵｲﾙﾀﾝｸ・消防関連 | EJ2: 煙道・煙突関連部材 | ER2: ﾎﾟﾘﾀﾞｸﾄ・ｸﾛｽﾗﾑﾀﾞｸﾄ | EZ2: ｽﾊﾟｲﾗﾙﾀﾞｸﾄ | FH2: ｱﾙﾐﾌﾚｷﾀﾞｸﾄ | FP2: ﾊｳｽｶｵﾝｷ(静音型) | GF2: ﾊｳｽｶｵﾝｷ(ｶﾞｽ焚き) | GN2: ﾋｰﾄｯﾌﾟ・ｶﾜｲﾀｰ | GV2: SGPｴﾛﾌｨﾝﾁｭｰﾌﾞ
B3: 1 | C3: ﾊｳｽｶｵﾝｷ 30型・29型 | D3: l3 | E3: 同上搬入据付工事 | I3: 機器減衰率係数 | K3: 049825000 | L3: ﾊｳｽｶｵﾝｷ | M3: HK2030TCV | N3: 台 | O3: 909000 | P3: 470450 | Q3: 1.25 | S3: 051111000 | T3: 小型温風機 | U3: KA-125 | V3: 台 | W3: 331000 | X3: 139730 | Y3: 0.52 | AA3: 038886000 | AB3: ｼｮｳｵﾝﾎﾞｲﾗ | AC3: SHB-310S1K | AD3: 台 | AE3: 512000 | AF3: 232620 | AG3: 1 | AI3: 052478000 | AJ3: ｼﾝｸﾛﾋｰﾀ | AK3: SBM100WNU_10 | AL3: 台 | AM3: 2579000 | AN3: 703660 | AO3: 2.3 | AQ3: 041992000 | AR3: ｵｰﾄｶﾝ | AS3: AWH-501A | AT3: 台 | AU3: 1000000 | AV3: 310890 | AW3: 1.3 | AY3: 026087000 | AZ3: ｸﾞﾘｰﾝｿｰﾗ | BA3: RHE-134E | BB3: 台 | BC3: 1845000 | BD3: 663790 | BE3: 1.2 | BG3: RB0000304 | BH3: 熱交換器 | BI3: ST-3(1m) | BJ3: 基 | BK3: 226000 | BL3: 81600 | BM3: 0.5 | BP3: ｴﾛﾌｨﾝﾁｭｰﾌﾞ（STK 5KF） | BQ3: 32A 25F 5500L | BR3: 本 | BS3: =ROUND(BT3/0.4,-3) -> 86000 | BT3: 34400 | BU3: 0.72 | BX3: ﾌｧﾝｺｲﾙﾕﾆｯﾄ | BY3: RF-20F | BZ3: 基 | CA3: 125000 | CB3: =CA3*0.48 -> 60000 | CC3: 1 | CF3: ｸｰﾘﾝｸﾞﾀﾜｰ | CG3: MT-514 | CH3: 基 | CI3: 120000 | CJ3: 66000 | CK3: 2.5 | CN3: 蓄熱ﾀﾝｸ | CO3: 100ﾘｯﾄﾙ | CP3: 基 | CQ3: 23000 | CR3: 15000 | CS3: 0.2 | CV3: ﾗｲﾝﾎﾟﾝﾌﾟ | CW3: 50Hz φ25 0.15kW | CX3: 台 | CY3: 102000 | CZ3: =ROUND(CY3*0.53,-1) -> 54060 | DA3: 0.3 | DC3: 052396000 | DD3: ｸﾞﾘｰﾝﾊﾟｯｹｰｼﾞ | DE3: NGP109TQX-J_4(親機) | DF3: ｾｯﾄ | DG3: 1573000 | DH3: 822710 | DI3: 2.9 | DL3: 空冷ﾁﾗｰﾕﾆｯﾄ | DM3: UWAP75A(3HP) | DN3: 基 | DO3: 1730000 | DP3: =ROUNDUP(DO3*$DP$2,-2) -> 259500 | DQ3: 0 | DT3: 膨張ﾀﾝｸ | DU3: ETU-100 ボールタップ一般型 | DV3: 台 | DW3: 352000 | DX3: 193600 | DY3: 0.3 | EA3: 047056000 | EB3: ｵｲﾙﾀﾝｸ | EC3: BOT-99 | ED3: 基 | EE3: 40100 | EF3: 17310 | EG3: 0.1 | EI3: 103230000 | EJ3: 煙突ｾｯﾄ | EK3: BEP-3P120A網付 | EL3: ｾｯﾄ | EM3: 33400 | EN3: 6360 | EO3: 0.7 | EQ3: 2500000022 | ER3: ﾎﾟﾘﾀﾞｸﾄ | ES3: 折幅400×200m(0.07) | ET3: 本 | EU3: 10690 | EV3: 4704 | EW3: 0 | EZ3: ｽﾊﾟｲﾗﾙﾀﾞｸﾄ(亜鉛) | FA3: φ200 | FB3: ｍ | FC3: 2100 | FD3: =FC3*0.65 -> 1365 | FE3: 0.16 | FG3: 186981000 | FH3: ｱﾙﾐﾌﾚｷﾀﾞｸﾄ | FI3: φ225×4000L | FJ3: 本 | FK3: 11600 | FL3: 2710 | FO3: 051234000 | FP3: ﾊｳｽｶｵﾝｷ | FQ3: HK2030GCSV | FR3: 台 | FS3: 1165000 | FT3: 498460 | FU3: 1.25 | FX3: ｴﾛﾌｨﾝ支持金具 | FY3: 1段1列 | FZ3: 本 | GA3: 18000 | GB3: 9000 | GC3: 0.11 | GE3: 051051000 | GF3: ﾊｳｽｶｵﾝｷ（LPｶﾞｽ焚き） | GG3: HK2030TCL | GH3: 台 | GI3: 1161000 | GJ3: 549400 | GK3: 1.25 | GM3: 043222000 | GN3: ﾋｰﾄｯﾌﾟ | GO3: HT-201E | GP3: 台 | GQ3: 693000 | GR3: 234170 | GS3: 0.7 | GV3: SGPｴﾛﾌｨﾝﾁｭｰﾌﾞ | GW3: 32A 25F 5500L | GX3: 本 | GY3: =ROUND(GZ3/0.33,-3) -> 111000 | GZ3: 36600 | HA3: 0.72
B4: 3 | C4: ﾊｳｽｶｵﾝｷ 静音型 | D4: fp3 | E4: 同上架台工事 | I4: 2 | K4: 049826000 | L4: ﾊｳｽｶｵﾝｷ | M4: HK2030TEV | N4: 台 | O4: 925000 | P4: 481600 | Q4: 1.25 | S4: 051113000 | T4: 小型温風機 | U4: KA-205 | V4: 台 | W4: 400000 | X4: 143600 | Y4: 0.7 | AA4: 038884000 | AB4: ｼｮｳｵﾝﾎﾞｲﾗ | AC4: SHB-310TK | AD4: 台 | AE4: 515000 | AF4: 232880 | AG4: 1 | AI4: 052479000 | AJ4: ｼﾝｸﾛﾋｰﾀ | AK4: SBM100WMU_10 | AL4: 台 | AM4: 2579000 | AN4: 702500 | AO4: 2.3 | AQ4: 041993000 | AR4: ｵｰﾄｶﾝ | AS4: AWH-601A | AT4: 台 | AU4: 1039000 | AV4: 313300 | AW4: 1.4 | AY4: 026090000 | AZ4: ｸﾞﾘｰﾝｿｰﾗ | BA4: RHE-154C | BB4: 台 | BC4: 1915000 | BD4: 710880 | BE4: 1.4 | BG4: RB0000305 | BH4: 熱交換器 | BI4: ST-5(1m) | BJ4: 基 | BK4: 291000 | BL4: 105600 | BM4: 0.6 | BP4: ｴﾛﾌｨﾝﾁｭｰﾌﾞ（STK 5KF） | BQ4: 32A 25F 4000L | BR4: 本 | BS4: =ROUND(BT4/0.4,-3) -> 79000 | BT4: 31600 | BU4: 0.52 | BX4: ﾌｧﾝｺｲﾙﾕﾆｯﾄ | BY4: RF-30F | BZ4: 基 | CA4: 141000 | CB4: =CA4*0.48 -> 67680 | CC4: 1.25 | CF4: ｸｰﾘﾝｸﾞﾀﾜｰ | CG4: MT-814 | CH4: 基 | CI4: 150000 | CJ4: 82000 | CK4: 2.5 | CN4: 蓄熱ﾀﾝｸ | CO4: 200ﾘｯﾄﾙ | CP4: 基 | CQ4: 31000 | CR4: 20000 | CS4: 0.2 | CV4: ---------- | DC4: 052395000 | DD4: ｸﾞﾘｰﾝﾊﾟｯｹｰｼﾞ | DE4: NGP109TQ-J_4(子機) | DF4: ｾｯﾄ | DG4: 1357000 | DH4: 746140 | DI4: 2.9 | DL4: 空冷ﾁﾗｰﾕﾆｯﾄ | DM4: UWAA125A(5HP) | DN4: 基 | DO4: 3080000 | DP4: =ROUNDUP(DO4*0.3,-2) -> 924000 | DQ4: 0 | DT4: 膨張ﾀﾝｸ | DU4: ETU-200 ボールタップ一般型 | DV4: 台 | DW4: 438000 | DX4: 240900 | DY4: 0.3 | EA4: 047057000 | EB4: ｵｲﾙﾀﾝｸ | EC4: BOT-200 | ED4: 基 | EE4: 84000 | EF4: 26080 | EG4: 0.2 | EI4: 104720000 | EJ4: 煙突ｾｯﾄ | EK4: BEP-3P1504網付 | EL4: ｾｯﾄ | EM4: 51300 | EN4: 13770 | EO4: 0.7 | EQ4: 2500000101 | ER4: ﾎﾟﾘﾀﾞｸﾄ | ES4: 折幅475×100m | ET4: 本 | EU4: 9070 | EV4: 3990 | EW4: 0 | EZ4: ｽﾊﾟｲﾗﾙﾀﾞｸﾄ(亜鉛) | FA4: φ225 | FB4: ｍ | FC4: 2500 | FD4: =FC4*0.65 -> 1625 | FE4: 0.18 | FH4: --------------- | FO4: 051235000 | FP4: ﾊｳｽｶｵﾝｷ | FQ4: HK2030GESV | FR4: 台 | FS4: 1183000 | FU4: 1.25 | FX4: ｴﾛﾌｨﾝ支持金具 | FY4: 2段1列 | FZ4: 本 | GA4: 22000 | GB4: 11000 | GC4: 0.15 | GE4: 051061000 | GF4: ﾊｳｽｶｵﾝｷ（LPｶﾞｽ焚き） | GG4: HK2030TEL | GH4: 台 | GI4: 1186000 | GJ4: 558480 | GK4: 1.25 | GM4: 043223000 | GN4: ﾋｰﾄｯﾌﾟ | GO4: HT-321F | GP4: 台 | GQ4: 788000 | GR4: 222040 | GS4: 0.9 | GV4: SGPｴﾛﾌｨﾝﾁｭｰﾌﾞ | GW4: 32A 25F 4000L | GX4: 本 | GY4: =ROUND(GZ4/0.33,-3) -> 100000 | GZ4: 33100 | HA4: 0.52
B5: 4 | C5: ﾊｳｽｶｵﾝｷ ｶﾞｽ焚き | D5: gf3 | E5: 同上架台及び機器据付工事 | I5: 0.15 | K5: 051779000 | L5: ﾊｳｽｶｵﾝｷ | M5: HK2030TRV | N5: 台 | O5: 1166000 | P5: 595420 | Q5: 1.25 | S5: 051115000 | T5: 小型温風機 | U5: KA-325 | V5: 台 | W5: 492000 | X5: 165270 | Y5: 0.9 | AA5: 038885000 | AB5: ｼｮｳｵﾝﾎﾞｲﾗ | AC5: SHB-310TK4 | AD5: 台 | AE5: 573000 | AF5: 235070 | AG5: 1 | AI5: 052480000 | AJ5: ｼﾝｸﾛﾋｰﾀ | AK5: SBM100WLU_10 | AL5: 台 | AM5: 2579000 | AN5: 702760 | AO5: 2.3 | AQ5: 041994000 | AR5: ｵｰﾄｶﾝ | AS5: AWH-701A | AT5: 台 | AU5: 1116000 | AV5: 313300 | AW5: 1.55 | AZ5: ---------- | BG5: RB0000306 | BH5: 熱交換器 | BI5: ST-8(1m) | BJ5: 基 | BK5: 385000 | BL5: 139200 | BM5: 0.7 | BP5: ｴﾛﾌｨﾝﾁｭｰﾌﾞ（STK 5KF） | BQ5: 32A 25F 3500L | BR5: 本 | BS5: =ROUND(BT5/0.4,-3) -> 76000 | BT5: 30400 | BU5: 0.46 | BX5: ﾌｧﾝｺｲﾙﾕﾆｯﾄ | BY5: RF-40F | BZ5: 基 | CA5: 149000 | CB5: =CA5*0.48 -> 71520 | CC5: 1.25 | CF5: ｸｰﾘﾝｸﾞﾀﾜｰ | CG5: MT-1014 | CH5: 基 | CI5: 175000 | CJ5: 96000 | CK5: 2.75 | CN5: 蓄熱ﾀﾝｸ | CO5: 500ﾘｯﾄﾙ | CP5: 基 | CQ5: 46000 | CR5: 30000 | CS5: 0.3 | CV5: ﾗｲﾝﾎﾟﾝﾌﾟ | CW5: 50Hz φ32 0.25kW | CX5: 台 | CY5: 139000 | CZ5: =ROUND(CY5*0.53,-1) -> 73670 | DA5: 0.3 | DD5: 室外機平置台(H500) | DF5: 式 | DG5: 150000 | DH5: 43450 | DL5: 空冷ﾁﾗｰﾕﾆｯﾄ | DM5: UWAA190A(8HP) | DN5: 基 | DO5: 3950000 | DP5: =ROUNDUP(DO5*0.3,-2) -> 1185000 | DQ5: 0 | DT5: 膨張ﾀﾝｸ | DU5: ETU-300 ボールタップ一般型 | DV5: 台 | DW5: 548000 | DX5: 301400 | DY5: 0.5 | EA5: 150729000 | EB5: ｵｲﾙﾀﾝｸ | EC5: BOT-490 | ED5: 基 | EE5: 119900 | EF5: 52990 | EG5: 0.3 | EI5: 102387000 | EJ5: 煙突ｾｯﾄ | EK5: BEP-3P2252網付 | EL5: ｾｯﾄ | EM5: 72800 | EN5: 23470 | EO5: 0.7 | EQ5: 2500000025 | ER5: ﾎﾟﾘﾀﾞｸﾄ | ES5: 折幅475×200m(0.07) | ET5: 本 | EU5: 12700 | EV5: 5586 | EW5: 0 | EZ5: ｽﾊﾟｲﾗﾙﾀﾞｸﾄ(亜鉛) | FA5: φ250 | FB5: ｍ | FC5: 2600 | FD5: =FC5*0.65 -> 1690 | FE5: 0.18 | FH5: 亜鉛鋼板ﾆｯﾌﾟﾙ | FI5: φ225 | FJ5: 本 | FK5: 710 | FL5: 426 | FP5: ---------- | FX5: ｴﾛﾌｨﾝ支持金具 | FY5: 1段2列 | FZ5: 本 | GA5: 20000 | GB5: 10000 | GC5: 0.12 | GE5: 051053000 | GF5: ﾊｳｽｶｵﾝｷ（LPｶﾞｽ焚き） | GG5: HK3030TCL | GH5: 台 | GI5: 1392000 | GJ5: 615910 | GK5: 1.45 | GM5: 043224000 | GN5: ﾋｰﾄｯﾌﾟ | GO5: HT-322E | GP5: 台 | GQ5: 886000 | GR5: 252490 | GS5: 0.7 | GV5: SGPｴﾛﾌｨﾝﾁｭｰﾌﾞ | GW5: 32A 25F 3500L | GX5: 本 | GY5: =ROUND(GZ5/0.33,-3) -> 97000 | GZ5: 31900 | HA5: 0.46
B6: 5 | C6: 小型温風機・ｸﾞﾛｳｴｱ | D6: t3 | E6: 同上架台及び据付工事 | K6: 049827000 | L6: ﾊｳｽｶｵﾝｷ | M6: HK3030TCV | N6: 台 | O6: 1129000 | P6: 490810 | Q6: 1.45 | S6: 051117000 | T6: 小型温風機 | U6: KA-325T | V6: 台 | W6: 542000 | X6: 176620 | Y6: 0.9 | AB6: ----------- | AI6: 052481000 | AJ6: ｼﾝｸﾛﾋｰﾀ | AK6: SBM100WNUJ_2（水道直結仕様） | AL6: 台 | AM6: 2730000 | AN6: 728300 | AO6: 2.3 | AQ6: 041995000 | AR6: ｵｰﾄｶﾝ | AS6: AWH-801A | AT6: 台 | AU6: 1185000 | AV6: 379920 | AW6: 1.65 | AY6: 105332000 | AZ6: ﾀﾞｲﾚｸﾄﾌｧﾝ | BA6: DFN-102TE | BB6: 台 | BC6: 207000 | BD6: 77000 | BE6: 0.2 | BG6: RB0000307 | BH6: 熱交換器 | BI6: ST-10(1m) | BJ6: 基 | BK6: 543000 | BL6: 196800 | BM6: 0.8 | BP6: ｴﾛﾌｨﾝﾁｭｰﾌﾞ（STK 5KF） | BQ6: 32A 25F 3000L | BR6: 本 | BS6: =ROUND(BT6/0.4,-3) -> 74000 | BT6: 29400 | BU6: 0.4 | BX6: ﾌｧﾝｺｲﾙﾕﾆｯﾄ | BY6: RF-60F | BZ6: 基 | CA6: 173000 | CB6: =CA6*0.48 -> 83040 | CC6: 1.5 | CF6: ｸｰﾘﾝｸﾞﾀﾜｰ | CG6: MT-1514 | CH6: 基 | CI6: 226000 | CJ6: 124000 | CK6: 2.75 | CN6: 蓄熱ﾀﾝｸ | CO6: 750ﾘｯﾄﾙ | CP6: 基 | CQ6: 118000 | CR6: 77000 | CS6: 0.3 | CV6: ﾗｲﾝﾎﾟﾝﾌﾟ | CW6: 50Hz φ32 0.4kW | CX6: 台 | CY6: 169000 | CZ6: =ROUND(CY6*0.53,-1) -> 89570 | DA6: 0.5 | DC6: 044798000 | DD6: ﾌﾚｯｸｽﾌﾛｰｱﾀﾞﾌﾟﾀｰｾｯﾄ | DF6: 式 | DG6: 170800 | DH6: 48200 | DL6: 空冷ﾁﾗｰﾕﾆｯﾄ | DM6: UWAA250A(10HP) | DN6: 基 | DO6: 4730000 | DP6: =ROUNDUP(DO6*0.3,-2) -> 1419000 | DQ6: 0 | DT6: 膨張ﾀﾝｸ | DU6: ETU-500 ボールタップ一般型 | DV6: 台 | DW6: 733000 | DX6: 403200 | DY6: 0.5 | EB6: ｵｲﾙﾀﾝｸ | EC6: BOT-900 | ED6: 基 | EE6: 330000 | EF6: 139200 | EG6: 1 | EI6: 002290000 | EJ6: 煙突ｾｯﾄ | EK6: BEP-HB1201 | EL6: ｾｯﾄ | EM6: 65700 | EN6: 23160 | EO6: 0.5 | EQ6: 2500000102 | ER6: ﾎﾟﾘﾀﾞｸﾄ | ES6: 折幅630×50m | ET6: 本 | EU6: 6020 | EV6: 2646 | EW6: 0 | EZ6: ｽﾊﾟｲﾗﾙﾀﾞｸﾄ(亜鉛) | FA6: φ300 | FB6: ｍ | FC6: 3200 | FD6: =FC6*0.65 -> 2080 | FE6: 0.18 | FH6: 亜鉛鋼板T管 | FI6: φ225 | FJ6: 本 | FK6: 4250 | FL6: 2550 | FO6: 051236000 | FP6: ﾊｳｽｶｵﾝｷ | FQ6: HK3030GCSV | FR6: 台 | FS6: 1407000 | FT6: 515700 | FU6: 1.45 | FX6: ｴﾛﾌｨﾝ支持金具 | FY6: 2段2列 | FZ6: 本 | GA6: 24800 | GB6: 12400 | GC6: 0.2 | GE6: 051063000 | GF6: ﾊｳｽｶｵﾝｷ（LPｶﾞｽ焚き） | GG6: HK3030TEL | GH6: 台 | GI6: 1407000 | GJ6: 632630 | GK6: 1.45 | GM6: 043225000 | GN6: ﾋｰﾄｯﾌﾟ | GO6: HT-322F | GP6: 台 | GQ6: 886000 | GR6: 249260 | GS6: 0.9 | GV6: SGPｴﾛﾌｨﾝﾁｭｰﾌﾞ | GW6: 32A 25F 3000L | GX6: 本 | GY6: =ROUND(GZ6/0.33,-3) -> 93000 | GZ6: 30700 | HA6: 0.4
B7: 6 | C7: ﾊｳｽﾎﾞｲﾗ | D7: ab3 | E7: 同上取付工事 | I7: ｴﾛﾌｨﾝ減衰率係数 | K7: 049828000 | L7: ﾊｳｽｶｵﾝｷ | M7: HK3030TEV | N7: 台 | O7: 1141000 | P7: 509220 | Q7: 1.45 | S7: 051119000 | T7: 小型温風機 | U7: KA-405T | V7: 台 | W7: 665000 | X7: 251450 | Y7: 1 | AA7: 025357000 | AB7: ﾊｳｽﾎﾞｲﾗ | AC7: HB-407TGA | AD7: 台 | AE7: 944000 | AF7: 458400 | AG7: 1.15 | AI7: 052482000 | AJ7: ｼﾝｸﾛﾋｰﾀ | AK7: SBM100WMUJ_2（水道直結仕様） | AL7: 台 | AM7: 2730000 | AN7: 728170 | AO7: 2.3 | AQ7: 041996000 | AR7: ｵｰﾄｶﾝ | AS7: AWH-901A | AT7: 台 | AU7: 1242000 | AV7: 382330 | AW7: 1.75 | AZ7: ---------- | BG7: RB0000308 | BH7: 熱交換器 | BI7: ST-20(1m) | BJ7: 基 | BK7: 676000 | BL7: 244800 | BM7: 1 | BP7: ｴﾛﾌｨﾝﾁｭｰﾌﾞ（STK 5KF） | BQ7: 32A 25F 2750L | BR7: 本 | BS7: =ROUND(BT7/0.4,-3) -> 73000 | BT7: 29000 | BU7: 0.36 | BX7: ﾌｧﾝｺｲﾙﾕﾆｯﾄ | BY7: RF-80F | BZ7: 基 | CA7: 210000 | CB7: =CA7*0.48 -> 100800 | CC7: 1.5 | CF7: ｸｰﾘﾝｸﾞﾀﾜｰ | CG7: MT-2014 | CH7: 基 | CI7: 277000 | CJ7: 152000 | CK7: 3 | CN7: 蓄熱ﾀﾝｸ | CO7: 1,000ﾘｯﾄﾙ | CP7: 基 | CQ7: 134000 | CR7: 88000 | CS7: 0.6 | CV7: ﾗｲﾝﾎﾟﾝﾌﾟ | CW7: 50Hz φ32 0.75kW | CX7: 台 | CY7: 225000 | CZ7: =ROUND(CY7*0.53,-1) -> 119250 | DA7: 0.5 | DC7: 028066000 | DD7: 省ｴﾈﾊｲﾌﾞﾘｯﾄﾞ制御盤 | DE7: NT-602 | DF7: 面 | DG7: 229000 | DH7: 52510 | DL7: 空冷ﾁﾗｰﾕﾆｯﾄ | DM7: UWAA375A(15HP) | DN7: 基 | DO7: 7130000 | DP7: =ROUNDUP(DO7*0.3,-2) -> 2139000 | DQ7: 0 | DT7: 膨張ﾀﾝｸ | DU7: ETU-750 ボールタップ一般型 | DV7: 台 | DW7: 815000 | DX7: 448300 | DY7: 0.5 | EB7: ｵｲﾙﾀﾝｸ | EC7: BOT-1900 | ED7: 基 | EE7: 380000 | EF7: 164280 | EG7: 1.4 | EI7: 103811000 | EJ7: 煙突ｾｯﾄ | EK7: BEP-KA1203 | EL7: ｾｯﾄ | EM7: 60400 | EN7: 20760 | EO7: 0.5 | EQ7: 2500000103 | ER7: ﾎﾟﾘﾀﾞｸﾄ | ES7: 折幅900×50m | ET7: 本 | EU7: 8590 | EV7: 3780 | EW7: 0 | EZ7: ｽﾊﾟｲﾗﾙﾀﾞｸﾄ(亜鉛) | FA7: φ350 | FB7: ｍ | FC7: 5200 | FD7: =FC7*0.65 -> 3380 | FE7: 0.18 | FO7: 051237000 | FP7: ﾊｳｽｶｵﾝｷ | FQ7: HK3030GESV | FR7: 台 | FS7: 1422000 | FT7: 537350 | FU7: 1.45 | FX7: ｴﾛﾌｨﾝ支持金具 | FY7: 3段1列 | FZ7: 本 | GA7: 24800 | GB7: 12400 | GC7: 0.3 | GE7: 051071000 | GF7: ﾊｳｽｶｵﾝｷ（LPｶﾞｽ焚き） | GG7: HK3030TFL | GH7: 台 | GI7: 1357000 | GJ7: 628610 | GK7: 1.45 | GN7: ---------- | GS7: 0 | GV7: SGPｴﾛﾌｨﾝﾁｭｰﾌﾞ | GW7: 32A 25F 2750L | GX7: 本 | GY7: =ROUND(GZ7/0.33,-3) -> 92000 | GZ7: 30200 | HA7: 0.36
B8: 7 | C8: ｼﾝｸﾛﾋｰﾀ | D8: aj3 | E8: 同上塗装補修工事 | I8: 1.2 | K8: 049829000 | L8: ﾊｳｽｶｵﾝｷ | M8: HK3030TFV | N8: 台 | O8: 1092000 | P8: 503120 | Q8: 1.45 | T8: ---------- | AA8: 025124000 | AB8: ﾊｳｽﾎﾞｲﾗ | AC8: HB-807TGA5 | AD8: 台 | AE8: 1511000 | AF8: 619670 | AG8: 1.6 | AI8: 052483000 | AJ8: ｼﾝｸﾛﾋｰﾀ | AK8: SBM100WLUJ_2（水道直結仕様） | AL8: 台 | AM8: 2730000 | AN8: 732690 | AO8: 2.3 | AQ8: 041997000 | AR8: ｵｰﾄｶﾝ | AS8: AWH-1001A | AT8: 台 | AU8: 1295000 | AV8: 399360 | AW8: 1.9 | AY8: 026708000 | AZ8: ﾈﾎﾟﾝﾌｧﾝ | BA8: FAN-302S1 | BB8: 台 | BC8: 48000 | BD8: 21150 | BE8: 0.2 | BG8: RB0000310 | BH8: 熱交換器 | BI8: ST-40(1m) | BJ8: 基 | BK8: 1019000 | BL8: 369600 | BM8: 1 | BP8: ｴﾛﾌｨﾝﾁｭｰﾌﾞ（STK 5KF） | BQ8: 32A 25F 2000L | BR8: 本 | BS8: =ROUND(BT8/0.4,-3) -> 69000 | BT8: 27500 | BU8: 0.26 | BX8: ﾌｧﾝｺｲﾙﾕﾆｯﾄ | BY8: RF-120F | BZ8: 基 | CA8: 274000 | CB8: =CA8*0.48 -> 131520 | CC8: 1.75 | CF8: ｸｰﾘﾝｸﾞﾀﾜｰ | CG8: MT-3014 | CH8: 基 | CI8: 390000 | CJ8: 214000 | CK8: 3 | CN8: 蓄熱ﾀﾝｸ | CO8: 1,500ﾘｯﾄﾙ | CP8: 基 | CQ8: 190000 | CR8: 124000 | CS8: 1 | CV8: ---------- | DC8: 103305000 | DD8: 湿度ｾﾝｻ | DE8: HUS-12 | DF8: 個 | DG8: 101800 | DH8: 24770 | DL8: 空冷ﾁﾗｰﾕﾆｯﾄ | DM8: UWAA500A(20HP) | DN8: 基 | DO8: 9160000 | DP8: =ROUNDUP(DO8*0.3,-2) -> 2748000 | DQ8: 0 | DT8: 膨張ﾀﾝｸ | DU8: ETU-1000 ボールタップ一般型 | DV8: 台 | DW8: 1055000 | DX8: 580300 | DY8: 0.5 | EB8: ｵｲﾙﾀﾝｸ | EC8: BOT- 5000 | ED8: 基 | EE8: 1448000 | EF8: 898000 | EG8: 2.4 | EI8: 104598000 | EJ8: 煙突ｾｯﾄ | EK8: BEP-KA120F | EL8: ｾｯﾄ | EM8: 72600 | EN8: 23890 | EO8: 0.5 | EQ8: 2500000104 | ER8: ﾎﾟﾘﾀﾞｸﾄ | ES8: 折幅1100×50m | ET8: 本 | EU8: 10500 | EV8: 4620 | EW8: 0 | EZ8: ｽﾊﾟｲﾗﾙﾀﾞｸﾄ(亜鉛) | FA8: φ400 | FB8: ｍ | FC8: 6300 | FD8: =FC8*0.65 -> 4095 | FE8: 0.19 | FO8: 051238000 | FP8: ﾊｳｽｶｵﾝｷ | FQ8: HK3030GFSV | FR8: 台 | FS8: 1370000 | FU8: 1.45 | FX8: ｴﾛﾌｨﾝ支持金具 | FY8: 3段2列 | FZ8: 本 | GA8: 42000 | GB8: 21000 | GC8: 0.5 | GE8: 051055000 | GF8: ﾊｳｽｶｵﾝｷ（LPｶﾞｽ焚き） | GG8: HK4030TCL | GH8: 台 | GI8: 1696000 | GJ8: 718970 | GK8: 1.7 | GM8: 038107000 | GN8: ﾋｰﾄｯﾌﾟ | GO8: HT-802TE | GP8: 台 | GQ8: 1477000 | GR8: 538650 | GS8: 1.5 | GV8: SGPｴﾛﾌｨﾝﾁｭｰﾌﾞ | GW8: 32A 25F 2000L | GX8: 本 | GY8: =ROUND(GZ8/0.33,-3) -> 86000 | GZ8: 28300 | HA8: 0.26
B9: 8 | C9: ｵｰﾄｶﾝ | D9: ar3 | E9: 同上基礎工事 | I9: 0.11 | K9: 051780000 | L9: ﾊｳｽｶｵﾝｷ | M9: HK3030TRV | N9: 台 | O9: 1396000 | P9: 610850 | Q9: 1.45 | S9: 051112000 | T9: 小型温風機 | U9: KA-125E | V9: 台 | W9: 389000 | X9: 170820 | Y9: 0.52 | AA9: 025125000 | AB9: ﾊｳｽﾎﾞｲﾗ | AC9: HB-807TGA6 | AD9: 台 | AE9: 1511000 | AF9: 617090 | AG9: 1.6 | AJ9: ----------- | AQ9: 041998000 | AR9: ｵｰﾄｶﾝ | AS9: AWH-1201A | AT9: 台 | AU9: 1484000 | AV9: 473840 | AW9: 2.05 | AY9: 049377000 | AZ9: ﾈﾎﾟﾝﾌｧﾝ | BA9: FAN-303T | BB9: 台 | BC9: 50000 | BD9: 19780 | BE9: 0.2 | BG9: RB0000311 | BH9: 熱交換器 | BI9: ST-50(1m) | BJ9: 基 | BK9: 1244000 | BL9: 451200 | BM9: 1 | BP9: ｴﾛﾌｨﾝﾁｭｰﾌﾞ（STK 5KF） | BQ9: 32A 25F 1500L | BR9: 本 | BS9: =ROUND(BT9/0.4,-3) -> 66000 | BT9: 26400 | BU9: 0.2 | BX9: ﾌｧﾝｺｲﾙﾕﾆｯﾄ | BY9: RF-3P | BZ9: 基 | CA9: 419000 | CB9: =CA9*0.48 -> 201120 | CC9: 1.5 | CF9: ｸｰﾘﾝｸﾞﾀﾜｰ | CG9: MT-4014 | CH9: 基 | CI9: 508000 | CJ9: 279000 | CK9: 3.5 | CN9: 蓄熱ﾀﾝｸ | CO9: 2,000ﾘｯﾄﾙ | CP9: 基 | CQ9: 238000 | CR9: 155000 | CS9: 1.5 | CV9: ﾗｲﾝﾎﾟﾝﾌﾟ | CW9: 50Hz φ40 0.25kW | CX9: 台 | CY9: 161000 | CZ9: =ROUND(CY9*0.53,-1) -> 85330 | DA9: 0.5 | DC9: 044702000 | DD9: 接続用ｹｰﾌﾞﾙｾｯﾄNGP109TX | DF9: 式 | DG9: 33900 | DH9: 5140 | DL9: 空冷ﾁﾗｰﾕﾆｯﾄ | DM9: UWAA630A(25HP) | DN9: 基 | DO9: 12000000 | DP9: =ROUNDUP(DO9*0.3,-2) -> 3600000 | DQ9: 0 | DT9: 同上架台 | DU9: 溶融亜鉛メッキ（SS400) 500H 100用 | DV9: 組 | DW9: 84000 | DX9: 46200 | DY9: 0.3 | EB9: ｵｲﾙﾀﾝｸ | EC9: BOT-10000 | ED9: 基 | EE9: 1980000 | EF9: 1230000 | EG9: 3.5 | EI9: 104719000 | EJ9: 煙突ｾｯﾄ | EK9: BEP-20T1504 | EL9: ｾｯﾄ | EM9: 72800 | EN9: 23890 | EO9: 0.7 | EQ9: RE0000378 | ER9: ﾎﾟﾘﾀﾞｸﾄ（局所施用） | ES9: 折幅160×200m | ET9: 本 | EU9: 45300 | EV9: 22770 | EW9: 0 | EZ9: ｽﾊﾟｲﾗﾙﾀﾞｸﾄ(亜鉛) | FA9: φ500 | FB9: ｍ | FC9: 7900 | FD9: =FC9*0.65 -> 5135 | FE9: 0.2 | FP9: ---------- | GE9: 051065000 | GF9: ﾊｳｽｶｵﾝｷ（LPｶﾞｽ焚き） | GG9: HK4030TEL | GH9: 台 | GI9: 1752000 | GJ9: 748140 | GK9: 1.7 | GM9: 038108000 | GN9: ﾋｰﾄｯﾌﾟ | GO9: HT-802TF | GP9: 台 | GQ9: 1477000 | GR9: 591160 | GS9: 1.5 | GV9: SGPｴﾛﾌｨﾝﾁｭｰﾌﾞ | GW9: 32A 25F 1500L | GX9: 本 | GY9: =ROUND(GZ9/0.33,-3) -> 82000 | GZ9: 27100 | HA9: 0.2
B10: 9 | C10: ﾋｰﾄｯﾌﾟ・ｶﾜｲﾀｰ | D10: gn3 | E10: 同上組立取付工事 | K10: 049830000 | L10: ﾊｳｽｶｵﾝｷ | M10: HK4030TCV | N10: 台 | O10: 1424000 | P10: 593740 | Q10: 1.7 | S10: 051114000 | T10: 小型温風機 | U10: KA-205E | V10: 台 | W10: 450000 | X10: 176880 | Y10: 0.7 | AA10: 025415000 | AB10: ﾊｳｽﾎﾞｲﾗ | AC10: HB-1007TA | AD10: 台 | AE10: 2145000 | AF10: 761850 | AG10: 1.7 | AI10: 052489000 | AJ10: ｼﾝｸﾛﾋｰﾀ | AK10: SBM150WNT_8 | AL10: 台 | AM10: 3494000 | AN10: 933310 | AO10: 3 | AQ10: 041999000 | AR10: ｵｰﾄｶﾝ | AS10: AWH-1501A | AT10: 台 | AU10: 1729000 | AV10: 475170 | AW10: 2.3 | AY10: 105493000 | AZ10: ﾈﾎﾟﾝﾌｧﾝ | BA10: FAN-400T | BB10: 台 | BC10: 55000 | BD10: 26720 | BE10: 0.2 | BH10: ---------- | BP10: ｴﾛﾌｨﾝﾁｭｰﾌﾞ（STK 5KF） | BQ10: 32A 25F 1000L | BR10: 本 | BS10: =ROUND(BT10/0.4,-3) -> 64000 | BT10: 25500 | BU10: 0.13 | BX10: ﾌｧﾝｺｲﾙﾕﾆｯﾄ | BY10: RF-5P | BZ10: 基 | CA10: 520000 | CB10: =CA10*0.48 -> 249600 | CC10: 1.5 | CF10: ｸｰﾘﾝｸﾞﾀﾜｰ | CG10: MT-5014 | CH10: 基 | CI10: 619000 | CJ10: 340000 | CK10: 3.5 | CN10: 蓄熱ﾀﾝｸ | CO10: 3,000ﾘｯﾄﾙ | CP10: 基 | CQ10: 335000 | CR10: 218000 | CS10: 2 | CV10: ﾗｲﾝﾎﾟﾝﾌﾟ | CW10: 50Hz φ40 0.4kW | CX10: 台 | CY10: 181000 | CZ10: =ROUND(CY10*0.53,-1) -> 95930 | DA10: 0.5 | DD10: ﾌｨﾙﾀﾄﾞﾗｲﾔ | DF10: 個 | DG10: 15000 | DH10: 9010 | DI10: 0 | DL10: 空冷ﾁﾗｰﾕﾆｯﾄ | DM10: UWAA750A(30HP) | DN10: 基 | DO10: 14420000 | DP10: =ROUNDUP(DO10*0.3,-2) -> 4326000 | DQ10: 0 | DT10: 同上架台 | DU10: 溶融亜鉛メッキ（SS400) 500H 200用 | DV10: 組 | DW10: 90000 | DX10: 49500 | DY10: 0.3 | EB10: ｵｲﾙﾀﾝｸ | EC10: BOT-15000 | ED10: 基 | EE10: 2470000 | EF10: 1530000 | EG10: 4.4 | EI10: 102384000 | EJ10: 煙突ｾｯﾄ | EK10: BEP-20T2252 | EL10: ｾｯﾄ | EM10: 108400 | EN10: 37760 | EO10: 0.7 | ER10: ---------- | EZ10: ｽﾊﾟｲﾗﾙﾀﾞｸﾄ(亜鉛) | FA10: φ550 | FB10: ｍ | FC10: 8700 | FD10: =FC10*0.65 -> 5655 | FE10: 0.2 | FO10: 051239000 | FP10: ﾊｳｽｶｵﾝｷ | FQ10: HK4030GCSV | FR10: 台 | FS10: 1899000 | FT10: 619800 | FU10: 1.7 | GE10: 051073000 | GF10: ﾊｳｽｶｵﾝｷ（LPｶﾞｽ焚き） | GG10: HK4030TFL | GH10: 台 | GI10: 1655000 | GJ10: 730900 | GK10: 1.7 | GM10: 038111000 | GN10: ﾋｰﾄｯﾌﾟ | GO10: HT-1202TE | GP10: 台 | GQ10: 1911000 | GR10: 725980 | GS10: 2 | GV10: SGPｴﾛﾌｨﾝﾁｭｰﾌﾞ | GW10: 32A 25F 1000L | GX10: 本 | GY10: =ROUND(GZ10/0.33,-3) -> 78000 | GZ10: 25900 | HA10: 0.13
B11: 10 | C11: 煙道・煙突関連部材・掃除具ｾｯﾄ | D11: ej3 | E11: ---------- | K11: 049831000 | L11: ﾊｳｽｶｵﾝｷ | M11: HK4030TEV | N11: 台 | O11: 1478000 | P11: 620960 | Q11: 1.7 | S11: 051116000 | T11: 小型温風機 | U11: KA-325E | V11: 台 | W11: 545000 | X11: 215850 | Y11: 0.9 | AA11: 025417000 | AB11: ﾊｳｽﾎﾞｲﾗ | AC11: HB-2007TA | AD11: 台 | AE11: 2735000 | AF11: 975890 | AG11: 2.75 | AI11: 052490000 | AJ11: ｼﾝｸﾛﾋｰﾀ | AK11: SBM150WMT_8 | AL11: 台 | AM11: 3494000 | AN11: 931760 | AO11: 3 | AQ11: 042000000 | AR11: ｵｰﾄｶﾝ | AS11: AWH-1801A | AT11: 台 | AU11: 1900000 | AV11: 504250 | AW11: 2.6 | AY11: 031741000 | AZ11: ﾈﾎﾟﾝVﾌｧﾝ | BA11: NVF-350T | BB11: 台 | BC11: 111000 | BD11: 43040 | BG11: RB0000313 | BH11: 熱交換器 | BI11: ST-3(2m) | BJ11: 基 | BK11: 358000 | BL11: 129600 | BM11: 1 | BP11: ---------- | BX11: ﾌｧﾝｺｲﾙﾕﾆｯﾄ | BY11: RF-8P | BZ11: 基 | CA11: 620000 | CB11: =CA11*0.48 -> 297600 | CC11: 2 | CF11: ｸｰﾘﾝｸﾞﾀﾜｰ | CG11: MT-6014 | CH11: 基 | CI11: 746000 | CJ11: 410000 | CK11: 3.5 | CV11: ﾗｲﾝﾎﾟﾝﾌﾟ | CW11: 50Hz φ40 0.75kW | CX11: 台 | CY11: 220000 | CZ11: =ROUND(CY11*0.53,-1) -> 116600 | DA11: 0.5 | DD11: ---------- | DL11: ---------- | DT11: 同上架台 | DU11: 溶融亜鉛メッキ（SS400) 500H 300用 | DV11: 組 | DW11: 102000 | DX11: 56100 | DY11: 0.3 | EB11: ｵｲﾙﾀﾝｸ | EC11: BOT-20000 | ED11: 基 | EE11: 2600000 | EF11: 1613000 | EG11: 5.1 | EJ11: 煙突ｾｯﾄ | EK11: φ250*3本+Ｌ+Pﾄｯﾌﾟ | EL11: ｾｯﾄ | EM11: 219900 | EN11: 109950 | EO11: 1.5 | EQ11: RE0000177 | ER11: ﾊﾟﾜｰﾀﾞｸﾄ | ES11: 折幅400×100m | ET11: 本 | EU11: 20400 | EV11: 9950 | EW11: 0 | EZ11: ｽﾊﾟｲﾗﾙﾀﾞｸﾄ(亜鉛) | FA11: φ600 | FB11: ｍ | FC11: 9500 | FD11: =FC11*0.65 -> 6175 | FE11: 0.24 | FO11: 051240000 | FP11: ﾊｳｽｶｵﾝｷ | FQ11: HK4030GESV | FR11: 台 | FS11: 1956000 | FT11: 650910 | FU11: 1.7 | GE11: 051057000 | GF11: ﾊｳｽｶｵﾝｷ（LPｶﾞｽ焚き） | GG11: HK5030TCL | GH11: 台 | GI11: 1902000 | GJ11: 856000 | GK11: 2 | GM11: 038112000 | GN11: ﾋｰﾄｯﾌﾟ | GO11: HT-1202TF | GP11: 台 | GQ11: 1911000 | GR11: 737980 | GS11: 2 | GV11: ----------
B12: 11 | C12: ﾎﾟﾘﾀﾞｸﾄ・ｸﾛｽﾗﾑﾀﾞｸﾄ | D12: er3 | E12: 機器搬入据付工事 | K12: 049832000 | L12: ﾊｳｽｶｵﾝｷ | M12: HK4030TFV | N12: 台 | O12: 1386000 | P12: 603330 | Q12: 1.7 | S12: 051118000 | T12: 小型温風機 | U12: KA-325TE | V12: 台 | W12: 596000 | X12: 228490 | Y12: 0.9 | AA12: 025418000 | AB12: ﾊｳｽﾎﾞｲﾗ | AC12: HB-3007TA | AD12: 台 | AE12: 3278000 | AF12: 1208630 | AG12: 3.4 | AI12: 052491000 | AJ12: ｼﾝｸﾛﾋｰﾀ | AK12: SBM150WLT_8 | AL12: 台 | AM12: 3494000 | AN12: 933310 | AO12: 3 | AQ12: 042001000 | AR12: ｵｰﾄｶﾝ | AS12: AWH-2001A | AT12: 台 | AU12: 2032000 | AV12: 499220 | AW12: 2.75 | AZ12: ---------- | BG12: RB0000314 | BH12: 熱交換器 | BI12: ST-5(2m) | BJ12: 基 | BK12: 450000 | BL12: 163200 | BM12: 1 | BP12: ｴﾛﾌｨﾝﾁｭｰﾌﾞ（STK 5KF） | BQ12: 32A 32F 5500L | BR12: 本 | BS12: =ROUND(BT12/0.4,-3) -> 93000 | BT12: 37000 | BU12: 0.72 | BX12: ﾌｧﾝｺｲﾙﾕﾆｯﾄ | BY12: RF-10P | BZ12: 基 | CA12: 715000 | CB12: =CA12*0.48 -> 343200 | CC12: 2 | CF12: ｸｰﾘﾝｸﾞﾀﾜｰ | CG12: MT-8014 | CH12: 基 | CI12: 997000 | CJ12: 548000 | CK12: 3.5 | CV12: ﾗｲﾝﾎﾟﾝﾌﾟ | CW12: 50Hz φ40 1.5kW | CX12: 台 | CY12: 294000 | CZ12: =ROUND(CY12*0.53,-1) -> 155820 | DA12: 0.6 | DC12: 048822000 | DD12: 誰でもﾋｰﾎﾟﾝ | DE12: EHP61(ｾｯﾄ) | DF12: ｾｯﾄ | DG12: 597000 | DH12: - | DI12: 1.6 | DL12: 空冷ﾋｰﾄﾎﾟﾝﾌﾟﾁﾗｰﾕﾆｯﾄ | DM12: UWYA125A(5HP) | DN12: 基 | DO12: 3820000 | DP12: =ROUNDUP(DO12*0.3,-2) -> 1146000 | DQ12: 0 | DT12: 同上架台 | DU12: 溶融亜鉛メッキ（SS400) 500H 500用 | DV12: 組 | DW12: 113000 | DX12: 62200 | DY12: 0.5 | EB12: ---------- | EJ12: 煙突ｾｯﾄ | EK12: φ300*3本+L+Pﾄｯﾌﾟ | EL12: ｾｯﾄ | EM12: 301000 | EN12: 150500 | EO12: 1.5 | EQ12: RE0000178 | ER12: ﾊﾟﾜｰﾀﾞｸﾄ | ES12: 折幅475×100m | ET12: 本 | EU12: 22800 | EV12: 11350 | EW12: 0 | EZ12: ｽﾊﾟｲﾗﾙﾀﾞｸﾄ(SUS) | FA12: φ200 | FB12: ｍ | FC12: 15600 | FD12: =FC12*0.65 -> 10140 | FE12: 0.16 | FO12: 051241000 | FP12: ﾊｳｽｶｵﾝｷ | FQ12: HK4030GFSV | FR12: 台 | FS12: 1856000 | FU12: 1.7 | GE12: 051067000 | GF12: ﾊｳｽｶｵﾝｷ（LPｶﾞｽ焚き） | GG12: HK5030TEL | GH12: 台 | GI12: 1972000 | GJ12: 906810 | GK12: 2 | GN12: ---------- | GV12: SGPｴﾛﾌｨﾝﾁｭｰﾌﾞ | GW12: 32A 32F 5500L | GX12: 本 | GY12: =ROUND(GZ12/0.33,-3) -> 119000 | GZ12: 39300 | HA12: 0.72
B13: 12 | C13: ｸﾞﾘｰﾝｿｰﾗ・ﾀﾞｲﾚｸﾄﾌｧﾝ | D13: az3 | E13: 機器取付工事 | K13: 051505000 | L13: ﾊｳｽｶｵﾝｷ | M13: HK4030FRV | N13: 台 | O13: 1746000 | P13: 752030 | Q13: 1.7 | S13: 051120000 | T13: 小型温風機 | U13: KA-405TE | V13: 台 | W13: 692000 | X13: 259200 | Y13: 1 | AA13: 025421000 | AB13: ﾊｳｽﾎﾞｲﾗ | AC13: HB-4007TA | AD13: 台 | AE13: 3581000 | AF13: 1317910 | AG13: 4 | AI13: 046046000 | AJ13: ｼﾝｸﾛﾋｰﾀ | AK13: SBM150WNTJ_2（水道直結仕様） | AL13: 台 | AM13: 3736000 | AN13: 985820 | AO13: 3 | AR13: ---------- | AY13: 017836000 | AZ13: ﾀﾞｸﾄﾌｧﾝ | BA13: DF-450T | BB13: 台 | BC13: 221000 | BD13: 76770 | BE13: 0.5 | BG13: RB0000315 | BH13: 熱交換器 | BI13: ST-8(2m) | BJ13: 基 | BK13: 623000 | BL13: 225600 | BM13: 1.2 | BP13: ｴﾛﾌｨﾝﾁｭｰﾌﾞ（STK 5KF） | BQ13: 32A 32F 4000L | BR13: 本 | BS13: =ROUND(BT13/0.4,-3) -> 84000 | BT13: 33500 | BU13: 0.52 | BX13: ﾌｧﾝｺｲﾙﾕﾆｯﾄ | BY13: RF-15P | BZ13: 基 | CA13: 1060000 | CB13: =CA13*0.48 -> 508800 | CC13: 2.5 | CF13: ｸｰﾘﾝｸﾞﾀﾜｰ | CG13: MT-10014 | CH13: 基 | CI13: 1273000 | CJ13: 700000 | CK13: 3.5 | CV13: ﾗｲﾝﾎﾟﾝﾌﾟ | CW13: 50Hz φ40 2.2kW | CX13: 台 | CY13: 327000 | CZ13: =ROUND(CY13*0.53,-1) -> 173310 | DA13: 0.6 | DC13: 028329000 | DD13: 誰でもﾋｰﾎﾟﾝ(ﾁｬﾝﾊﾞｰﾀｲﾌﾟ) | DE13: EHP61C-N（室内機） | DF13: 台 | DG13: 494000 | DH13: 153910 | DI13: 1.6 | DL13: 空冷ﾋｰﾄﾎﾟﾝﾌﾟﾁﾗｰﾕﾆｯﾄ | DM13: UWYA190A(8HP) | DN13: 基 | DO13: 4920000 | DP13: =ROUNDUP(DO13*0.3,-2) -> 1476000 | DQ13: 0 | DT13: 同上架台 | DU13: 溶融亜鉛メッキ（SS400) 500H 750用 | DV13: 組 | DW13: 118000 | DX13: 64900 | DY13: 0.5 | EA13: 014963000 | EB13: 消火器 | EC13: ABC-10形 | ED13: 本 | EE13: 26200 | EF13: 4780 | EG13: 0.1 | EJ13: 煙突ｾｯﾄ | EK13: φ350*3本+L+Pﾄｯﾌﾟ | EL13: ｾｯﾄ | EM13: 378600 | EN13: 189300 | EO13: 1.5 | EQ13: RE0000180 | ER13: ﾊﾟﾜｰﾀﾞｸﾄ | ES13: 折幅550×100m | ET13: 本 | EU13: 27600 | EV13: 12950 | EW13: 0 | EZ13: ｽﾊﾟｲﾗﾙﾀﾞｸﾄ(SUS) | FA13: φ225 | FB13: ｍ | FC13: 17600 | FD13: =FC13*0.65 -> 11440 | FE13: 0.18 | FP13: ---------- | GE13: 051075000 | GF13: ﾊｳｽｶｵﾝｷ（LPｶﾞｽ焚き） | GG13: HK5030TFL | GH13: 台 | GI13: 1852000 | GJ13: 824100 | GK13: 2 | GM13: 039196000 | GN13: ｶﾜｲﾀｰ | GO13: KT1026TPF3 | GP13: 台 | GQ13: 2851000 | GR13: 838610 | GS13: 2 | GV13: SGPｴﾛﾌｨﾝﾁｭｰﾌﾞ | GW13: 32A 32F 4000L | GX13: 本 | GY13: =ROUND(GZ13/0.33,-3) -> 107000 | GZ13: 35200 | HA13: 0.52
B14: 13 | C14: 熱交換器 | D14: bh3 | E14: 機器架台及び据付工事 | K14: 051781000 | L14: ﾊｳｽｶｵﾝｷ | M14: HK4030GRV | N14: 台 | O14: 1746000 | P14: 720010 | Q14: 1.7 | T14: ---------- | AB14: ----------- | AI14: 052492000 | AJ14: ｼﾝｸﾛﾋｰﾀ | AK14: SBM150WMTJ_3（水道直結仕様） | AL14: 台 | AM14: 3736000 | AN14: 994720 | AO14: 3 | AQ14: 042002000 | AR14: ｵｰﾄｶﾝ | AS14: AWH-501SA | AT14: 台 | AU14: 1000000 | AV14: 310890 | AW14: 1.3 | AY14: 018835000 | AZ14: φ300吹出口ﾌﾗﾝｼﾞｾｯﾄ | BA14: BFS-DFφ300 | BB14: 台 | BC14: 13100 | BD14: 3830 | BG14: RB0000316 | BH14: 熱交換器 | BI14: ST-10(2m) | BJ14: 基 | BK14: 847000 | BL14: 307200 | BM14: 1.5 | BP14: ｴﾛﾌｨﾝﾁｭｰﾌﾞ（STK 5KF） | BQ14: 32A 32F 3500L | BR14: 本 | BS14: =ROUND(BT14/0.4,-3) -> 80000 | BT14: 32100 | BU14: 0.46 | BX14: ﾌｧﾝｺｲﾙﾕﾆｯﾄ | BY14: RF-20P | BZ14: 基 | CA14: 1420000 | CB14: =CA14*0.48 -> 681600 | CC14: 2.5 | CV14: ---------- | DC14: 036831000 | DD14: 誰でもﾋｰﾎﾟﾝ | DE14: EHP61G（室外機） | DF14: 台 | DG14: 585000 | DH14: 177970 | DI14: 1.6 | DL14: 空冷ﾋｰﾄﾎﾟﾝﾌﾟﾁﾗｰﾕﾆｯﾄ | DM14: UWYA250A(10HP) | DN14: 基 | DO14: 5830000 | DP14: =ROUNDUP(DO14*0.3,-2) -> 1749000 | DQ14: 0 | DT14: 同上架台 | DU14: 溶融亜鉛メッキ（SS400) 500H 1000用 | DV14: 組 | DW14: 168000 | DX14: 92400 | DY14: 0.5 | EB14: 消火器 | EC14: ABC-50形 | ED14: 基 | EE14: 85000 | EF14: 43500 | EG14: 0.1 | EJ14: ---------- | EQ14: RE0000174 | ER14: ﾊﾟﾜｰﾀﾞｸﾄ | ES14: 折幅630×50m | ET14: 本 | EU14: 18000 | EV14: 8150 | EW14: 0 | EZ14: ｽﾊﾟｲﾗﾙﾀﾞｸﾄ(SUS) | FA14: φ250 | FB14: ｍ | FC14: 19500 | FD14: =FC14*0.65 -> 12675 | FE14: 0.18 | FO14: 051242000 | FP14: ﾊｳｽｶｵﾝｷ | FQ14: HK5030GCSV | FR14: 台 | FS14: 2114000 | FT14: 724930 | FU14: 2 | GE14: 051059000 | GF14: ﾊｳｽｶｵﾝｷ（LPｶﾞｽ焚き） | GG14: HK6030TCL | GH14: 台 | GI14: 2107000 | GJ14: 912260 | GK14: 2.2 | GM14: 039197000 | GN14: ｶﾜｲﾀｰ | GO14: KT1026TPG3 | GP14: 台 | GQ14: 2851000 | GR14: 854610 | GS14: 2 | GV14: SGPｴﾛﾌｨﾝﾁｭｰﾌﾞ | GW14: 32A 32F 3500L | GX14: 本 | GY14: =ROUND(GZ14/0.33,-3) -> 102000 | GZ14: 33600 | HA14: 0.46
B15: 14 | C15: STKｴﾛﾌｨﾝﾁｭｰﾌﾞ | D15: bp3 | E15: 機器架台工事 | K15: 051782000 | L15: ﾊｳｽｶｵﾝｷ | M15: HK4030TYV | N15: 台 | O15: 1722000 | P15: 762530 | Q15: 1.7 | S15: 042809000 | T15: 小型温風機（LPガス焚き） | U15: KA-325EL | V15: 台 | W15: 935000 | X15: 373890 | Y15: 0.9 | AI15: 052493000 | AJ15: ｼﾝｸﾛﾋｰﾀ | AK15: SBM150WLTJ_3（水道直結仕様） | AL15: 台 | AM15: 3736000 | AN15: 994590 | AO15: 3 | AQ15: 042003000 | AR15: ｵｰﾄｶﾝ | AS15: AWH-601SA | AT15: 台 | AU15: 1039000 | AV15: 313300 | AW15: 1.4 | AY15: 018834000 | AZ15: φ400吹出口ﾌﾗﾝｼﾞｾｯﾄ | BA15: BFS-DFφ400 | BB15: 台 | BC15: 15700 | BD15: 3250 | BG15: RB0000317 | BH15: 熱交換器 | BI15: ST-20(2m) | BJ15: 基 | BK15: 1032000 | BL15: 374400 | BM15: 1.75 | BP15: ｴﾛﾌｨﾝﾁｭｰﾌﾞ（STK 5KF） | BQ15: 32A 32F 3000L | BR15: 本 | BS15: =ROUND(BT15/0.4,-3) -> 77000 | BT15: 30900 | BU15: 0.4 | CV15: ﾗｲﾝﾎﾟﾝﾌﾟ | CW15: 50Hz φ50 0.4kW | CX15: 台 | CY15: 192000 | CZ15: =ROUND(CY15*0.53,-1) -> 101760 | DA15: 0.5 | DC15: 025678000 | DD15: 操作盤 | DE15: EHPOB (EHP61用) | DF15: 面 | DG15: 31800 | DH15: 10700 | DI15: 1.6 | DL15: 空冷ﾋｰﾄﾎﾟﾝﾌﾟﾁﾗｰﾕﾆｯﾄ | DM15: UWYA375A(15HP) | DN15: 基 | DO15: 8880000 | DP15: =ROUNDUP(DO15*0.3,-2) -> 2664000 | DQ15: 0 | DT15: ---------- | EA15: 174001000 | EB15: 格納箱 | EC15: ABC-10用 | ED15: 個 | EE15: 11300 | EF15: 2710 | EG15: 0.2 | EI15: 050735000 | EJ15: 煙室ｾｯﾄ | EK15: ES-2330 | EL15: ｾｯﾄ | EM15: 119000 | EN15: 35870 | EO15: 0.5 | EQ15: RE0000175 | ER15: ﾊﾟﾜｰﾀﾞｸﾄ | ES15: 折幅900×50m | ET15: 本 | EU15: 21600 | EV15: 10650 | EW15: 0 | EZ15: ｽﾊﾟｲﾗﾙﾀﾞｸﾄ(SUS) | FA15: φ300 | FB15: ｍ | FC15: 26900 | FD15: =FC15*0.65 -> 17485 | FE15: 0.18 | FO15: 051243000 | FP15: ﾊｳｽｶｵﾝｷ | FQ15: HK5030GESV | FR15: 台 | FS15: 2177000 | FT15: 0 | FU15: 2 | GE15: 051069000 | GF15: ﾊｳｽｶｵﾝｷ（LPｶﾞｽ焚き） | GG15: HK6030TEL | GH15: 台 | GI15: 2205000 | GJ15: 974480 | GK15: 2.2 | GM15: 039198000 | GN15: ｶﾜｲﾀｰ | GO15: KT1526TPF3 | GP15: 台 | GQ15: 3211000 | GR15: 857060 | GS15: 2.5 | GV15: SGPｴﾛﾌｨﾝﾁｭｰﾌﾞ | GW15: 32A 32F 3000L | GX15: 本 | GY15: =ROUND(GZ15/0.33,-3) -> 98000 | GZ15: 32200 | HA15: 0.4
B16: 15 | C16: SGPｴﾛﾌｨﾝﾁｭｰﾌﾞ | D16: ｇv3 | E16: 機器基礎工事 | K16: 049833000 | L16: ﾊｳｽｶｵﾝｷ | M16: HK5030TCV | N16: 台 | O16: 1620000 | P16: 701210 | Q16: 2 | S16: 042793000 | T16: 小型温風機（13Aガス焚き） | U16: KA-325EN | V16: 台 | W16: 935000 | X16: 373630 | Y16: 0.9 | AJ16: ----------- | AQ16: 042004000 | AR16: ｵｰﾄｶﾝ | AS16: AWH-701SA | AT16: 台 | AU16: 1116000 | AV16: 313300 | AW16: 1.55 | AY16: 018836000 | AZ16: φ400ﾌﾗﾝｼﾞ取付板ｾｯﾄ | BA16: BFS-DF400S | BB16: 枚 | BC16: 13500 | BD16: 1990 | BH16: ---------- | BP16: ｴﾛﾌｨﾝﾁｭｰﾌﾞ（STK 5KF） | BQ16: 32A 32F 2750L | BR16: 本 | BS16: =ROUND(BT16/0.4,-3) -> 76000 | BT16: 30200 | BU16: 0.36 | CV16: ﾗｲﾝﾎﾟﾝﾌﾟ | CW16: 50Hz φ50 0.75kW | CX16: 台 | CY16: 223000 | CZ16: =ROUND(CY16*0.53,-1) -> 118190 | DA16: 0.6 | DC16: 027332000 | DD16: 送風機増速盤 | DE16: EHPFC (50Hz電源用) | DF16: 面 | DG16: 97300 | DH16: 35000 | DI16: 1.6 | DL16: 空冷ﾋｰﾄﾎﾟﾝﾌﾟﾁﾗｰﾕﾆｯﾄ | DM16: UWYA500A(20HP) | DN16: 基 | DO16: 11400000 | DP16: =ROUNDUP(DO16*0.3,-2) -> 3420000 | DQ16: 0 | DT16: 膨張ﾀﾝｸ | DU16: HUW-40 ボールタップ一般型 | DV16: 台 | DW16: 352000 | DX16: 193600 | DY16: 0.5 | EB16: 格納箱 | EC16: ABC-50用 | ED16: 個 | EE16: 63000 | EF16: 25000 | EG16: 0.3 | EI16: 050736000 | EJ16: 煙室ｾｯﾄ | EK16: ES-4030 | EL16: ｾｯﾄ | EM16: 126000 | EN16: 40000 | EO16: 0.5 | EQ16: RE0000176 | ER16: ﾊﾟﾜｰﾀﾞｸﾄ | ES16: 折幅1100×50m | ET16: 本 | EU16: 25100 | EV16: 12550 | EW16: 0 | EZ16: ｽﾊﾟｲﾗﾙﾀﾞｸﾄ(SUS) | FA16: φ350 | FB16: ｍ | FC16: 36300 | FD16: =FC16*0.65 -> 23595 | FE16: 0.19 | FO16: 051244000 | FP16: ﾊｳｽｶｵﾝｷ | FQ16: HK5030GFSV | FR16: 台 | FS16: 2061000 | FT16: 692910 | FU16: 2 | GE16: 051077000 | GF16: ﾊｳｽｶｵﾝｷ（LPｶﾞｽ焚き） | GG16: HK6030TFL | GH16: 台 | GI16: 2051000 | GJ16: 875180 | GK16: 2.2 | GM16: 105850000 | GN16: ｶﾜｲﾀｰ | GO16: KT1526TPHF | GP16: 台 | GQ16: 2701000 | GR16: 779130 | GS16: 2.5 | GV16: SGPｴﾛﾌｨﾝﾁｭｰﾌﾞ | GW16: 32A 32F 2750L | GX16: 本 | GY16: =ROUND(GZ16/0.33,-3) -> 95000 | GZ16: 31400 | HA16: 0.36
B17: 16 | C17: ｴﾛﾌｨﾝ支持金具 | D17: fx3 | E17: 煙突支持取付工事 | K17: 049834000 | L17: ﾊｳｽｶｵﾝｷ | M17: HK5030TEV | N17: 台 | O17: 1680000 | P17: 752540 | Q17: 2 | S17: 042812000 | T17: 小型温風機（LPガス焚き） | U17: KA-325TEL | V17: 台 | W17: 948000 | X17: 386790 | Y17: 0.9 | AI17: 046049000 | AJ17: ｼﾝｸﾛﾋｰﾀ | AK17: SBM150HNT_4 13A 高温出湯 | AL17: 台 | AM17: 3875000 | AN17: 939890 | AO17: 3 | AQ17: 042005000 | AR17: ｵｰﾄｶﾝ | AS17: AWH-801SA | AT17: 台 | AU17: 1185000 | AV17: 379920 | AW17: 1.65 | AY17: 018837000 | AZ17: 架台ｾｯﾄ | BA17: BKD-DF | BB17: ｾｯﾄ | BC17: 67900 | BD17: 19480 | BG17: 103419000 | BH17: 熱交換器ｺｲﾙ | BI17: BNC-150 | BJ17: 基 | BK17: 121700 | BL17: 33020 | BM17: 0.5 | BP17: ｴﾛﾌｨﾝﾁｭｰﾌﾞ（STK 5KF） | BQ17: 32A 32F 2000L | BR17: 本 | BS17: =ROUND(BT17/0.4,-3) -> 71000 | BT17: 28500 | BU17: 0.26 | CV17: ﾗｲﾝﾎﾟﾝﾌﾟ | CW17: 50Hz φ50 1.5kW | CX17: 台 | CY17: 291000 | CZ17: =ROUND(CY17*0.53,-1) -> 154230 | DA17: 0.7 | DC17: 019031000 | DD17: ﾌｧﾝﾀｲﾏｾｯﾄ | DE17: EHPCX | DF17: 式 | DG17: 23100 | DH17: 3200 | DL17: 空冷ﾋｰﾄﾎﾟﾝﾌﾟﾁﾗｰﾕﾆｯﾄ | DM17: UWYA630A(25HP) | DN17: 基 | DO17: 14870000 | DP17: =ROUNDUP(DO17*0.3,-2) -> 4461000 | DQ17: 0 | DT17: 膨張ﾀﾝｸ | DU17: HUW-60 ボールタップ一般型 | DV17: 台 | DW17: 376000 | DX17: 206800 | DY17: 0.75 | EB17: 危険物看板 | EC17: 火気厳禁他1点 | ED17: ｾｯﾄ | EE17: 4980 | EF17: 1560 | EG17: 0.5 | EI17: 050737000 | EJ17: 煙室ｾｯﾄ | EK17: ES-5630 | EL17: ｾｯﾄ | EM17: 145000 | EN17: 52380 | EO17: 0.5 | EQ17: RE0000181 | ER17: ﾊﾟﾜｰﾀﾞｸﾄ | ES17: 折幅400×200m(0.07) | ET17: 本 | EU17: 26300 | EV17: 12950 | EW17: 0 | EZ17: ｽﾊﾟｲﾗﾙﾀﾞｸﾄ(SUS) | FA17: φ400 | FB17: ｍ | FC17: 49000 | FD17: =FC17*0.65 -> 31850 | FE17: 0.19 | FP17: ---------- | GF17: ﾊｳｽｶｵﾝｷ（LPｶﾞｽ焚き） | GG17: HK8030TCL | GH17: 台 | GI17: 2900000 | GJ17: 1258610 | GK17: 2.8 | GM17: 039003000 | GN17: ｶﾜｲﾀｰ | GO17: KT1526TPFW | GP17: 台 | GQ17: 3312000 | GR17: 959890 | GS17: 2.5 | GV17: SGPｴﾛﾌｨﾝﾁｭｰﾌﾞ | GW17: 32A 32F 2000L | GX17: 本 | GY17: =ROUND(GZ17/0.33,-3) -> 89000 | GZ17: 29300 | HA17: 0.26
B18: 17 | C18: ﾌｧﾝｺｲﾙﾕﾆｯﾄ | D18: bx3 | E18: 煙突取付工事 | K18: 049835000 | L18: ﾊｳｽｶｵﾝｷ | M18: HK5030TFV | N18: 台 | O18: 1572000 | P18: 668670 | Q18: 2 | S18: 042810000 | T18: 小型温風機（13Aガス焚き） | U18: KA-325TEN | V18: 台 | W18: 948000 | X18: 386790 | Y18: 0.9 | AI18: 052495000 | AJ18: ｼﾝｸﾛﾋｰﾀ | AK18: SBM150HNT_5 13A 高温出湯 | AL18: 台 | AM18: 3875000 | AN18: 950730 | AO18: 3 | AQ18: 042006000 | AR18: ｵｰﾄｶﾝ | AS18: AWH-901SA | AT18: 台 | AU18: 1242000 | AV18: 382330 | AW18: 1.75 | AY18: 018838000 | AZ18: ﾁｬﾝﾊﾞﾎﾞｯｸｽ | BA18: BCB-DF | BB18: 台 | BC18: 109200 | BD18: 20510 | BP18: ｴﾛﾌｨﾝﾁｭｰﾌﾞ（STK 5KF） | BQ18: 32A 32F 1500L | BR18: 本 | BS18: =ROUND(BT18/0.4,-3) -> 68000 | BT18: 27300 | BU18: 0.2 | CV18: ﾗｲﾝﾎﾟﾝﾌﾟ | CW18: 50Hz φ50 2.2kW | CX18: 台 | CY18: 327000 | CZ18: =ROUND(CY18*0.53,-1) -> 173310 | DA18: 0.7 | DC18: 019037000 | DD18: ﾈﾎﾟﾝｻｰﾓｾｯﾄ | DE18: EHPCX | DF18: 式 | DG18: 33500 | DH18: 4360 | DL18: 空冷ﾋｰﾄﾎﾟﾝﾌﾟﾁﾗｰﾕﾆｯﾄ | DM18: UWYA750A(30HP) | DN18: 基 | DO18: 17870000 | DP18: =ROUNDUP(DO18*0.3,-2) -> 5361000 | DQ18: 0 | DT18: 膨張ﾀﾝｸ | DU18: HUW-80 ボールタップ一般型 | DV18: 台 | DW18: 431000 | DX18: 237100 | DY18: 1 | EB18: 同上取付金具 | EC18: (取付を含む) | ED18: 式 | EE18: 25000 | EF18: 10000 | EG18: 0.5 | EI18: 050738000 | EJ18: 煙室ｾｯﾄ | EK18: ES-8030 | EL18: ｾｯﾄ | EM18: 147000 | EN18: 63990 | EO18: 0.7 | EQ18: RE0000182 | ER18: ﾊﾟﾜｰﾀﾞｸﾄ | ES18: 折幅475×200m(0.07) | ET18: 本 | EU18: 29800 | EV18: 14900 | EW18: 0 | EZ18: ｽﾊﾟｲﾗﾙﾀﾞｸﾄ(SUS) | FA18: φ450 | FB18: ｍ | FC18: 52800 | FD18: =FC18*0.65 -> 34320 | FE18: 0.19 | FO18: 051245000 | FP18: ﾊｳｽｶｵﾝｷ | FQ18: HK6030GCSV | FR18: 台 | FS18: 2328000 | FT18: 746190 | FU18: 2.2 | GF18: ---------- | GM18: 007369000 | GN18: ｶﾜｲﾀｰ | GO18: KT1526TPHFW | GP18: 台 | GQ18: 2777000 | GR18: 882220 | GS18: 2.5 | GV18: SGPｴﾛﾌｨﾝﾁｭｰﾌﾞ | GW18: 32A 32F 1500L | GX18: 本 | GY18: =ROUND(GZ18/0.33,-3) -> 85000 | GZ18: 27900 | HA18: 0.2
B19: 18 | C19: ﾗｲﾝﾎﾟﾝﾌﾟ | D19: cv3 | E19: 煙道・煙突取付工事 | K19: 049836000 | L19: ﾊｳｽｶｵﾝｷ | M19: HK6030TCV | N19: 台 | O19: 1814000 | P19: 722990 | Q19: 2.2 | T19: ---------- | AI19: 052496000 | AJ19: ｼﾝｸﾛﾋｰﾀ | AK19: SBM150HMT_5 12A 高温出湯 | AL19: 台 | AM19: 3875000 | AN19: 949050 | AO19: 3 | AQ19: 042007000 | AR19: ｵｰﾄｶﾝ | AS19: AWH-1001SA | AT19: 台 | AU19: 1295000 | AV19: 399360 | AW19: 1.9 | BP19: ｴﾛﾌｨﾝﾁｭｰﾌﾞ（STK 5KF） | BQ19: 32A 32F 1000L | BR19: 本 | BS19: =ROUND(BT19/0.4,-3) -> 65000 | BT19: 26000 | BU19: 0.13 | CV19: ﾗｲﾝﾎﾟﾝﾌﾟ | CW19: 50Hz φ50 3.7kW | CX19: 台 | CY19: 440000 | CZ19: =ROUND(CY19*0.53,-1) -> 233200 | DA19: 0.8 | DC19: 039749000 | DD19: EHPﾊｲﾌﾞﾘｯﾄﾞ制御基板ｾｯﾄ | DE19: EHP-HCS | DF19: 式 | DG19: 71900 | DH19: 4500 | DT19: 膨張ﾀﾝｸ | DU19: HUW-100 ボールタップ一般型 | DV19: 台 | DW19: 466000 | DX19: 256300 | DY19: 1.5 | EA19: 044668000 | EB19: 消火器設置台 | EC19: ＶＴ１ＲＢ | ED19: 個 | EE19: 4530 | EF19: 1250 | EG19: 0.1 | EI19: 105768000 | EJ19: 煙室ｾｯﾄ | EK19: ES-2327 | EL19: ｾｯﾄ | EM19: 119000 | EN19: 36590 | EO19: 0.5 | EQ19: RE0000183 | ER19: ﾊﾟﾜｰﾀﾞｸﾄ | ES19: 折幅550×200m(0.07) | ET19: 本 | EU19: 33500 | EV19: 17200 | EW19: 0 | EZ19: ｽﾊﾟｲﾗﾙﾀﾞｸﾄ(SUS) | FA19: φ500 | FB19: ｍ | FC19: 54900 | FD19: =FC19*0.65 -> 35685 | FE19: 0.2 | FO19: 051246000 | FP19: ﾊｳｽｶｵﾝｷ | FQ19: HK6030GESV | FR19: 台 | FS19: 2400000 | FT19: 811530 | FU19: 2.2 | GE19: 051052000 | GF19: ﾊｳｽｶｵﾝｷ（13Aｶﾞｽ焚き） | GG19: HK2030TCN | GH19: 台 | GI19: 1197000 | GJ19: 553550 | GK19: 1.25 | GM19: 039200000 | GN19: ｶﾜｲﾀｰ | GO19: KT2026TPF3 | GP19: 台 | GQ19: 4017000 | GR19: 1185670 | GS19: 3.1 | GV19: SGPｴﾛﾌｨﾝﾁｭｰﾌﾞ | GW19: 32A 32F 1000L | GX19: 本 | GY19: =ROUND(GZ19/0.33,-3) -> 80000 | GZ19: 26400 | HA19: 0.13
B20: 19 | C20: ﾊﾟｯｹｰｼﾞｴｱｺﾝ(NGP・重工) | D20: dd3 | E20: 煙道保温工事 | K20: 049837000 | L20: ﾊｳｽｶｵﾝｷ | M20: HK6030TEV | N20: 台 | O20: 1882000 | P20: 792990 | Q20: 2.2 | S20: 051160000 | T20: ｸﾞﾛｳｴｱ（灯油焚き） | U20: CG-254S1 | V20: 台 | W20: 322000 | X20: 159980 | Y20: 0.5 | AI20: 046051000 | AJ20: ｼﾝｸﾛﾋｰﾀ | AK20: SBM150HLT_4 LPG 高温出湯 | AL20: 台 | AM20: 3875000 | AN20: 938600 | AO20: 3 | AQ20: 042008000 | AR20: ｵｰﾄｶﾝ | AS20: AWH-1201SA | AT20: 台 | AU20: 1484000 | AV20: 473840 | AW20: 2.05 | BP20: ---------- | CV20: ---------- | DT20: 膨張ﾀﾝｸ | DU20: HUW-150 ボールタップ一般型 | DV20: 台 | DW20: 544000 | DX20: 299200 | DY20: 2 | EB20: ---------- | EI20: 105769000 | EJ20: 煙室ｾｯﾄ | EK20: ES-4027 | EL20: ｾｯﾄ | EM20: 126000 | EN20: 40820 | EO20: 0.5 | ER20: ---------- | EZ20: ｽﾊﾟｲﾗﾙﾀﾞｸﾄ(SUS) | FA20: φ550 | FB20: ｍ | FC20: 60100 | FD20: =FC20*0.65 -> 39065 | FE20: 0.2 | FO20: 051247000 | FP20: ﾊｳｽｶｵﾝｷ | FQ20: HK6030GFSV | FR20: 台 | FS20: 2268000 | FT20: 712620 | FU20: 2.2 | GE20: 051062000 | GF20: ﾊｳｽｶｵﾝｷ（13Aｶﾞｽ焚き） | GG20: HK2030TEN | GH20: 台 | GI20: 1215000 | GJ20: 562370 | GK20: 1.25 | GM20: 105852000 | GN20: ｶﾜｲﾀｰ | GO20: KT2026TPHF | GP20: 台 | GQ20: 3721000 | GR20: 1087100 | GS20: 3.1 | GV20: ----------
B21: 20 | C21: ﾁﾗｰﾕﾆｯﾄ(ﾀﾞｲｷﾝ) | D21: dl3 | E21: ---------- | K21: 049838000 | L21: ﾊｳｽｶｵﾝｷ | M21: HK6030TFV | N21: 台 | O21: 1763000 | P21: 685520 | Q21: 2.2 | S21: 051161000 | T21: ｸﾞﾛｳｴｱ（灯油焚き） | U21: CG-254S2 | V21: 台 | W21: 344000 | X21: 168500 | Y21: 0.5 | AI21: 052497000 | AJ21: ｼﾝｸﾛﾋｰﾀ | AK21: SBM150HLT_5 LPG 高温出湯 | AL21: 台 | AM21: 3875000 | AN21: 949050 | AO21: 3 | AQ21: 042009000 | AR21: ｵｰﾄｶﾝ | AS21: AWH-1501SA | AT21: 台 | AU21: 1729000 | AV21: 475170 | AW21: 2.15 | BP21: ｴﾛﾌｨﾝﾁｭｰﾌﾞ（STK 5KF） | BQ21: 40A 25F 5500L | BR21: 本 | BS21: =ROUND(BT21/0.4,-3) -> 89000 | BT21: 35400 | BU21: 0.72 | CV21: ﾗｲﾝﾎﾟﾝﾌﾟ | CW21: 50Hz φ65 0.75kW | CX21: 台 | CY21: 246000 | CZ21: =ROUND(CY21*0.53,-1) -> 130380 | DA21: 0.7 | DT21: 同上架台 | DU21: 溶融亜鉛メッキ（SS400) 500H 40用 | DV21: 組 | DW21: 60000 | DX21: 33000 | DY21: 0.3 | EB21: ｵｲﾙﾀﾝｸ | EC21: KS1-399SZ | ED21: 基 | EE21: 100300 | EF21: 40200 | EG21: 0.3 | EI21: 105770000 | EJ21: 煙室ｾｯﾄ | EK21: ES-5627 | EL21: ｾｯﾄ | EM21: 145000 | EN21: 52890 | EO21: 0.5 | EQ21: RE0000080 | ER21: ｸﾛｽﾗﾑﾀﾞｸﾄ | ES21: 折幅630×15m | ET21: 本 | EU21: 12200 | EV21: 5990 | EW21: 0 | EZ21: ｽﾊﾟｲﾗﾙﾀﾞｸﾄ(SUS) | FA21: φ600 | FB21: ｍ | FC21: 65400 | FD21: =FC21*0.65 -> 42510 | FE21: 0.24 | FP21: ---------- | GE21: 051054000 | GF21: ﾊｳｽｶｵﾝｷ（13Aｶﾞｽ焚き） | GG21: HK3030TCN | GH21: 台 | GI21: 1592000 | GJ21: 616300 | GK21: 1.45 | GM21: 039202000 | GN21: ｶﾜｲﾀｰ | GO21: KT2026TPG3 | GP21: 台 | GQ21: 4017000 | GR21: 1204760 | GS21: 3.1 | GV21: SGPｴﾛﾌｨﾝﾁｭｰﾌﾞ | GW21: 40A 25F 5500L | GX21: 本 | GY21: =ROUND(GZ21/0.33,-3) -> 116000 | GZ21: 38200 | HA21: 0.72
B22: 21 | C22: ｸｰﾘﾝｸﾞﾀﾜｰ | D22: cf3 | E22: ｴﾛﾌｨﾝ取付工事 | K22: 050747000 | L22: ﾊｳｽｶｵﾝｷ | M22: HK8030GCV | N22: 台 | O22: 2623000 | P22: 1068730 | Q22: 2.8 | S22: 051162000 | T22: ｸﾞﾛｳｴｱ（灯油焚き） | U22: CG-554T2 | V22: 台 | W22: 413000 | X22: 177140 | Y22: 0.7 | AI22: 052498000 | AJ22: ｼﾝｸﾛﾋｰﾀ | AK22: SBM150HNTJ_2 13A 高温,直結 | AL22: 台 | AM22: 4118000 | AN22: 1012010 | AO22: 3 | AR22: ---------- | BP22: ｴﾛﾌｨﾝﾁｭｰﾌﾞ（STK 5KF） | BQ22: 40A 25F 4000L | BR22: 本 | BS22: =ROUND(BT22/0.4,-3) -> 81000 | BT22: 32200 | BU22: 0.52 | CV22: ﾗｲﾝﾎﾟﾝﾌﾟ | CW22: 50Hz φ65 1.5kW | CX22: 台 | CY22: 289000 | CZ22: =ROUND(CY22*0.53,-1) -> 153170 | DA22: 0.8 | DT22: 同上架台 | DU22: 溶融亜鉛メッキ（SS400) 500H 60用 | DV22: 組 | DW22: 60000 | DX22: 33000 | DY22: 0.3 | EB22: ｵｲﾙﾀﾝｸ | EC22: KS2-490SJ | ED22: 基 | EE22: 98800 | EF22: 36300 | EG22: 0.3 | EI22: 039393000 | EJ22: 煙室ｾｯﾄ | EK22: ES-8026 | EL22: ｾｯﾄ | EM22: 147000 | EN22: 64190 | EO22: 0.7 | EQ22: RE0000081 | ER22: ｸﾛｽﾗﾑﾀﾞｸﾄ | ES22: 折幅630×20m | ET22: 本 | EU22: 15300 | EV22: 7930 | EW22: 0 | EZ22: ﾀﾞｸﾄﾍﾞﾝﾄﾞ(亜鉛) | FA22: φ200 | FB22: 個 | FC22: 4300 | FD22: =FC22*0.65 -> 2795 | FE22: 0.16 | FG22: 044722000 | FH22: ﾊﾟﾈﾙﾌﾚｯｼｬｰ | FI22: HFP-1503 | FJ22: 台 | FK22: 2911000 | FL22: 1060000 | FP22: ﾊｳｽｶｵﾝｷ | FQ22: HK8030GCSV | FR22: 台 | FS22: 2975000 | FT22: 1030240 | FU22: 2.8 | GE22: 051064000 | GF22: ﾊｳｽｶｵﾝｷ（13Aｶﾞｽ焚き） | GG22: HK3030TEN | GH22: 台 | GI22: 1606000 | GJ22: 615630 | GK22: 1.45 | GM22: 026284000 | GN22: ｶﾜｲﾀｰ | GO22: KT2026TPHG | GP22: 台 | GQ22: 3721000 | GR22: 1106190 | GS22: 3.1 | GV22: SGPｴﾛﾌｨﾝﾁｭｰﾌﾞ | GW22: 40A 25F 4000L | GX22: 本 | GY22: =ROUND(GZ22/0.33,-3) -> 103000 | GZ22: 34100 | HA22: 0.52
B23: 22 | C23: 蓄熱ﾀﾝｸ | D23: cn3 | E23: 支持金具取付工事 | K23: 050748000 | L23: ﾊｳｽｶｵﾝｷ | M23: HK8030GFV | N23: 台 | O23: 2572000 | P23: 1024260 | Q23: 2.8 | S23: 051163000 | T23: ｸﾞﾛｳｴｱ（灯油焚き） | U23: CG-854T2 | V23: 台 | W23: 537000 | X23: 240490 | Y23: 0.9 | AI23: 052499000 | AJ23: ｼﾝｸﾛﾋｰﾀ | AK23: SBM150HMTJ_2 12A 高温,直結 | AL23: 台 | AM23: 4118000 | AN23: 1011880 | AO23: 3 | AQ23: 042029000 | AR23: ｵｰﾄｶﾝ | AS23: AWH-501GBL | AT23: 台 | AU23: 1900000 | AV23: 520580 | AW23: 1.3 | BP23: ｴﾛﾌｨﾝﾁｭｰﾌﾞ（STK 5KF） | BQ23: 40A 25F 3500L | BR23: 本 | BS23: =ROUND(BT23/0.4,-3) -> 78000 | BT23: 31200 | BU23: 0.46 | CV23: ﾗｲﾝﾎﾟﾝﾌﾟ | CW23: 50Hz φ65 2.2kW | CX23: 台 | CY23: 362000 | CZ23: =ROUND(CY23*0.53,-1) -> 191860 | DA23: 0.8 | DT23: 同上架台 | DU23: 溶融亜鉛メッキ（SS400) 500H 80用 | DV23: 組 | DW23: 80000 | DX23: 44000 | DY23: 0.3 | EB23: ｵｲﾙﾀﾝｸ | EC23: YMA-990G1 | ED23: 基 | EE23: 394500 | EF23: 236700 | EG23: 1 | EJ23: ---------- | EQ23: RE0000082 | ER23: ｸﾛｽﾗﾑﾀﾞｸﾄ | ES23: 折幅630×30m | ET23: 本 | EU23: 21800 | EV23: 11770 | EW23: 0 | EZ23: ﾀﾞｸﾄﾍﾞﾝﾄﾞ(亜鉛) | FA23: φ225 | FB23: 個 | FC23: 5100 | FD23: =FC23*0.65 -> 3315 | FE23: 0.18 | FH23: --------------- | FP23: ﾊｳｽｶｵﾝｷ | FQ23: HK8030GFSV | FR23: 台 | FS23: 2969000 | FT23: 1014370 | FU23: 2.8 | GE23: 051072000 | GF23: ﾊｳｽｶｵﾝｷ（13Aｶﾞｽ焚き） | GG23: HK3030TFN | GH23: 台 | GI23: 1554000 | GJ23: 593350 | GK23: 1.45 | GV23: SGPｴﾛﾌｨﾝﾁｭｰﾌﾞ | GW23: 40A 25F 3500L | GX23: 本 | GY23: =ROUND(GZ23/0.33,-3) -> 99000 | GZ23: 32800 | HA23: 0.46
B24: 23 | C24: 膨張ﾀﾝｸ(ﾎｰｺｽ) | D24: dt3 | E24: 防油堤及びﾀﾝｸ基礎工事 | K24: 050745000 | L24: ﾊｳｽｶｵﾝｷ | M24: HK8030FCV | N24: 台 | O24: 2623000 | P24: 1153380 | Q24: 2.8 | T24: ---------- | AI24: 052500000 | AJ24: ｼﾝｸﾛﾋｰﾀ | AK24: SBM150HLTJ_2 LPG 高温,直結 | AL24: 台 | AM24: 4118000 | AN24: 1011880 | AO24: 3 | AQ24: 042031000 | AR24: ｵｰﾄｶﾝ | AS24: AWH-601GBL | AT24: 台 | AU24: 1974000 | AV24: 564960 | AW24: 1.4 | BP24: ｴﾛﾌｨﾝﾁｭｰﾌﾞ（STK 5KF） | BQ24: 40A 25F 3000L | BR24: 本 | BS24: =ROUND(BT24/0.4,-3) -> 75000 | BT24: 30000 | BU24: 0.4 | CV24: ﾗｲﾝﾎﾟﾝﾌﾟ | CW24: 50Hz φ65 3.7kW | CX24: 台 | CY24: 440000 | CZ24: =ROUND(CY24*0.53,-1) -> 233200 | DA24: 0.8 | DT24: 同上架台 | DU24: 溶融亜鉛メッキ（SS400) 500H 100用 | DV24: 組 | DW24: 80000 | DX24: 44000 | DY24: 0.3 | EB24: 防油堤 | EC24: AL-500G | ED24: 基 | EE24: 128400 | EF24: 77040 | EG24: 2.3 | EI24: 308793000 | EJ24: 煙突直管 | EK24: φ120 | EL24: 本 | EM24: 8470 | EN24: 2090 | EO24: 0.1 | EQ24: RE0000083 | ER24: ｸﾛｽﾗﾑﾀﾞｸﾄ | ES24: 折幅630×40m | ET24: 本 | EU24: 29200 | EV24: 15760 | EW24: 0 | EZ24: ﾀﾞｸﾄﾍﾞﾝﾄﾞ(亜鉛) | FA24: φ250 | FB24: 個 | FC24: 6400 | FD24: =FC24*0.65 -> 4160 | FE24: 0.18 | GE24: 051056000 | GF24: ﾊｳｽｶｵﾝｷ（13Aｶﾞｽ焚き） | GG24: HK4030TCN | GH24: 台 | GI24: 1919000 | GJ24: 735170 | GK24: 1.7 | GV24: SGPｴﾛﾌｨﾝﾁｭｰﾌﾞ | GW24: 40A 25F 3000L | GX24: 本 | GY24: =ROUND(GZ24/0.33,-3) -> 95000 | GZ24: 31400 | HA24: 0.4
B25: 24 | C25: ｵｲﾙﾀﾝｸ・消防関連 | D25: eb3 | E25: 矩体の孔明け補修工事 | K25: 050746000 | L25: ﾊｳｽｶｵﾝｷ | M25: HK8030FFV | N25: 台 | O25: 2572000 | P25: 1089470 | Q25: 2.8 | S25: 031617000 | T25: ｸﾞﾛｳｴｱ（LPガス焚き） | U25: CG-205SL | V25: 台 | W25: 247000 | X25: 117150 | AJ25: ----------- | AQ25: 042033000 | AR25: ｵｰﾄｶﾝ | AS25: AWH-701GBL | AT25: 台 | AU25: 2066000 | AV25: 564960 | AW25: 1.55 | BP25: ｴﾛﾌｨﾝﾁｭｰﾌﾞ（STK 5KF） | BQ25: 40A 25F 2750L | BR25: 本 | BS25: =ROUND(BT25/0.4,-3) -> 74000 | BT25: 29500 | BU25: 0.36 | CV25: ﾗｲﾝﾎﾟﾝﾌﾟ | CW25: 50Hz φ65 5.5kW | CX25: 台 | CY25: 585000 | CZ25: =ROUND(CY25*0.53,-1) -> 310050 | DA25: 1.2 | DT25: 同上架台 | DU25: 溶融亜鉛メッキ（SS400) 500H 150用 | DV25: 組 | DW25: 83000 | DX25: 45700 | DY25: 0.3 | EB25: 防油堤 | EC25: BYT-490K | ED25: 基 | EE25: 233300 | EF25: 116650 | EG25: 2.3 | EI25: 181571000 | EJ25: 煙突直管 | EK25: φ150 | EL25: 本 | EM25: 9930 | EN25: 2290 | EO25: 0.1 | EQ25: RE0000084 | ER25: ｸﾛｽﾗﾑﾀﾞｸﾄ | ES25: 折幅630×50m | ET25: 本 | EU25: 35400 | EV25: 19430 | EW25: 0 | EZ25: ﾀﾞｸﾄﾍﾞﾝﾄﾞ(亜鉛) | FA25: φ300 | FB25: 個 | FC25: 9000 | FD25: =FC25*0.65 -> 5850 | FE25: 0.18 | GE25: 051066000 | GF25: ﾊｳｽｶｵﾝｷ（13Aｶﾞｽ焚き） | GG25: HK4030TEN | GH25: 台 | GI25: 1969000 | GJ25: 763820 | GK25: 1.7 | GV25: SGPｴﾛﾌｨﾝﾁｭｰﾌﾞ | GW25: 40A 25F 2750L | GX25: 本 | GY25: =ROUND(GZ25/0.33,-3) -> 94000 | GZ25: 30900 | HA25: 0.36
B26: 25 | C26: ｽﾊﾟｲﾗﾙﾀﾞｸﾄ | D26: ez3 | E26: 孔明け補修工事 | L26: ---------- | S26: 041665000 | T26: CG-205用架台セット | U26: BCK-1100 | V26: ｾｯﾄ | W26: 48600 | X26: 19220 | AI26: 043555000 | AJ26: ｼﾝｸﾛﾋｰﾀ | AK26: SBM150UNT_2 | AL26: 台 | AM26: 5177000 | AN26: 1401900 | AO26: 3 | AQ26: 042035000 | AR26: ｵｰﾄｶﾝ | AS26: AWH-801GBL | AT26: 台 | AU26: 2188000 | AV26: 633350 | AW26: 1.65 | BP26: ｴﾛﾌｨﾝﾁｭｰﾌﾞ（STK 5KF） | BQ26: 40A 25F 2000L | BR26: 本 | BS26: =ROUND(BT26/0.4,-3) -> 70000 | BT26: 27900 | BU26: 0.26 | CV26: ---------- | DT26: ---------- | EB26: 防油堤 | EC26: NS1.9A(ﾌﾟﾚｷｬｽﾄ) | ED26: 基 | EE26: 280000 | EF26: 68750 | EG26: 5 | EI26: 131575000 | EJ26: 煙突直管 | EK26: φ175 | EL26: 本 | EM26: 11300 | EN26: 1880 | EO26: 0.1 | EQ26: RE0000085 | ER26: ｸﾛｽﾗﾑﾀﾞｸﾄ | ES26: 折幅630×100m | ET26: 本 | EU26: 69400 | EV26: 38790 | EW26: 0 | EZ26: ﾀﾞｸﾄﾍﾞﾝﾄﾞ(亜鉛) | FA26: φ350 | FB26: 個 | FC26: 11300 | FD26: =FC26*0.65 -> 7345 | FE26: 0.19 | GE26: 051074000 | GF26: ﾊｳｽｶｵﾝｷ（13Aｶﾞｽ焚き） | GG26: HK4030TFN | GH26: 台 | GI26: 1877000 | GJ26: 693090 | GK26: 1.7 | GV26: SGPｴﾛﾌｨﾝﾁｭｰﾌﾞ | GW26: 40A 25F 2000L | GX26: 本 | GY26: =ROUND(GZ26/0.33,-3) -> 87000 | GZ26: 28800 | HA26: 0.26
B27: 26 | C27: ｱﾙﾐﾌﾚｷﾀﾞｸﾄ | D27: fh3 | E27: ﾀﾞｸﾄ敷設工事 | K27: 052771000 | L27: ﾊｳｽｶｵﾝｷ | M27: HK2029TCV | N27: 台 | O27: 797000 | P27: 383340 | Q27: 1.25 | S27: 051167000 | T27: ｸﾞﾛｳｴｱ（LPガス焚き） | U27: CG-254S1G | V27: 台 | W27: 501000 | X27: 279060 | Y27: 0.5 | AI27: 043557000 | AJ27: ｼﾝｸﾛﾋｰﾀ | AK27: SBM150ULT_2 | AL27: 台 | AM27: 5177000 | AN27: 1399060 | AO27: 3 | AQ27: 042037000 | AR27: ｵｰﾄｶﾝ | AS27: AWH-901GBL | AT27: 台 | AU27: 2264000 | AV27: 639410 | AW27: 1.75 | BP27: ｴﾛﾌｨﾝﾁｭｰﾌﾞ（STK 5KF） | BQ27: 40A 25F 1500L | BR27: 本 | BS27: =ROUND(BT27/0.4,-3) -> 68000 | BT27: 27200 | BU27: 0.2 | CV27: ﾗｲﾝﾎﾟﾝﾌﾟ | CW27: 50Hz φ80 1.5kW | CX27: 台 | CY27: 302000 | CZ27: =ROUND(CY27*0.53,-1) -> 160060 | DA27: 0.9 | DT27: 密閉膨張ﾀﾝｸ | DU27: ER-8 5.3L | DV27: 基 | DW27: 22000 | DX27: 12100 | DY27: 0.3 | EI27: 308714000 | EJ27: 煙突直管 | EK27: φ225 | EL27: 本 | EM27: 12600 | EN27: 3340 | EO27: 0.1 | EQ27: RE0000086 | ER27: ｸﾛｽﾗﾑﾀﾞｸﾄ | ES27: 折幅900×15m | ET27: 本 | EU27: 15300 | EV27: 8240 | EW27: 0 | EZ27: ﾀﾞｸﾄﾍﾞﾝﾄﾞ(亜鉛) | FA27: φ400 | FB27: 個 | FC27: 15500 | FD27: =FC27*0.65 -> 10075 | FE27: 0.19 | GE27: 051058000 | GF27: ﾊｳｽｶｵﾝｷ（13Aｶﾞｽ焚き） | GG27: HK5030TCN | GH27: 台 | GI27: 2098000 | GJ27: 824320 | GK27: 2 | GV27: SGPｴﾛﾌｨﾝﾁｭｰﾌﾞ | GW27: 40A 25F 1500L | GX27: 本 | GY27: =ROUND(GZ27/0.33,-3) -> 84000 | GZ27: 27600 | HA27: 0.2
B28: 27 | C28: ﾌﾚｯｼｬｰｼﾘｰｽﾞ | D28: fh22 | E28: 消耗品雑材 | K28: 052772000 | L28: ﾊｳｽｶｵﾝｷ | M28: HK2029TEV | N28: 台 | O28: 821000 | P28: 393450 | Q28: 1.25 | S28: 051168000 | T28: ｸﾞﾛｳｴｱ（LPガス焚き） | U28: CG-254S2G | V28: 台 | W28: 518000 | X28: 288220 | Y28: 0.5 | AJ28: ----------- | AQ28: 042039000 | AR28: ｵｰﾄｶﾝ | AS28: AWH-1001GBL | AT28: 台 | AU28: 2431000 | AV28: 638120 | AW28: 1.9 | BP28: ｴﾛﾌｨﾝﾁｭｰﾌﾞ（STK 5KF） | BQ28: 40A 25F 1000L | BR28: 本 | BS28: =ROUND(BT28/0.4,-3) -> 65000 | BT28: 25800 | BU28: 0.13 | CV28: ﾗｲﾝﾎﾟﾝﾌﾟ | CW28: 50Hz φ80 2.2kW | CX28: 台 | CY28: 351000 | CZ28: =ROUND(CY28*0.53,-1) -> 186030 | DA28: 1 | DT28: 密閉膨張ﾀﾝｸ | DU28: ER-18 11.4L | DV28: 基 | DW28: 37000 | DX28: 20350 | DY28: 0.5 | EI28: 131555000 | EJ28: 煙突直管 | EK28: φ250 | EL28: 本 | EM28: 16400 | EN28: 3440 | EO28: 0.15 | EQ28: RE0000087 | ER28: ｸﾛｽﾗﾑﾀﾞｸﾄ | ES28: 折幅900×20m | ET28: 本 | EU28: 20300 | EV28: 10890 | EW28: 0 | EZ28: ﾀﾞｸﾄﾍﾞﾝﾄﾞ(亜鉛) | FA28: φ450 | FB28: 個 | FC28: 18900 | FD28: =FC28*0.65 -> 12285 | FE28: 0.2 | GE28: 051068000 | GF28: ﾊｳｽｶｵﾝｷ（13Aｶﾞｽ焚き） | GG28: HK5030TEN | GH28: 台 | GI28: 2168000 | GJ28: 902150 | GK28: 2 | GV28: SGPｴﾛﾌｨﾝﾁｭｰﾌﾞ | GW28: 40A 25F 1000L | GX28: 本 | GY28: =ROUND(GZ28/0.33,-3) -> 79000 | GZ28: 26200 | HA28: 0.13
K29: 052773000 | L29: ﾊｳｽｶｵﾝｷ | M29: HK3029TCV | N29: 台 | O29: 982000 | P29: 403820 | Q29: 1.45 | S29: 051169000 | T29: ｸﾞﾛｳｴｱ（LPガス焚き） | U29: CG-554TG2 | V29: 台 | W29: 684000 | X29: 291190 | Y29: 0.7 | AJ29: ｼﾝｸﾛﾋｰﾀ（A重油焚き） | AK29: SBB-1002HA | AL29: 台 | AM29: 9500000 | AN29: 3500000 | AO29: 7 | AQ29: 042041000 | AR29: ｵｰﾄｶﾝ | AS29: AWH-1201GBL | AT29: 台 | AU29: 2800000 | AV29: 757460 | AW29: 2.05 | BP29: ---------- | CV29: ﾗｲﾝﾎﾟﾝﾌﾟ | CW29: 50Hz φ80 3.7kW | CX29: 台 | CY29: 466000 | CZ29: =ROUND(CY29*0.53,-1) -> 246980 | DA29: 1 | DT29: 密閉膨張ﾀﾝｸ | DU29: ER-24 16.3L | DV29: 基 | DW29: 51000 | DX29: 28050 | DY29: 0.75 | EJ29: 煙突直管 | EK29: φ300 | EL29: 本 | EM29: 42600 | EN29: 19170 | EO29: 0.2 | EQ29: RE0000088 | ER29: ｸﾛｽﾗﾑﾀﾞｸﾄ | ES29: 折幅900×30m | ET29: 本 | EU29: 29000 | EV29: 16210 | EW29: 0 | EZ29: ﾀﾞｸﾄﾍﾞﾝﾄﾞ(亜鉛) | FA29: φ500 | FB29: 個 | FC29: 22900 | FD29: =FC29*0.65 -> 14885 | FE29: 0.2 | GE29: 051076000 | GF29: ﾊｳｽｶｵﾝｷ（13Aｶﾞｽ焚き） | GG29: HK5030TFN | GH29: 台 | GI29: 2048000 | GJ29: 791160 | GK29: 2 | GV29: ----------
K30: 052774000 | L30: ﾊｳｽｶｵﾝｷ | M30: HK3029TEV | N30: 台 | O30: 990000 | P30: 420930 | Q30: 1.45 | AJ30: 旧型 ｼﾝｸﾛﾋｰﾀ(LPG焚・中圧仕様) | AK30: SBB-1002HL | AL30: 台 | AM30: 9500000 | AN30: 3500000 | AO30: 7 | AQ30: 042043000 | AR30: ｵｰﾄｶﾝ | AS30: AWH-1501GBL | AT30: 台 | AU30: 3042000 | AV30: 752560 | AW30: 2.3 | BP30: ｴﾛﾌｨﾝﾁｭｰﾌﾞ（STK 5KF） | BQ30: 40A 32F 5500L | BR30: 本 | BS30: =ROUND(BT30/0.4,-3) -> 96000 | BT30: 38200 | BU30: 0.72 | CV30: ﾗｲﾝﾎﾟﾝﾌﾟ | CW30: 50Hz φ80 5.5kW | CX30: 台 | CY30: 592000 | CZ30: =ROUND(CY30*0.53,-1) -> 313760 | DA30: 1.2 | DT30: 密閉膨張ﾀﾝｸ | DU30: ER-35 23.8L | DV30: 基 | DW30: 69000 | DX30: 37950 | DY30: 1 | EJ30: 煙突直管 | EK30: φ350 | EL30: 本 | EM30: 51800 | EN30: 23310 | EO30: 0.2 | EQ30: RE0000089 | ER30: ｸﾛｽﾗﾑﾀﾞｸﾄ | ES30: 折幅900×40m | ET30: 本 | EU30: 39200 | EV30: 21700 | EW30: 0 | EZ30: ﾀﾞｸﾄﾍﾞﾝﾄﾞ(亜鉛) | FA30: φ550 | FB30: 個 | FC30: 27300 | FD30: =FC30*0.65 -> 17745 | FE30: 0.2 | GE30: 051060000 | GF30: ﾊｳｽｶｵﾝｷ（13Aｶﾞｽ焚き） | GG30: HK6030TCN | GH30: 台 | GI30: 2307000 | GJ30: 882310 | GK30: 2.2 | GV30: SGPｴﾛﾌｨﾝﾁｭｰﾌﾞ | GW30: 40A 32F 5500L | GX30: 本 | GY30: =ROUND(GZ30/0.33,-3) -> 124000 | GZ30: 41000 | HA30: 0.72
K31: 052775000 | L31: ﾊｳｽｶｵﾝｷ | M31: HK4029TCV | N31: 台 | O31: 1221000 | P31: 482640 | Q31: 1.7 | AJ31: ｼﾝｸﾛﾋｰﾀ(13A焚・中圧仕様) | AK31: SBB-1002HN | AL31: 台 | AM31: 9500000 | AN31: 3500000 | AO31: 7 | AQ31: 042045000 | AR31: ｵｰﾄｶﾝ | AS31: AWH-1801GBL | AT31: 台 | AU31: 3348000 | AV31: 760300 | AW31: 2.6 | BP31: ｴﾛﾌｨﾝﾁｭｰﾌﾞ（STK 5KF） | BQ31: 40A 32F 4000L | BR31: 本 | BS31: =ROUND(BT31/0.4,-3) -> 84000 | BT31: 33600 | BU31: 0.52 | CV31: ﾗｲﾝﾎﾟﾝﾌﾟ | CW31: 50Hz φ80 7.5kW | CX31: 台 | CY31: 674000 | CZ31: =ROUND(CY31*0.53,-1) -> 357220 | DA31: 1.5 | DT31: 密閉膨張ﾀﾝｸ | DU31: ER-50 30.0L | DV31: 基 | DW31: 84000 | DX31: 46200 | DY31: 1.25 | EI31: 308796000 | EJ31: 煙突半直管 | EK31: φ120 | EL31: 本 | EM31: 5170 | EN31: 1040 | EO31: 0.1 | EQ31: RE0000090 | ER31: ｸﾛｽﾗﾑﾀﾞｸﾄ | ES31: 折幅900×50m | ET31: 本 | EU31: 49300 | EV31: 26850 | EW31: 0 | EZ31: ﾀﾞｸﾄﾍﾞﾝﾄﾞ(亜鉛) | FA31: φ600 | FB31: 個 | FC31: 31700 | FD31: =FC31*0.65 -> 20605 | FE31: 0.24 | GE31: 051070000 | GF31: ﾊｳｽｶｵﾝｷ（13Aｶﾞｽ焚き） | GG31: HK6030TEN | GH31: 台 | GI31: 2381000 | GJ31: 974610 | GK31: 2.2 | GV31: SGPｴﾛﾌｨﾝﾁｭｰﾌﾞ | GW31: 40A 32F 4000L | GX31: 本 | GY31: =ROUND(GZ31/0.33,-3) -> 110000 | GZ31: 36200 | HA31: 0.52
K32: 052776000 | L32: ﾊｳｽｶｵﾝｷ | M32: HK4029TEV | N32: 台 | O32: 1283000 | P32: 508050 | Q32: 1.7 | AJ32: ｼﾝｸﾛﾋｰﾀ（LPG焚・超高効率仕様） | AK32: SBB-1005HL | AL32: 台 | AM32: 11500000 | AN32: 5400000 | AO32: 9 | AQ32: 042047000 | AR32: ｵｰﾄｶﾝ | AS32: AWH-2001GBL | AT32: 台 | AU32: 3499000 | AV32: 756820 | AW32: 2.75 | BP32: ｴﾛﾌｨﾝﾁｭｰﾌﾞ（STK 5KF） | BQ32: 40A 32F 3500L | BR32: 本 | BS32: =ROUND(BT32/0.4,-3) -> 82000 | BT32: 32800 | BU32: 0.46 | CV32: ﾗｲﾝﾎﾟﾝﾌﾟ | CW32: 50Hz φ80 11kW | CX32: 台 | CY32: 910000 | CZ32: =ROUND(CY32*0.53,-1) -> 482300 | DA32: 2 | DT32: ---------- | EI32: 308802000 | EJ32: 煙突半直管 | EK32: φ150 | EL32: 本 | EM32: 5960 | EN32: 1250 | EO32: 0.1 | EQ32: RE0000091 | ER32: ｸﾛｽﾗﾑﾀﾞｸﾄ | ES32: 折幅900×100m | ET32: 本 | EU32: 96000 | EV32: 53630 | EW32: 0 | EZ32: ﾀﾞｸﾄﾍﾞﾝﾄﾞ(SUS) | FA32: φ200 | FB32: 個 | FC32: 21300 | FD32: =FC32*0.65 -> 13845 | FE32: 0.16 | GE32: 051078000 | GF32: ﾊｳｽｶｵﾝｷ（13Aｶﾞｽ焚き） | GG32: HK6030TFN | GH32: 台 | GI32: 2131000 | GJ32: 843390 | GK32: 2.2 | GV32: SGPｴﾛﾌｨﾝﾁｭｰﾌﾞ | GW32: 40A 32F 3500L | GX32: 本 | GY32: =ROUND(GZ32/0.33,-3) -> 105000 | GZ32: 34600 | HA32: 0.46
K33: 052777000 | L33: ﾊｳｽｶｵﾝｷ | M33: HK5029TCV | N33: 台 | O33: 1430000 | P33: 589070 | Q33: 2 | AJ33: ----------- | AR33: ---------- | BP33: ｴﾛﾌｨﾝﾁｭｰﾌﾞ（STK 5KF） | BQ33: 40A 32F 3000L | BR33: 本 | BS33: =ROUND(BT33/0.4,-3) -> 79000 | BT33: 31500 | BU33: 0.4 | CV33: ---------- | DT33: 密閉膨張ﾀﾝｸ | DU33: JTX-80 50L | DV33: 基 | DW33: 107000 | DX33: 58850 | DY33: 2.25 | EI33: 313348000 | EJ33: 煙突半直管 | EK33: φ225 | EL33: 本 | EM33: 11000 | EN33: 1880 | EO33: 0.1 | EQ33: RE0000098 | ER33: ｸﾛｽﾗﾑﾀﾞｸﾄ | ES33: 折幅1100×15m | ET33: 本 | EU33: 17800 | EV33: 8950 | EW33: 0 | EZ33: ﾀﾞｸﾄﾍﾞﾝﾄﾞ(SUS) | FA33: φ225 | FB33: 個 | FC33: 25800 | FD33: =FC33*0.65 -> 16770 | FE33: 0.18 | GV33: SGPｴﾛﾌｨﾝﾁｭｰﾌﾞ | GW33: 40A 32F 3000L | GX33: 本 | GY33: =ROUND(GZ33/0.33,-3) -> 100000 | GZ33: 33000 | HA33: 0.4
C34: 【変更履歴】 | K34: 052778000 | L34: ﾊｳｽｶｵﾝｷ | M34: HK5029TEV | N34: 台 | O34: 1500000 | P34: 641450 | Q34: 2 | AJ34: ｼﾝｸﾛﾋｰﾀ(高温水仕様) | AK34: SB-306MＨ□Ｈ(油焚) | AL34: 台 | AM34: 5156000 | AN34: 1178400 | AQ34: 042028000 | AR34: ｵｰﾄｶﾝ | AS34: AWH-501GBN | AT34: 台 | AU34: 1900000 | AV34: 507680 | AW34: 1.3 | BP34: ｴﾛﾌｨﾝﾁｭｰﾌﾞ（STK 5KF） | BQ34: 40A 32F 2750L | BR34: 本 | BS34: =ROUND(BT34/0.4,-3) -> 77000 | BT34: 30900 | BU34: 0.36 | CV34: ﾗｲﾝﾎﾟﾝﾌﾟ | CW34: 60Hz φ25 0.15kW | CX34: 台 | CY34: 102000 | CZ34: =ROUND(CY34*0.53,-1) -> 54060 | DA34: 0.3 | DT34: 密閉膨張ﾀﾝｸ | DU34: JTX-100 63L | DV34: 基 | DW34: 153000 | DX34: 84150 | DY34: 2.5 | EI34: 322370000 | EJ34: 煙突半直管 | EK34: φ250 | EL34: 本 | EM34: 23700 | EN34: 4490 | EO34: 0.1 | EQ34: RE0000099 | ER34: ｸﾛｽﾗﾑﾀﾞｸﾄ | ES34: 折幅1100×20m | ET34: 本 | EU34: 25500 | EV34: 11810 | EW34: 0 | EZ34: ﾀﾞｸﾄﾍﾞﾝﾄﾞ(SUS) | FA34: φ250 | FB34: 個 | FC34: 30500 | FD34: =FC34*0.65 -> 19825 | FE34: 0.18 | GV34: SGPｴﾛﾌｨﾝﾁｭｰﾌﾞ | GW34: 40A 32F 2750L | GX34: 本 | GY34: =ROUND(GZ34/0.33,-3) -> 98000 | GZ34: 32300 | HA34: 0.36
C35: ’10.12訂正箇所 製品値上分 | K35: 052779000 | L35: ﾊｳｽｶｵﾝｷ | M35: HK5029TFV | N35: 台 | O35: 1360000 | P35: 557180 | Q35: 2 | AJ35: ｼﾝｸﾛﾋｰﾀ(高温水仕様) | AK35: SB-406MＨ□Ｈ(油焚) | AL35: 台 | AM35: 6783000 | AN35: 1550400 | AQ35: 042030000 | AR35: ｵｰﾄｶﾝ | AS35: AWH-601GBN | AT35: 台 | AU35: 1974000 | AV35: 561350 | AW35: 1.4 | BP35: ｴﾛﾌｨﾝﾁｭｰﾌﾞ（STK 5KF） | BQ35: 40A 32F 2000L | BR35: 本 | BS35: =ROUND(BT35/0.4,-3) -> 73000 | BT35: 29200 | BU35: 0.26 | CV35: ---------- | DT35: 密閉膨張ﾀﾝｸ | DU35: JTX-150 95L | DV35: 基 | DW35: 203000 | DX35: 111650 | DY35: 3 | EH35: =EF23/EE23 -> 0.6 | EJ35: ---------- | EQ35: RE0000100 | ER35: ｸﾛｽﾗﾑﾀﾞｸﾄ | ES35: 折幅1100×30m | ET35: 本 | EU35: 31500 | EV35: 17600 | EW35: 0 | EZ35: ﾀﾞｸﾄﾍﾞﾝﾄﾞ(SUS) | FA35: φ300 | FB35: 個 | FC35: 49100 | FD35: =FC35*0.65 -> 31915 | FE35: 0.18 | GV35: SGPｴﾛﾌｨﾝﾁｭｰﾌﾞ | GW35: 40A 32F 2000L | GX35: 本 | GY35: =ROUND(GZ35/0.33,-3) -> 91000 | GZ35: 29900 | HA35: 0.26
C36: ’10.11訂正箇所 部品値上分 | K36: 052780000 | L36: ﾊｳｽｶｵﾝｷ | M36: HK6029TCV | N36: 台 | O36: 1590000 | P36: 612410 | Q36: 2.2 | AJ36: ｼﾝｸﾛﾋｰﾀ(高温水仕様) | AK36: SB-506MＨ□Ｈ(油焚) | AL36: 台 | AM36: 7256000 | AN36: 1658400 | AQ36: 042032000 | AR36: ｵｰﾄｶﾝ | AS36: AWH-701GBN | AT36: 台 | AU36: 2066000 | AV36: 597350 | AW36: 1.55 | BP36: ｴﾛﾌｨﾝﾁｭｰﾌﾞ（STK 5KF） | BQ36: 40A 32F 1500L | BR36: 本 | BS36: =ROUND(BT36/0.4,-3) -> 69000 | BT36: 27600 | BU36: 0.2 | CV36: ﾗｲﾝﾎﾟﾝﾌﾟ | CW36: 60Hz φ32 0.25kW | CX36: 台 | CY36: 139000 | CZ36: =ROUND(CY36*0.53,-1) -> 73670 | DA36: 0.3 | DT36: 密閉膨張ﾀﾝｸ | DU36: JTX-200 120L | DV36: 基 | DW36: 273000 | DX36: 150150 | DY36: 3 | EH36: =EF24/EE24 -> 0.6 | EI36: 308799000 | EJ36: 煙突ｴﾋﾞﾏｶﾞﾘ | EK36: φ120 | EL36: 個 | EM36: 6490 | EN36: 1360 | EO36: 0.1 | EQ36: RE0000101 | ER36: ｸﾛｽﾗﾑﾀﾞｸﾄ | ES36: 折幅1100×40m | ET36: 本 | EU36: 43000 | EV36: 23550 | EW36: 0 | EZ36: ﾀﾞｸﾄﾍﾞﾝﾄﾞ(SUS) | FA36: φ350 | FB36: 個 | FC36: 59100 | FD36: =FC36*0.65 -> 38415 | FE36: 0.19 | GV36: SGPｴﾛﾌｨﾝﾁｭｰﾌﾞ | GW36: 40A 32F 1500L | GX36: 本 | GY36: =ROUND(GZ36/0.33,-3) -> 86000 | GZ36: 28300 | HA36: 0.2
C37: ’11.05訂正箇所 値上・原価訂正 | K37: 052781000 | L37: ﾊｳｽｶｵﾝｷ | M37: HK6029TEV | N37: 台 | O37: 1635000 | P37: 679300 | Q37: 2.2 | AJ37: ----------- | AQ37: 042034000 | AR37: ｵｰﾄｶﾝ | AS37: AWH-801GBN | AT37: 台 | AU37: 2188000 | AV37: 679150 | AW37: 1.65 | BP37: ｴﾛﾌｨﾝﾁｭｰﾌﾞ（STK 5KF） | BQ37: 40A 32F 1000L | BR37: 本 | BS37: =ROUND(BT37/0.4,-3) -> 66000 | BT37: 26300 | BU37: 0.13 | CV37: ﾗｲﾝﾎﾟﾝﾌﾟ | CW37: 60Hz φ32 0.4kW | CX37: 台 | CY37: 162000 | CZ37: =ROUND(CY37*0.53,-1) -> 85860 | DA37: 0.5 | DT37: 密閉膨張ﾀﾝｸ | DU37: JTX-300 190L | DV37: 基 | DW37: 369000 | DX37: 202950 | DY37: 3.5 | EH37: =EF25/EE25 -> 0.5 | EI37: 131776000 | EJ37: 煙突ｴﾋﾞﾏｶﾞﾘ | EK37: φ175 | EL37: 個 | EM37: 12700 | EN37: 2090 | EO37: 0.1 | EQ37: RE0000102 | ER37: ｸﾛｽﾗﾑﾀﾞｸﾄ | ES37: 折幅1100×50m | ET37: 本 | EU37: 52900 | EV37: 29140 | EW37: 0 | EZ37: ﾀﾞｸﾄﾍﾞﾝﾄﾞ(SUS) | FA37: φ400 | FB37: 個 | FC37: 72600 | FD37: =FC37*0.65 -> 47190 | FE37: 0.19 | GV37: SGPｴﾛﾌｨﾝﾁｭｰﾌﾞ | GW37: 40A 32F 1000L | GX37: 本 | GY37: =ROUND(GZ37/0.33,-3) -> 81000 | GZ37: 26700 | HA37: 0.13
C38: ’14.08 価格・構成見直しにつき、再構成 | K38: 052782000 | L38: ﾊｳｽｶｵﾝｷ | M38: HK6029TFV | N38: 台 | O38: 1550000 | P38: 574680 | Q38: 2.2 | AJ38: ｼﾝｸﾛﾋｰﾀ(高温水仕様) | AK38: SB-306MＨ□Ｈ(ｶﾞｽ焚) | AL38: 台 | AM38: 6794000 | AN38: 1552800 | AQ38: 042036000 | AR38: ｵｰﾄｶﾝ | AS38: AWH-901GBN | AT38: 台 | AU38: 2264000 | AV38: 667280 | AW38: 1.75 | BP38: ---------- | CV38: ﾗｲﾝﾎﾟﾝﾌﾟ | CW38: 60Hz φ32 0.75kW | CX38: 台 | CY38: 205000 | CZ38: =ROUND(CY38*0.53,-1) -> 108650 | DA38: 0.5 | DT38: ---------- | EH38: =EF26/EE26 -> 0.24553571 | EI38: 313349000 | EJ38: 煙道ｴﾙﾎﾞ | EK38: φ150 | EL38: 個 | EM38: 7210 | EN38: 1560 | EO38: 0.1 | EQ38: RE0000103 | ER38: ｸﾛｽﾗﾑﾀﾞｸﾄ | ES38: 折幅1100×100m | ET38: 本 | EU38: 104900 | EV38: 58190 | EW38: 0 | EZ38: ﾀﾞｸﾄﾍﾞﾝﾄﾞ(SUS) | FA38: φ450 | FB38: 個 | FC38: 86900 | FD38: =FC38*0.65 -> 56485 | FE38: 0.2 | GV38: ----------
C39: 69期農用機器･熱機器･KHV･ｻｰﾋﾞｽ部品価格表対応 | AJ39: ｼﾝｸﾛﾋｰﾀ(高温水仕様) | AK39: SB-406MＨ□Ｈ(ｶﾞｽ焚) | AL39: 台 | AM39: 9072000 | AN39: 2073600 | AQ39: 042038000 | AR39: ｵｰﾄｶﾝ | AS39: AWH-1001GBN | AT39: 台 | AU39: 2431000 | AV39: 680180 | AW39: 1.9 | BP39: ｴﾛﾌｨﾝﾁｭｰﾌﾞ（STK 5KF） | BQ39: 50A 25F 5500L | BR39: 本 | BS39: =ROUND(BT39/0.4,-3) -> 94000 | BT39: 37700 | BU39: 0.94 | CV39: ﾗｲﾝﾎﾟﾝﾌﾟ | CW39: 60Hz φ32 1.5kW | CX39: 台 | CY39: 267000 | CZ39: =ROUND(CY39*0.53,-1) -> 141510 | DA39: 0.5 | DT39: 密閉膨張ﾀﾝｸ | DU39: AFX-200ＮＸ | DV39: 基 | DW39: 1011000 | DX39: 556050 | DY39: 3 | EI39: 131637000 | EJ39: 煙道ｴﾙﾎﾞ | EK39: φ225 | EL39: 個 | EM39: 16000 | EN39: 2820 | EO39: 0.1 | ER39: ---------- | EZ39: ﾀﾞｸﾄﾍﾞﾝﾄﾞ(SUS) | FA39: φ500 | FB39: 個 | FC39: 102600 | FD39: =FC39*0.65 -> 66690 | FE39: 0.2 | GV39: SGPｴﾛﾌｨﾝﾁｭｰﾌﾞ | GW39: 50A 25F 5500L | GX39: 本 | GY39: =ROUND(GZ39/0.33,-3) -> 127000 | GZ39: 42000 | HA39: 0.94
C40: 70期価格修正 | AJ40: ｼﾝｸﾛﾋｰﾀ(高温水仕様) | AK40: SB-506MＨ□Ｈ(ｶﾞｽ焚) | AL40: 台 | AM40: 10143000 | AN40: 2318400 | AQ40: 042040000 | AR40: ｵｰﾄｶﾝ | AS40: AWH-1201GBN | AT40: 台 | AU40: 2800000 | AV40: 757460 | AW40: 2.05 | BP40: ｴﾛﾌｨﾝﾁｭｰﾌﾞ（STK 5KF） | BQ40: 50A 25F 4000L | BR40: 本 | BS40: =ROUND(BT40/0.4,-3) -> 86000 | BT40: 34200 | BU40: 0.68 | CV40: ---------- | DT40: 密閉膨張ﾀﾝｸ | DU40: AFX-300ＮＸ | DV40: 基 | DW40: 1117000 | DX40: 614350 | DY40: 3 | EI40: 131775000 | EJ40: 煙道ｴﾙﾎﾞ | EK40: φ250 | EL40: 個 | EM40: 30900 | EN40: 4280 | EO40: 0.15 | EQ40: RE0000104 | ER40: ｺｰﾅｰﾀﾞｸﾄ | ES40: L-63 | ET40: 個 | EU40: 19400 | EV40: 9000 | EW40: 0 | EZ40: ﾀﾞｸﾄﾍﾞﾝﾄﾞ(SUS) | FA40: φ550 | FB40: 個 | FC40: 114800 | FD40: =FC40*0.65 -> 74620 | FE40: 0.2 | GV40: SGPｴﾛﾌｨﾝﾁｭｰﾌﾞ | GW40: 50A 25F 4000L | GX40: 本 | GY40: =ROUND(GZ40/0.33,-3) -> 112000 | GZ40: 37000 | HA40: 0.68
C41: 71期価格修正 | AJ41: ----------- | AQ41: 042042000 | AR41: ｵｰﾄｶﾝ | AS41: AWH-1501GBN | AT41: 台 | AU41: 3042000 | AV41: 757590 | AW41: 2.3 | BP41: ｴﾛﾌｨﾝﾁｭｰﾌﾞ（STK 5KF） | BQ41: 50A 25F 3500L | BR41: 本 | BS41: =ROUND(BT41/0.4,-3) -> 81000 | BT41: 32500 | BU41: 0.6 | CV41: ﾗｲﾝﾎﾟﾝﾌﾟ | CW41: 60Hz φ40 0.4kW | CX41: 台 | CY41: 182000 | CZ41: =ROUND(CY41*0.53,-1) -> 96460 | DA41: 0.5 | DT41: 密閉膨張ﾀﾝｸ | DU41: AFX-400ＮＸ | DV41: 基 | DW41: 1278000 | DX41: 702900 | DY41: 3.5 | EJ41: 煙道ｴﾙﾎﾞ | EK41: φ300 | EL41: 個 | EM41: 67400 | EN41: 30330 | EO41: 0.2 | EQ41: RE0000105 | ER41: ｺｰﾅｰﾀﾞｸﾄ | ES41: L-90 | ET41: 個 | EU41: 23000 | EV41: 10900 | EW41: 0 | EZ41: ﾀﾞｸﾄﾍﾞﾝﾄﾞ(SUS) | FA41: φ600 | FB41: 個 | FC41: 127700 | FD41: =FC41*0.65 -> 83005 | FE41: 0.24 | GV41: SGPｴﾛﾌｨﾝﾁｭｰﾌﾞ | GW41: 50A 25F 3500L | GX41: 本 | GY41: =ROUND(GZ41/0.33,-3) -> 107000 | GZ41: 35200 | HA41: 0.6
C42: 19.02断熱マット追加 | AJ42: ｼﾝｸﾛﾋｰﾀ(高温水仕様) | AK42: SBR-106MH□Ｈ(油焚) | AL42: 台 | AM42: 2940000 | AN42: 672000 | AQ42: 042044000 | AR42: ｵｰﾄｶﾝ | AS42: AWH-1801GBN | AT42: 台 | AU42: 3348000 | AV42: 825070 | AW42: 2.6 | BP42: ｴﾛﾌｨﾝﾁｭｰﾌﾞ（STK 5KF） | BQ42: 50A 25F 3000L | BR42: 本 | BS42: =ROUND(BT42/0.4,-3) -> 78000 | BT42: 31200 | BU42: 0.55 | CV42: ﾗｲﾝﾎﾟﾝﾌﾟ | CW42: 60Hz φ40 0.75kW | CX42: 台 | CY42: 200000 | CZ42: =ROUND(CY42*0.53,-1) -> 106000 | DA42: 0.5 | DT42: 密閉膨張ﾀﾝｸ | DU42: AFX-500ＮＸ | DV42: 基 | DW42: 1380000 | DX42: 759000 | DY42: 3.5 | EJ42: 煙道ｴﾙﾎﾞ | EK42: φ350 | EL42: 個 | EM42: 88800 | EN42: 39960 | EO42: 0.2 | EQ42: RE0000106 | ER42: ｺｰﾅｰﾀﾞｸﾄ | ES42: L-110 | ET42: 個 | EU42: 28100 | EV42: 13300 | EW42: 0 | EZ42: ﾀﾞｸﾄﾁｰｽﾞ(亜鉛) | FA42: φ300 | FB42: 個 | FC42: 8300 | FD42: =FC42*0.65 -> 5395 | FE42: 0.16 | GV42: SGPｴﾛﾌｨﾝﾁｭｰﾌﾞ | GW42: 50A 25F 3000L | GX42: 本 | GY42: =ROUND(GZ42/0.33,-3) -> 102000 | GZ42: 33600 | HA42: 0.55
C43: 72期価格修正 | AJ43: ｼﾝｸﾛﾋｰﾀ(高温水仕様) | AK43: SBR-136MH□Ｈ(油焚) | AL43: 台 | AM43: 3108000 | AN43: 710400 | AQ43: 042046000 | AR43: ｵｰﾄｶﾝ | AS43: AWH-2001GBN | AT43: 台 | AU43: 3499000 | AV43: 825070 | AW43: 2.75 | BP43: ｴﾛﾌｨﾝﾁｭｰﾌﾞ（STK 5KF） | BQ43: 50A 25F 2750L | BR43: 本 | BS43: =ROUND(BT43/0.4,-3) -> 76000 | BT43: 30500 | BU43: 0.47 | CV43: ﾗｲﾝﾎﾟﾝﾌﾟ | CW43: 60Hz φ40 1.5kW | CX43: 台 | CY43: 263000 | CZ43: =ROUND(CY43*0.53,-1) -> 139390 | DA43: 0.6 | DT43: 密閉膨張ﾀﾝｸ | DU43: AFX-600ＮＸ | DV43: 基 | DW43: 1660000 | DX43: 913000 | DY43: 4 | EI43: 329799000 | EJ43: 煙突H型 | EK43: φ120 | EL43: 個 | EM43: 15000 | EN43: 2920 | EO43: 0.1 | EQ43: RE0000107 | ER43: ｺｰﾅｰﾀﾞｸﾄ | ES43: T-63 | ET43: 個 | EU43: 26100 | EV43: 12500 | EW43: 0 | EZ43: ﾀﾞｸﾄﾁｰｽﾞ(亜鉛) | FA43: φ350 | FB43: 個 | FC43: 11000 | FD43: =FC43*0.65 -> 7150 | FE43: 0.18 | GV43: SGPｴﾛﾌｨﾝﾁｭｰﾌﾞ | GW43: 50A 25F 2750L | GX43: 本 | GY43: =ROUND(GZ43/0.33,-3) -> 99000 | GZ43: 32800 | HA43: 0.47
C44: 73期価格修正 | AJ44: ｼﾝｸﾛﾋｰﾀ(高温水仕様) | AK44: SBR-166MH□Ｈ(油焚) | AL44: 台 | AM44: 3318000 | AN44: 758400 | BP44: ｴﾛﾌｨﾝﾁｭｰﾌﾞ（STK 5KF） | BQ44: 50A 25F 2000L | BR44: 本 | BS44: =ROUND(BT44/0.4,-3) -> 72000 | BT44: 28800 | BU44: 0.34 | CV44: ﾗｲﾝﾎﾟﾝﾌﾟ | CW44: 60Hz φ40 2.2kW | CX44: 台 | CY44: 327000 | CZ44: =ROUND(CY44*0.53,-1) -> 173310 | DA44: 0.6 | DT44: 密閉膨張ﾀﾝｸ | DU44: AFX-800ＮＸ | DV44: 基 | DW44: 1978000 | DX44: 1087900 | DY44: 4 | EI44: 308409000 | EJ44: 煙突H型 | EK44: φ150 | EL44: 個 | EM44: 28900 | EN44: 6260 | EO44: 0.1 | EQ44: RE0000108 | ER44: ｺｰﾅｰﾀﾞｸﾄ | ES44: T-90 | ET44: 個 | EU44: 32200 | EV44: 15400 | EW44: 0 | EZ44: ﾀﾞｸﾄﾁｰｽﾞ(亜鉛) | FA44: φ400 | FB44: 個 | FC44: 15300 | FD44: =FC44*0.65 -> 9945 | FE44: 0.18 | GV44: SGPｴﾛﾌｨﾝﾁｭｰﾌﾞ | GW44: 50A 25F 2000L | GX44: 本 | GY44: =ROUND(GZ44/0.33,-3) -> 92000 | GZ44: 30400 | HA44: 0.34
C45: 74期価格修正 | AJ45: ｼﾝｸﾛﾋｰﾀ(高温水仕様) | AK45: SBR-206MH□Ｈ(油焚) | AL45: 台 | AM45: 4274000 | AN45: 976800 | BP45: ｴﾛﾌｨﾝﾁｭｰﾌﾞ（STK 5KF） | BQ45: 50A 25F 1500L | BR45: 本 | BS45: =ROUND(BT45/0.4,-3) -> 69000 | BT45: 27400 | BU45: 0.26 | CV45: ﾗｲﾝﾎﾟﾝﾌﾟ | CW45: 60Hz φ40 3.7kW | CX45: 台 | CY45: 396000 | CZ45: =ROUND(CY45*0.53,-1) -> 209880 | DA45: 0.7 | DT45: 密閉膨張ﾀﾝｸ | DU45: AFX-1000ＮＸ | DV45: 基 | DW45: 2300000 | DX45: 1265000 | DY45: 4.5 | EI45: 308411000 | EJ45: 煙突H型 | EK45: φ225 | EL45: 個 | EM45: 45700 | EN45: 14290 | EO45: 0.1 | EQ45: RE0000109 | ER45: ｺｰﾅｰﾀﾞｸﾄ | ES45: T-110 | ET45: 個 | EU45: 38400 | EV45: 18800 | EW45: 0 | EZ45: ﾀﾞｸﾄﾁｰｽﾞ(亜鉛) | FA45: φ450 | FB45: 個 | FC45: 18800 | FD45: =FC45*0.65 -> 12220 | FE45: 0.18 | GV45: SGPｴﾛﾌｨﾝﾁｭｰﾌﾞ | GW45: 50A 25F 1500L | GX45: 本 | GY45: =ROUND(GZ45/0.33,-3) -> 87000 | GZ45: 28600 | HA45: 0.26
C46: 75期価格修正 | AJ46: ｼﾝｸﾛﾋｰﾀ(高温水仕様) | AK46: SBR-256MH□Ｈ(油焚) | AL46: 台 | AM46: 4641000 | AN46: 1060800 | BP46: ｴﾛﾌｨﾝﾁｭｰﾌﾞ（STK 5KF） | BQ46: 50A 25F 1000L | BR46: 本 | BS46: =ROUND(BT46/0.4,-3) -> 66000 | BT46: 26200 | BU46: 0.17 | CV46: ---------- | DT46: 密閉膨張ﾀﾝｸ | DU46: AFX-1200ＮＸ | DV46: 基 | DW46: 2600000 | DX46: 1430000 | DY46: 4.5 | EJ46: Pﾄｯﾌﾟ | EK46: φ250 | EL46: 個 | EM46: 76300 | EN46: 34340 | EO46: 0.3 | ER46: ---------- | EZ46: ﾀﾞｸﾄﾁｰｽﾞ(亜鉛) | FA46: φ500 | FB46: 個 | FC46: 22100 | FD46: =FC46*0.65 -> 14365 | FE46: 0.2 | GV46: SGPｴﾛﾌｨﾝﾁｭｰﾌﾞ | GW46: 50A 25F 1000L | GX46: 本 | GY46: =ROUND(GZ46/0.33,-3) -> 82000 | GZ46: 27000 | HA46: 0.17
C47: 76期価格修正 | AJ47: ----------- | BP47: ---------- | CV47: ﾗｲﾝﾎﾟﾝﾌﾟ | CW47: 60Hz φ50 0.75kW | CX47: 台 | CY47: 214000 | CZ47: =ROUND(CY47*0.53,-1) -> 113420 | DA47: 0.6 | DT47: 密閉膨張ﾀﾝｸ | DU47: AFX-1400ＮＸ | DV47: 基 | DW47: 3020000 | DX47: 1661000 | DY47: 4.5 | EJ47: Pﾄｯﾌﾟ | EK47: φ300 | EL47: 個 | EM47: 105800 | EN47: 47610 | EO47: 0.3 | EQ47: 104027000 | ER47: ﾀﾞｸﾄｺﾈｸﾀｰ | ES47: DC-191 | ET47: ｾｯﾄ | EU47: 1990 | EV47: 620 | EW47: 0 | EZ47: ﾀﾞｸﾄﾁｰｽﾞ(亜鉛) | FA47: φ550 | FB47: 個 | FC47: 34400 | FD47: =FC47*0.65 -> 22360 | FE47: 0.2 | GV47: ----------
C48: 77期価格修正 | AJ48: ｼﾝｸﾛﾋｰﾀ(高温水仕様) | AK48: SBR-106MH□Ｈ(ｶﾞｽ焚) | AL48: 台 | AM48: 3623000 | AN48: 828000 | BP48: ｴﾛﾌｨﾝﾁｭｰﾌﾞ（STK 5KF） | BQ48: 50A 32F 5500L | BR48: 本 | BS48: =ROUND(BT48/0.4,-3) -> 101000 | BT48: 40500 | BU48: 0.94 | CV48: ﾗｲﾝﾎﾟﾝﾌﾟ | CW48: 60Hz φ50 1.5kW | CX48: 台 | CY48: 263000 | CZ48: =ROUND(CY48*0.53,-1) -> 139390 | DA48: 0.7 | DT48: ---------- | EJ48: Pﾄｯﾌﾟ | EK48: φ350 | EL48: 個 | EM48: 134400 | EN48: 60480 | EO48: 0.3 | EQ48: 104028000 | ER48: ﾀﾞｸﾄｺﾈｸﾀｰ | ES48: DC-251 | ET48: ｾｯﾄ | EU48: 2240 | EV48: 660 | EW48: 0 | EZ48: ﾀﾞｸﾄﾁｰｽﾞ(亜鉛) | FA48: φ600 | FB48: 個 | FC48: 39500 | FD48: =FC48*0.65 -> 25675 | FE48: 0.24 | GV48: SGPｴﾛﾌｨﾝﾁｭｰﾌﾞ | GW48: 50A 32F 5500L | GX48: 本 | GY48: =ROUND(GZ48/0.33,-3) -> 136000 | GZ48: 45000 | HA48: 0.94
C49: 78期価格修正 | AJ49: ｼﾝｸﾛﾋｰﾀ(高温水仕様) | AK49: SBR-136MH□Ｈ(ｶﾞｽ焚) | AL49: 台 | AM49: 4421000 | AN49: 1010400 | BP49: ｴﾛﾌｨﾝﾁｭｰﾌﾞ（STK 5KF） | BQ49: 50A 32F 4000L | BR49: 本 | BS49: =ROUND(BT49/0.4,-3) -> 90000 | BT49: 36000 | BU49: 0.68 | CV49: ﾗｲﾝﾎﾟﾝﾌﾟ | CW49: 60Hz φ50 2.2kW | CX49: 台 | CY49: 321000 | CZ49: =ROUND(CY49*0.53,-1) -> 170130 | DA49: 0.7 | DT49: 密閉膨張ﾀﾝｸ | DU49: ST-8 3.0L | DV49: 基 | DW49: 28000 | DX49: =DW49*0.55 -> 15400 | EI49: 202598000 | EJ49: 煙道延長ｾｯﾄ | EK49: BEA-H-900 | EL49: ｾｯﾄ | EM49: 103100 | EN49: 22710 | EO49: 0.4 | EQ49: 104029000 | ER49: ﾀﾞｸﾄｺﾈｸﾀｰ | ES49: DC-301 | ET49: ｾｯﾄ | EU49: 2370 | EV49: 700 | EW49: 0 | EZ49: ﾀﾞｸﾄﾁｰｽﾞ(SUS) | FA49: φ300 | FB49: 個 | FC49: 53600 | FD49: =FC49*0.65 -> 34840 | FE49: 0.16 | GV49: SGPｴﾛﾌｨﾝﾁｭｰﾌﾞ | GW49: 50A 32F 4000L | GX49: 本 | GY49: =ROUND(GZ49/0.33,-3) -> 118000 | GZ49: 39100 | HA49: 0.68
C50: 79期価格修正 | AJ50: ｼﾝｸﾛﾋｰﾀ(高温水仕様) | AK50: SBR-166MH□Ｈ(ｶﾞｽ焚) | AL50: 台 | AM50: 4641000 | AN50: 1060800 | BP50: ｴﾛﾌｨﾝﾁｭｰﾌﾞ（STK 5KF） | BQ50: 50A 32F 3500L | BR50: 本 | BS50: =ROUND(BT50/0.4,-3) -> 86000 | BT50: 34400 | BU50: 0.6 | CV50: ﾗｲﾝﾎﾟﾝﾌﾟ | CW50: 60Hz φ50 3.7kW | CX50: 台 | CY50: 402000 | CZ50: =ROUND(CY50*0.53,-1) -> 213060 | DA50: 0.8 | DT50: 密閉膨張ﾀﾝｸ | DU50: ST-17 8.2L | DV50: 基 | DW50: 47000 | DX50: =DW50*0.55 -> 25850 | EI50: 202600000 | EJ50: 煙道延長ｾｯﾄ | EK50: BEA-BF-900 | EL50: ｾｯﾄ | EM50: 130200 | EN50: 28900 | EO50: 0.4 | EQ50: 104030000 | ER50: ﾀﾞｸﾄｺﾈｸﾀｰ | ES50: DC-351 | ET50: ｾｯﾄ | EU50: 2870 | EV50: 740 | EW50: 0 | EZ50: ﾀﾞｸﾄﾁｰｽﾞ(SUS) | FA50: φ350 | FB50: 個 | FC50: 65100 | FD50: =FC50*0.65 -> 42315 | FE50: 0.18 | GV50: SGPｴﾛﾌｨﾝﾁｭｰﾌﾞ | GW50: 50A 32F 3500L | GX50: 本 | GY50: =ROUND(GZ50/0.33,-3) -> 112000 | GZ50: 37100 | HA50: 0.6
AJ51: ｼﾝｸﾛﾋｰﾀ(高温水仕様) | AK51: SBR-206MH□Ｈ(ｶﾞｽ焚) | AL51: 台 | AM51: 5975000 | AN51: 1365600 | BP51: ｴﾛﾌｨﾝﾁｭｰﾌﾞ（STK 5KF） | BQ51: 50A 32F 3000L | BR51: 本 | BS51: =ROUND(BT51/0.4,-3) -> 82000 | BT51: 32800 | BU51: 0.55 | CV51: ﾗｲﾝﾎﾟﾝﾌﾟ | CW51: 60Hz φ50 5.5kW | CX51: 台 | CY51: 501000 | CZ51: =ROUND(CY51*0.53,-1) -> 265530 | DA51: 1.2 | DT51: 密閉膨張ﾀﾝｸ | DU51: ST-28 10.9L | DV51: 基 | DW51: 68000 | DX51: =DW51*0.55 -> 37400 | EI51: 202602000 | EJ51: 煙道延長ｾｯﾄ | EK51: BEA-DA-900 | EL51: ｾｯﾄ | EM51: 165600 | EN51: 21800 | EO51: 0.4 | EQ51: 104032000 | ER51: ﾀﾞｸﾄｺﾈｸﾀｰ | ES51: DC-401 | ET51: ｾｯﾄ | EU51: 3120 | EV51: 840 | EW51: 0 | EZ51: ﾀﾞｸﾄﾁｰｽﾞ(SUS) | FA51: φ400 | FB51: 個 | FC51: 80300 | FD51: =FC51*0.65 -> 52195 | FE51: 0.18 | GV51: SGPｴﾛﾌｨﾝﾁｭｰﾌﾞ | GW51: 50A 32F 3000L | GX51: 本 | GY51: =ROUND(GZ51/0.33,-3) -> 105000 | GZ51: 34600 | HA51: 0.55
AJ52: ｼﾝｸﾛﾋｰﾀ(高温水仕様) | AK52: SBR-256MH□Ｈ(ｶﾞｽ焚) | AL52: 台 | AM52: 6269000 | AN52: 1432800 | BP52: ｴﾛﾌｨﾝﾁｭｰﾌﾞ（STK 5KF） | BQ52: 50A 32F 2750L | BR52: 本 | BS52: =ROUND(BT52/0.4,-3) -> 80000 | BT52: 32000 | BU52: 0.47 | CV52: ---------- | DT52: 密閉膨張ﾀﾝｸ | DU52: ST-39V 23.0L | DV52: 基 | DW52: 88000 | DX52: =DW52*0.55 -> 48400 | EI52: 105442000 | EJ52: 煙突断熱材ｾｯﾄ | EK52: BED-1501 | EL52: ｾｯﾄ | EM52: 52000 | EN52: 9910 | EO52: 0.1 | ER52: ---------- | EZ52: ﾀﾞｸﾄﾁｰｽﾞ(SUS) | FA52: φ450 | FB52: 個 | FC52: 88600 | FD52: =FC52*0.65 -> 57590 | FE52: 0.18 | GV52: SGPｴﾛﾌｨﾝﾁｭｰﾌﾞ | GW52: 50A 32F 2750L | GX52: 本 | GY52: =ROUND(GZ52/0.33,-3) -> 104000 | GZ52: 34200 | HA52: 0.47
BP53: ｴﾛﾌｨﾝﾁｭｰﾌﾞ（STK 5KF） | BQ53: 50A 32F 2000L | BR53: 本 | BS53: =ROUND(BT53/0.4,-3) -> 74000 | BT53: 29700 | BU53: 0.34 | CV53: ﾗｲﾝﾎﾟﾝﾌﾟ | CW53: 60Hz φ65 1.5kW | CX53: 台 | CY53: 294000 | CZ53: =ROUND(CY53*0.53,-1) -> 155820 | DA53: 0.8 | DT53: 密閉膨張ﾀﾝｸ | DU53: ST-55V 32.0L | DV53: 基 | DW53: 107000 | DX53: =DW53*0.55 -> 58850 | EI53: 105443000 | EJ53: 煙突断熱材ｾｯﾄ | EK53: BED-2251 | EL53: ｾｯﾄ | EM53: 63400 | EN53: 11790 | EO53: 0.1 | EQ53: RE0000235 | ER53: ｸｻﾋﾞｯｸ | ES53: （200ヶ入り） | ET53: 袋 | EU53: 19200 | EV53: 6300 | EW53: 0 | EZ53: ﾀﾞｸﾄﾁｰｽﾞ(SUS) | FA53: φ500 | FB53: 個 | FC53: 97300 | FD53: =FC53*0.65 -> 63245 | FE53: 0.2 | GV53: SGPｴﾛﾌｨﾝﾁｭｰﾌﾞ | GW53: 50A 32F 2000L | GX53: 本 | GY53: =ROUND(GZ53/0.33,-3) -> 95000 | GZ53: 31400 | HA53: 0.34
BP54: ｴﾛﾌｨﾝﾁｭｰﾌﾞ（STK 5KF） | BQ54: 50A 32F 1500L | BR54: 本 | BS54: =ROUND(BT54/0.4,-3) -> 71000 | BT54: 28200 | BU54: 0.26 | CV54: ﾗｲﾝﾎﾟﾝﾌﾟ | CW54: 60Hz φ65 2.2kW | CX54: 台 | CY54: 312000 | CZ54: =ROUND(CY54*0.53,-1) -> 165360 | DA54: 0.8 | DT54: 密閉膨張ﾀﾝｸ | DU54: ST-76V 39.0L | DV54: 基 | DW54: 136000 | DX54: =DW54*0.55 -> 74800 | EI54: 100789000 | EJ54: 煙突消音器ｾｯﾄ | EK54: BEM-1500 | EL54: 本 | EM54: 109700 | EN54: 31520 | EO54: 0.2 | ER54: ---------- | EZ54: ﾀﾞｸﾄﾁｰｽﾞ(SUS) | FA54: φ550 | FB54: 個 | FC54: 108900 | FD54: =FC54*0.65 -> 70785 | FE54: 0.2 | GV54: SGPｴﾛﾌｨﾝﾁｭｰﾌﾞ | GW54: 50A 32F 1500L | GX54: 本 | GY54: =ROUND(GZ54/0.33,-3) -> 89000 | GZ54: 29400 | HA54: 0.26
BP55: ｴﾛﾌｨﾝﾁｭｰﾌﾞ（STK 5KF） | BQ55: 50A 32F 1000L | BR55: 本 | BS55: =ROUND(BT55/0.4,-3) -> 67000 | BT55: 26600 | BU55: 0.17 | CV55: ﾗｲﾝﾎﾟﾝﾌﾟ | CW55: 60Hz φ65 3.7kW | CX55: 台 | CY55: 420000 | CZ55: =ROUND(CY55*0.53,-1) -> 222600 | DA55: 0.8 | DT55: 密閉膨張ﾀﾝｸ | DU55: ST-116V 39.0L | DV55: 基 | DW55: 200000 | DX55: =DW55*0.55 -> 110000 | EI55: 100806000 | EJ55: 煙突消音器ｾｯﾄ | EK55: BEM-2250 | EL55: 本 | EM55: 222100 | EN55: 64870 | EO55: 0.3 | EQ55: 101645000 | ER55: 吹出口ｴﾙﾎﾞ | ES55: BDE-KA220 | ET55: ｾｯﾄ | EU55: 26200 | EV55: 6990 | EW55: 0 | EZ55: ﾀﾞｸﾄﾁｰｽﾞ(SUS) | FA55: φ600 | FB55: 個 | FC55: 120500 | FD55: =FC55*0.65 -> 78325 | FE55: 0.24 | GV55: SGPｴﾛﾌｨﾝﾁｭｰﾌﾞ | GW55: 50A 32F 1000L | GX55: 本 | GY55: =ROUND(GZ55/0.33,-3) -> 84000 | GZ55: 27600 | HA55: 0.17
BP56: ---------- | CV56: ﾗｲﾝﾎﾟﾝﾌﾟ | CW56: 60Hz φ65 5.5kW | CX56: 台 | CY56: 585000 | CZ56: =ROUND(CY56*0.53,-1) -> 310050 | DA56: 1.2 | DT56: 密閉膨張ﾀﾝｸ | DU56: ST-167V 116.0L | DV56: 基 | DW56: 257000 | DX56: =DW56*0.55 -> 141350 | EI56: 036660000 | EJ56: 断熱ﾏｯﾄ(2枚1組) | EK56: t25×605×910 | EL56: 組 | EM56: 10900 | EN56: 4070 | EO56: 0.1 | EQ56: 101646000 | ER56: 吹出口ｴﾙﾎﾞ | ES56: BDE-KA300 | ET56: ｾｯﾄ | EU56: 39500 | EV56: 11160 | EW56: 0 | GV56: ----------
BP57: ｴﾛﾌｨﾝﾁｭｰﾌﾞ（STK 5KF） | BQ57: 65A 25F 5500L | BR57: 本 | BS57: =ROUND(BT57/0.4,-3) -> 112000 | BT57: 44880 | BU57: 1.21 | CV57: ﾗｲﾝﾎﾟﾝﾌﾟ | CW57: 60Hz φ65 7.5kW | CX57: 台 | CY57: 654000 | CZ57: =ROUND(CY57*0.53,-1) -> 346620 | DA57: 1.5 | DT57: 密閉膨張ﾀﾝｸ | DU57: ST-235V 116.0L | DV57: 基 | DW57: 346000 | DX57: =DW57*0.55 -> 190300 | EI57: 007033000 | EJ57: 掃除具ｾｯﾄ | EK57: ＢＨＳ５００ ５０Ａ | EL57: ｾｯﾄ | EM57: 12400 | EN57: 7100 | GV57: SGPｴﾛﾌｨﾝﾁｭｰﾌﾞ | GW57: 65A 25F 5500L | GX57: 本 | GY57: =ROUND(GZ57/0.33,-3) -> 151000 | GZ57: 49700 | HA57: 1.21
BP58: ｴﾛﾌｨﾝﾁｭｰﾌﾞ（STK 5KF） | BQ58: 65A 25F 4000L | BR58: 本 | BS58: =ROUND(BT58/0.4,-3) -> 99000 | BT58: 39700 | BU58: 0.88 | CV58: ---------- | DT58: 密閉膨張ﾀﾝｸ | DU58: ST-326V 162.0L | DV58: 基 | DW58: 467000 | DX58: =DW58*0.55 -> 256850 | EI58: 007060000 | EJ58: 掃除具ｾｯﾄ | EK58: ＢＨＳ６５０ ６５Ａ | EL58: ｾｯﾄ | EM58: 12400 | EN58: 5220 | GV58: SGPｴﾛﾌｨﾝﾁｭｰﾌﾞ | GW58: 65A 25F 4000L | GX58: 本 | GY58: =ROUND(GZ58/0.33,-3) -> 131000 | GZ58: 43200 | HA58: 0.88
BP59: ｴﾛﾌｨﾝﾁｭｰﾌﾞ（STK 5KF） | BQ59: 65A 25F 3500L | BR59: 本 | BS59: =ROUND(BT59/0.4,-3) -> 94000 | BT59: 37700 | BU59: 0.77 | CV59: ﾗｲﾝﾎﾟﾝﾌﾟ | CW59: 60Hz φ80 2.2kW | CX59: 台 | CY59: 339000 | CZ59: =ROUND(CY59*0.53,-1) -> 179670 | DA59: 1 | DT59: ---------- | GV59: SGPｴﾛﾌｨﾝﾁｭｰﾌﾞ | GW59: 65A 25F 3500L | GX59: 本 | GY59: =ROUND(GZ59/0.33,-3) -> 125000 | GZ59: 41100 | HA59: 0.77
BP60: ｴﾛﾌｨﾝﾁｭｰﾌﾞ（STK 5KF） | BQ60: 65A 25F 3000L | BR60: 本 | BS60: =ROUND(BT60/0.4,-3) -> 91000 | BT60: 36200 | BU60: 0.7 | CV60: ﾗｲﾝﾎﾟﾝﾌﾟ | CW60: 60Hz φ80 3.7kW | CX60: 台 | CY60: 427000 | CZ60: =ROUND(CY60*0.53,-1) -> 226310 | DA60: 1 | DT60: 密閉膨張ﾀﾝｸ | DU60: AST-9V 2.9L | DV60: 基 | DW60: 270000 | DX60: =DW60*0.55 -> 148500 | GV60: SGPｴﾛﾌｨﾝﾁｭｰﾌﾞ | GW60: 65A 25F 3000L | GX60: 本 | GY60: =ROUND(GZ60/0.33,-3) -> 118000 | GZ60: 39000 | HA60: 0.7
BP61: ｴﾛﾌｨﾝﾁｭｰﾌﾞ（STK 5KF） | BQ61: 65A 25F 2750L | BR61: 本 | BS61: =ROUND(BT61/0.4,-3) -> 88000 | BT61: 35200 | BU61: 0.61 | CV61: ﾗｲﾝﾎﾟﾝﾌﾟ | CW61: 60Hz φ80 5.5kW | CX61: 台 | CY61: 556000 | CZ61: =ROUND(CY61*0.53,-1) -> 294680 | DA61: 1.2 | DT61: 密閉膨張ﾀﾝｸ | DU61: AST-18V 7.7L | DV61: 基 | DW61: 289000 | DX61: =DW61*0.55 -> 158950 | GV61: SGPｴﾛﾌｨﾝﾁｭｰﾌﾞ | GW61: 65A 25F 2750L | GX61: 本 | GY61: =ROUND(GZ61/0.33,-3) -> 115000 | GZ61: 37800 | HA61: 0.61
BP62: ｴﾛﾌｨﾝﾁｭｰﾌﾞ（STK 5KF） | BQ62: 65A 25F 2000L | BR62: 本 | BS62: =ROUND(BT62/0.4,-3) -> 82000 | BT62: 32600 | BU62: 0.44 | CV62: ﾗｲﾝﾎﾟﾝﾌﾟ | CW62: 60Hz φ80 7.5kW | CX62: 台 | CY62: 674000 | CZ62: =ROUND(CY62*0.53,-1) -> 357220 | DA62: 1.5 | DT62: 密閉膨張ﾀﾝｸ | DU62: AST-29V 7.7L | DV62: 基 | DW62: 339000 | DX62: =DW62*0.55 -> 186450 | GV62: SGPｴﾛﾌｨﾝﾁｭｰﾌﾞ | GW62: 65A 25F 2000L | GX62: 本 | GY62: =ROUND(GZ62/0.33,-3) -> 104000 | GZ62: 34400 | HA62: 0.44
BP63: ｴﾛﾌｨﾝﾁｭｰﾌﾞ（STK 5KF） | BQ63: 65A 25F 1500L | BR63: 本 | BS63: =ROUND(BT63/0.4,-3) -> 78000 | BT63: 31000 | BU63: 0.33 | CV63: ﾗｲﾝﾎﾟﾝﾌﾟ | CW63: 60Hz φ80 11kW | CX63: 台 | CY63: 736000 | CZ63: =ROUND(CY63*0.53,-1) -> 390080 | DA63: 2 | DT63: 密閉膨張ﾀﾝｸ | DU63: AST-45V 33.0L | DV63: 基 | DW63: 410000 | DX63: =DW63*0.55 -> 225500 | GV63: SGPｴﾛﾌｨﾝﾁｭｰﾌﾞ | GW63: 65A 25F 1500L | GX63: 本 | GY63: =ROUND(GZ63/0.33,-3) -> 98000 | GZ63: 32400 | HA63: 0.33
BP64: ｴﾛﾌｨﾝﾁｭｰﾌﾞ（STK 5KF） | BQ64: 65A 25F 1000L | BR64: 本 | BS64: =ROUND(BT64/0.4,-3) -> 73000 | BT64: 29200 | BU64: 0.22 | CV64: ---------- | DT64: 密閉膨張ﾀﾝｸ | DU64: AST-70V 33.0L | DV64: 基 | DW64: 451000 | DX64: =DW64*0.55 -> 248050 | GV64: SGPｴﾛﾌｨﾝﾁｭｰﾌﾞ | GW64: 65A 25F 1000L | GX64: 本 | GY64: =ROUND(GZ64/0.33,-3) -> 91000 | GZ64: 30100 | HA64: 0.22
BP65: ---------- | CV65: ﾗｲﾝﾎﾟﾝﾌﾟ | CW65: 50Hz φ125 7.5kW低揚程 | CX65: 台 | CY65: 628000 | CZ65: 314000 | DT65: 密閉膨張ﾀﾝｸ | DU65: AST-100V 33.0L | DV65: 基 | DW65: 528000 | DX65: =DW65*0.55 -> 290400 | GV65: ----------
BP66: ｴﾛﾌｨﾝﾁｭｰﾌﾞ（STK 5KF） | BQ66: 65A 32F 5500L | BR66: 本 | BS66: =ROUND(BT66/0.4,-3) -> 120000 | BT66: 47900 | BU66: 1.21 | CV66: ﾗｲﾝﾎﾟﾝﾌﾟ | CW66: 50Hz φ125 7.5kW高揚程 | CX66: 台 | CY66: 726000 | CZ66: 363000 | DT66: 密閉膨張ﾀﾝｸ | DU66: AST-130V 66.0L | DV66: 基 | DW66: 615000 | DX66: =DW66*0.55 -> 338250 | GV66: SGPｴﾛﾌｨﾝﾁｭｰﾌﾞ | GW66: 65A 32F 5500L | GX66: 本 | GY66: =ROUND(GZ66/0.33,-3) -> 160000 | GZ66: 52800 | HA66: 1.21
BP67: ｴﾛﾌｨﾝﾁｭｰﾌﾞ（STK 5KF） | BQ67: 65A 32F 4000L | BR67: 本 | BS67: =ROUND(BT67/0.4,-3) -> 106000 | BT67: 42200 | BU67: 0.88 | CV67: ﾗｲﾝﾎﾟﾝﾌﾟ | CW67: 50Hz φ125 11kW | CX67: 台 | CY67: 814000 | CZ67: 407000 | DT67: 密閉膨張ﾀﾝｸ | DU67: AST-175V 66.0L | DV67: 基 | DW67: 710000 | DX67: =DW67*0.55 -> 390500 | GV67: SGPｴﾛﾌｨﾝﾁｭｰﾌﾞ | GW67: 65A 32F 4000L | GX67: 本 | GY67: =ROUND(GZ67/0.33,-3) -> 140000 | GZ67: 46100 | HA67: 0.88
BP68: ｴﾛﾌｨﾝﾁｭｰﾌﾞ（STK 5KF） | BQ68: 65A 32F 3500L | BR68: 本 | BS68: =ROUND(BT68/0.4,-3) -> 100000 | BT68: 39800 | BU68: 0.77 | CV68: ﾗｲﾝﾎﾟﾝﾌﾟ | CW68: 50Hz φ125 15kW | CX68: 台 | CY68: 936000 | CZ68: 468000 | DT68: 密閉膨張ﾀﾝｸ | DU68: AST-215V 109.0L | DV68: 基 | DW68: 832000 | DX68: =DW68*0.55 -> 457600 | GV68: SGPｴﾛﾌｨﾝﾁｭｰﾌﾞ | GW68: 65A 32F 3500L | GX68: 本 | GY68: =ROUND(GZ68/0.33,-3) -> 131000 | GZ68: 43200 | HA68: 0.77
BP69: ｴﾛﾌｨﾝﾁｭｰﾌﾞ（STK 5KF） | BQ69: 65A 32F 3000L | BR69: 本 | BS69: =ROUND(BT69/0.4,-3) -> 95000 | BT69: 38000 | BU69: 0.7 | CV69: ﾗｲﾝﾎﾟﾝﾌﾟ | CW69: 50Hz φ125 18kW | CX69: 台 | CY69: 1044000 | CZ69: 522000 | DT69: 密閉膨張ﾀﾝｸ | DU69: AST-260V 109.0L | DV69: 基 | DW69: 878000 | DX69: =DW69*0.55 -> 482900 | GV69: SGPｴﾛﾌｨﾝﾁｭｰﾌﾞ | GW69: 65A 32F 3000L | GX69: 本 | GY69: =ROUND(GZ69/0.33,-3) -> 124000 | GZ69: 40800 | HA69: 0.7
BP70: ｴﾛﾌｨﾝﾁｭｰﾌﾞ（STK 5KF） | BQ70: 65A 32F 2750L | BR70: 本 | BS70: =ROUND(BT70/0.4,-3) -> 93000 | BT70: 37000 | BU70: 0.61 | CV70: ﾗｲﾝﾎﾟﾝﾌﾟ | CW70: 50Hz φ125 22kW | CX70: 台 | CY70: 1122000 | CZ70: 561000 | DT70: ---------- | GV70: SGPｴﾛﾌｨﾝﾁｭｰﾌﾞ | GW70: 65A 32F 2750L | GX70: 本 | GY70: =ROUND(GZ70/0.33,-3) -> 119000 | GZ70: 39300 | HA70: 0.61
BP71: ｴﾛﾌｨﾝﾁｭｰﾌﾞ（STK 5KF） | BQ71: 65A 32F 2000L | BR71: 本 | BS71: =ROUND(BT71/0.4,-3) -> 85000 | BT71: 34000 | BU71: 0.44 | CV71: ﾗｲﾝﾎﾟﾝﾌﾟ | CW71: 50Hz φ125 30kW | CX71: 台 | CY71: 1266000 | CZ71: 633000 | DT71: 密閉膨張ﾀﾝｸ | DU71: EX-200V 160.0L | DV71: 基 | DW71: 1032000 | DX71: =DW71*0.55 -> 567600 | GV71: SGPｴﾛﾌｨﾝﾁｭｰﾌﾞ | GW71: 65A 32F 2000L | GX71: 本 | GY71: =ROUND(GZ71/0.33,-3) -> 108000 | GZ71: 35800 | HA71: 0.44
BP72: ｴﾛﾌｨﾝﾁｭｰﾌﾞ（STK 5KF） | BQ72: 65A 32F 1500L | BR72: 本 | BS72: =ROUND(BT72/0.4,-3) -> 80000 | BT72: 32000 | BU72: 0.33 | CV72: ---------- | DT72: 密閉膨張ﾀﾝｸ | DU72: EX-300V 240.0L | DV72: 基 | DW72: 1139000 | DX72: =DW72*0.55 -> 626450 | GV72: SGPｴﾛﾌｨﾝﾁｭｰﾌﾞ | GW72: 65A 32F 1500L | GX72: 本 | GY72: =ROUND(GZ72/0.33,-3) -> 101000 | GZ72: 33300 | HA72: 0.33
BP73: ｴﾛﾌｨﾝﾁｭｰﾌﾞ（STK 5KF） | BQ73: 65A 32F 1000L | BR73: 本 | BS73: =ROUND(BT73/0.4,-3) -> 75000 | BT73: 29800 | BU73: 0.22 | CV73: ﾗｲﾝﾎﾟﾝﾌﾟ | CW73: 50Hz φ150 15kW低揚程 | CX73: 台 | CY73: 1122000 | CZ73: 561000 | DT73: 密閉膨張ﾀﾝｸ | DU73: EX-400V 320.0L | DV73: 基 | DW73: 1302000 | DX73: =DW73*0.55 -> 716100 | GV73: SGPｴﾛﾌｨﾝﾁｭｰﾌﾞ | GW73: 65A 32F 1000L | GX73: 本 | GY73: =ROUND(GZ73/0.33,-3) -> 93000 | GZ73: 30700 | HA73: 0.22
CV74: ﾗｲﾝﾎﾟﾝﾌﾟ | CW74: 50Hz φ150 15kW高揚程 | CX74: 台 | CY74: 1122000 | CZ74: 561000 | DT74: 密閉膨張ﾀﾝｸ | DU74: EX-500V 400.0L | DV74: 基 | DW74: 1466000 | DX74: =DW74*0.55 -> 806300
CV75: ﾗｲﾝﾎﾟﾝﾌﾟ | CW75: 50Hz φ150 18kW | CX75: 台 | CY75: 1332000 | CZ75: 666000 | DT75: 密閉膨張ﾀﾝｸ | DU75: EX-600V 480.0L | DV75: 基 | DW75: 1680000 | DX75: =DW75*0.55 -> 924000
CV76: ﾗｲﾝﾎﾟﾝﾌﾟ | CW76: 50Hz φ150 22kW | CX76: 台 | CY76: 1392000 | CZ76: 696000 | DT76: 密閉膨張ﾀﾝｸ | DU76: EX-800V 640.0L | DV76: 基 | DW76: 2000000 | DX76: =DW76*0.55 -> 1100000
CV77: ﾗｲﾝﾎﾟﾝﾌﾟ | CW77: 50Hz φ150 30kW | CX77: 台 | CY77: 1486000 | CZ77: 743000 | DT77: 密閉膨張ﾀﾝｸ | DU77: EX-1000V 800.0L | DV77: 基 | DW77: 2331000 | DX77: =DW77*0.55 -> 1282050
CV78: ﾗｲﾝﾎﾟﾝﾌﾟ | CW78: 50Hz φ150 37kW | CX78: 台 | CY78: 1952000 | CZ78: 976000 | DT78: 密閉膨張ﾀﾝｸ | DU78: EX-1200V 960.0L | DV78: 基 | DW78: 2675000 | DX78: =DW78*0.55 -> 1471250
CV79: ﾗｲﾝﾎﾟﾝﾌﾟ | CW79: 50Hz φ150 45kW | CX79: 台 | CY79: 2178000 | CZ79: 1089000 | DT79: 密閉膨張ﾀﾝｸ | DU79: EX-1400V 1120.0L | DV79: 基 | DW79: 3185000 | DX79: =DW79*0.55 -> 1751750
CV80: ﾗｲﾝﾎﾟﾝﾌﾟ | CW80: 50Hz φ150 55kW | CX80: 台 | CY80: 2454000 | CZ80: 1227000 | DT80: 密閉膨張ﾀﾝｸ | DU80: EX-1600V 1280.0L | DV80: 基 | DW80: 3580000 | DX80: =DW80*0.55 -> 1969000
CV81: ﾗｲﾝﾎﾟﾝﾌﾟ | CW81: 50Hz φ150 75kW | CX81: 台 | CY81: 3482000 | CZ81: 1741000 | DT81: 密閉膨張ﾀﾝｸ | DU81: EX-2000V 1600.0L | DV81: 基 | DW81: 4303000 | DX81: =DW81*0.55 -> 2366650
CV82: ---------- | DT82: 密閉膨張ﾀﾝｸ | DU82: EX-3000V 2400.0L | DV82: 基 | DW82: 6639000 | DX82: =DW82*0.55 -> 3651450
CV83: ﾗｲﾝﾎﾟﾝﾌﾟ | CW83: 50Hz φ200 22kW | CX83: 台 | CY83: 1442000 | CZ83: 721000 | DT83: 密閉膨張ﾀﾝｸ | DU83: EX-4000V 3200.0L | DV83: 基 | DW83: 7755000 | DX83: =DW83*0.55 -> 4265250
CV84: ﾗｲﾝﾎﾟﾝﾌﾟ | CW84: 50Hz φ200 30kW | CX84: 台 | CY84: 1650000 | CZ84: 825000 | DT84: 密閉膨張ﾀﾝｸ | DU84: EX-5000V 4000.0L | DV84: 基 | DW84: 8349000 | DX84: =DW84*0.55 -> 4591950
CV85: ﾗｲﾝﾎﾟﾝﾌﾟ | CW85: 50Hz φ200 37kW | CX85: 台 | CY85: 2498000 | CZ85: 1249000
CV86: ﾗｲﾝﾎﾟﾝﾌﾟ | CW86: 50Hz φ200 45kW | CX86: 台 | CY86: 2772000 | CZ86: 1386000
CV87: ﾗｲﾝﾎﾟﾝﾌﾟ | CW87: 50Hz φ200 55kW | CX87: 台 | CY87: 3256000 | CZ87: 1628000
CV88: ﾗｲﾝﾎﾟﾝﾌﾟ | CW88: 50Hz φ200 75kW | CX88: 台 | CY88: 3740000 | CZ88: 1870000
CV89: ﾗｲﾝﾎﾟﾝﾌﾟ | CW89: 50Hz φ200 90kW | CX89: 台 | CY89: 4282000 | CZ89: 2141000
CV90: ----------
CV91: ﾗｲﾝﾎﾟﾝﾌﾟ | CW91: 60Hz φ125 7.5kW | CX91: 台 | CY91: 628000 | CZ91: 314000
CV92: ﾗｲﾝﾎﾟﾝﾌﾟ | CW92: 60Hz φ125 11kW低揚程 | CX92: 台 | CY92: 814000 | CZ92: 407000
CV93: ﾗｲﾝﾎﾟﾝﾌﾟ | CW93: 60Hz φ125 11kW高揚程 | CX93: 台 | CY93: 814000 | CZ93: 407000
CV94: ﾗｲﾝﾎﾟﾝﾌﾟ | CW94: 60Hz φ125 15kW | CX94: 台 | CY94: 936000 | CZ94: 468000
CV95: ﾗｲﾝﾎﾟﾝﾌﾟ | CW95: 60Hz φ125 18kW低揚程 | CX95: 台 | CY95: 1044000 | CZ95: 522000
CV96: ﾗｲﾝﾎﾟﾝﾌﾟ | CW96: 60Hz φ125 18kW高揚程 | CX96: 台 | CY96: 1044000 | CZ96: 522000
CV97: ﾗｲﾝﾎﾟﾝﾌﾟ | CW97: 60Hz φ125 22kW | CX97: 台 | CY97: 1122000 | CZ97: 561000
CV98: ﾗｲﾝﾎﾟﾝﾌﾟ | CW98: 60Hz φ125 30kW | CX98: 台 | CY98: 1266000 | CZ98: 633000
CV99: ﾗｲﾝﾎﾟﾝﾌﾟ | CW99: 60Hz φ125 37kW | CX99: 台 | CY99: 1430000 | CZ99: 715000
CV100: ﾗｲﾝﾎﾟﾝﾌﾟ | CW100: 60Hz φ125 45kW | CX100: 台 | CY100: 1980000 | CZ100: 990000 | DL100: 空冷ﾁﾗｰﾕﾆｯﾄ | DM100: RCUP75A2(3HP) | DN100: 基 | DO100: 1620000
...

Sheet 電材表
H1: 品番 | I1: 品名 | J1: 型式 | K1: 単位 | L1: 価格 | M1: 原価 | N1: 歩単 | P1: 品番 | Q1: 品名 | R1: 型式 | S1: 単位 | T1: 価格 | U1: 原価 | V1: 歩単 | X1: 品番 | Y1: 品名 | Z1: 型式 | AA1: 単位 | AB1: 価格 | AC1: 原価 | AD1: 歩単 | AF1: 品番 | AG1: 品名 | AH1: 型式 | AI1: 単位 | AJ1: 価格 | AK1: 原価 | AL1: 歩単 | AN1: 品番 | AO1: 品名 | AP1: 型式 | AQ1: 単位 | AR1: 価格 | AS1: 原価 | AT1: 歩単 | AV1: 品番 | AW1: 品名 | AX1: 型式 | AY1: 単位 | AZ1: 価格 | BA1: 原価 | BB1: 歩単 | BD1: 品番 | BE1: 品名 | BF1: 型式 | BG1: 単位 | BH1: 価格 | BI1: 原価 | BJ1: 歩単 | BM1: 品番 | BN1: 品名 | BO1: 型式 | BP1: 単位 | BQ1: 価格 | BR1: 原価 | BS1: 歩単
AW2: 電線管材工単価 | BE2: 配線材工単価 | BI2: 0.85 | BN2: 配線用遮断器
B3: 1 | C3: 複合環境制御・ｱｸﾞﾘﾈｯﾄ | D3: i3 | H3: 017534000 | I3: 温室環境制御盤 | J3: MC-3001 | K3: 面 | L3: 254000 | M3: 81540 | N3: 0 | P3: 008526000 | Q3: 4段ｻｰﾓ | R3: NT-145 | S3: 台 | T3: 75000 | U3: 28060 | V3: 0 | AF3: 007881000 | AG3: 換気窓制御盤 | AH3: TSC-1204 | AI3: 面 | AJ3: 135000 | AK3: 61670 | AL3: 1.5 | AW3: 電線管(露出) | AX3: Ｅ19 | AY3: ｍ | AZ3: 1640 | BA3: 1400 | BB3: 0 | BE3: ﾋﾞﾆﾙｼｰｽｹｰﾌﾞﾙ | BF3: CVV 0.75-1C | BG3: ｍ | BH3: 410 | BI3: 350 | BJ3: 0.015 | BN3: ｵｰﾄﾌﾞﾚｰｶ | BO3: 2P 15AT/30AF BW32AAG-2P015 | BP3: 個 | BQ3: 2572 | BR3: 1740 | BS3: 0
B4: 2 | C4: 天窓側窓関連 | D4: ag3 | H4: 017535000 | I4: 温室環境制御盤 | J4: MC-3501 | K4: 面 | L4: 335000 | M4: 85410 | N4: 0 | P4: 008809000 | Q4: 4段ｻｰﾓ | R4: NT-145S1 | S4: 台 | T4: 76000 | U4: 29480 | V4: 0 | AF4: 007882000 | AG4: 換気窓制御盤 | AH4: TSC-1404 | AI4: 面 | AJ4: 188000 | AK4: 72120 | AL4: 1.5 | AW4: 電線管(露出) | AX4: Ｅ25 | AY4: ｍ | AZ4: 1960 | BA4: 1670 | BB4: 0 | BE4: ﾋﾞﾆﾙｼｰｽｹｰﾌﾞﾙ | BF4: CVV 0.75-2C | BG4: ｍ | BH4: 480 | BI4: 410 | BJ4: 0.016 | BN4: ｵｰﾄﾌﾞﾚｰｶ | BO4: 3P 15AT/30AF BW32AAG-3P015 | BP4: 個 | BQ4: 3669 | BR4: 1700 | BS4: 0
B5: 3 | C5: 周辺機器制御 | D5: q3 | H5: 042411000 | I5: 統合環境制御盤 | J5: MC-6001 | K5: 面 | L5: 618000 | M5: 200360 | N5: 0 | P5: 008810000 | Q5: 4段ｻｰﾓ | R5: NT-145C | S5: 台 | T5: 76000 | U5: 29210 | V5: 0 | AF5: 007885000 | AG5: 換気窓制御盤 | AH5: TSC-4204 | AI5: 面 | AJ5: 186000 | AK5: 64250 | AL5: 1.5 | AW5: 電線管(露出) | AX5: Ｅ31 | AY5: ｍ | AZ5: 2550 | BA5: 2160 | BB5: 0 | BE5: ﾋﾞﾆﾙｼｰｽｹｰﾌﾞﾙ | BF5: CVV 0.75-3C | BG5: ｍ | BH5: 530 | BI5: 450 | BJ5: 0.017
B6: 4 | C6: ----------- | I6: ------------ | P6: 008811000 | Q6: 4段ｻｰﾓ | R6: NT-145CS1 | S6: 台 | T6: 76000 | U6: 25860 | V6: 0 | AF6: 007886000 | AG6: 換気窓制御盤 | AH6: TSC-4404 | AI6: 面 | AJ6: 236000 | AK6: 76890 | AL6: 1.5 | AW6: 電線管(露出) | AX6: Ｅ39 | AY6: ｍ | AZ6: 2860 | BA6: 2430 | BB6: 0 | BE6: ﾋﾞﾆﾙｼｰｽｹｰﾌﾞﾙ | BF6: CVV 0.75-4C | BG6: ｍ | BH6: 580 | BI6: 500 | BJ6: 0.018
B7: 5 | C7: ----------- | H7: 103305000 | I7: 湿度ｾﾝｻｰｾｯﾄ | J7: HUS-12 | K7: 個 | L7: 101800 | M7: 24770 | N7: 0 | P7: 044249000 | Q7: 多段ｻｰﾓ | R7: NＴ-381ＨＮ | S7: 台 | T7: 168000 | U7: 57280 | V7: 0 | AG7: ------------ | AW7: 電線管(露出) | AX7: Ｅ51 | AY7: ｍ | AZ7: 4010 | BA7: 3410 | BB7: 0 | BE7: ﾋﾞﾆﾙｼｰｽｹｰﾌﾞﾙ | BF7: CVV 1.25-1C | BG7: ｍ | BH7: 470 | BI7: 400 | BJ7: 0.017
B8: 6 | C8: ----------- | H8: 018380000 | I8: 温湿度ｾﾝｻｰｾｯﾄ | J8: HUS-13 | K8: 個 | L8: 56500 | M8: 18370 | N8: 0 | Q8: ------------ | AF8: 040023000 | AG8: 天窓減速機 | AH8: TSD-403RAN1 | AI8: 台 | AJ8: 151000 | AK8: 65020 | AL8: 1.5 | AW8: 電線管(露出) | AX8: Ｅ63 | AY8: ｍ | AZ8: 5510 | BA8: 4680 | BB8: 0 | BE8: ﾋﾞﾆﾙｼｰｽｹｰﾌﾞﾙ | BF8: CVV 1.25-2C | BG8: ｍ | BH8: 560 | BI8: 470 | BJ8: 0.018
B9: 7 | C9: ----------- | H9: 144507000 | I9: 室温ｾﾝｻｰｾｯﾄ | J9: TS-102P | K9: 個 | L9: 18100 | M9: 2530 | N9: 0 | P9: 029939000 | Q9: CO2ｺﾝﾄﾛｰﾗ | R9: CGC-600 | S9: 台 | T9: 96000 | U9: 62060 | V9: 0 | AF9: 040025000 | AG9: 天窓減速機 | AH9: TSD-403LAN1 | AI9: 台 | AJ9: 151000 | AK9: 64380 | AL9: 1.5 | AW9: 電線管(露出) | AX9: Ｅ75 | AY9: ｍ | AZ9: 6510 | BA9: 5540 | BB9: 0 | BE9: ﾋﾞﾆﾙｼｰｽｹｰﾌﾞﾙ | BF9: CVV 1.25-3C | BG9: ｍ | BH9: 620 | BI9: 520 | BJ9: 0.019
B10: 8 | C10: 電線管（材工単価） | D10: aw3 | H10: 043920000 | I10: ｾﾝｻｰｶﾊﾞｰ | J10: BSC-10 | K10: 個 | L10: 27300 | M10: 11300 | N10: 0 | P10: 038180000 | Q10: CO2ｺﾝﾄﾛｰﾗ | R10: CGC-600SET14 | S10: 台 | T10: 155000 | U10: 89490 | V10: 0 | AF10: 040060000 | AG10: 天窓減速機 | AH10: TSD-403LAS1 | AI10: 台 | AJ10: 151000 | AK10: 69150 | AL10: 1.5 | AW10: ﾗｲﾆﾝｸﾞ鋼管(埋設) | AX10: 16 | AY10: ｍ | AZ10: 1500 | BA10: 1280 | BB10: 0 | BE10: ﾋﾞﾆﾙｼｰｽｹｰﾌﾞﾙ | BF10: CVV 1.25-4C | BG10: ｍ | BH10: 680 | BI10: 580 | BJ10: 0.02
B11: 9 | C11: 電線 （材工単価） | D11: be3 | H11: 038167000 | I11: CO2ｾﾝｻｰ | J11: CGS-14 | K11: 個 | L11: 66800 | M11: 27430 | N11: 0 | Q11: ------------ | V11: 0 | AF11: 029133000 | AG11: 天窓減速機 | AH11: TSD-603RAN1 | AI11: 台 | AJ11: 155000 | AK11: 63220 | AL11: 1.5 | AW11: ﾗｲﾆﾝｸﾞ鋼管(埋設) | AX11: 22 | AY11: ｍ | AZ11: 2000 | BA11: 1700 | BB11: 0 | BE11: ------------
B12: 10 | C12: 遮断器 （材工単価） | D12: bn3 | H12: 001614000 | I12: 日射ｾﾝｻｰ | J12: HRS-10A | K12: 個 | L12: 26000 | M12: 11070 | N12: 0 | P12: 101761000 | Q12: ﾈﾎﾟﾝｻｰﾓ | R12: NT-100 | S12: 個 | T12: 22100 | U12: 4590 | AW12: ﾗｲﾆﾝｸﾞ鋼管(埋設) | AX12: 28 | AY12: ｍ | AZ12: 2610 | BA12: 2210 | BB12: 0 | BE12: ｹｰﾌﾞﾙ(管内配線) | BF12: CVV 1.25-2C | BG12: ｍ | BH12: 440 | BI12: 380 | BJ12: 0.015
B13: 11 | H13: 011527000 | I13: 雨ｾﾝｻｰ | J13: RTS-11A | K13: 個 | L13: 32400 | M13: 10060 | N13: 0 | Q13: ------------ | V13: 0 | AW13: ﾗｲﾆﾝｸﾞ鋼管(埋設) | AX13: 36 | AY13: ｍ | AZ13: 3140 | BA13: 2670 | BB13: 0 | BE13: ｹｰﾌﾞﾙ(管内配線) | BF13: CVV 1.25-3C | BG13: ｍ | BH13: 510 | BI13: 440 | BJ13: 0.017
H14: 144535000 | I14: 温度ｾﾝｻｰ | J14: TS-102A 25M | K14: 個 | L14: 5220 | M14: 730 | N14: 0 | P14: 105821000 | Q14: ｷｬｽﾉｰﾙ | R14: HCA-5031 | S14: 個 | T14: 21000 | U14: 4900 | AW14: ﾗｲﾆﾝｸﾞ鋼管(埋設) | AX14: 42 | AY14: ｍ | AZ14: 4110 | BA14: 3500 | BB14: 0 | BE14: ｹｰﾌﾞﾙ(管内配線) | BF14: CVV 1.25-4C | BG14: ｍ | BH14: 590 | BI14: 510 | BJ14: 0.019
H15: 144530000 | I15: 水温･地温ｾﾝｻｰ | J15: TS-101W | K15: 個 | L15: 10500 | M15: 1040 | N15: 0 | Q15: ------------ | V15: 0 | AW15: ﾗｲﾆﾝｸﾞ鋼管(埋設) | AX15: 54 | AY15: ｍ | AZ15: 5550 | BA15: 4720 | BB15: 0 | BE15: ｹｰﾌﾞﾙ(管内配線) | BF15: CVV 1.25-5C | BG15: ｍ | BH15: 750 | BI15: 640 | BJ15: 0.025
H16: 041821000 | I16: 土壌水分ｾﾝｻｰ | J16: DWS-10L | K16: 個 | L16: 112600 | M16: 38520 | N16: 0 | P16: 016967000 | Q16: ﾎﾟﾝﾌﾟｺﾝﾄﾛｰﾗ | R16: PS-T23 | S16: 台 | T16: 95000 | U16: 35610 | V16: 0 | BE16: ｹｰﾌﾞﾙ(管内配線) | BF16: CVV 1.25-6C | BG16: ｍ | BH16: 770 | BI16: 650 | BJ16: 0.025
H17: 041823000 | I17: 土壌水分+温度+ECｾﾝｻｰ | J17: DWS-20L | K17: 個 | L17: 281100 | M17: 68490 | N17: 0 | Q17: ------------ | BE17: ｹｰﾌﾞﾙ(管内配線) | BF17: CVV 1.25-7C | BG17: ｍ | BH17: 920 | BI17: 780 | BJ17: 0.03
H18: 014146001 | I18: 風速ｾﾝｻｰ | J18: WTS-30 | K18: 個 | L18: 303000 | M18: 54800 | N18: 0 | P18: 212767000 | Q18: 感震器 | R18: BES-100 | S18: 個 | T18: 20100 | U18: 5580 | V18: 0 | BE18: ｹｰﾌﾞﾙ(管内配線) | BF18: CVV 1.25-8C | BG18: ｍ | BH18: 940 | BI18: 800 | BJ18: 0.03
H19: 014285001 | I19: 風向+風速ｾﾝｻｰ | J19: WTS-40 | K19: 個 | L19: 461000 | M19: 91480 | N19: 0 | P19: 027155000 | Q19: 不完全燃焼警報器 | R19: SG-35 | S19: 個 | T19: 85800 | U19: 31120 | V19: 0 | BE19: ｹｰﾌﾞﾙ(管内配線) | BF19: CVV 1.25-10C | BG19: ｍ | BH19: 990 | BI19: 840 | BJ19: 0.03
I20: ---MC-6001で使用--------- | Q20: ------------ | V20: 0 | BE20: ------------
H21: =H27 -> 024322000 | I21: =I27 -> 変換ｺﾈｸﾀB | J21: =J27 -> 湿度用 | K21: =K27 -> 個 | L21: =L27 -> 1620 | M21: =M27 -> 250 | N21: =N27 -> 0 | P21: 105659000 | Q21: ﾈﾎﾟﾝﾀｲﾏBOX | R21: TMB-200-11 | S21: 面 | T21: 63800 | U21: 11730 | V21: 0 | BE21: ｹｰﾌﾞﾙ(ﾗｯｸ配線) | BF21: CVV 1.25-2C | BG21: ｍ | BH21: 520 | BI21: 450 | BJ21: 0.02
H22: =H29 -> 024326000 | I22: =I29 -> 変換ｺﾈｸﾀD | J22: =J29 -> 風速用 | K22: =K29 -> 個 | L22: =L29 -> 1620 | M22: =M29 -> 150 | N22: =N29 -> 0 | P22: 105877000 | Q22: ﾈﾎﾟﾝﾀｲﾏBOX | R22: TMB-100-11 | S22: 面 | T22: 66800 | U22: 11810 | V22: 0 | BE22: ｹｰﾌﾞﾙ(ﾗｯｸ配線) | BF22: CVV 1.25-3C | BG22: ｍ | BH22: 580 | BI22: 500 | BJ22: 0.023
H23: =H30 -> 024332000 | I23: =I30 -> 変換ｺﾈｸﾀE | J23: =J30 -> 風向風速用 | K23: =K30 -> 個 | L23: =L30 -> 4370 | M23: 1490 | N23: =N30 -> 0 | BE23: ｹｰﾌﾞﾙ(ﾗｯｸ配線) | BF23: CVV 1.25-4C | BG23: ｍ | BH23: 690 | BI23: 580 | BJ23: 0.026
H24: 046454000 | I24: 変換ｺﾈｸﾀJ | J24: BSC-10用 | K24: 個 | L24: 4850 | M24: 1360 | N24: 0 | BE24: ｹｰﾌﾞﾙ(ﾗｯｸ配線) | BF24: CVV 1.25-5C | BG24: ｍ | BH24: 870 | BI24: 740 | BJ24: 0.034
I25: ---MAC-5010で使用-------- | BE25: ｹｰﾌﾞﾙ(ﾗｯｸ配線) | BF25: CVV 1.25-6C | BG25: ｍ | BH25: 890 | BI25: 760 | BJ25: 0.034
C26: 【変更履歴】 | H26: 024321000 | I26: 変換ｺﾈｸﾀA | J26: 温度･日射用 | K26: 個 | L26: 1620 | M26: 230 | N26: 0 | BE26: ｹｰﾌﾞﾙ(ﾗｯｸ配線) | BF26: CVV 1.25-7C | BG26: ｍ | BH26: 1060 | BI26: 900 | BJ26: 0.041
C27: ’11.05訂正箇所 値上・原価訂正 | H27: 024322000 | I27: 変換ｺﾈｸﾀB | J27: 湿度用 | K27: 個 | L27: 1620 | M27: 250 | N27: 0 | BE27: ｹｰﾌﾞﾙ(ﾗｯｸ配線) | BF27: CVV 1.25-8C | BG27: ｍ | BH27: 1080 | BI27: 930 | BJ27: 0.041
C28: ’14.08 価格・構成見直しにつき、再構成 | H28: 024324000 | I28: 変換ｺﾈｸﾀC | J28: 二酸化炭素用 | K28: 個 | L28: 1620 | M28: 270 | N28: 0 | BE28: ｹｰﾌﾞﾙ(ﾗｯｸ配線) | BF28: CVV 1.25-10C | BG28: ｍ | BH28: 1320 | BI28: 1130 | BJ28: 0.05
C29: 2016_4/69期農用機器価格表対応 | H29: 024326000 | I29: 変換ｺﾈｸﾀD | J29: 風速用 | K29: 個 | L29: 1620 | M29: 150 | N29: 0 | BE29: ------------
C30: 70期価格修正 | H30: 024332000 | I30: 変換ｺﾈｸﾀE | J30: 風向風速用 | K30: 個 | L30: 4370 | M30: 1490 | N30: 0 | BE30: ｹｰﾌﾞﾙ(ﾗｯｸ配線) | BF30: CV 2.0-4C | BG30: m | BH30: 780 | BI30: 660 | BJ30: 0.02
C31: 71期価格修正 | H31: 039362000 | I31: 変換ｺﾈｸﾀF | J31: 汎用ｾﾝｻｰ用 | K31: 個 | L31: 7280 | M31: 1250 | N31: 0 | BE31: ｹｰﾌﾞﾙ(ﾗｯｸ配線) | BF31: CV 3.5-4C | BG31: m | BH31: 960 | BI31: 820 | BJ31: 0.024
C32: 73期農用機器･熱機器･KHV･ｻｰﾋﾞｽ部品価格表対応 | I32: ------------ | BE32: ｹｰﾌﾞﾙ(ﾗｯｸ配線) | BF32: CV 5.5-4C | BG32: m | BH32: 1220 | BI32: 1040 | BJ32: 0.03
C33: ’19.09訂正箇所：配線材品名・型式、D10～13 | H33: 106351000 | I33: 雨･風速・風向感知器 | J33: TSC-53 | K33: ｾｯﾄ | L33: 1043000 | M33: 161030 | N33: 0 | BE33: ｹｰﾌﾞﾙ(ﾗｯｸ配線) | BF33: CV 8.0-4C | BG33: m | BH33: 1400 | BI33: 1190 | BJ33: 0.035
C34: 74期価格修正 | H34: 106348000 | I34: 雨･風速感知器 | J34: TSC-13 | K34: ｾｯﾄ | L34: 600000 | M34: 104390 | N34: 0 | BE34: ------------
C35: 75期価格修正・ABX追加・AN標準変更 | H35: 105991000 | I35: 雨感知器 | J35: TSC-23 | K35: ｾｯﾄ | L35: 100400 | M35: 22490 | N35: 0 | BE35: ｹｰﾌﾞﾙ(管内配線) | BF35: CV 2.0-4C | BG35: m | BH35: 720 | BI35: 620 | BJ35: 0.024
C36: 76期価格修正 | H36: 001623000 | I36: 風速感知器 | J36: TSC-33 | K36: ｾｯﾄ | L36: 530100 | M36: 93590 | N36: 0 | BE36: ｹｰﾌﾞﾙ(管内配線) | BF36: CV 3.5-4C | BG36: m | BH36: 820 | BI36: 700 | BJ36: 0.03
C37: 77期価格修正 | H37: 010087000 | I37: 避雷器 | J37: LA-200T | K37: 個 | L37: 61500 | M37: 16840 | N37: 0 | BE37: ｹｰﾌﾞﾙ(管内配線) | BF37: CV 5.5-4C | BG37: m | BH37: 1020 | BI37: 870 | BJ37: 0.034
C38: 78期価格修正 | I38: --ANｱﾄﾞﾊﾞﾝｽ---------- | BE38: ｹｰﾌﾞﾙ(管内配線) | BF38: CV 8.0-4C | BG38: m | BH38: 1230 | BI38: 1050 | BJ38: 0.038
C39: 79期価格修正 | H39: 043781000 | I39: ANｱﾄﾞﾊﾞﾝｽ AN-BOX | J39: ABX-1000A | K39: 台 | L39: 406000 | M39: 188780 | N39: 0 | BE39: ------------
C40: 制御盤取付工事 | H40: 039361000 | I40: ﾓﾆﾀﾘﾝｸﾞｾﾝｻｰ | J40: MAC-5010 | K40: 台 | L40: 134000 | M40: 71530 | N40: 0 | BE40: ｼｰﾙﾄﾞ線 | BF40: MVVS 0.5SQ-2C | BG40: ｍ | BH40: =ROUNDUP(BI40/$BI$2,-1) -> 120 | BI40: 100 | BJ40: 0.015 | BK40: 59 | BL40: 100m社内
C41: 同上取付工事 | H41: 049363000 | I41: AN-BOX用警報入力ﾕﾆｯﾄ | J41: AAL-1001A | K41: 台 | L41: 57500 | M41: 12330 | N41: 0 | BE41: ｼｰﾙﾄﾞ線 | BF41: MVVS 0.75SQ-3C | BG41: ｍ | BH41: =ROUNDUP(BI41/$BI$2,-1) -> 190 | BI41: 155 | BJ41: 0.017 | BK41: 91
C42: 電源配線工事 | H42: RE1000123 | I42: AN-BOX登録料 | J42: (初回) | K42: 台 | L42: 5000 | M42: 3000 | N42: 0 | BE42: ｼｰﾙﾄﾞ線 | BF42: MVVS 1.25SQ-3C | BG42: ｍ | BH42: =ROUNDUP(BI42/$BI$2,-1) -> 230 | BI42: 190 | BJ42: 0.019 | BK42: 116 | BL42: 100m社内
C43: 二次配線工事 | H43: RE1000110 | I43: ANｱﾄﾞﾊﾞﾝｽ遠隔機器利用料 | J43: (月払い) | K43: 台/月 | L43: 2300 | M43: 1299 | N43: 0 | BE43: ------------
C44: 制御配線工事 | H44: RE1000113 | I44: ANｱﾄﾞﾊﾞﾝｽ遠隔機器利用料 | J44: (年払い) | K44: 台/年 | L44: 24900 | M44: 15588 | N44: 0 | BE44: ﾋﾞﾆｰﾙｷｬﾌﾞﾀｲﾔｺｰﾄﾞ | BF44: VCTF 0.75SQ-2C 富士 | BG44: ｍ | BH44: =ROUNDUP(BI44/$BI$2,-1) -> 80 | BI44: 60 | BJ44: 0.016 | BK44: 38
C45: 通信配線工事 | H45: RE1000116 | I45: ANｱﾄﾞﾊﾞﾝｽ遠隔機器利用料 | J45: (2ヵ月停止) | K45: 台/年 | L45: 23000 | M45: 15588 | N45: 0 | BE45: ﾋﾞﾆｰﾙｷｬﾌﾞﾀｲﾔｺｰﾄﾞ | BF45: VCTF 0.75SQ-3C 富士 | BG45: ｍ | BH45: =ROUNDUP(BI45/$BI$2,-1) -> 100 | BI45: 81 | BJ45: 0.017 | BK45: 47 | BL45: 100m社内
C46: 同上配線工事 | H46: RE1000119 | I46: ANｱﾄﾞﾊﾞﾝｽ遠隔機器利用料 | J46: (3ヵ月停止) | K46: 台/年 | L46: 20700 | M46: 15588 | N46: 0 | BE46: ﾋﾞﾆｰﾙｷｬﾌﾞﾀｲﾔｺｰﾄﾞ | BF46: VCTF 0.75SQ-4C 富士 | BG46: ｍ | BH46: =ROUNDUP(BI46/$BI$2,-1) -> 130 | BI46: 110 | BJ46: 0.018 | BK46: 53 | BL46: 100m社内
C47: 分電盤取付工事 | H47: RE1000122 | I47: ANｱﾄﾞﾊﾞﾝｽ遠隔機器利用料 | J47: （4ヵ月停止） | K47: 台/年 | L47: 18400 | M47: 15588 | N47: 0 | BE47: ﾋﾞﾆｰﾙｷｬﾌﾞﾀｲﾔｺｰﾄﾞ | BF47: VCTF 0.75SQ-6C 富士 | BG47: ｍ | BH47: =ROUNDUP(BI47/$BI$2,-1) -> 200 | BI47: 170 | BJ47: 0.019 | BK47: 84 | BL47: 100m社内
C48: 制御器取付工事 | H48: RE1000109 | I48: ANｱﾄﾞﾊﾞﾝｽﾓﾆﾀﾘﾝｸﾞ機器利用料 | J48: (月払い) | K48: 台/月 | L48: 1700 | M48: 904 | N48: 0 | BE48: ﾋﾞﾆｰﾙｷｬﾌﾞﾀｲﾔｺｰﾄﾞ | BF48: VCTF 0.75SQ-7C 富士 | BG48: ｍ | BH48: =ROUNDUP(BI48/$BI$2,-1) -> 230 | BI48: 190 | BJ48: 0.02 | BK48: 117 | BL48: 100m社内
C49: 警報機取付工事 | H49: RE1000112 | I49: ANｱﾄﾞﾊﾞﾝｽﾓﾆﾀﾘﾝｸﾞ機器利用料 | J49: (年払い) | K49: 台/年 | L49: 18400 | M49: 10848 | N49: 0 | BE49: ﾋﾞﾆｰﾙｷｬﾌﾞﾀｲﾔｺｰﾄﾞ | BF49: VCTF 2.0SQ-2C 富士 | BG49: ｍ | BH49: =ROUNDUP(BI49/$BI$2,-1) -> 160 | BI49: 130 | BJ49: 0.022 | BK49: 73 | BL49: 100m社内
C50: 計測器取付工事 | H50: RE1000115 | I50: ANｱﾄﾞﾊﾞﾝｽﾓﾆﾀﾘﾝｸﾞ機器利用料 | J50: (2ヵ月停止) | K50: 台/年 | L50: 17000 | M50: 10848 | N50: 0 | BE50: ﾋﾞﾆｰﾙｷｬﾌﾞﾀｲﾔｺｰﾄﾞ | BF50: VCTF 2.0SQ-3C 富士 | BG50: ｍ | BH50: =ROUNDUP(BI50/$BI$2,-1) -> 220 | BI50: 180 | BJ50: 0.023 | BK50: 90
C51: 避雷針取付工事 | H51: RE1000118 | I51: ANｱﾄﾞﾊﾞﾝｽﾓﾆﾀﾘﾝｸﾞ機器利用料 | J51: (3ヵ月停止) | K51: 台/年 | L51: 15300 | M51: 10848 | N51: 0 | BE51: ﾋﾞﾆｰﾙｷｬﾌﾞﾀｲﾔｺｰﾄﾞ | BF51: VCTF 2.0SQ-4C 富士 | BG51: ｍ | BH51: =ROUNDUP(BI51/$BI$2,-1) -> 260 | BI51: 220 | BJ51: 0.024 | BK51: 121
C52: 避雷器取付工事 | H52: RE1000121 | I52: ANｱﾄﾞﾊﾞﾝｽﾓﾆﾀﾘﾝｸﾞ機器利用料 | J52: （4ヵ月停止） | K52: 台/年 | L52: 13600 | M52: 10848 | N52: 0 | BE52: ﾋﾞﾆｰﾙｷｬﾌﾞﾀｲﾔｺｰﾄﾞ | BF52: VCT 3.5SQ-4C 富士 | BG52: ｍ | BH52: =ROUNDUP(BI52/$BI$2,-1) -> 490 | BI52: 410 | BJ52: 0.03
C53: ｾﾝｻ取付工事 | H53: RE1000108 | I53: ANｱﾄﾞﾊﾞﾝｽ警報機器利用料 | J53: (月払い) | K53: 台/月 | L53: 1300 | M53: 650 | N53: 0 | BE53: ﾋﾞﾆｰﾙｷｬﾌﾞﾀｲﾔｺｰﾄﾞ | BF53: VCT 5.5SQ-4C 富士 | BG53: ｍ | BH53: =ROUNDUP(BI53/$BI$2,-1) -> 730 | BI53: 620 | BJ53: 0.034 | BK53: 320
C54: 同上ｾﾝｻ取付工事 | H54: RE1000111 | I54: ANｱﾄﾞﾊﾞﾝｽ警報機器利用料 | J54: (年払い) | K54: 台/年 | L54: 14100 | M54: 7800 | N54: 0 | BE54: ﾋﾞﾆｰﾙｷｬﾌﾞﾀｲﾔｺｰﾄﾞ | BF54: VCT 8.0SQ-4C 伸興 | BG54: ｍ | BH54: =ROUNDUP(BI54/$BI$2,-1) -> 830 | BI54: 700 | BJ54: 0.038 | BK54: 550
C55: ｱｰｽ工事 | H55: RE1000114 | I55: ANｱﾄﾞﾊﾞﾝｽ警報機器利用料 | J55: (2ヵ月停止) | K55: 台/年 | L55: 13000 | M55: 7800 | N55: 0
C56: 制御機器試運転調整 | H56: RE1000117 | I56: ANｱﾄﾞﾊﾞﾝｽ警報機器利用料 | J56: (3ヵ月停止) | K56: 台/年 | L56: 11700 | M56: 7800 | N56: 0
C57: ｿﾌﾄｲﾝｽﾄｰﾙ･調整 | H57: RE1000120 | I57: ANｱﾄﾞﾊﾞﾝｽ警報機器利用料 | J57: （4ヵ月停止） | K57: 台/年 | L57: 10400 | M57: 7800 | N57: 0
C58: 消耗品雑材

Sheet 管材表
J1: 品番 | K1: 品名 | L1: 型式 | M1: 単位 | N1: 価格 | O1: 原価 | P1: 歩単 | R1: 品番 | S1: 品名 | T1: 型式 | U1: 単位 | V1: 価格 | W1: 原価 | X1: 歩単 | Z1: 品番 | AA1: 品名 | AB1: 型式 | AC1: 単位 | AD1: 価格 | AE1: 原価 | AF1: 歩単 | AH1: 品番 | AI1: 品名 | AJ1: 型式 | AK1: 単位 | AL1: 価格 | AM1: 原価 | AN1: 歩単 | AP1: 品番 | AQ1: 品名 | AR1: 型式 | AS1: 単位 | AT1: 価格 | AU1: 原価 | AV1: 歩単 | AX1: 品番 | AY1: 品名 | AZ1: 型式 | BA1: 単位 | BB1: 価格 | BC1: 原価 | BD1: 歩単 | BF1: 品番 | BG1: 品名 | BH1: 型式 | BI1: 単位 | BJ1: 価格 | BK1: 原価 | BL1: 歩単 | BN1: 品番 | BO1: 品名 | BP1: 型式 | BQ1: 単位 | BR1: 価格 | BS1: 原価 | BT1: 歩単 | BV1: 品番 | BW1: 品名 | BX1: 型式 | BY1: 単位 | BZ1: 価格 | CA1: 原価 | CB1: 歩単 | CD1: 品番 | CE1: 品名 | CF1: 型式 | CG1: 単位 | CH1: 価格 | CI1: 原価 | CJ1: 歩単 | CL1: 品番 | CM1: 品名 | CN1: 型式 | CO1: 単位 | CP1: 価格 | CQ1: 原価 | CR1: 歩単 | CT1: 品番 | CU1: 品名 | CV1: 型式 | CW1: 単位 | CX1: 価格 | CY1: 原価 | CZ1: 歩単 | DB1: 品番 | DC1: 品名 | DD1: 型式 | DE1: 単位 | DF1: 価格 | DG1: 原価 | DH1: 歩単 | DJ1: 品番 | DK1: 品名 | DL1: 型式 | DM1: 単位 | DN1: 価格 | DO1: 原価 | DP1: 歩単 | DR1: 品番 | DS1: 品名 | DT1: 型式 | DU1: 単位 | DV1: 価格 | DW1: 原価 | DX1: 歩単 | DZ1: 品番 | EA1: 品名 | EB1: 型式 | EC1: 単位 | ED1: 価格 | EE1: 原価 | EF1: 歩単 | EH1: 品番 | EI1: 品名 | EJ1: 型式 | EK1: 単位 | EL1: 価格 | EM1: 原価 | EN1: 歩単 | EP1: 品番 | EQ1: 品名 | ER1: 型式 | ES1: 単位 | ET1: 価格 | EU1: 原価 | EV1: 歩単 | EX1: 品番 | EY1: 品名 | EZ1: 型式 | FA1: 単位 | FB1: 価格 | FC1: 原価 | FD1: 歩単 | FF1: 品番 | FG1: 品名 | FH1: 型式 | FI1: 単位 | FJ1: 価格 | FK1: 原価 | FL1: 歩単 | FN1: 品番 | FO1: 品名 | FP1: 型式 | FQ1: 単位 | FR1: 価格 | FS1: 原価 | FT1: 歩単 | FV1: 品番 | FW1: 品名 | FX1: 型式 | FY1: 単位 | FZ1: 価格 | GA1: 原価 | GB1: 歩単
B3: 1 | C3: SGP鋼管 | D3: k3 | E3: 1 | F3: 機械室配管工事費 | I3: 機械室配管 | K3: SGP鋼管(白) | L3: 15A | M3: m | N3: 2650 | O3: 1410 | P3: 0.12 | S3: STK鋼管 | T3: 40A(Znﾒｯｷ) | U3: m | V3: 3050 | W3: 2410 | X3: 0.23 | AA3: 外面被覆鋼管 | AB3: 15A | AC3: m | AD3: 2640 | AE3: 1980 | AF3: 0.12 | AI3: ｽﾃﾝﾚｽ管 | AJ3: 15A | AK3: m | AL3: 3710 | AM3: 2800 | AN3: 0.12 | AQ3: 塩ﾋﾞ管 | AR3: VP φ13 | AS3: m | AT3: 250 | AU3: 160 | AV3: 0.06 | AY3: 硬質ﾎﾟﾘ管 | AZ3: φ22/19 200m | BA3: 巻 | BB3: 43560 | BC3: 31370 | BD3: 12 | BG3: ｹﾞｰﾄ弁 | BH3: 15A | BI3: 個 | BJ3: 6510 | BK3: 4230 | BL3: 0.08 | BO3: ﾁｬｯｷ弁 | BP3: 15A(ｽｲﾝｸﾞ) | BQ3: 個 | BR3: 5810 | BS3: 3780 | BT3: 0.08 | BW3: ﾊﾞﾀﾌﾗｲ弁 | BX3: 50A(ｳｴﾊ) | BY3: 個 | BZ3: 27100 | CA3: 17620 | CB3: 0.1 | CE3: ｸﾞﾛｰﾌﾞ弁 | CF3: 15A | CG3: 個 | CH3: 7000 | CI3: 4550 | CJ3: 0.08 | CM3: ﾏﾚｰﾌﾞﾙ弁 | CN3: 15A | CO3: 個 | CP3: 12200 | CQ3: 7930 | CR3: 0.08 | CU3: ﾎﾞｰﾙ弁(2方) | CV3: 15A | CW3: 個 | CX3: 7660 | CY3: 4980 | CZ3: 0.08 | DC3: Yｽﾄﾚｰﾅ | DD3: 15A | DE3: 個 | DF3: 6080 | DG3: 3950 | DH3: 0.08 | DK3: 電動ﾎﾞｰﾙ弁(2方) | DL3: 15A | DM3: 個 | DN3: 24400 | DO3: 15860 | DP3: 0.08 | DS3: ﾌﾚｷｼﾞｮｲﾝﾄ(U) | DT3: 15A*300L | DU3: 本 | DV3: 3700 | DW3: 1700 | DX3: 0.12 | EA3: 伸縮継手 | EB3: 20A(複式) | EC3: 個 | ED3: 79600 | EE3: =ED3*0.55 -> 43780 | EF3: 0.62 | EI3: 減圧弁(蒸気用) | EJ3: 15A RP9-L | EK3: 個 | EL3: 126000 | EM3: =EL3*0.65 -> 81900 | EN3: 1.14 | EQ3: 温度計 | ER3: 丸L形 120℃ | ES3: 個 | ET3: 11700 | EU3: 6210 | EV3: 0.08 | EX3: 101678000 | EY3: 油配管ｾｯﾄ | EZ3: BOP-CU5M | FA3: 個 | FB3: 16500 | FC3: 4670 | FD3: 0.3 | FG3: 保温(ｶﾗｰﾗｯｷﾝｸﾞ) | FH3: 15A | FI3: ｍ | FJ3: 7680 | FK3: 5150 | FL3: 0 | FO3: 保温(亀甲巻き) | FP3: 15A | FQ3: ｍ | FR3: 3690 | FS3: 2270 | FT3: 0 | FW3: ﾗｲﾄｶﾊﾞｰ | FX3: 15A | FY3: ｍ | FZ3: 370 | GA3: 260 | GB3: 0.04
B4: 2 | C4: STK鋼管 | D4: s3 | E4: 2 | F4: 屋外配管工事費 | I4: 2.3 | K4: SGP鋼管(白) | L4: 20A | M4: m | N4: 3260 | O4: 1720 | P4: 0.14 | S4: STK鋼管 | T4: 50A(Znﾒｯｷ) | U4: m | V4: 4170 | W4: 3350 | X4: 0.29 | AA4: 外面被覆鋼管 | AB4: 20A | AC4: m | AD4: 3040 | AE4: 2280 | AF4: 0.14 | AI4: ｽﾃﾝﾚｽ管 | AJ4: 20A | AK4: m | AL4: 4510 | AM4: 3400 | AN4: 0.14 | AQ4: 塩ﾋﾞ管 | AR4: VP φ16 | AS4: m | AT4: 360 | AU4: 240 | AV4: 0.07 | AY4: 硬質ﾎﾟﾘ管 | AZ4: PE12-13 外径φ21.5 120m | BA4: 巻 | BB4: 24300 | BC4: 17740 | BD4: 7.2 | BG4: ｹﾞｰﾄ弁 | BH4: 20A | BI4: 個 | BJ4: 8690 | BK4: 5650 | BL4: 0.09 | BO4: ﾁｬｯｷ弁 | BP4: 20A(ｽｲﾝｸﾞ) | BQ4: 個 | BR4: 7430 | BS4: 4830 | BT4: 0.09 | BW4: ﾊﾞﾀﾌﾗｲ弁 | BX4: 65A(ｳｴﾊ) | BY4: 個 | BZ4: 28400 | CA4: 18460 | CB4: 0.19 | CE4: ｸﾞﾛｰﾌﾞ弁 | CF4: 20A | CG4: 個 | CH4: 9150 | CI4: 5950 | CJ4: 0.09 | CM4: ﾏﾚｰﾌﾞﾙ弁 | CN4: 20A | CO4: 個 | CP4: 13900 | CQ4: 9040 | CR4: 0.09 | CU4: ﾎﾞｰﾙ弁(2方) | CV4: 20A | CW4: 個 | CX4: 9100 | CY4: 5920 | CZ4: 0.09 | DC4: Yｽﾄﾚｰﾅ | DD4: 20A | DE4: 個 | DF4: 7750 | DG4: 5040 | DH4: 0.09 | DK4: 電動ﾎﾞｰﾙ弁(2方) | DL4: 20A | DM4: 個 | DN4: 26500 | DO4: 17230 | DP4: 0.09 | DS4: ﾌﾚｷｼﾞｮｲﾝﾄ(U) | DT4: 20A*300L | DU4: 本 | DV4: 4700 | DW4: 2160 | DX4: 0.12 | EA4: 伸縮継手 | EB4: 25A(複式) | EC4: 個 | ED4: 82600 | EE4: =ED4*0.55 -> 45430 | EF4: 0.84 | EI4: 減圧弁(蒸気用) | EJ4: 20A RP9-L | EK4: 個 | EL4: 126000 | EM4: =EL4*0.65 -> 81900 | EN4: 1.35 | EQ4: 温度計 | ER4: 丸S形 120℃ | ES4: 個 | ET4: 11700 | EU4: 6210 | EV4: 0.08 | EX4: 101674000 | EY4: 油配管ｾｯﾄ | EZ4: BOP-CU10M | FA4: 個 | FB4: 32100 | FC4: 7240 | FD4: 0.5 | FG4: 保温(ｶﾗｰﾗｯｷﾝｸﾞ) | FH4: 20A | FI4: ｍ | FJ4: 7920 | FK4: 5310 | FL4: 0 | FO4: 保温(亀甲巻き) | FP4: 20A | FQ4: ｍ | FR4: 3780 | FS4: 2340 | FT4: 0 | FW4: ﾗｲﾄｶﾊﾞｰ | FX4: 20A | FY4: ｍ | FZ4: 390 | GA4: 310 | GB4: 0.04
B5: 3 | C5: ﾗｲﾆﾝｸﾞ鋼管 | D5: aa3 | E5: 3 | F5: 架空配管工事費 | I5: 0.15 | K5: SGP鋼管(白) | L5: 25A | M5: m | N5: 4540 | O5: 2400 | P5: 0.17 | S5: STK鋼管 | T5: 65A(Znﾒｯｷ) | U5: m | V5: 5880 | W5: 4730 | X5: 0.37 | AA5: 外面被覆鋼管 | AB5: 25A | AC5: m | AD5: 3680 | AE5: 2760 | AF5: 0.17 | AI5: ｽﾃﾝﾚｽ管 | AJ5: 25A | AK5: m | AL5: 5450 | AM5: 4090 | AN5: 0.14 | AQ5: 塩ﾋﾞ管 | AR5: VP φ20 | AS5: m | AT5: 420 | AU5: 270 | AV5: 0.07 | AY5: 硬質ﾎﾟﾘ管 | AZ5: PE12-20 外径φ27 120m | BA5: 巻 | BB5: 31380 | BC5: 22900 | BD5: 8.4 | BG5: ｹﾞｰﾄ弁 | BH5: 25A | BI5: 個 | BJ5: 11900 | BK5: 7740 | BL5: 0.12 | BO5: ﾁｬｯｷ弁 | BP5: 25A(ｽｲﾝｸﾞ) | BQ5: 個 | BR5: 11400 | BS5: 7410 | BT5: 0.12 | BW5: ﾊﾞﾀﾌﾗｲ弁 | BX5: 80A(ｳｴﾊ) | BY5: 個 | BZ5: 33000 | CA5: 21450 | CB5: 0.23 | CE5: ｸﾞﾛｰﾌﾞ弁 | CF5: 25A | CG5: 個 | CH5: 13000 | CI5: 8450 | CJ5: 0.12 | CM5: ﾏﾚｰﾌﾞﾙ弁 | CN5: 25A | CO5: 個 | CP5: 17500 | CQ5: 11380 | CR5: 0.12 | CU5: ﾎﾞｰﾙ弁(2方) | CV5: 25A | CW5: 個 | CX5: 12400 | CY5: 8060 | CZ5: 0.12 | DC5: Yｽﾄﾚｰﾅ | DD5: 25A | DE5: 個 | DF5: 12100 | DG5: 7870 | DH5: 0.12 | DK5: 電動ﾎﾞｰﾙ弁(2方) | DL5: 25A | DM5: 個 | DN5: 35100 | DO5: 22820 | DP5: 0.12 | DS5: ﾌﾚｷｼﾞｮｲﾝﾄ(U) | DT5: 25A*300L | DU5: 本 | DV5: 5700 | DW5: 2620 | DX5: 0.14 | EA5: 伸縮継手 | EB5: 32A(複式) | EC5: 個 | ED5: 93600 | EE5: =ED5*0.55 -> 51480 | EF5: 0.86 | EI5: 減圧弁(蒸気用) | EJ5: 25A RP9-L | EK5: 個 | EL5: 158000 | EM5: =EL5*0.65 -> 102700 | EN5: 1.85 | EQ5: 温度計 | ER5: φ80 120℃ | ES5: 個 | ET5: 14040 | EU5: 7440 | EV5: 0.08 | EX5: 103313000 | EY5: 油配管ｾｯﾄ | EZ5: BOP-CU20M | FA5: 個 | FB5: 46600 | FC5: 11250 | FD5: 0.8 | FG5: 保温(ｶﾗｰﾗｯｷﾝｸﾞ) | FH5: 25A | FI5: ｍ | FJ5: 8040 | FK5: 5390 | FL5: 0 | FO5: 保温(亀甲巻き) | FP5: 25A | FQ5: ｍ | FR5: 4140 | FS5: 2570 | FT5: 0 | FW5: ﾗｲﾄｶﾊﾞｰ | FX5: 25A | FY5: ｍ | FZ5: 470 | GA5: 340 | GB5: 0.05
B6: 4 | C6: ｽﾃﾝﾚｽ管・継手 | D6: ai3 | E6: 4 | F6: 温室内配管工事費 | K6: SGP鋼管(白) | L6: 32A | M6: m | N6: 6020 | O6: 3190 | P6: 0.21 | S6: STK鋼管 | T6: 80A(Znﾒｯｷ) | U6: m | V6: 6900 | W6: 5530 | X6: 0.42 | AA6: 外面被覆鋼管 | AB6: 32A | AC6: m | AD6: 4680 | AE6: 3510 | AF6: 0.21 | AI6: ｽﾃﾝﾚｽ管 | AJ6: 32A | AK6: m | AL6: 6890 | AM6: 5180 | AN6: 0.17 | AQ6: 塩ﾋﾞ管 | AR6: VP φ25 | AS6: m | AT6: 600 | AU6: 390 | AV6: 0.09 | AY6: 硬質ﾎﾟﾘ管 | AZ6: PE12-25 外径φ34 90m | BA6: 巻 | BB6: 32350 | BC6: 23620 | BD6: 8.1 | BG6: ｹﾞｰﾄ弁 | BH6: 32A | BI6: 個 | BJ6: 20100 | BK6: 13070 | BL6: 0.14 | BO6: ﾁｬｯｷ弁 | BP6: 32A(ｽｲﾝｸﾞ) | BQ6: 個 | BR6: 16300 | BS6: 10600 | BT6: 0.14 | BW6: ﾊﾞﾀﾌﾗｲ弁 | BX6: 100A(ｳｴﾊ) | BY6: 個 | BZ6: 42600 | CA6: 27690 | CB6: 0.28 | CE6: ｸﾞﾛｰﾌﾞ弁 | CF6: 32A | CG6: 個 | CH6: 24000 | CI6: 15600 | CJ6: 0.14 | CM6: ﾏﾚｰﾌﾞﾙ弁 | CN6: 32A | CO6: 個 | CP6: 27600 | CQ6: 17940 | CR6: 0.14 | CU6: ﾎﾞｰﾙ弁(2方) | CV6: 32A | CW6: 個 | CX6: 18600 | CY6: 12090 | CZ6: 0.14 | DC6: Yｽﾄﾚｰﾅ | DD6: 32A | DE6: 個 | DF6: 17800 | DG6: 11570 | DH6: 0.14 | DK6: 電動ﾎﾞｰﾙ弁(2方) | DL6: 32A | DM6: 個 | DN6: 48400 | DO6: 31460 | DP6: 0.14 | DS6: ﾌﾚｷｼﾞｮｲﾝﾄ(U) | DT6: 32A*300L | DU6: 本 | DV6: 7300 | DW6: 3360 | DX6: 0.16 | EA6: 伸縮継手 | EB6: 40A(複式) | EC6: 個 | ED6: 107000 | EE6: =ED6*0.55 -> 58850 | EF6: 0.88 | EI6: 減圧弁(蒸気用) | EJ6: 32A RP9-L | EK6: 個 | EL6: 159000 | EM6: =EL6*0.65 -> 103350 | EN6: 2.33 | EQ6: 水高温度計 | ER6: φ100 S形 | ES6: 個 | ET6: 23400 | EU6: 12410 | EV6: 0.08 | EX6: 105296000 | EY6: 油配管ｾｯﾄ | EZ6: BOP-805M | FA6: 個 | FB6: 11800 | FC6: 4430 | FD6: 0.3 | FG6: 保温(ｶﾗｰﾗｯｷﾝｸﾞ) | FH6: 32A | FI6: ｍ | FJ6: 8280 | FK6: 5550 | FL6: 0 | FO6: 保温(亀甲巻き) | FP6: 32A | FQ6: ｍ | FR6: 4230 | FS6: 2630 | FT6: 0 | FW6: ﾗｲﾄｶﾊﾞｰ | FX6: 32A | FY6: ｍ | FZ6: 600 | GA6: 440 | GB6: 0.05
B7: 5 | C7: 塩ﾋﾞ管・耐熱塩ビ管 | D7: aq3 | E7: 5 | F7: 排水配管工事費 | I7: 室内配管 | K7: SGP鋼管(白) | L7: 40A | M7: m | N7: 6910 | O7: 3660 | P7: 0.23 | S7: STK鋼管 | T7: 100A(Znﾒｯｷ) | U7: m | V7: 9590 | W7: 7660 | X7: 0.57 | AA7: 外面被覆鋼管 | AB7: 40A | AC7: m | AD7: 5180 | AE7: 3890 | AF7: 0.23 | AI7: ｽﾃﾝﾚｽ管 | AJ7: 40A | AK7: m | AL7: 7660 | AM7: 5780 | AN7: 0.21 | AQ7: 塩ﾋﾞ管 | AR7: VP φ30 | AS7: m | AT7: 760 | AU7: 490 | AV7: 0.1 | AY7: 硬質ﾎﾟﾘ管 | AZ7: PE12-30 外径φ42 90m | BA7: 巻 | BB7: 43210 | BC7: 31540 | BD7: 9 | BG7: ｹﾞｰﾄ弁 | BH7: 40A | BI7: 個 | BJ7: 26700 | BK7: 17360 | BL7: 0.16 | BO7: ﾁｬｯｷ弁 | BP7: 40A(ｽｲﾝｸﾞ) | BQ7: 個 | BR7: 21200 | BS7: 13780 | BT7: 0.16 | BW7: ﾊﾞﾀﾌﾗｲ弁 | BX7: 125A(ｳｴﾊ) | BY7: 個 | BZ7: 60600 | CA7: 39390 | CB7: 0.34 | CE7: ｸﾞﾛｰﾌﾞ弁 | CF7: 40A | CG7: 個 | CH7: 27700 | CI7: 18010 | CJ7: 0.16 | CM7: ﾏﾚｰﾌﾞﾙ弁 | CN7: 40A | CO7: 個 | CP7: 29200 | CQ7: 18980 | CR7: 0.16 | CU7: ﾎﾞｰﾙ弁(2方) | CV7: 40A | CW7: 個 | CX7: 22500 | CY7: 14630 | CZ7: 0.16 | DC7: Yｽﾄﾚｰﾅ | DD7: 40A | DE7: 個 | DF7: 22200 | DG7: 14430 | DH7: 0.16 | DK7: 電動ﾎﾞｰﾙ弁(2方) | DL7: 40A | DM7: 個 | DN7: 61000 | DO7: 39650 | DP7: 0.16 | DS7: ﾌﾚｷｼﾞｮｲﾝﾄ(U) | DT7: 40A*300L | DU7: 本 | DV7: 9100 | DW7: 4190 | DX7: 0.18 | EA7: 伸縮継手 | EB7: 50A(複式) | EC7: 個 | ED7: 121000 | EE7: =ED7*0.55 -> 66550 | EF7: 1.12 | EI7: 減圧弁(蒸気用) | EJ7: 40A RP9-L | EK7: 個 | EL7: 184000 | EM7: =EL7*0.65 -> 119600 | EN7: 2.63 | EQ7: 水高温度計 | ER7: φ100 L形 | ES7: 個 | ET7: 21060 | EU7: 11180 | EV7: 0.08 | EX7: 105297000 | EY7: 油配管ｾｯﾄ | EZ7: BOP-810M | FA7: 個 | FB7: 18100 | FC7: 7390 | FD7: 0.4 | FG7: 保温(ｶﾗｰﾗｯｷﾝｸﾞ) | FH7: 40A | FI7: ｍ | FJ7: 8520 | FK7: 5720 | FL7: 0 | FO7: 保温(亀甲巻き) | FP7: 40A | FQ7: ｍ | FR7: 4370 | FS7: 2690 | FT7: 0 | FW7: ﾗｲﾄｶﾊﾞｰ | FX7: 40A | FY7: ｍ | FZ7: 680 | GA7: 480 | GB7: 0.06
B8: 6 | C8: ﾎﾟﾘ管・ﾎﾟﾘﾌﾞﾃﾞﾝ管 | D8: ay3 | E8: 6 | F8: 養液ﾍﾞｯﾄ配管工事費 | I8: 2.3 | K8: SGP鋼管(白) | L8: 50A | M8: m | N8: 9480 | O8: 5020 | P8: 0.29 | S8: STK鋼管 | T8: 125A(Znﾒｯｷ) | U8: m | V8: 12510 | W8: 10000 | X8: 0.69 | AA8: 外面被覆鋼管 | AB8: 50A | AC8: m | AD8: 6850 | AE8: 5140 | AF8: 0.29 | AI8: ｽﾃﾝﾚｽ管 | AJ8: 50A | AK8: m | AL8: 9490 | AM8: 7150 | AN8: 0.23 | AQ8: 塩ﾋﾞ管 | AR8: VP φ40 | AS8: m | AT8: 1080 | AU8: 700 | AV8: 0.12 | AY8: ---------- | BG8: ｹﾞｰﾄ弁 | BH8: 50A | BI8: 個 | BJ8: 39100 | BK8: 25420 | BL8: 0.18 | BO8: ﾁｬｯｷ弁 | BP8: 50A(ｽｲﾝｸﾞ) | BQ8: 個 | BR8: 34100 | BS8: 22170 | BT8: 0.18 | BW8: ﾊﾞﾀﾌﾗｲ弁 | BX8: 150A(ｳｴﾊ) | BY8: 個 | BZ8: 66200 | CA8: 43030 | CB8: 0.38 | CE8: ｸﾞﾛｰﾌﾞ弁 | CF8: 50A | CG8: 個 | CH8: 45600 | CI8: 29640 | CJ8: 0.18 | CM8: ﾏﾚｰﾌﾞﾙ弁 | CN8: 50A | CO8: 個 | CP8: 41100 | CQ8: 26720 | CR8: 0.18 | CU8: ﾎﾞｰﾙ弁(2方) | CV8: 50A | CW8: 個 | CX8: 33600 | CY8: 21840 | CZ8: 0.18 | DC8: Yｽﾄﾚｰﾅ | DD8: 50A | DE8: 個 | DF8: 36800 | DG8: 23920 | DH8: 0.18 | DK8: 電動ﾎﾞｰﾙ弁(2方) | DL8: 50A | DM8: 個 | DN8: 70200 | DO8: 45630 | DP8: 0.18 | DS8: ﾌﾚｷｼﾞｮｲﾝﾄ(U) | DT8: 50A*300L | DU8: 本 | DV8: 12400 | DW8: 5700 | DX8: 0.22 | EA8: 伸縮継手 | EB8: 65A(複式) | EC8: 個 | ED8: 146000 | EE8: =ED8*0.55 -> 80300 | EF8: 1.5 | EI8: 減圧弁(蒸気用) | EJ8: 50A RP9-L | EK8: 個 | EL8: 217000 | EM8: =EL8*0.65 -> 141050 | EN8: 2.93 | EQ8: 圧力計 | ER8: φ100 10m | ES8: 個 | ET8: 17160 | EU8: 9100 | EV8: 0.08 | EX8: 046602000 | EY8: 逃し管ｾｯﾄ | EZ8: BOP-EP8M | FA8: 個 | FB8: 18000 | FC8: 4600 | FD8: 0.2 | FG8: 保温(ｶﾗｰﾗｯｷﾝｸﾞ) | FH8: 50A | FI8: ｍ | FJ8: 9120 | FK8: 6110 | FL8: 0 | FO8: 保温(亀甲巻き) | FP8: 50A | FQ8: ｍ | FR8: 5180 | FS8: 3200 | FT8: 0 | FW8: ﾗｲﾄｶﾊﾞｰ | FX8: 50A | FY8: ｍ | FZ8: 760 | GA8: 430 | GB8: 0.06
B9: 7 | C9: ｹﾞｰﾄ弁 | D9: bg3 | E9: 7 | F9: 養液ﾀﾝｸ内配管工事費 | I9: 0.13 | K9: SGP鋼管(白) | L9: 65A | M9: m | N9: 13540 | O9: 7180 | P9: 0.37 | S9: STK鋼管 | T9: 150A(Znﾒｯｷ) | U9: m | V9: 17780 | W9: 14250 | X9: 0.88 | AA9: 外面被覆鋼管 | AB9: 65A | AC9: m | AD9: 9330 | AE9: 7000 | AF9: 0.37 | AI9: ｽﾃﾝﾚｽ管 | AJ9: 65A | AK9: m | AL9: 12000 | AM9: 9050 | AN9: 0.29 | AQ9: 塩ﾋﾞ管 | AR9: VP φ50 | AS9: m | AT9: 1460 | AU9: 950 | AV9: 0.15 | AY9: ﾎﾟﾘｼﾞｮｲﾝﾄ | AZ9: φ13 | BA9: 個 | BB9: 1260 | BC9: 920 | BD9: 0.08 | BG9: ---------- | BO9: ---------- | BW9: ﾊﾞﾀﾌﾗｲ弁 | BX9: 200A(ｳｴﾊ) | BY9: 個 | BZ9: 111000 | CA9: 72150 | CB9: 0.55 | CE9: ---------- | CM9: ---------- | CU9: ﾎﾞｰﾙ弁(2方) | CV9: 65A | CW9: 個 | CX9: 75600 | CY9: 49140 | CZ9: 0.32 | DC9: Yｽﾄﾚｰﾅ | DD9: 65A | DE9: 個 | DF9: 90600 | DG9: 58890 | DH9: 0.32 | DK9: ---------- | DS9: ﾌﾚｷｼﾞｮｲﾝﾄ(F) | DT9: 65A*300L | DU9: 本 | DV9: 21100 | DW9: 5490 | DX9: 0.37 | EA9: 伸縮継手 | EB9: 80A(複式) | EC9: 個 | ED9: 184000 | EE9: =ED9*0.55 -> 101200 | EF9: 1.7 | EI9: 減圧弁(蒸気用) | EJ9: 65A RP9-L | EK9: 個 | EL9: 289000 | EM9: =EL9*0.65 -> 187850 | EN9: 3.29 | EQ9: 圧力計 | ER9: φ100 | ES9: 個 | ET9: 17160 | EU9: 9100 | EV9: 0.08 | EX9: 181612000 | EY9: ﾌﾚｷｼﾌﾞﾙﾎｰｽ | EZ9: 3/8B×1500 SUS | FA9: 本 | FB9: 15500 | FC9: 2920 | FD9: 0.2 | FG9: 保温(ｶﾗｰﾗｯｷﾝｸﾞ) | FH9: 65A | FI9: ｍ | FJ9: 10080 | FK9: 6760 | FL9: 0 | FO9: 保温(亀甲巻き) | FP9: 65A | FQ9: ｍ | FR9: 5630 | FS9: 3490 | FT9: 0 | FW9: ﾗｲﾄｶﾊﾞｰ | FX9: 65A | FY9: ｍ | FZ9: 970 | GA9: 560 | GB9: 0.08
B10: 8 | C10: ﾁｬｯｷ弁 | D10: bo3 | E10: 8 | F10: ﾍﾞｯﾄ放熱管敷設工事費 | K10: SGP鋼管(白) | L10: 80A | M10: m | N10: 16220 | O10: 8590 | P10: 0.42 | S10: STK鋼管 | T10: 200A(Znﾒｯｷ) | U10: m | V10: 27050 | W10: 21660 | X10: 1.26 | AA10: 外面被覆鋼管 | AB10: 80A | AC10: m | AD10: 10570 | AE10: 7930 | AF10: 0.42 | AI10: ｽﾃﾝﾚｽ ｴﾙﾎﾞ | AJ10: 15A | AK10: 個 | AL10: 1550 | AM10: 1140 | AN10: 0 | AQ10: 塩ﾋﾞ管 | AR10: VP φ65 | AS10: m | AT10: 1400 | AU10: 910 | AV10: 0.2 | AY10: ﾎﾟﾘｼﾞｮｲﾝﾄ | AZ10: φ20 | BA10: 個 | BB10: 1820 | BC10: 1310 | BD10: 0.09 | BG10: ｹﾞｰﾄ弁 | BH10: 50A(ﾌﾗﾝｼﾞ) | BI10: 個 | BJ10: 91000 | BK10: 59150 | BL10: 0.32 | BO10: ﾁｬｯｷ弁 | BP10: 50A(ｳｴﾊ) | BQ10: 個 | BR10: 95300 | BS10: 61950 | BT10: 0.18 | BW10: ﾊﾞﾀﾌﾗｲ弁 | BX10: 250A(ｳｴﾊ) | BY10: 個 | BZ10: 217000 | CA10: 141050 | CB10: 0.63 | CE10: ｸﾞﾛｰﾌﾞ弁 | CF10: 50A(ﾌﾗﾝｼﾞ) | CG10: 個 | CH10: 103000 | CI10: 66950 | CJ10: 0.18 | CM10: ﾏﾚｰﾌﾞﾙ弁 | CN10: 50A(ﾌﾗﾝｼﾞ) | CO10: 個 | CP10: 93200 | CQ10: 60580 | CR10: 0.18 | CU10: ﾎﾞｰﾙ弁(2方) | CV10: 80A | CW10: 個 | CX10: 125000 | CY10: 81250 | CZ10: 0.39 | DC10: Yｽﾄﾚｰﾅ | DD10: 80A | DE10: 個 | DF10: 120000 | DG10: 78000 | DH10: 0.39 | DK10: 電動ﾎﾞｰﾙ弁(3方) | DL10: 15A | DM10: 個 | DN10: 29800 | DO10: 19370 | DP10: 0.08 | DS10: ﾌﾚｷｼﾞｮｲﾝﾄ(F) | DT10: 80A*300L | DU10: 本 | DV10: 23900 | DW10: 6210 | DX10: 0.44 | EA10: 伸縮継手 | EB10: 100A(複式) | EC10: 個 | ED10: 251000 | EE10: =ED10*0.55 -> 138050 | EF10: 2.42 | EI10: 減圧弁(蒸気用) | EJ10: 80A RP9-L | EK10: 個 | EL10: 409000 | EM10: =EL10*0.65 -> 265850 | EN10: 3.77 | EQ10: ｻｲﾎﾝﾊﾟｲﾌﾟ | ER10: 15A | ES10: 個 | ET10: 2810 | EU10: 1490 | EV10: 0.08 | EY10: 注油口 | EZ10: 50A | FA10: 個 | FB10: 15000 | FC10: 10000 | FD10: 0 | FG10: 保温(ｶﾗｰﾗｯｷﾝｸﾞ) | FH10: 80A | FI10: ｍ | FJ10: 10800 | FK10: 7240 | FL10: 0 | FO10: 保温(亀甲巻き) | FP10: 80A | FQ10: ｍ | FR10: 6170 | FS10: 3810 | FT10: 0 | FW10: ﾗｲﾄｶﾊﾞｰ | FX10: 80A | FY10: ｍ | FZ10: 1180 | GA10: 670 | GB10: 0.08
B11: 9 | C11: ﾊﾞﾀﾌﾗｲ弁 | D11: bw3 | E11: 9 | F11: 冷媒配管工事費 | I11: 屋外配管 | K11: SGP鋼管(白) | L11: 100A | M11: m | N11: 23300 | O11: 12350 | P11: 0.57 | S11: STK鋼管 | T11: 250A(Znﾒｯｷ) | U11: m | V11: 37980 | W11: 30370 | X11: 1.79 | AA11: 外面被覆鋼管 | AB11: 100A | AC11: m | AD11: 15130 | AE11: 11350 | AF11: 0.57 | AI11: ｽﾃﾝﾚｽ ｴﾙﾎﾞ | AJ11: 20A | AK11: 個 | AL11: 2210 | AM11: 1640 | AN11: 0 | AQ11: 塩ﾋﾞ管 | AR11: VP φ75 | AS11: m | AT11: 2790 | AU11: 1810 | AV11: 0.23 | AY11: ﾎﾟﾘｼﾞｮｲﾝﾄ | AZ11: φ25 | BA11: 個 | BB11: 2380 | BC11: 1720 | BD11: 0.12 | BG11: ｹﾞｰﾄ弁 | BH11: 65A(ﾌﾗﾝｼﾞ) | BI11: 個 | BJ11: 110000 | BK11: 71500 | BL11: 0.39 | BO11: ﾁｬｯｷ弁 | BP11: 65A(ｳｴﾊ) | BQ11: 個 | BR11: 125000 | BS11: 81250 | BT11: 0.32 | BW11: ﾊﾞﾀﾌﾗｲ弁 | BX11: 300A(ｳｴﾊ) | BY11: 個 | BZ11: 276000 | CA11: 179400 | CB11: 0.77 | CE11: ｸﾞﾛｰﾌﾞ弁 | CF11: 65A(ﾌﾗﾝｼﾞ) | CG11: 個 | CH11: 135000 | CI11: 87750 | CJ11: 0.32 | CM11: ﾏﾚｰﾌﾞﾙ弁 | CN11: 65A(ﾌﾗﾝｼﾞ) | CO11: 個 | CP11: 112000 | CQ11: 72800 | CR11: 0.32 | CU11: ﾎﾞｰﾙ弁(2方) | CV11: 100A | CW11: 個 | CX11: 173000 | CY11: 112450 | CZ11: 0.48 | DC11: ---------- | DK11: 電動ﾎﾞｰﾙ弁(3方) | DL11: 20A | DM11: 個 | DN11: 31800 | DO11: 20670 | DP11: 0.09 | DS11: ﾌﾚｷｼﾞｮｲﾝﾄ(F) | DT11: 100A*300L | DU11: 本 | DV11: 28600 | DW11: 7440 | DX11: 0.54 | EA11: 伸縮継手 | EB11: 125A(複式) | EC11: 個 | ED11: 306000 | EE11: =ED11*0.55 -> 168300 | EF11: 3.61 | EI11: 減圧弁(蒸気用) | EJ11: 100A RP9-L | EK11: 個 | EL11: 707000 | EM11: =EL11*0.65 -> 459550 | EN11: 4.12 | EQ11: 空気抜弁 | ER11: 15A(AF-4M) | ES11: 個 | ET11: 30600 | EU11: =ET11*0.8 -> 24480 | EV11: 0.08 | EY11: ---------- | FG11: 保温(ｶﾗｰﾗｯｷﾝｸﾞ) | FH11: 100A | FI11: ｍ | FJ11: 13440 | FK11: 9000 | FL11: 0 | FO11: 保温(亀甲巻き) | FP11: 100A | FQ11: ｍ | FR11: 9050 | FS11: 5610 | FT11: 0 | FW11: ﾗｲﾄｶﾊﾞｰ | FX11: 100A | FY11: ｍ | FZ11: 1450 | GA11: 930 | GB11: 0.1
B12: 10 | C12: ｸﾞﾛｰﾌﾞ弁 | D12: ce3 | E12: 10 | F12: 配管継手類 | I12: 2.3 | K12: SGP鋼管 | L12: 125A | M12: m | N12: 24260 | O12: 38390 | P12: 0.69 | S12: STK鋼管 | T12: 300A(Znﾒｯｷ) | U12: m | V12: 47570 | W12: 38090 | X12: 2.37 | AI12: ｽﾃﾝﾚｽ ｴﾙﾎﾞ | AJ12: 25A | AK12: 個 | AL12: 3160 | AM12: 2320 | AN12: 0 | AQ12: 塩ﾋﾞ管 | AR12: VP φ100 | AS12: m | AT12: 4110 | AU12: 2670 | AV12: 0.29 | AY12: ﾎﾟﾘｼﾞｮｲﾝﾄ | AZ12: φ30 | BA12: 個 | BB12: 4560 | BC12: 3290 | BD12: 0.14 | BG12: ｹﾞｰﾄ弁 | BH12: 80A(ﾌﾗﾝｼﾞ) | BI12: 個 | BJ12: 141000 | BK12: 91650 | BL12: 0.48 | BO12: ﾁｬｯｷ弁 | BP12: 80A(ｳｴﾊ) | BQ12: 個 | BR12: 143000 | BS12: 92950 | BT12: 0.39 | CE12: ｸﾞﾛｰﾌﾞ弁 | CF12: 80A(ﾌﾗﾝｼﾞ) | CG12: 個 | CH12: 158000 | CI12: 102700 | CJ12: 0.39 | CM12: ﾏﾚｰﾌﾞﾙ弁 | CN12: 80A(ﾌﾗﾝｼﾞ) | CO12: 個 | CP12: 134000 | CQ12: 87100 | CR12: 0.39 | CU12: ---------- | DC12: Yｽﾄﾚｰﾅ | DD12: 50A(ﾌﾗﾝｼﾞ) | DE12: 個 | DF12: 50000 | DG12: 32500 | DH12: 0.18 | DK12: 電動ﾎﾞｰﾙ弁(3方) | DL12: 25A | DM12: 個 | DN12: 44000 | DO12: 28600 | DP12: 0.12 | DS12: ﾌﾚｷｼﾞｮｲﾝﾄ(F) | DT12: 125A*300L | DU12: 本 | DV12: 40700 | DW12: 10580 | DX12: 0.57 | EA12: 伸縮継手 | EB12: 150A(複式) | EC12: 個 | ED12: 433000 | EE12: =ED12*0.55 -> 238150 | EF12: 4.42 | EI12: 温度調節弁 | EJ12: 25A TD-2 | EK12: 個 | EL12: 192000 | EM12: =EL12*0.665 -> 127680 | EN12: 1.1 | EQ12: 空気抜弁(逆止弁付） | ER12: 15A(AF-9H) | ES12: 個 | ET12: 36100 | EU12: =ET12*0.8 -> 28880 | EV12: 0.08 | EY12: ｷﾞﾔﾎﾟﾝﾌﾟ | EZ12: φ12 0.2 kw | FA12: 台 | FB12: 198500 | FC12: 129030 | FD12: 0.3 | FG12: 保温(ｶﾗｰﾗｯｷﾝｸﾞ) | FH12: 125A | FI12: ｍ | FJ12: 15840 | FK12: 10610 | FL12: 0 | FO12: 保温(亀甲巻き) | FP12: 125A | FQ12: ｍ | FR12: 10530 | FS12: 6550 | FT12: 0 | FW12: ﾗｲﾄｶﾊﾞｰ | FX12: 125A | FY12: ｍ | FZ12: 2070 | GA12: 1020 | GB12: 0.12
B13: 11 | C13: ﾏﾚｰﾌﾞﾙ弁 | D13: cm3 | E13: 11 | F13: 配管工事費 | I13: 0.11 | K13: SGP鋼管 | L13: 150A | M13: m | N13: 33060 | O13: 17530 | P13: 0.88 | S13: ---------- | AI13: ｽﾃﾝﾚｽ ｴﾙﾎﾞ | AJ13: 32A | AK13: 個 | AL13: 5070 | AM13: 3540 | AN13: 0 | AQ13: 塩ﾋﾞ管 | AR13: VP φ125 | AS13: m | AT13: 6000 | AU13: 3900 | AV13: 0.36 | AY13: ---------- | BG13: ｹﾞｰﾄ弁 | BH13: 100A(ﾌﾗﾝｼﾞ) | BI13: 個 | BJ13: 170000 | BK13: 110500 | BL13: 0.57 | BO13: ﾁｬｯｷ弁 | BP13: 100A(ｳｴﾊ) | BQ13: 個 | BR13: 191000 | BS13: 124150 | BT13: 0.48 | CE13: ｸﾞﾛｰﾌﾞ弁 | CF13: 100A(ﾌﾗﾝｼﾞ) | CG13: 個 | CH13: 212000 | CI13: 137800 | CJ13: 0.48 | CM13: ﾏﾚｰﾌﾞﾙ弁 | CN13: 100A(ﾌﾗﾝｼﾞ) | CO13: 個 | CP13: 181000 | CQ13: 117650 | CR13: 0.48 | CU13: ﾎﾞｰﾙ弁(3方) | CV13: 15A | CW13: 個 | CX13: 9010 | CY13: 5860 | CZ13: 0.08 | DC13: Yｽﾄﾚｰﾅ | DD13: 65A(ﾌﾗﾝｼﾞ) | DE13: 個 | DF13: 75600 | DG13: 49140 | DH13: 0.32 | DK13: 電動ﾎﾞｰﾙ弁(3方) | DL13: 32A | DM13: 個 | DN13: 58900 | DO13: 38290 | DP13: 0.14 | DS13: ﾌﾚｷｼﾞｮｲﾝﾄ(F) | DT13: 150A*300L | DU13: 本 | DV13: 50300 | DW13: 13080 | DX13: 0.65 | EA13: 伸縮継手 | EB13: 200A(複式) | EC13: 個 | ED13: 645000 | EE13: =ED13*0.55 -> 354750 | EF13: 4.88 | EI13: 温度調節弁 | EJ13: 32A TD-2 | EK13: 個 | EL13: 207000 | EM13: =EL13*0.665 -> 137655 | EN13: 1.14 | EQ13: 空気抜弁 | ER13: 15A(AF-10H) | ES13: 個 | ET13: 30000 | EU13: =ET13*0.8 -> 24000 | EV13: 0.08 | EY13: ｷﾞﾔﾎﾟﾝﾌﾟ | EZ13: φ12 0.4 kw | FA13: 台 | FB13: 223000 | FC13: 144950 | FD13: 0.4 | FG13: 保温(ｶﾗｰﾗｯｷﾝｸﾞ) | FH13: 150A | FI13: ｍ | FJ13: 18240 | FK13: 12220 | FL13: 0 | FO13: 保温(亀甲巻き) | FP13: 150A | FQ13: ｍ | FR13: 12020 | FS13: 7460 | FT13: 0 | FW13: ----------
B14: 12 | C14: ﾎﾞｰﾙ弁 | D14: cu3 | E14: 12 | F14: 配管支持具 | K14: SGP鋼管 | L14: 200A | M14: m | N14: 50330 | O14: 26680 | P14: 1.26 | S14: STK鋼管(5.5m) | T14: 40A(Znﾒｯｷ) | U14: 本 | V14: 16770 | W14: 13263.545 | X14: 1.27 | AI14: ｽﾃﾝﾚｽ ｴﾙﾎﾞ | AJ14: 40A | AK14: 個 | AL14: 5890 | AM14: 4130 | AN14: 0 | AQ14: 塩ﾋﾞ管 | AR14: VP φ150 | AS14: m | AT14: 8370 | AU14: 5440 | AV14: 0.43 | AY14: ﾎﾟﾘ管用ｿｹｯﾄ | AZ14: 13S | BA14: 個 | BB14: 1100 | BC14: 660 | BD14: 0.08 | BG14: ｹﾞｰﾄ弁 | BH14: 125A(ﾌﾗﾝｼﾞ) | BI14: 個 | BJ14: 249000 | BK14: 161850 | BL14: 0.65 | BO14: ﾁｬｯｷ弁 | BP14: 125A(ｳｴﾊ) | BQ14: 個 | BR14: 247000 | BS14: 160550 | BT14: 0.57 | CE14: ｸﾞﾛｰﾌﾞ弁 | CF14: 125A(ﾌﾗﾝｼﾞ) | CG14: 個 | CH14: 378000 | CI14: 245700 | CJ14: 0.57 | CM14: ﾏﾚｰﾌﾞﾙ弁 | CN14: 125A(ﾌﾗﾝｼﾞ) | CO14: 個 | CP14: 309000 | CQ14: 200850 | CR14: 0.57 | CU14: ﾎﾞｰﾙ弁(3方) | CV14: 20A | CW14: 個 | CX14: 9970 | CY14: 6480 | CZ14: 0.09 | DC14: Yｽﾄﾚｰﾅ | DD14: 80A(ﾌﾗﾝｼﾞ) | DE14: 個 | DF14: 93100 | DG14: 60520 | DH14: 0.39 | DK14: 電動ﾎﾞｰﾙ弁(3方) | DL14: 40A | DM14: 個 | DN14: 76000 | DO14: 49400 | DP14: 0.16 | DS14: ﾌﾚｷｼﾞｮｲﾝﾄ(F) | DT14: 200A*300L | DU14: 本 | DV14: 95100 | DW14: 24730 | DX14: 0.95 | EA14: 伸縮継手 | EB14: 250A(複式) | EC14: 個 | ED14: 861000 | EE14: =ED14*0.55 -> 473550 | EF14: 5.57 | EI14: 温度調節弁 | EJ14: 40A TD-2 | EK14: 個 | EL14: 231000 | EM14: =EL14*0.665 -> 153615 | EN14: 1.61 | EQ14: 空気抜弁 | ER14: 15A(小型) | ES14: 個 | ET14: 19200 | EU14: =ET14*0.8 -> 15360 | EV14: 0.08 | EY14: ｷﾞﾔﾎﾟﾝﾌﾟ | EZ14: φ15 0.4 kw | FA14: 台 | FB14: 267000 | FC14: 173550 | FD14: 0.4 | FG14: 保温(ｶﾗｰﾗｯｷﾝｸﾞ) | FH14: 200A | FI14: ｍ | FJ14: 35540 | FK14: 23810 | FL14: 1 | FO14: 保温(亀甲巻き) | FP14: 200A | FQ14: ｍ | FR14: 17190 | FS14: 10670 | FT14: 0 | FW14: ﾊﾟｲﾌﾟｶﾞｰﾄﾞ | FX14: 15A | FY14: ｍ | FZ14: 770 | GA14: 650 | GB14: 0.02
B15: 13 | C15: ｽﾄﾚｰﾅ | D15: ｄｃ3 | E15: 13 | F15: 消耗品雑材 | I15: ｴﾛﾌｨﾝ工事 | K15: SGP鋼管 | L15: 250A | M15: m | N15: 97500 | O15: 51670 | P15: 1.79 | S15: STK鋼管(5.5m) | T15: 50A(Znﾒｯｷ) | U15: 本 | V15: 22960 | W15: 18435.036 | X15: 1.6 | AI15: ｽﾃﾝﾚｽ ｴﾙﾎﾞ | AJ15: 50A | AK15: 個 | AL15: 8760 | AM15: 6180 | AN15: 0 | AQ15: ---------- | AY15: ﾎﾟﾘ管用ｿｹｯﾄ | AZ15: 20S | BA15: 個 | BB15: 1380 | BC15: 830 | BD15: 0.09 | BG15: ｹﾞｰﾄ弁 | BH15: 150A(ﾌﾗﾝｼﾞ) | BI15: 個 | BJ15: 271000 | BK15: 176150 | BL15: 0.95 | BO15: ﾁｬｯｷ弁 | BP15: 150A(ｳｴﾊ) | BQ15: 個 | BR15: 336000 | BS15: 218400 | BT15: 0.65 | CE15: ｸﾞﾛｰﾌﾞ弁 | CF15: 150A(ﾌﾗﾝｼﾞ) | CG15: 個 | CH15: 520000 | CI15: 338000 | CJ15: 0.65 | CM15: ﾏﾚｰﾌﾞﾙ弁 | CN15: 150A(ﾌﾗﾝｼﾞ) | CO15: 個 | CP15: 326000 | CQ15: 211900 | CR15: 0.65 | CU15: ﾎﾞｰﾙ弁(3方) | CV15: 25A | CW15: 個 | CX15: 14100 | CY15: 9170 | CZ15: 0.12 | DC15: Yｽﾄﾚｰﾅ | DD15: 100A(ﾌﾗﾝｼﾞ) | DE15: 個 | DF15: 126000 | DG15: 81900 | DH15: 0.48 | DK15: 電動ﾎﾞｰﾙ弁(3方) | DL15: 50A | DM15: 個 | DN15: 85300 | DO15: 55450 | DP15: 0.18 | DS15: ---------- | EA15: ---------- | EI15: 温度調節弁 | EJ15: 50A TD-2 | EK15: 個 | EL15: 251000 | EM15: =EL15*0.665 -> 166915 | EN15: 1.8 | EY15: ｷﾞﾔﾎﾟﾝﾌﾟ | EZ15: φ15 0.75kw | FA15: 台 | FB15: 278600 | FC15: 222880 | FD15: 0.5 | FG15: 保温(ｶﾗｰﾗｯｷﾝｸﾞ) | FH15: 250A | FI15: ｍ | FJ15: 43770 | FK15: 29320 | FL15: 2 | FO15: 保温(亀甲巻き) | FP15: 250A | FQ15: ｍ | FR15: 21780 | FS15: 13530 | FT15: 0 | FW15: ﾊﾟｲﾌﾟｶﾞｰﾄﾞ | FX15: 20A | FY15: ｍ | FZ15: 820 | GA15: 700 | GB15: 0.02
B16: 14 | C16: 電動弁･混合三方弁 | D16: dk3 | E16: 14 | F16: ---------------- | I16: 1.2 | K16: SGP鋼管 | L16: 300A | M16: m | N16: 117500 | O16: 62280 | P16: 2.37 | S16: STK鋼管(5.5m) | T16: 65A(Znﾒｯｷ) | U16: 本 | V16: 32340 | W16: 26026 | X16: 2.04 | AI16: ｽﾃﾝﾚｽ ｴﾙﾎﾞ | AJ16: 65A | AK16: 個 | AL16: 20020 | AM16: 11290 | AN16: 0 | AQ16: 塩ﾋﾞ管 | AR16: VU φ40 | AS16: m | AT16: 460 | AU16: 300 | AV16: 0.12 | AY16: ﾎﾟﾘ管用ｿｹｯﾄ | AZ16: 25S | BA16: 個 | BB16: 1620 | BC16: 970 | BD16: 0.12 | BG16: ｹﾞｰﾄ弁 | BH16: 200A(ﾌﾗﾝｼﾞ) | BI16: 個 | BJ16: 378000 | BK16: 245700 | BL16: 1.04 | BO16: ﾁｬｯｷ弁 | BP16: 200A(ｳｴﾊ) | BQ16: 個 | BR16: 500000 | BS16: 325000 | BT16: 0.95 | CE16: ｸﾞﾛｰﾌﾞ弁 | CF16: 200A(ﾌﾗﾝｼﾞ) | CG16: 個 | CH16: 825000 | CI16: 536250 | CJ16: 0.95 | CM16: ﾏﾚｰﾌﾞﾙ弁 | CN16: 200A(ﾌﾗﾝｼﾞ) | CO16: 個 | CP16: 554000 | CQ16: 360100 | CR16: 0.95 | CU16: ﾎﾞｰﾙ弁(3方) | CV16: 32A | CW16: 個 | CX16: 21100 | CY16: 13720 | CZ16: 0.14 | DC16: Yｽﾄﾚｰﾅ | DD16: 125A(ﾌﾗﾝｼﾞ) | DE16: 個 | DF16: 202000 | DG16: 131300 | DH16: 0.57 | DK16: ---------- | DS16: ﾌﾚｷｼﾞｮｲﾝﾄ(U) | DT16: 15A*500L | DU16: 本 | DV16: 4400 | DW16: 2020 | DX16: 0.12 | EA16: ﾒｶﾆｶﾙ配管接手 | EB16: ｿｹｯﾄ 15Ａ | EC16: 個 | ED16: 2350 | EE16: =ROUND(ED16*0.65,-1) -> 1530 | EF16: 0.12 | EI16: 温度調節弁 | EJ16: 65A TD-2 | EK16: 個 | EL16: 272000 | EM16: =EL16*0.665 -> 180880 | EN16: 2.26 | EY16: ｷﾞﾔﾎﾟﾝﾌﾟ | EZ16: φ20 0.75kw | FA16: 台 | FB16: 340600 | FC16: 272480 | FD16: 0.5 | FG16: 保温(ｶﾗｰﾗｯｷﾝｸﾞ) | FH16: 300A | FI16: ｍ | FJ16: 53200 | FK16: 35640 | FL16: 3 | FO16: 保温(亀甲巻き) | FP16: 300A | FQ16: ｍ | FR16: 26510 | FS16: 16470 | FT16: 0 | FW16: ﾊﾟｲﾌﾟｶﾞｰﾄﾞ | FX16: 25A | FY16: ｍ | FZ16: 870 | GA16: 710 | GB16: 0.03
B17: 15 | C17: ﾌﾚｷｼﾞｮｲﾝﾄ | D17: ds3 | E17: 15 | F17: ｴﾛﾌｨﾝ取付工事費 | I17: 0.11 | S17: STK鋼管(5.5m) | T17: 80A(Znﾒｯｷ) | U17: 本 | V17: 37930 | W17: 30405.425 | X17: 2.31 | AI17: ｽﾃﾝﾚｽ ﾁ-ｽﾞ | AJ17: 15A | AK17: 個 | AL17: 2050 | AM17: 1500 | AN17: 0 | AQ17: 塩ﾋﾞ管 | AR17: VU φ50 | AS17: m | AT17: 570 | AU17: 370 | AV17: 0.15 | AY17: ﾎﾟﾘ管用ｿｹｯﾄ | AZ17: 30S | BA17: 個 | BB17: 2060 | BC17: 1240 | BD17: 0.14 | BG17: ---------- | BO17: ﾁｬｯｷ弁 | BP17: 250A(ｳｴﾊ) | BQ17: 個 | BR17: 730000 | BS17: 474500 | BT17: 1.13 | CU17: ﾎﾞｰﾙ弁(3方) | CV17: 40A | CW17: 個 | CX17: 26300 | CY17: 17100 | CZ17: 0.16 | DC17: Yｽﾄﾚｰﾅ | DD17: 150A(ﾌﾗﾝｼﾞ) | DE17: 個 | DF17: 252000 | DG17: 163800 | DH17: 0.65 | DK17: 電動ﾊﾞﾀﾌﾗｲ弁 | DL17: 50A(ｳｴﾊ) | DM17: 個 | DN17: 136000 | DO17: 88400 | DP17: 0.18 | DS17: ﾌﾚｷｼﾞｮｲﾝﾄ(U) | DT17: 20A*500L | DU17: 本 | DV17: 5800 | DW17: 2670 | DX17: 0.12 | EA17: ﾒｶﾆｶﾙ配管接手 | EB17: ｿｹｯﾄ 20Ａ | EC17: 個 | ED17: 2900 | EE17: =ROUND(ED17*0.65,-1) -> 1890 | EF17: 0.12 | EI17: 温度調節弁 | EJ17: 80A TD-2 | EK17: 個 | EL17: 351000 | EM17: =EL17*0.665 -> 233415 | EN17: 2.72 | EY17: ｷﾞﾔﾎﾟﾝﾌﾟ | EZ17: φ20 1.5 kw | FA17: 台 | FB17: 353400 | FC17: 282720 | FD17: 0.5 | FG17: ---------- | FO17: ---------- | FW17: ﾊﾟｲﾌﾟｶﾞｰﾄﾞ | FX17: 32A | FY17: ｍ | FZ17: 930 | GA17: 770 | GB17: 0.03
B18: 16 | C18: 伸縮継手・ﾊｲﾊﾟｰﾛｯｸ | D18: ea3 | E18: 16 | F18: 養液ﾍﾞｯﾄ配管工事費 | S18: STK鋼管(5.5m) | T18: 100A(Znﾒｯｷ) | U18: 本 | V18: 52740 | W18: 42133.884 | X18: 3.14 | AI18: ｽﾃﾝﾚｽ ﾁｰｽﾞ | AJ18: 20A | AK18: 個 | AL18: 2940 | AM18: 2180 | AN18: 0 | AQ18: 塩ﾋﾞ管 | AR18: VU φ65 | AS18: m | AT18: 880 | AU18: 570 | AV18: 0.2 | AY18: ---------- | BG18: ｹﾞｰﾄ弁 | BH18: 15A(FH) | BI18: 個 | BJ18: 4380 | BK18: 2850 | BL18: 0.08 | BO18: ﾁｬｯｷ弁 | BP18: 300A(ｳｴﾊ) | BQ18: 個 | BR18: 1074000 | BS18: 698100 | BT18: 1.4 | CU18: ﾎﾞｰﾙ弁(3方) | CV18: 50A | CW18: 個 | CX18: 40300 | CY18: 26200 | CZ18: 0.18 | DC18: Yｽﾄﾚｰﾅ | DD18: 200A(ﾌﾗﾝｼﾞ) | DE18: 個 | DF18: 349000 | DG18: 226850 | DH18: 0.95 | DK18: 電動ﾊﾞﾀﾌﾗｲ弁 | DL18: 65A(ｳｴﾊ) | DM18: 個 | DN18: 137000 | DO18: 89050 | DP18: 0.32 | DS18: ﾌﾚｷｼﾞｮｲﾝﾄ(U) | DT18: 25A*500L | DU18: 本 | DV18: 7000 | DW18: 3220 | DX18: 0.14 | EA18: ﾒｶﾆｶﾙ配管接手 | EB18: ｿｹｯﾄ 25Ａ | EC18: 個 | ED18: 3820 | EE18: =ROUND(ED18*0.65,-1) -> 2480 | EF18: 0.14 | EI18: 温度調節弁 | EJ18: 100A TD-2 | EK18: 個 | EL18: 453000 | EM18: =EL18*0.665 -> 301245 | EN18: 3.2 | FG18: 保温(ｽﾃﾝﾗｯｷﾝｸﾞ) | FH18: 15A | FI18: ｍ | FJ18: 10680 | FK18: 7160 | FL18: 0 | FO18: 煙道保温工事 | FP18: ﾛｯｸｳｰﾙ | FQ18: ㎡ | FT18: 0 | FW18: ﾊﾟｲﾌﾟｶﾞｰﾄﾞ | FX18: 40A | FY18: ｍ | FZ18: 1040 | GA18: 880 | GB18: 0.04
B19: 17 | C19: 蒸気関連・落水防止弁 | D19: ei3 | E19: 17 | F19: 養液ﾀﾝｸ内配管工事費 | S19: STK鋼管(5.5m) | T19: 125A(Znﾒｯｷ) | U19: 本 | V19: 68800 | W19: 55012.698 | X19: 3.8 | AI19: ｽﾃﾝﾚｽ ﾁｰｽﾞ | AJ19: 25A | AK19: 個 | AL19: 4200 | AM19: 3080 | AN19: 0 | AQ19: 塩ﾋﾞ管 | AR19: VU φ75 | AS19: m | AT19: 1160 | AU19: 760 | AV19: 0.23 | AY19: ﾎﾟﾘ管用ｴﾙﾎﾞ | AZ19: 13L | BA19: 個 | BB19: 1230 | BC19: 740 | BD19: 0.08 | BG19: ｹﾞｰﾄ弁 | BH19: 20A(FH) | BI19: 個 | BJ19: 5270 | BK19: 3430 | BL19: 0.09 | CU19: ﾎﾞｰﾙ弁(3方) | CV19: 65A | CW19: 個 | CX19: 79800 | CY19: 51870 | CZ19: 0.32 | DC19: Yｽﾄﾚｰﾅ | DD19: 250A(ﾌﾗﾝｼﾞ) | DE19: 個 | DF19: 594000 | DG19: 386100 | DH19: 1.13 | DK19: 電動ﾊﾞﾀﾌﾗｲ弁 | DL19: 80A(ｳｴﾊ) | DM19: 個 | DN19: 139000 | DO19: 90350 | DP19: 0.39 | DS19: ﾌﾚｷｼﾞｮｲﾝﾄ(U) | DT19: 32A*500L | DU19: 本 | DV19: 9000 | DW19: 4140 | DX19: 0.16 | EA19: ﾒｶﾆｶﾙ配管接手 | EB19: ｿｹｯﾄ 32Ａ | EC19: 個 | ED19: 4840 | EE19: =ROUND(ED19*0.65,-1) -> 3150 | EF19: 0.16 | EI19: 管末ﾄﾗｯﾌﾟ | EJ19: 15A AK-1H | EK19: 個 | EL19: 21100 | EM19: =EL19*0.65 -> 13715 | EN19: 1.08 | FG19: 保温(ｽﾃﾝﾗｯｷﾝｸﾞ) | FH19: 20A | FI19: ｍ | FJ19: 11040 | FK19: 7400 | FL19: 0 | FO19: ﾀﾝｸ保温工事 | FP19: ｸﾞﾗｽﾛﾝ | FQ19: ㎡ | FT19: 0 | FW19: ﾊﾟｲﾌﾟｶﾞｰﾄﾞ | FX19: 50A | FY19: ｍ | FZ19: 1140 | GA19: 940 | GB19: 0.04
B20: 18 | C20: 温度・圧力計・空気抜弁 | D20: eq3 | E20: 18 | F20: ﾍﾞｯﾄ放熱管敷設工事費 | S20: STK鋼管(5.5m) | T20: 150A(Znﾒｯｷ) | U20: 本 | V20: 97770 | W20: 78401.723 | X20: 4.84 | AI20: ｽﾃﾝﾚｽ ﾁｰｽﾞ | AJ20: 32A | AK20: 個 | AL20: 6600 | AM20: 4610 | AN20: 0 | AQ20: 塩ﾋﾞ管 | AR20: VU φ100 | AS20: m | AT20: 1750 | AU20: 1140 | AV20: 0.29 | AY20: ﾎﾟﾘ管用ｴﾙﾎﾞ | AZ20: 20L | BA20: 個 | BB20: 1800 | BC20: 1080 | BD20: 0.09 | BG20: ｹﾞｰﾄ弁 | BH20: 25A(FH) | BI20: 個 | BJ20: 7440 | BK20: 4840 | BL20: 0.12 | CU20: ﾎﾞｰﾙ弁(3方) | CV20: 80A | CW20: 個 | CX20: 125000 | CY20: 81250 | CZ20: 0.39 | DC20: Yｽﾄﾚｰﾅ | DD20: 300A(ﾌﾗﾝｼﾞ) | DE20: 個 | DF20: 811000 | DG20: 527150 | DH20: 1.4 | DK20: 電動ﾊﾞﾀﾌﾗｲ弁 | DL20: 100A(ｳｴﾊ) | DM20: 個 | DN20: 144000 | DO20: 93600 | DP20: 0.48 | DS20: ﾌﾚｷｼﾞｮｲﾝﾄ(F) | DT20: 40A*500L | DU20: 本 | DV20: 18000 | DW20: 4680 | DX20: 0.18 | EA20: ﾒｶﾆｶﾙ配管接手 | EB20: ｿｹｯﾄ 40Ａ | EC20: 個 | ED20: 5410 | EE20: =ROUND(ED20*0.65,-1) -> 3520 | EF20: 0.18 | EI20: 管末ﾄﾗｯﾌﾟ | EJ20: 20A AK-1H | EK20: 個 | EL20: 23800 | EM20: =EL20*0.65 -> 15470 | EN20: 1.08 | FG20: 保温(ｽﾃﾝﾗｯｷﾝｸﾞ) | FH20: 25A | FI20: ｍ | FJ20: 11280 | FK20: 7560 | FL20: 0 | FO20: 同上保温工事 | FP20: ｸﾞﾗｽﾛﾝ | FQ20: ㎡ | FT20: 0 | FW20: ﾊﾟｲﾌﾟｶﾞｰﾄﾞ | FX20: 65A | FY20: ｍ | FZ20: 1240 | GA20: 1040 | GB20: 0.05
B21: 19 | C21: 油配管部材・ｷﾞﾔﾎﾟﾝﾌﾟ | D21: ey3 | E21: 19 | F21: 冷媒配管工事費 | S21: STK鋼管(5.5m) | T21: 200A(Znﾒｯｷ) | U21: 本 | V21: 148770 | W21: 119107.74 | X21: 6.93 | AI21: ｽﾃﾝﾚｽ ﾁｰｽﾞ | AJ21: 40A | AK21: 個 | AL21: 7660 | AM21: 5370 | AN21: 0 | AQ21: 塩ﾋﾞ管 | AR21: VU φ125 | AS21: m | AT21: 2830 | AU21: 1840 | AV21: 0.36 | AY21: ﾎﾟﾘ管用ｴﾙﾎﾞ | AZ21: 25L | BA21: 個 | BB21: 1910 | BC21: 1150 | BD21: 0.12 | BG21: ｹﾞｰﾄ弁 | BH21: 32A(FH) | BI21: 個 | BJ21: 10200 | BK21: 6630 | BL21: 0.14 | CU21: ---------- | DC21: ---------- | DK21: 電動ﾊﾞﾀﾌﾗｲ弁 | DL21: 125A(ｳｴﾊ) | DM21: 個 | DN21: 219000 | DO21: 142350 | DP21: 0.57 | DS21: ﾌﾚｷｼﾞｮｲﾝﾄ(F) | DT21: 50A*500L | DU21: 本 | DV21: 22700 | DW21: 5900 | DX21: 0.22 | EA21: ﾒｶﾆｶﾙ配管接手 | EB21: ｿｹｯﾄ 50Ａ | EC21: 個 | ED21: 7330 | EE21: =ROUND(ED21*0.65,-1) -> 4760 | EF21: 0.22 | EI21: 管末ﾄﾗｯﾌﾟ | EJ21: 25A AK-1H | EK21: 個 | EL21: 33400 | EM21: =EL21*0.65 -> 21710 | EN21: 1.08 | FG21: 保温(ｽﾃﾝﾗｯｷﾝｸﾞ) | FH21: 32A | FI21: ｍ | FJ21: 11760 | FK21: 7890 | FL21: 0 | FW21: ﾊﾟｲﾌﾟｶﾞｰﾄﾞ | FX21: 80A | FY21: ｍ | FZ21: 1460 | GA21: 1220 | GB21: 0.05
B22: 20 | C22: 配管保温(材工) | D22: fg3 | E22: 20 | F22: 排水配管工事費 | S22: STK鋼管(5.5m) | T22: 250A(Znﾒｯｷ) | U22: 本 | V22: 208870 | W22: 167051.15 | X22: 9.85 | AI22: ｽﾃﾝﾚｽ ﾁｰｽﾞ | AJ22: 50A | AK22: 個 | AL22: 11700 | AM22: 8260 | AN22: 0 | AQ22: 塩ﾋﾞ管 | AR22: VU φ150 | AS22: m | AT22: 4060 | AU22: 2640 | AV22: 0.43 | AY22: ﾎﾟﾘ管用ｴﾙﾎﾞ | AZ22: 30L | BA22: 個 | BB22: 1950 | BC22: 1170 | BD22: 0.14 | BG22: ｹﾞｰﾄ弁 | BH22: 40A(FH) | BI22: 個 | BJ22: 12800 | BK22: 8320 | BL22: 0.16 | CU22: ﾎﾞｰﾙ弁(ｱﾝｸﾞﾙ) | CV22: 15A | CW22: 個 | CX22: 3190 | CY22: 2070 | CZ22: 0.08 | DC22: ｵｲﾙｽﾄﾚｰﾅ(複式) | DD22: 20A(ﾌﾗﾝｼﾞ) | DE22: 個 | DF22: 190000 | DG22: 123500 | DH22: 0.09 | DK22: 電動ﾊﾞﾀﾌﾗｲ弁 | DL22: 150A(ｳｴﾊ) | DM22: 個 | DN22: 228000 | DO22: 148200 | DP22: 0.65 | DS22: ﾌﾚｷｼﾞｮｲﾝﾄ(F) | DT22: 65A*500L | DU22: 本 | DV22: 26000 | DW22: 6760 | DX22: 0.37 | EA22: ﾒｶﾆｶﾙ配管接手 | EB22: ｿｹｯﾄ 65Ａ | EC22: 個 | ED22: 15550 | EE22: =ROUND(ED22*0.65,-1) -> 10110 | EF22: 0.37 | EI22: 多量ﾄﾗｯﾌﾟ | EJ22: 20A AF-11H | EK22: 個 | EL22: 89100 | EM22: =EL22*0.65 -> 57915 | EN22: 1.46 | FG22: 保温(ｽﾃﾝﾗｯｷﾝｸﾞ) | FH22: 40A | FI22: ｍ | FJ22: 12240 | FK22: 8200 | FL22: 0 | FW22: ----------
B23: 21 | C23: 配管亀甲保温(材工) | D23: fo3 | E23: 21 | F23: 機器回り配管工事費 | S23: STK鋼管(5.5m) | T23: 300A(Znﾒｯｷ) | U23: 本 | V23: 261640 | W23: 209499.89 | X23: 13.04 | AI23: ｽﾃﾝﾚｽ ﾁｰｽﾞ | AJ23: 65A | AK23: 個 | AL23: 26770 | AM23: 15090 | AN23: 0 | AQ23: 塩ﾋﾞ管 | AR23: VU φ200 | AS23: m | AT23: 6710 | AU23: 4360 | AV23: 0.56 | AY23: ---------- | BG23: ｹﾞｰﾄ弁 | BH23: 50A(FH) | BI23: 個 | BJ23: 19400 | BK23: 12610 | BL23: 0.18 | CU23: ﾎﾞｰﾙ弁(ｱﾝｸﾞﾙ) | CV23: 20A | CW23: 個 | CX23: 3630 | CY23: 2360 | CZ23: 0.09 | DC23: ｵｲﾙｽﾄﾚｰﾅ(複式) | DD23: 25A(ﾌﾗﾝｼﾞ) | DE23: 個 | DF23: 191000 | DG23: 124150 | DH23: 0.12 | DK23: 電動ﾊﾞﾀﾌﾗｲ弁 | DL23: 200A(ｳｴﾊ) | DM23: 個 | DN23: 283000 | DO23: 183950 | DP23: 0.95 | DS23: ﾌﾚｷｼﾞｮｲﾝﾄ(F) | DT23: 80A*500L | DU23: 本 | DV23: 29600 | DW23: 7700 | DX23: 0.44 | EA23: ﾒｶﾆｶﾙ配管接手 | EB23: ｿｹｯﾄ 80Ａ | EC23: 個 | ED23: 19360 | EE23: =ROUND(ED23*0.65,-1) -> 12580 | EF23: 0.44 | EI23: 多量ﾄﾗｯﾌﾟ | EJ23: 25A AF-11H | EK23: 個 | EL23: 103000 | EM23: =EL23*0.65 -> 66950 | EN23: 1.46 | FG23: 保温(ｽﾃﾝﾗｯｷﾝｸﾞ) | FH23: 50A | FI23: ｍ | FJ23: 13560 | FK23: 9090 | FL23: 0 | FW23: 煙道保温工事 | FX23: ﾛｯｸｳｰﾙ | FY23: ㎡ | FZ23: 46500 | GA23: 37200 | GB23: 0
B24: 22 | C24: ﾊﾟｲﾌﾟｶﾞｰﾄﾞ･その他 | D24: fw3 | E24: 22 | F24: 保温工事費 | AI24: ｽﾃﾝﾚｽ ﾕﾆｵﾝ | AJ24: 15A | AK24: 個 | AL24: 4170 | AM24: 3060 | AN24: 0 | AQ24: 塩ﾋﾞ管 | AR24: VU φ250 | AS24: m | AT24: 10050 | AU24: 6540 | AV24: 0.69 | AY24: ﾎﾟﾘ管用ﾁｰｽﾞ | AZ24: 13L | BA24: 個 | BB24: 1900 | BC24: 1140 | BD24: 0.08 | BG24: ｹﾞｰﾄ弁 | BH24: 65A(FH) | BI24: 個 | BJ24: 40300 | BK24: 26200 | BL24: 0.32 | CU24: ---------- | DC24: ｵｲﾙｽﾄﾚｰﾅ(複式) | DD24: 32A(ﾌﾗﾝｼﾞ) | DE24: 個 | DF24: 284000 | DG24: 184600 | DH24: 0.14 | DK24: ---------- | DS24: ﾌﾚｷｼﾞｮｲﾝﾄ(F) | DT24: 100A*500L | DU24: 本 | DV24: 35200 | DW24: 9150 | DX24: 0.54 | EA24: ﾒｶﾆｶﾙ配管接手 | EB24: ｴﾙﾎﾞ 15Ａ | EC24: 個 | ED24: 3000 | EE24: =ROUND(ED24*0.65,-1) -> 1950 | EF24: 0.12 | EI24: 多量ﾄﾗｯﾌﾟ | EJ24: 32A AF-11H | EK24: 個 | EL24: 103000 | EM24: =EL24*0.65 -> 66950 | EN24: 1.87 | FG24: 保温(ｽﾃﾝﾗｯｷﾝｸﾞ) | FH24: 65A | FI24: ｍ | FJ24: 15120 | FK24: 10130 | FL24: 0 | FW24: ﾀﾝｸ保温工事 | FX24: ｸﾞﾗｽﾛﾝ | FY24: ㎡ | FZ24: 50000 | GA24: 40000 | GB24: 0
E25: 23 | F25: 保温工事費(材工共) | AI25: ｽﾃﾝﾚｽ ﾕﾆｵﾝ | AJ25: 20A | AK25: 個 | AL25: 5450 | AM25: 4050 | AN25: 0 | AQ25: 塩ﾋﾞ管 | AR25: VU φ300 | AS25: m | AT25: 14140 | AU25: 9190 | AV25: 0.83 | AY25: ﾎﾟﾘ管用ﾁｰｽﾞ | AZ25: 20L | BA25: 個 | BB25: 4150 | BC25: 2490 | BD25: 0.09 | BG25: ｹﾞｰﾄ弁 | BH25: 80A(FH) | BI25: 個 | BJ25: 55000 | BK25: 35750 | BL25: 0.39 | CU25: ﾎﾞｰﾙ弁(2方) | CV25: 15A(G-FF) | CW25: 個 | CX25: 3130 | CY25: 2030 | CZ25: 0.08 | DC25: ｵｲﾙｽﾄﾚｰﾅ(複式) | DD25: 40A(ﾌﾗﾝｼﾞ) | DE25: 個 | DF25: 311000 | DG25: 202150 | DH25: 0.16 | DK25: 電動混合三方弁(ﾎﾞｰﾙ) | DL25: 40A | DM25: ｾｯﾄ | DN25: 298800 | DO25: 224100 | DP25: 0.83 | DS25: ﾌﾚｷｼﾞｮｲﾝﾄ(F) | DT25: 125A*500L | DU25: 本 | DV25: 50500 | DW25: 13130 | DX25: 0.57 | EA25: ﾒｶﾆｶﾙ配管接手 | EB25: ｴﾙﾎﾞ 20Ａ | EC25: 個 | ED25: 3490 | EE25: =ROUND(ED25*0.65,-1) -> 2270 | EF25: 0.12 | EI25: 多量ﾄﾗｯﾌﾟ | EJ25: 40A AF-11H | EK25: 個 | EL25: 137000 | EM25: =EL25*0.65 -> 89050 | EN25: 1.87 | FG25: 保温(ｽﾃﾝﾗｯｷﾝｸﾞ) | FH25: 80A | FI25: ｍ | FJ25: 16440 | FK25: 11020 | FL25: 0 | FW25: 同上保温工事 | FX25: ｸﾞﾗｽﾛﾝ | FY25: ㎡ | FZ25: 50000 | GA25: 40000 | GB25: 0
E26: 24 | F26: 埋設配管保温工事費 | AI26: ｽﾃﾝﾚｽ ﾕﾆｵﾝ | AJ26: 25A | AK26: 個 | AL26: 6960 | AM26: 5100 | AN26: 0 | AQ26: 塩ﾋﾞ管 | AR26: VU φ350 | AS26: m | AT26: 19070 | AU26: 12390 | AV26: 0.96 | AY26: ﾎﾟﾘ管用ﾁｰｽﾞ | AZ26: 25L | BA26: 個 | BB26: 4300 | BC26: 2580 | BD26: 0.12 | CU26: ﾎﾞｰﾙ弁(2方) | CV26: 20A(G-FF) | CW26: 個 | CX26: 3660 | CY26: 2380 | CZ26: 0.09 | DC26: ｵｲﾙｽﾄﾚｰﾅ(複式) | DD26: 50A(ﾌﾗﾝｼﾞ) | DE26: 個 | DF26: 359000 | DG26: 233350 | DH26: 0.18 | DK26: 電動混合三方弁(ﾌﾗﾝｼﾞ) | DL26: 50A | DM26: ｾｯﾄ | DN26: 307200 | DO26: 230400 | DP26: 0.95 | DS26: ﾌﾚｷｼﾞｮｲﾝﾄ(F) | DT26: 150A*500L | DU26: 本 | DV26: 62200 | DW26: 16170 | DX26: 0.65 | EA26: ﾒｶﾆｶﾙ配管接手 | EB26: ｴﾙﾎﾞ 25Ａ | EC26: 個 | ED26: 4950 | EE26: =ROUND(ED26*0.65,-1) -> 3220 | EF26: 0.14 | EI26: 多量ﾄﾗｯﾌﾟ | EJ26: 50A AF-11H | EK26: 個 | EL26: 137000 | EM26: =EL26*0.65 -> 89050 | EN26: 2.21 | FG26: 保温(ｽﾃﾝﾗｯｷﾝｸﾞ) | FH26: 100A | FI26: ｍ | FJ26: 20160 | FK26: 13520 | FL26: 0
E27: 25 | F27: 埋設配管防蝕工事費 | AI27: ｽﾃﾝﾚｽ ﾕﾆｵﾝ | AJ27: 32A | AK27: 個 | AL27: 10010 | AM27: 6990 | AN27: 0 | AQ27: 塩ﾋﾞ管 | AR27: VU φ400 | AS27: m | AT27: 25330 | AU27: 16470 | AV27: 1.1 | AY27: ﾎﾟﾘ管用ﾁｰｽﾞ | AZ27: 30L | BA27: 個 | BB27: 5450 | BC27: 3270 | BD27: 0.14 | CU27: ﾎﾞｰﾙ弁(2方) | CV27: 25A(G-FF) | CW27: 個 | CX27: 4880 | CY27: 3180 | CZ27: 0.12 | DK27: 電動混合三方弁(ﾌﾗﾝｼﾞ) | DL27: 65A | DM27: ｾｯﾄ | DN27: 426320 | DO27: 319740 | DP27: 1.04 | DS27: ﾌﾚｷｼﾞｮｲﾝﾄ(F) | DT27: 200A*500L | DU27: 本 | DV27: 122300 | DW27: 31800 | DX27: 0.95 | EA27: ﾒｶﾆｶﾙ配管接手 | EB27: ｴﾙﾎﾞ 32Ａ | EC27: 個 | ED27: 6040 | EE27: =ROUND(ED27*0.65,-1) -> 3930 | EF27: 0.16 | EI27: 安全弁 | EJ27: 15A SL-37-D | EK27: 個 | EL27: 28500 | EM27: =EL27*0.44 -> 12540 | EN27: 0.11 | FG27: 保温(ｽﾃﾝﾗｯｷﾝｸﾞ) | FH27: 125A | FI27: ｍ | FJ27: 23520 | FK27: 15760 | FL27: 0
E28: 26 | F28: 埋設配管補強工事費 | AI28: ｽﾃﾝﾚｽ ﾕﾆｵﾝ | AJ28: 40A | AK28: 個 | AL28: 12520 | AM28: 8780 | AN28: 0 | AQ28: 塩ﾋﾞ管 | AR28: VU φ450 | AS28: m | AT28: 32030 | AU28: 20820 | AV28: 1.24 | AY28: ---------- | DK28: 電動混合三方弁(ﾌﾗﾝｼﾞ) | DL28: 80A | DM28: ｾｯﾄ | DN28: 493190 | DO28: 369890 | DP28: 1.12 | DS28: ---------- | EA28: ﾒｶﾆｶﾙ配管接手 | EB28: ｴﾙﾎﾞ 40Ａ | EC28: 個 | ED28: 7480 | EE28: =ROUND(ED28*0.65,-1) -> 4860 | EF28: 0.18 | EI28: 安全弁 | EJ28: 20A SL-37-D | EK28: 個 | EL28: 31400 | EM28: =EL28*0.44 -> 13816 | EN28: 0.11 | FG28: 保温(ｽﾃﾝﾗｯｷﾝｸﾞ) | FH28: 150A | FI28: ｍ | FJ28: 27120 | FK28: 18170 | FL28: 0
E29: 27 | F29: 配管塗装工事 | AI29: ｽﾃﾝﾚｽ ﾕﾆｵﾝ | AJ29: 50A | AK29: 個 | AL29: 17520 | AM29: 12370 | AN29: 0 | AQ29: 塩ﾋﾞ管 | AR29: VU φ500 | AS29: m | AT29: 40230 | AU29: 26150 | AV29: 1.38 | AY29: ﾎﾟﾘﾌﾞﾃﾞﾝ管 | AZ29: 13A | BA29: ｍ | BB29: 370 | BC29: 270 | BD29: 0.07 | DK29: 電動混合三方弁(ﾌﾗﾝｼﾞ) | DL29: 100A | DM29: ｾｯﾄ | DN29: 618580 | DO29: 463940 | DP29: 1.21 | DS29: ﾌﾚｷｼﾞｮｲﾝﾄ(U) | DT29: 32A*800L | DU29: 本 | DV29: 12000 | DW29: 5520 | DX29: 0.16 | EA29: ﾒｶﾆｶﾙ配管接手 | EB29: ｴﾙﾎﾞ 50Ａ | EC29: 個 | ED29: 10650 | EE29: =ROUND(ED29*0.65,-1) -> 6920 | EF29: 0.22 | EI29: 安全弁 | EJ29: 25A SL-37-D | EK29: 個 | EL29: 40500 | EM29: =EL29*0.44 -> 17820 | EN29: 0.12 | FG29: 保温(ｽﾃﾝﾗｯｷﾝｸﾞ) | FH29: 200A | FI29: ｍ | FJ29: 44060 | FK29: 29520 | FL29: 1
E30: 28 | F30: 孔明け補修工事 | V30: 重さ | AI30: ｽﾃﾝﾚｽ ﾕﾆｵﾝ | AJ30: 65A | AK30: 個 | AL30: 24040 | AM30: 13550 | AN30: 0 | AQ30: ---------- | AY30: ﾎﾟﾘﾌﾞﾃﾞﾝ管 | AZ30: 16A | BA30: ｍ | BB30: 510 | BC30: 370 | BD30: 0.09 | DK30: 電動混合三方弁(ﾌﾗﾝｼﾞ) | DL30: 125A | DM30: ｾｯﾄ | DN30: 891300 | DO30: 668480 | DP30: 1.3 | DS30: ﾌﾚｷｼﾞｮｲﾝﾄ(F) | DT30: 40A*800L | DU30: 本 | DV30: 24700 | DW30: 6420 | DX30: 0.18 | EA30: ﾒｶﾆｶﾙ配管接手 | EB30: ｴﾙﾎﾞ 65Ａ | EC30: 個 | ED30: 20620 | EE30: =ROUND(ED30*0.65,-1) -> 13400 | EF30: 0.37 | EI30: 安全弁 | EJ30: 32A SL-37-D | EK30: 個 | EL30: 49500 | EM30: =EL30*0.44 -> 21780 | EN30: 0.15 | FG30: 保温(ｽﾃﾝﾗｯｷﾝｸﾞ) | FH30: 250A | FI30: ｍ | FJ30: 56130 | FK30: 37610 | FL30: 2
E31: 29 | F31: 埋設配管掘削・埋め戻し工事 | S31: STK鋼管 | T31: 40A(Znﾒｯｷ) | U31: ｍ | V31: 2.63 | W31: kg/m | AQ31: 塩ﾋﾞ管(耐衝撃性) | AR31: HI φ13 | AS31: m | AT31: 310 | AU31: 200 | AV31: 0.06 | AY31: ﾎﾟﾘﾌﾞﾃﾞﾝ管 | AZ31: 20A | BA31: ｍ | BB31: 700 | BC31: 500 | BD31: 0.1 | DK31: 電動混合三方弁(ﾌﾗﾝｼﾞ) | DL31: 150A | DM31: ｾｯﾄ | DN31: 1122220 | DO31: 841670 | DP31: 1.4 | DS31: ﾌﾚｷｼﾞｮｲﾝﾄ(F) | DT31: 50A*800L | DU31: 本 | DV31: 31300 | DW31: 8140 | DX31: 0.22 | EA31: ﾒｶﾆｶﾙ配管接手 | EB31: ｴﾙﾎﾞ 80Ａ | EC31: 個 | ED31: 26800 | EE31: =ROUND(ED31*0.65,-1) -> 17420 | EF31: 0.44 | EI31: 安全弁 | EJ31: 40A SL-37-D | EK31: 個 | EL31: 64400 | EM31: =EL31*0.44 -> 28336 | EN31: 0.17 | FG31: 保温(ｽﾃﾝﾗｯｷﾝｸﾞ) | FH31: 300A | FI31: ｍ | FJ31: 65700 | FK31: 44020 | FL31: 3
E32: 30 | F32: 埋設配管掘削工事 | S32: STK鋼管 | T32: 50A(Znﾒｯｷ) | U32: ｍ | V32: 3.3 | AQ32: 塩ﾋﾞ管(耐衝撃性) | AR32: HI φ16 | AS32: m | AT32: 460 | AU32: 300 | AV32: 0.07 | AY32: ﾎﾟﾘﾌﾞﾃﾞﾝ管 | AZ32: 25A | BA32: ｍ | BB32: 850 | BC32: 610 | BD32: 0.11 | DS32: ﾌﾚｷｼﾞｮｲﾝﾄ(F) | DT32: 65A*800L | DU32: 本 | DV32: 35900 | DW32: 9330 | DX32: 0.37 | EA32: ﾒｶﾆｶﾙ配管接手 | EB32: 異径ﾁｰｽﾞ32×15 | EC32: 個 | ED32: 6800 | EE32: =ED32*0.65 -> 4420 | EF32: 0.16 | EI32: 安全弁 | EJ32: 50A SL-37-D | EK32: 個 | EL32: 85700 | EM32: =EL32*0.44 -> 37708 | EN32: 0.22 | FG32: ---------- | FL32: 0
E33: 31 | F33: 埋設配管埋め戻し工事 | S33: STK鋼管 | T33: 65A(Znﾒｯｷ) | U33: ｍ | V33: 5.08 | AQ33: 塩ﾋﾞ管(耐衝撃性) | AR33: HI φ20 | AS33: m | AT33: 500 | AU33: 330 | AV33: 0.07 | AY33: ﾎﾟﾘﾌﾞﾃﾞﾝ管 | AZ33: 30A | BA33: ｍ | BB33: 1310 | BC33: 950 | BD33: 0.14 | DS33: ﾌﾚｷｼﾞｮｲﾝﾄ(F) | DT33: 80A*800L | DU33: 本 | DV33: 40300 | DW33: 10480 | DX33: 0.44 | EA33: ﾒｶﾆｶﾙ配管接手 | EB33: 異径ﾁｰｽﾞ32×20 | EC33: 個 | ED33: 6800 | EE33: =ED33*0.65 -> 4420 | EF33: 0.16 | EI33: 減圧弁(水用) | EJ33: 15A RD-31 | EK33: 個 | EL33: 82200 | EM33: =EL33*0.65 -> 53430 | EN33: 0.11 | FG33: 保温(ﾃｰﾌﾟ巻) | FH33: 15A | FI33: ｍ | FJ33: 4100 | FK33: 2530 | FL33: 0
S34: STK鋼管 | T34: 80A(Znﾒｯｷ) | U34: ｍ | V34: 5.96 | AQ34: 塩ﾋﾞ管(耐衝撃性) | AR34: HI φ25 | AS34: m | AT34: 760 | AU34: 500 | AV34: 0.09 | AY34: ﾎﾟﾘﾌﾞﾃﾞﾝ管 | AZ34: 40A | BA34: ｍ | BB34: 1740 | BC34: 1260 | BD34: 0.18 | DS34: ﾌﾚｷｼﾞｮｲﾝﾄ(F) | DT34: 100A*800L | DU34: 本 | DV34: 48100 | DW34: 12510 | DX34: 0.54 | EA34: ﾒｶﾆｶﾙ配管接手 | EB34: 異径ﾁｰｽﾞ40×15 | EC34: 個 | ED34: 8810 | EE34: =ED34*0.65 -> 5726.5 | EF34: 0.18 | EI34: 減圧弁(水用) | EJ34: 20A RD-31 | EK34: 個 | EL34: 85200 | EM34: =EL34*0.65 -> 55380 | EN34: 0.11 | FG34: 保温(ﾃｰﾌﾟ巻) | FH34: 20A | FI34: ｍ | FJ34: 4230 | FK34: 2610 | FL34: 0
S35: STK鋼管 | T35: 100A(Znﾒｯｷ) | U35: ｍ | V35: 8.77 | AQ35: 塩ﾋﾞ管(耐衝撃性) | AR35: HI φ30 | AS35: m | AT35: 970 | AU35: 630 | AV35: 0.1 | AY35: ﾎﾟﾘﾌﾞﾃﾞﾝ管 | AZ35: 50A | BA35: ｍ | BB35: 2660 | BC35: 1920 | BD35: 0.2 | DS35: ﾌﾚｷｼﾞｮｲﾝﾄ(F) | DT35: 125A*800L | DU35: 本 | DV35: 69700 | DW35: 18120 | DX35: 0.57 | EA35: ﾒｶﾆｶﾙ配管接手 | EB35: 異径ﾁｰｽﾞ40×20 | EC35: 個 | ED35: 8810 | EE35: =ED35*0.65 -> 5726.5 | EF35: 0.18 | EI35: 減圧弁(水用) | EJ35: 25A RD-31 | EK35: 個 | EL35: 94000 | EM35: =EL35*0.65 -> 61100 | EN35: 0.12 | FG35: 保温(ﾃｰﾌﾟ巻) | FH35: 25A | FI35: ｍ | FJ35: 4680 | FK35: 2900 | FL35: 0
C36: 【変更履歴】 | S36: STK鋼管 | T36: 125A(Znﾒｯｷ) | U36: ｍ | V36: 12.1 | AQ36: 塩ﾋﾞ管(耐衝撃性) | AR36: HI φ40 | AS36: m | AT36: 1330 | AU36: 870 | AV36: 0.12 | AY36: ﾎﾟﾘﾌﾞﾃﾞﾝ管 | AZ36: 65A | BA36: ｍ | BB36: 4260 | BC36: 3070 | BD36: 0.27 | DS36: ﾌﾚｷｼﾞｮｲﾝﾄ(F) | DT36: 150A*800L | DU36: 本 | DV36: 84900 | DW36: 22070 | DX36: 0.65 | EA36: ﾒｶﾆｶﾙ配管接手 | EB36: 異径ﾁｰｽﾞ50×15 | EC36: 個 | ED36: 10830 | EE36: =ED36*0.65 -> 7039.5 | EF36: 0.22 | EI36: 減圧弁(水用) | EJ36: 32A RD-31 | EK36: 個 | EL36: 127000 | EM36: =EL36*0.65 -> 82550 | EN36: 0.15 | FG36: 保温(ﾃｰﾌﾟ巻) | FH36: 32A | FI36: ｍ | FJ36: 4860 | FK36: 3010 | FL36: 0
C37: ’10.12.17訂正箇所 部品値上 | S37: STK鋼管 | T37: 150A(Znﾒｯｷ) | U37: ｍ | V37: 17.8 | AQ37: 塩ﾋﾞ管(耐衝撃性) | AR37: HI φ50 | AS37: m | AT37: 1770 | AU37: 1150 | AV37: 0.15 | AY37: ﾎﾟﾘﾌﾞﾃﾞﾝ管 | AZ37: 75A | BA37: ｍ | BB37: 5850 | BC37: 4210 | BD37: 0.38 | DS37: ﾌﾚｷｼﾞｮｲﾝﾄ(F) | DT37: 200A*800L | DU37: 本 | DV37: 162600 | DW37: 42280 | DX37: 0.95 | EA37: ﾒｶﾆｶﾙ配管接手 | EB37: 異径ﾁｰｽﾞ50×20 | EC37: 個 | ED37: 10830 | EE37: =ED37*0.65 -> 7039.5 | EF37: 0.22 | EI37: 減圧弁(水用) | EJ37: 40A RD-31 | EK37: 個 | EL37: 129000 | EM37: =EL37*0.65 -> 83850 | EN37: 0.17 | FG37: 保温(ﾃｰﾌﾟ巻) | FH37: 40A | FI37: ｍ | FJ37: 4950 | FK37: 3080 | FL37: 0
C38: ’11.05.13訂正箇所 20%UP | S38: STK鋼管 | T38: 200A(Znﾒｯｷ) | U38: ｍ | V38: 23.5 | AQ38: ---------- | AY38: ﾎﾟﾘﾌﾞﾃﾞﾝ管 | AZ38: 100A | BA38: ｍ | BB38: 10360 | BC38: 7460 | BD38: 0.39 | DS38: ---------- | EI38: 減圧弁(水用) | EJ38: 50A RD-31 | EK38: 個 | EL38: 152000 | EM38: =EL38*0.65 -> 98800 | EN38: 0.22 | FG38: 保温(ﾃｰﾌﾟ巻) | FH38: 50A | FI38: ｍ | FJ38: 5760 | FK38: 3580 | FL38: 0
C39: ’14.08.19訂正箇所 原価値上 | S39: STK鋼管 | T39: 250A(Znﾒｯｷ) | U39: ｍ | V39: 45 | AQ39: 塩ﾋﾞ管(耐熱性) | AR39: HT φ13 | AS39: m | AT39: 400 | AU39: 290 | AV39: 0.06 | AY39: ---------- | DS39: ﾎﾞｰﾙﾌﾚｷｼﾞｮｲﾝﾄ | DT39: 32A*125L | DU39: 個 | DV39: 14000 | DW39: =ROUND(DV39*0.6,-1) -> 8400 | DX39: 0.16 | EI39: 落水防止弁 | EJ39: MD-20H 40A | EK39: 個 | EL39: 194000 | EM39: =EL39*0.65 -> 126100 | EN39: 0.17 | FG39: 保温(ﾃｰﾌﾟ巻) | FH39: 65A | FI39: ｍ | FJ39: 6350 | FK39: 3930 | FL39: 0
C40: 69期価格修正 | S40: STK鋼管 | T40: 300A(Znﾒｯｷ) | U40: ｍ | V40: 53.8 | AQ40: 塩ﾋﾞ管(耐熱性) | AR40: HT φ16 | AS40: m | AT40: 600 | AU40: 430 | AV40: 0.07 | AY40: ﾎﾟﾘﾌﾞﾃﾞﾝ ｿｹｯﾄ | AZ40: 20A | BA40: 個 | BB40: 480 | BC40: =ROUND(BB40*0.72,-1) -> 350 | BD40: 0 | DS40: ﾎﾞｰﾙﾌﾚｷｼﾞｮｲﾝﾄ | DT40: 40A*125L | DU40: 個 | DV40: 15000 | DW40: =ROUND(DV40*0.6,-1) -> 9000 | DX40: 0.18 | EI40: 落水防止弁 | EJ40: MD-20H 50A | EK40: 個 | EL40: 209000 | EM40: =EL40*0.65 -> 135850 | EN40: 0.18 | FG40: 保温(ﾃｰﾌﾟ巻) | FH40: 80A | FI40: ｍ | FJ40: 6930 | FK40: 4300 | FL40: 0
C41: 70期価格修正 | S41: ---------- | AQ41: 塩ﾋﾞ管(耐熱性) | AR41: HT φ20 | AS41: m | AT41: 720 | AU41: 520 | AV41: 0.07 | AY41: ﾎﾟﾘﾌﾞﾃﾞﾝ ｿｹｯﾄ | AZ41: 25A | BA41: 個 | BB41: 620 | BC41: =ROUND(BB41*0.72,-1) -> 450 | BD41: 0 | DS41: ﾎﾞｰﾙﾌﾚｷｼﾞｮｲﾝﾄ | DT41: 50A*125L | DU41: 個 | DV41: 17000 | DW41: =ROUND(DV41*0.6,-1) -> 10200 | DX41: 0.22 | EI41: 落水防止弁 | EJ41: MD-20H 65A | EK41: 個 | EL41: 305000 | EM41: =EL41*0.65 -> 198250 | EN41: 0.32 | FG41: 保温(ﾃｰﾌﾟ巻) | FH41: 100A | FI41: ｍ | FJ41: 8370 | FK41: 5190 | FL41: 0
C42: 71期価格修正 | S42: STK鋼管(5.5m) | T42: 40A(Znﾒｯｷ) | U42: 本 | V42: =5.5*V31 -> 14.465 | W42: kg/本 | AQ42: 塩ﾋﾞ管(耐熱性) | AR42: HT φ25 | AS42: m | AT42: 1040 | AU42: 750 | AV42: 0.09 | AY42: ﾎﾟﾘﾌﾞﾃﾞﾝ ｿｹｯﾄ | AZ42: 30A | BA42: 個 | BB42: 750 | BC42: =ROUND(BB42*0.72,-1) -> 540 | BD42: 0 | DS42: ﾎﾞｰﾙﾌﾚｷｼﾞｮｲﾝﾄ | DT42: 65A*125L | DU42: 個 | DV42: 21000 | DW42: =ROUND(DV42*0.6,-1) -> 12600 | DX42: 0.37 | EI42: 落水防止弁 | EJ42: MD-20H 80A | EK42: 個 | EL42: 350000 | EM42: =EL42*0.65 -> 227500 | EN42: 0.39 | FG42: 保温(ﾃｰﾌﾟ巻) | FH42: 125A | FI42: ｍ | FJ42: 9770 | FK42: 6070 | FL42: 0
C43: 72期価格修正 | S43: STK鋼管(5.5m) | T43: 50A(Znﾒｯｷ) | U43: 本 | V43: =5.5*V32 -> 18.15 | AQ43: 塩ﾋﾞ管(耐熱性) | AR43: HT φ30 | AS43: m | AT43: 1290 | AU43: 930 | AV43: 0.1 | AY43: ﾎﾟﾘﾌﾞﾃﾞﾝ ｿｹｯﾄ | AZ43: 40A | BA43: 個 | BB43: 970 | BC43: =ROUND(BB43*0.72,-1) -> 700 | BD43: 0 | DS43: ﾎﾞｰﾙﾌﾚｷｼﾞｮｲﾝﾄ | DT43: 80A*125L | DU43: 個 | DV43: 23000 | DW43: =ROUND(DV43*0.6,-1) -> 13800 | DX43: 0.44 | EI43: 落水防止弁 | EJ43: MD-20H 100A | EK43: 個 | EL43: 485000 | EM43: =EL43*0.65 -> 315250 | EN43: 0.48 | FG43: 保温(ﾃｰﾌﾟ巻) | FH43: 150A | FI43: ｍ | FJ43: 11210 | FK43: 6970 | FL43: 0
C44: 73期価格修正 | S44: STK鋼管(5.5m) | T44: 65A(Znﾒｯｷ) | U44: 本 | V44: =5.5*V33 -> 27.94 | AQ44: 塩ﾋﾞ管(耐熱性) | AR44: HT φ40 | AS44: m | AT44: 1880 | AU44: 1350 | AV44: 0.12 | AY44: ﾎﾟﾘﾌﾞﾃﾞﾝ ｿｹｯﾄ | AZ44: 50A | BA44: 個 | BB44: 1410 | BC44: =ROUND(BB44*0.72,-1) -> 1020 | BD44: 0 | DS44: ﾎﾞｰﾙﾌﾚｷｼﾞｮｲﾝﾄ | DT44: 100A*150L | DU44: 個 | DV44: 27000 | DW44: =ROUND(DV44*0.6,-1) -> 16200 | DX44: 0.54 | EI44: 落水防止弁 | EJ44: MD-20H 125A | EK44: 個 | EL44: 949000 | EM44: =EL44*0.65 -> 616850 | EN44: 0.57 | FG44: 保温(ﾃｰﾌﾟ巻) | FH44: 200A | FI44: ｍ | FJ44: 17190 | FK44: 10680 | FL44: 1
C45: 74期価格修正 | S45: STK鋼管(5.5m) | T45: 80A(Znﾒｯｷ) | U45: 本 | V45: =5.5*V34 -> 32.78 | AQ45: 塩ﾋﾞ管(耐熱性) | AR45: HT φ50 | AS45: m | AT45: 2870 | AU45: 2070 | AV45: 0.15 | AY45: ﾎﾟﾘﾌﾞﾃﾞﾝ ｿｹｯﾄ | AZ45: 65A | BA45: 個 | BB45: 2530 | BC45: =ROUND(BB45*0.72,-1) -> 1820 | BD45: 0 | DS45: ﾎﾞｰﾙﾌﾚｷｼﾞｮｲﾝﾄ | DT45: 125A*175L | DU45: 個 | DV45: 40000 | DW45: =ROUND(DV45*0.6,-1) -> 24000 | DX45: 0.57 | EI45: 落水防止弁 | EJ45: MD-20H 150A | EK45: 個 | EL45: 1266000 | EM45: =EL45*0.65 -> 822900 | EN45: 0.65 | FG45: 保温(ﾃｰﾌﾟ巻) | FH45: 250A | FI45: ｍ | FJ45: 21830 | FK45: 13570 | FL45: 2
C46: 75期価格修正 | S46: STK鋼管(5.5m) | T46: 100A(Znﾒｯｷ) | U46: 本 | V46: =5.5*V35 -> 48.235 | AQ46: 塩ﾋﾞ管(耐熱性) | AR46: HT φ65 | AS46: m | AT46: 3920 | AU46: 2830 | AV46: 0.2 | AY46: ﾎﾟﾘﾌﾞﾃﾞﾝ ｿｹｯﾄ | AZ46: 75A | BA46: 個 | BB46: 4230 | BC46: =ROUND(BB46*0.72,-1) -> 3050 | BD46: 0 | DS46: ﾎﾞｰﾙﾌﾚｷｼﾞｮｲﾝﾄ | DT46: 150A*200L | DU46: 個 | DV46: 50000 | DW46: =ROUND(DV46*0.6,-1) -> 30000 | DX46: 0.65 | FG46: 保温(ﾃｰﾌﾟ巻) | FH46: 300A | FI46: ｍ | FJ46: 25880 | FK46: 16100 | FL46: 3
C47: 76期価格修正 | S47: STK鋼管(5.5m) | T47: 125A(Znﾒｯｷ) | U47: 本 | V47: =5.5*V36 -> 66.55 | AQ47: 塩ﾋﾞ管(耐熱性) | AR47: HT φ75 | AS47: m | AT47: 5550 | AU47: 4000 | AV47: 0.23 | AY47: ﾎﾟﾘﾌﾞﾃﾞﾝ ｿｹｯﾄ | AZ47: 100A | BA47: 個 | BB47: 7280 | BC47: =ROUND(BB47*0.72,-1) -> 5240 | BD47: 0 | DS47: ﾎﾞｰﾙﾌﾚｷｼﾞｮｲﾝﾄ | DT47: 200A*200L | DU47: 個 | DV47: 65000 | DW47: =ROUND(DV47*0.6,-1) -> 39000 | DX47: 0.95 | FG47: ----------
C48: 77期価格修正 | S48: STK鋼管(5.5m) | T48: 150A(Znﾒｯｷ) | U48: 本 | V48: =5.5*V37 -> 97.9 | AQ48: 塩ﾋﾞ管(耐熱性) | AR48: HT φ100 | AS48: m | AT48: 8610 | AU48: 6200 | AV48: 0.29 | AY48: ---------- | DS48: ﾎﾞｰﾙﾌﾚｷｼﾞｮｲﾝﾄ | DT48: 250A*250L | DU48: 個 | DV48: 97000 | DW48: =ROUND(DV48*0.6,-1) -> 58200 | DX48: 1.13 | FG48: 煙道保温工事 | FH48: ﾛｯｸｳｰﾙ | FI48: ㎡ | FL48: 0
C49: 78期価格修正 | S49: STK鋼管(5.5m) | T49: 200A(Znﾒｯｷ) | U49: 本 | V49: =5.5*V38 -> 129.25 | AQ49: 塩ﾋﾞ管(耐熱性) | AR49: HT φ125 | AS49: m | AT49: 11530 | AU49: 8300 | AV49: 0.36 | AY49: ﾎﾟﾘﾌﾞﾃﾞﾝ ｴﾙﾎﾞ | AZ49: 20A | BA49: 個 | BB49: 580 | BC49: =ROUND(BB49*0.72,-1) -> 420 | BD49: 0 | FG49: ﾀﾝｸ 保温工事 | FH49: ｸﾞﾗｽﾛﾝ | FI49: ㎡ | FL49: 0
C50: 79期価格修正 | S50: STK鋼管(5.5m) | T50: 250A(Znﾒｯｷ) | U50: 本 | V50: =5.5*V39 -> 247.5 | AQ50: 塩ﾋﾞ管(耐熱性) | AR50: HT φ150 | AS50: m | AT50: 15800 | AU50: 11370 | AV50: 0.43 | AY50: ﾎﾟﾘﾌﾞﾃﾞﾝ ｴﾙﾎﾞ | AZ50: 25A | BA50: 個 | BB50: 820 | BC50: =ROUND(BB50*0.72,-1) -> 590 | BD50: 0 | FG50: 同上保温工事 | FH50: ｸﾞﾗｽﾛﾝ | FI50: ㎡ | FL50: 0
S51: STK鋼管(5.5m) | T51: 300A(Znﾒｯｷ) | U51: 本 | V51: =5.5*V40 -> 295.9 | AY51: ﾎﾟﾘﾌﾞﾃﾞﾝ ｴﾙﾎﾞ | AZ51: 30A | BA51: 個 | BB51: 1280 | BC51: =ROUND(BB51*0.72,-1) -> 920 | BD51: 0
AY52: ﾎﾟﾘﾌﾞﾃﾞﾝ ｴﾙﾎﾞ | AZ52: 40A | BA52: 個 | BB52: 1680 | BC52: =ROUND(BB52*0.72,-1) -> 1210 | BD52: 0
AY53: ﾎﾟﾘﾌﾞﾃﾞﾝ ｴﾙﾎﾞ | AZ53: 50A | BA53: 個 | BB53: 2640 | BC53: =ROUND(BB53*0.72,-1) -> 1900 | BD53: 0
AY54: ﾎﾟﾘﾌﾞﾃﾞﾝ ｴﾙﾎﾞ | AZ54: 65A | BA54: 個 | BB54: 3430 | BC54: =ROUND(BB54*0.72,-1) -> 2470 | BD54: 0
AY55: ﾎﾟﾘﾌﾞﾃﾞﾝ ｴﾙﾎﾞ | AZ55: 75A | BA55: 個 | BB55: 5800 | BC55: =ROUND(BB55*0.72,-1) -> 4180 | BD55: 0
AY56: ﾎﾟﾘﾌﾞﾃﾞﾝ ｴﾙﾎﾞ | AZ56: 100A | BA56: 個 | BB56: 11200 | BC56: =ROUND(BB56*0.72,-1) -> 8060 | BD56: 0
AY57: ----------
AY58: ﾎﾟﾘﾌﾞﾃﾞﾝ管 | AZ58: φ20×120ｍ | BA58: 巻 | BB58: 70800 | BC58: 50976 | BD58: 8.4
AY59: ﾎﾟﾘﾌﾞﾃﾞﾝ管 | AZ59: φ25×100ｍ | BA59: 巻 | BB59: 70000 | BC59: 50400 | BD59: 9
AY60: ﾎﾟﾘﾌﾞﾃﾞﾝ管 | AZ60: φ30×60ｍ | BA60: 巻 | BB60: 57600 | BC60: 41480 | BD60: 6

Sheet 標準項
A2: 標準項目 | E2: SHB-310TK | N2: HK2030TCV | W2: HK2030TEV | AE2: BOT-490 | AN2: NGP109TQX-J | AW2: KA-125E | BF2: エロフィン配管（40A) | BO2: CG-254S2
A3: ---ﾊｳｽﾎﾞｲﾗ---- | E3: =CONCATENATE("○",機器表!AB4," ",機器表!AC4) -> ○ｼｮｳｵﾝﾎﾞｲﾗ SHB-310TK | F3: 1 | G3: =機器表!AD4 -> 台 | H3: =機器表!AE4 -> 515000 | I3: =機器表!AF4 -> 232880 | J3: =機器表!AG4 -> 1 | K3: Ca | N3: ○ﾊｳｽｶｵﾝｷ HK2030TCV | O3: 1 | P3: =機器表!N3 -> 台 | Q3: =機器表!O3 -> 909000 | R3: =機器表!P3 -> 470450 | S3: =機器表!Q3 -> 1.25 | T3: Ca | W3: ○ﾊｳｽｶｵﾝｷ HK2030TEV | X3: 1 | Y3: =機器表!N4 -> 台 | Z3: =機器表!O4 -> 925000 | AA3: =機器表!P4 -> 481600 | AB3: =機器表!Q4 -> 1.25 | AC3: Ca | AE3: ○ｵｲﾙﾀﾝｸ BOT-490 | AF3: 1 | AG3: =機器表!ED5 -> 基 | AH3: =機器表!EE5 -> 119900 | AI3: =機器表!EF5 -> 52990 | AJ3: =機器表!EG5 -> 0.3 | AK3: Ca | AN3: ○グリーンパッケージ NGP109TQX-J | AO3: 1 | AP3: =機器表!DF3 -> ｾｯﾄ | AQ3: =機器表!DG3 -> 1573000 | AR3: =機器表!DH3 -> 822710 | AS3: =機器表!DI3 -> 2.9 | AT3: Ca | AW3: ○小型温風機 KA-125E | AX3: 1 | AY3: =機器表!V9 -> 台 | AZ3: =機器表!W9 -> 389000 | BA3: =機器表!X9 -> 170820 | BB3: =機器表!Y9 -> 0.52 | BC3: Ca | BF3: ○ｴﾛﾌｨﾝﾁｭｰﾌﾞ 40A 32F 2750L | BG3: 60 | BH3: 本 | BI3: =機器表!BS34 -> 77000 | BJ3: =機器表!BT34 -> 30900 | BK3: 0.36 | BL3: Ca | BO3: ○グロウエア CG-254S2 | BP3: 1 | BQ3: =機器表!V21 -> 台 | BR3: =機器表!W21 -> 344000 | BS3: =機器表!X21 -> 168500 | BT3: =機器表!Y21 -> 0.5 | BU3: Ca
A4: SHB-310TK | B4: e3 | C4: 1 | E4: ④同上搬入据付工事 | F4: 1 | G4: 式 | H4: =ROUND(項目表!$E$3*標準項!K4,-3) -> 48000 | I4: =ROUND(項目表!$F$3*標準項!K4,-3) -> 29000 | K4: 1 | N4: ④同上搬入据付工事 | O4: 1 | P4: 式 | Q4: =ROUND(項目表!$E$3*標準項!T4,-3) -> 59000 | R4: =ROUND(項目表!$F$3*標準項!T4,-3) -> 37000 | T4: 1.25 | W4: ④同上搬入据付工事 | X4: 1 | Y4: 式 | Z4: =ROUND(項目表!$E$3*標準項!AC4,-3) -> 59000 | AA4: =ROUND(項目表!$F$3*標準項!AC4,-3) -> 37000 | AC4: 1.25 | AE4: ④機器組立工事 | AF4: 1 | AG4: 式 | AH4: =ROUND(項目表!$E$3*標準項!AK4,-3) -> 14000 | AI4: =ROUND(項目表!$F$3*標準項!AK4,-3) -> 9000 | AK4: 0.3 | AN4: （室内機・室外機 親機セット） | AS4: 0 | AW4: ④同上搬入据付工事 | AX4: 1 | AY4: 式 | AZ4: =ROUND(項目表!$E$3*標準項!BC4,-3) -> 25000 | BA4: =ROUND(項目表!$F$3*標準項!BC4,-3) -> 15000 | BC4: 0.52 | BF4: ○ｴﾛﾌｨﾝﾁｭｰﾌﾞ 40A 32F 1500L | BG4: 8 | BH4: 本 | BI4: =機器表!BS36 -> 69000 | BJ4: =機器表!BT36 -> 27600 | BK4: 0.2 | BL4: Ca | BO4: ④同上搬入据付工事 | BP4: 1 | BQ4: 式 | BR4: =ROUND(項目表!$E$3*標準項!BU4,-3) -> 24000 | BS4: =ROUND(項目表!$F$3*標準項!BU4,-3) -> 15000 | BU4: 0.5
A5: HB-407TGA | B5: e27 | C5: =C4+1 -> 2 | E5: =CONCATENATE("③",電材表!Q18," ",電材表!R18) -> ③感震器 BES-100 | F5: 1 | G5: =電材表!S18 -> 個 | H5: =電材表!T18 -> 20100 | I5: =電材表!U18 -> 5580 | J5: =電材表!V18 -> 0 | K5: Cc | N5: =CONCATENATE("③",電材表!Q18," ",電材表!R18) -> ③感震器 BES-100 | O5: 1 | P5: =電材表!S18 -> 個 | Q5: =電材表!T18 -> 20100 | R5: =電材表!U18 -> 5580 | S5: =電材表!V18 -> 0 | T5: Cc | W5: =CONCATENATE("③",電材表!Q18," ",電材表!R18) -> ③感震器 BES-100 | X5: 1 | Y5: =電材表!S18 -> 個 | Z5: =電材表!T18 -> 20100 | AA5: =電材表!U18 -> 5580 | AB5: =電材表!V18 -> 0 | AC5: Cc | AE5: ④同上搬入据付工事 | AF5: 1 | AG5: 式 | AH5: =ROUND(項目表!$E$3*標準項!AK5,-3) -> 14000 | AI5: =ROUND(項目表!$F$3*標準項!AK5,-3) -> 9000 | AK5: 0.3 | AN5: （省エネハイブリッド制御盤他 付属） | AS5: 0 | AW5: =CONCATENATE("③",電材表!Q18," ",電材表!R18) -> ③感震器 BES-100 | AX5: 1 | AY5: =電材表!S18 -> 個 | AZ5: =電材表!T18 -> 20100 | BA5: =電材表!U18 -> 5580 | BB5: =電材表!V18 -> 0 | BC5: Cc | BF5: ④ｴﾛﾌｨﾝ取付工事 | BG5: 1 | BH5: 式 | BI5: =ROUND(項目表!$E$3*BL5,-3) -> 265000 | BJ5: =ROUND(項目表!$F$3*BL5,-3) -> 164000 | BL5: 5.57 | BO5: =CONCATENATE("③",電材表!Q10," ",電材表!R10) -> ③CO2ｺﾝﾄﾛｰﾗ CGC-600SET14 | BP5: 1 | BQ5: =電材表!S10 -> 台 | BR5: =電材表!T10 -> 155000 | BS5: =電材表!U10 -> 89490 | BT5: =電材表!V11 -> 0 | BU5: Cc
A6: HB-807TGA | B6: e53 | C6: =C5+1 -> 3 | E6: =CONCATENATE("○",機器表!EJ6," ",機器表!EK6) -> ○煙突ｾｯﾄ BEP-HB1201 | F6: 1 | G6: =機器表!EL6 -> ｾｯﾄ | H6: =機器表!EM6 -> 65700 | I6: =機器表!EN6 -> 23160 | J6: =機器表!EO6 -> 0.5 | K6: Ca | N6: ○煙室ｾｯﾄ ES- 2330 | O6: 1 | P6: =機器表!EL15 -> ｾｯﾄ | Q6: =機器表!EM15 -> 119000 | R6: =機器表!EN15 -> 35870 | S6: =機器表!EO15 -> 0.5 | T6: Ca | W6: ○煙室ｾｯﾄ ES- 2330 | X6: 1 | Y6: =機器表!EL15 -> ｾｯﾄ | Z6: =機器表!EM15 -> 119000 | AA6: =機器表!EN15 -> 35870 | AB6: =機器表!EO15 -> 0.5 | AC6: Ca | AE6: ①油配管ｾｯﾄ BOP-CU5M | AF6: 1 | AG6: =管材表!FA3 -> 個 | AH6: =管材表!FB3 -> 16500 | AI6: =管材表!FC3 -> 4670 | AJ6: =管材表!FD3 -> 0.3 | AK6: Cb | AN6: ④同上搬入据付工事 | AO6: 1 | AP6: 式 | AQ6: 165000 | AR6: 88000 | AS6: 0 | AW6: ○煙突ｾｯﾄ BEP-KA 1203 | AX6: 1 | AY6: =機器表!EL7 -> ｾｯﾄ | AZ6: =機器表!EM7 -> 60400 | BA6: =機器表!EN7 -> 20760 | BB6: =機器表!EO7 -> 0.5 | BC6: Ca | BF6: ○ｴﾛﾌｨﾝ支持金具 2段1列 | BG6: 40 | BH6: 本 | BI6: =機器表!GA4 -> 22000 | BJ6: =機器表!GB4 -> 11000 | BK6: 0.15 | BL6: Ca | BO6: =CONCATENATE("③",電材表!I9," ",電材表!J9) -> ③室温ｾﾝｻｰｾｯﾄ TS-102P | BP6: 1 | BQ6: =電材表!K9 -> 個 | BR6: =電材表!L9 -> 18100 | BS6: =電材表!M9 -> 2530 | BT6: =電材表!N9 -> 0 | BU6: Cc
A7: HB-1007TA | B7: e80 | C7: =C6+1 -> 4 | E7: =CONCATENATE("○",機器表!EJ24," ",機器表!EK24) -> ○煙突直管 φ120 | F7: 1 | G7: =機器表!EL24 -> 本 | H7: =機器表!EM24 -> 8470 | I7: =機器表!EN24 -> 2090 | J7: =機器表!EO24 -> 0.1 | K7: Ca | N7: ④同上取付工事 | O7: 1 | P7: 式 | Q7: =ROUND(項目表!$E$3*標準項!T7,-3) -> 24000 | R7: =ROUND(項目表!$F$3*標準項!T7,-3) -> 15000 | T7: =S6 -> 0.5 | W7: ④同上取付工事 | X7: 1 | Y7: 式 | Z7: =ROUND(項目表!$E$3*標準項!AC7,-3) -> 24000 | AA7: =ROUND(項目表!$F$3*標準項!AC7,-3) -> 15000 | AC7: =AB6 -> 0.5 | AE7: ①逃し管ｾｯﾄ BOP-EP8M | AF7: 1 | AG7: =管材表!FA8 -> 個 | AH7: =管材表!FB8 -> 18000 | AI7: =管材表!FC8 -> 4600 | AJ7: =管材表!FD8 -> 0.2 | AK7: Cb | AN7: ④冷媒配管工事費 10mまで | AO7: 1 | AP7: 式 | AQ7: 200000 | AR7: 100000 | AS7: 0 | AW7: ○煙突直管 φ120 | AX7: 1 | AY7: =機器表!EL24 -> 本 | AZ7: =機器表!EM24 -> 8470 | BA7: =機器表!EN24 -> 2090 | BB7: =機器表!EO24 -> 0.1 | BC7: Ca | BF7: ④同上取付工事 | BG7: 1 | BH7: 式 | BI7: =ROUND(項目表!$E$3*BL7,-3) -> 188000 | BJ7: =ROUND(項目表!$F$3*BL7,-3) -> 116000 | BL7: 3.96 | BO7: =CONCATENATE("③",電材表!Q19," ",電材表!R19) -> ③不完全燃焼警報器 SG-35 | BP7: 1 | BQ7: =電材表!S19 -> 個 | BR7: =電材表!T19 -> 85800 | BS7: =電材表!U19 -> 31120 | BT7: =電材表!V19 -> 0 | BU7: Cc
A8: HB-2007TA | B8: e110 | C8: =C7+1 -> 5 | E8: =CONCATENATE("○",機器表!EJ36," ",機器表!EK36) -> ○煙突ｴﾋﾞﾏｶﾞﾘ φ120 | F8: 1 | G8: =機器表!EL36 -> 個 | H8: =機器表!EM36 -> 6490 | I8: =機器表!EN36 -> 1360 | J8: =機器表!EO36 -> 0.1 | K8: Ca | N8: ○煙突ｾｯﾄ BEP-20T 1504 | O8: 1 | P8: =機器表!EL9 -> ｾｯﾄ | Q8: =機器表!EM9 -> 72800 | R8: =機器表!EN9 -> 23890 | S8: =機器表!EO9 -> 0.7 | T8: Ca | W8: ○煙突ｾｯﾄ BEP-20T 1504 | X8: 1 | Y8: =機器表!EL9 -> ｾｯﾄ | Z8: =機器表!EM9 -> 72800 | AA8: =機器表!EN9 -> 23890 | AB8: =機器表!EO9 -> 0.7 | AC8: Ca | AE8: =CONCATENATE("①",管材表!CM3," ",管材表!CN3) -> ①ﾏﾚｰﾌﾞﾙ弁 15A | AF8: 1 | AG8: =管材表!CO3 -> 個 | AH8: =管材表!CP3 -> 12200 | AI8: =管材表!CQ3 -> 7930 | AJ8: =管材表!CR3 -> 0.08 | AK8: Cb | AN8: ④同上配管断熱・防食ﾃｰﾌﾟ工事 | AO8: 1 | AP8: 式 | AQ8: 9600 | AR8: 6000 | AS8: 0 | AW8: ○煙突ｴﾋﾞﾏｶﾞﾘ φ120 | AX8: 1 | AY8: =機器表!EL36 -> 個 | AZ8: =機器表!EM36 -> 6490 | BA8: =機器表!EN36 -> 1360 | BB8: =機器表!EO36 -> 0.1 | BC8: Ca | BF8: =CONCATENATE("①",管材表!K7," ",管材表!L7) -> ①SGP鋼管(白) 40A | BG8: 20 | BH8: =管材表!M8 -> m | BI8: =管材表!N7 -> 6910 | BJ8: =管材表!O7 -> 3660 | BK8: =管材表!P7 -> 0.23 | BL8: Cb | BO8: =CONCATENATE("③",電材表!Q18," ",電材表!R18) -> ③感震器 BES-100 | BP8: 1 | BQ8: =電材表!S18 -> 個 | BR8: =電材表!T18 -> 20100 | BS8: =電材表!U18 -> 5580 | BT8: =電材表!V18 -> 0 | BU8: Cc
A9: HB-3007TA | B9: e142 | C9: =C8+1 -> 6 | E9: ②煙突支持金具 | F9: 1 | G9: 式 | H9: 18000 | I9: 12000 | J9: 0 | N9: ○煙突直管 φ150 | O9: 2 | P9: =機器表!EL25 -> 本 | Q9: =機器表!EM25 -> 9930 | R9: =機器表!EN25 -> 2290 | S9: =機器表!EO25 -> 0.1 | T9: Ca | W9: ○煙突直管 φ150 | X9: 2 | Y9: =機器表!EL25 -> 本 | Z9: =機器表!EM25 -> 9930 | AA9: =機器表!EN25 -> 2290 | AB9: =機器表!EO25 -> 0.1 | AC9: Ca | AE9: ④配管工事費 | AF9: 1 | AG9: 式 | AH9: =ROUND(項目表!$E$3*標準項!AK9,-3) -> 28000 | AI9: =ROUND(項目表!$F$3*標準項!AK9,-3) -> 17000 | AK9: 0.58 | AN9: ④ドレーン配管工事 3mまで | AO9: 1 | AP9: 式 | AQ9: 6000 | AR9: 3000 | AS9: 0 | AW9: ②煙突支持金具 | AX9: 1 | AY9: 個 | AZ9: 15000 | BA9: 10000 | BB9: 0 | BF9: =CONCATENATE("①",管材表!DK14," ",管材表!DL14) -> ①電動ﾎﾞｰﾙ弁(3方) 40A | BG9: 1 | BH9: =管材表!DM14 -> 個 | BI9: =管材表!DN14 -> 76000 | BJ9: =管材表!DO14 -> 49400 | BK9: =管材表!DP14 -> 0.16 | BL9: Cb | BO9: ④同上取付工事 | BP9: 1 | BQ9: 式 | BR9: 11000 | BS9: 7000
A10: HB-4007TA | B10: e174 | C10: =C9+1 -> 7 | E10: ④煙道・煙突取付工事 | F10: 1 | G10: 式 | H10: =ROUND(項目表!$E$3*標準項!K10,-3) -> 33000 | I10: =ROUND(項目表!$F$3*標準項!K10,-3) -> 21000 | K10: 0.7 | N10: ○煙道ｴﾙﾎﾞ φ150 | O10: 1 | P10: =機器表!EL38 -> 個 | Q10: =機器表!EM38 -> 7210 | R10: =機器表!EN38 -> 1560 | S10: =機器表!EO38 -> 0.1 | T10: Ca | W10: ○煙道ｴﾙﾎﾞ φ150 | X10: 1 | Y10: =機器表!EL38 -> 個 | Z10: =機器表!EM38 -> 7210 | AA10: =機器表!EN38 -> 1560 | AB10: =機器表!EO38 -> 0.1 | AC10: Ca | AE10: ②消耗品雑材 | AF10: 1 | AG10: 式 | AH10: 5000 | AI10: 3000 | AN10: ④ｱﾙﾐﾌﾚｷﾀﾞｸﾄ取付 φ225 | AO10: 1 | AP10: 式 | AQ10: 6000 | AR10: 3000 | AW10: ④同上煙突取付工事 | AX10: 1 | AY10: 式 | AZ10: =ROUND(項目表!$E$3*BC10,-3) -> 36000 | BA10: =ROUND(項目表!$F$3*BC10,-3) -> 22000 | BC10: 0.75 | BF10: =CONCATENATE("①",管材表!BG7," ",管材表!BH7) -> ①ｹﾞｰﾄ弁 40A | BG10: 3 | BH10: =管材表!BI7 -> 個 | BI10: =管材表!BJ7 -> 26700 | BJ10: =管材表!BK7 -> 17360 | BK10: =管材表!BL7 -> 0.16 | BL10: Cb | BO10: ○ｵｲﾙﾀﾝｸ BOT-200 | BP10: 1 | BQ10: =機器表!ED4 -> 基 | BR10: =機器表!EE4 -> 84000 | BS10: =機器表!EF4 -> 26080 | BT10: =機器表!EG4 -> 0.2 | BU10: Ca
A11: ---ﾊｳｽｶｵﾝｷ---- | E11: ④煙道断熱工事 ﾛｯｸｳｰﾙ | F11: 1 | G11: 式 | H11: 15000 | I11: 10000 | J11: 0 | N11: ②煙突支持金具 | O11: 1 | P11: 個 | Q11: 25000 | R11: 14000 | W11: ②煙突支持金具 | X11: 1 | Y11: 個 | Z11: 25000 | AA11: 14000 | AN11: ①ｱﾙﾐﾌﾚｷﾀﾞｸﾄ φ225×4000L | AO11: 3 | AP11: =機器表!FJ3 -> 本 | AQ11: =機器表!FK3 -> 11600 | AR11: =機器表!FL3 -> 2710 | AS11: =機器表!FM3 -> 0 | AT11: Ca | AW11: ④煙道断熱工事 | AX11: 1 | AY11: 式 | AZ11: 15000 | BA11: 10000 | BB11: 0 | BF11: =CONCATENATE("①",管材表!BG3," ",管材表!BH3) -> ①ｹﾞｰﾄ弁 15A | BG11: 4 | BH11: =管材表!BI3 -> 個 | BI11: =管材表!BJ3 -> 6510 | BJ11: =管材表!BK3 -> 4230 | BK11: =管材表!BL3 -> 0.08 | BL11: Cb | BO11: ④同上組立工事 | BP11: 1 | BQ11: 式 | BR11: =ROUND(項目表!$E$3*標準項!BU11,-3) -> 10000 | BS11: =ROUND(項目表!$F$3*標準項!BU11,-3) -> 6000 | BU11: =BT10 -> 0.2
A12: HK2030TCV | B12: n3 | C12: 8 | E12: =CONCATENATE("①",管材表!K7," ",管材表!L7) -> ①SGP鋼管(白) 40A | F12: 4 | G12: =管材表!M7 -> m | H12: =管材表!N7 -> 6910 | I12: =管材表!O7 -> 3660 | J12: =管材表!P7 -> 0.23 | K12: Cb | N12: ④煙道・煙突取付工事 | O12: 1 | P12: 式 | Q12: =ROUND(項目表!$E$3*標準項!T12,-3) -> 43000 | R12: =ROUND(項目表!$F$3*標準項!T12,-3) -> 26000 | T12: 0.9 | W12: ④煙道・煙突取付工事 | X12: 1 | Y12: 式 | Z12: =ROUND(項目表!$E$3*標準項!AC12,-3) -> 43000 | AA12: =ROUND(項目表!$F$3*標準項!AC12,-3) -> 26000 | AC12: 0.9 | AE12: ｵｲﾙﾀﾝｸ 1900L | AN12: ④省ｴﾈﾊｲﾌﾞﾘｯﾄﾞ制御盤取付工事（NGP内機） | AO12: 1 | AP12: 式 | AQ12: 3000 | AR12: 1500 | AS12: 0 | AW12: ②消耗品雑材 | AX12: 1 | AY12: 式 | AZ12: 15000 | BA12: 7500 | BB12: 0 | BF12: ①空気抜弁(逆止弁付） 15A(AF-9H) | BG12: 4 | BH12: 個 | BI12: =管材表!ET12 -> 36100 | BJ12: =管材表!EU12 -> 28880 | BK12: 0.08 | BL12: Cb | BO12: ④同上搬入据付工事 | BP12: 1 | BQ12: 式 | BR12: =ROUND(項目表!$E$3*標準項!BU12,-3) -> 10000 | BS12: =ROUND(項目表!$F$3*標準項!BU12,-3) -> 6000 | BU12: =BT10 -> 0.2
A13: HK2030TEV | B13: w3 | C13: =C12+1 -> 9 | E13: =CONCATENATE("①",管材表!K5," ",管材表!L5) -> ①SGP鋼管(白) 25A | F13: 4 | G13: =管材表!M5 -> m | H13: =管材表!N5 -> 4540 | I13: =管材表!O5 -> 2400 | J13: =管材表!P5 -> 0.17 | K13: Cb | N13: ④煙道断熱工事 | O13: 1 | P13: ｾｯﾄ | Q13: 20000 | R13: 13000 | S13: 0.1 | T13: Ca | W13: ④煙道断熱工事 | X13: 1 | Y13: ｾｯﾄ | Z13: 20000 | AA13: 13000 | AB13: 0.1 | AC13: Ca | AE13: ○ｵｲﾙﾀﾝｸ 1900L | AF13: 1 | AG13: 基 | AH13: =機器表!EE7 -> 380000 | AI13: =機器表!EF7 -> 164280 | AJ13: =機器表!EG7 -> 1.4 | AK13: Ca | AN13: ④HK連動配線工事（露出） 20m | AO13: 1 | AP13: 式 | AQ13: 50000 | AR13: 23000 | BF13: ①配管継手類 | BG13: 1 | BH13: 式 | BI13: 90000 | BJ13: 60000 | BK13: 0 | BO13: ①油配管ｾｯﾄ BOP-805M | BP13: 1 | BQ13: =管材表!FA6 -> 個 | BR13: =管材表!FB6 -> 11800 | BS13: =管材表!FC6 -> 4430 | BT13: =管材表!FD6 -> 0.3 | BU13: Cb
A14: HK3030TCV | B14: n25 | C14: =C13+1 -> 10 | E14: =CONCATENATE("①",管材表!K3," ",管材表!L3) -> ①SGP鋼管(白) 15A | F14: 4 | G14: =管材表!M3 -> m | H14: =管材表!N3 -> 2650 | I14: =管材表!O3 -> 1410 | J14: =管材表!P3 -> 0.12 | K14: Cb | N14: ○ﾊﾟﾜｰﾀﾞｸﾄ 折幅630×50m | O14: 1 | P14: =機器表!ET14 -> 本 | Q14: =機器表!EU14 -> 18000 | R14: =機器表!EV14 -> 8150 | S14: =機器表!EW14 -> 0 | T14: Ca | W14: ○ﾊﾟﾜｰﾀﾞｸﾄ 折幅475×200m(0.07) | X14: 1 | Y14: =機器表!ET18 -> 本 | Z14: =機器表!EU18 -> 29800 | AA14: =機器表!EV18 -> 14900 | AB14: =機器表!EW18 -> 0 | AC14: Ca | AE14: ④同上搬入据付工事 | AF14: 1 | AG14: 式 | AH14: =ROUND(項目表!$E$3*標準項!AK14,-3) -> 67000 | AI14: =ROUND(項目表!$F$3*標準項!AK14,-3) -> 41000 | AK14: 1.4 | AN14: ④ｾﾝｻｰ敷設工事（室温・湿度） | AO14: 1 | AP14: 式 | AQ14: 10000 | AR14: 5000 | BF14: ④配管工事費 | BG14: 1 | BH14: 式 | BI14: 175000 | BJ14: 117000 | BL14: 4.67 | BO14: ①逃し管ｾｯﾄ BOP-EP8M | BP14: 1 | BQ14: =管材表!FA8 -> 個 | BR14: =管材表!FB8 -> 18000 | BS14: =管材表!FC8 -> 4600 | BT14: =管材表!FD8 -> 0.2 | BU14: Cb
A15: HK3030TEV | B15: w25 | C15: =C14+1 -> 11 | E15: =CONCATENATE("①",管材表!BG7," ",管材表!BH7) -> ①ｹﾞｰﾄ弁 40A | F15: 2 | G15: =管材表!BI7 -> 個 | H15: =管材表!BJ7 -> 26700 | I15: =管材表!BK7 -> 17360 | J15: =管材表!BL7 -> 0.16 | K15: Cb | N15: ○ﾊﾟﾜｰﾀﾞｸﾄ 折幅475×200m(0.07) | O15: 1 | P15: =機器表!ET18 -> 本 | Q15: =機器表!EU18 -> 29800 | R15: =機器表!EV18 -> 14900 | S15: =機器表!EW18 -> 0 | T15: Ca | W15: ④吹出口筒 φ225×300L | X15: 2 | Y15: 本 | Z15: 6300 | AA15: 1000 | AE15: ④塗装工事 | AF15: 1 | AG15: 式 | AH15: =ROUND(項目表!$E$3*標準項!AK15,-3) -> 25000 | AI15: =ROUND(項目表!$F$3*標準項!AK15,-3) -> 15000 | AK15: 0.52 | AN15: ①ﾌｨﾙﾀﾄﾞﾗｲﾔ | AO15: 1 | AP15: 個 | AQ15: =機器表!DG10 -> 15000 | AR15: =機器表!DH10 -> 9010 | AS15: 0 | AT15: Ca | AW15: KA-205E | BF15: ④埋設部防蝕工事 | BG15: 1 | BH15: 式 | BI15: 15000 | BJ15: 10000 | BL15: 0.4 | BO15: =CONCATENATE("①",管材表!CM3," ",管材表!CN3) -> ①ﾏﾚｰﾌﾞﾙ弁 15A | BP15: 1 | BQ15: =管材表!CO3 -> 個 | BR15: =管材表!CP3 -> 12200 | BS15: =管材表!CQ3 -> 7930 | BT15: =管材表!CR3 -> 0.08 | BU15: Cb
A16: HK4030TCV | B16: n48 | C16: =C15+1 -> 12 | E16: =CONCATENATE("①",管材表!BG3," ",管材表!BH3) -> ①ｹﾞｰﾄ弁 15A | F16: 2 | G16: =管材表!BI3 -> 個 | H16: =管材表!BJ3 -> 6510 | I16: =管材表!BK3 -> 4230 | J16: =管材表!BL3 -> 0.08 | K16: Cb | N16: ○ﾀﾞｸﾄｺﾈｸﾀｰ DC-301 | O16: 6 | P16: =機器表!ET49 -> ｾｯﾄ | Q16: =機器表!EU49 -> 2370 | R16: =機器表!EV49 -> 700 | S16: =機器表!EW49 -> 0 | T16: Ca | W16: ②掃除具ｾｯﾄ BHS650 | X16: 1 | Y16: =機器表!EL58 -> ｾｯﾄ | Z16: =機器表!EM58 -> 12400 | AA16: =機器表!EN58 -> 5220 | AB16: =機器表!EO58 -> 0 | AC16: Ca | AE16: =CONCATENATE("①",管材表!K8," ",管材表!L8) -> ①SGP鋼管(白) 50A | AF16: 4 | AG16: =管材表!M8 -> m | AH16: =管材表!N8 -> 9480 | AI16: =管材表!O8 -> 5020 | AJ16: =管材表!P8 -> 0.29 | AK16: Cb | AN16: ②消耗品雑材 | AO16: 1 | AP16: 式 | AQ16: 30000 | AR16: 15000 | AS16: 0 | AW16: ○小型温風機 KA-205E | AX16: 1 | AY16: =機器表!V10 -> 台 | AZ16: =機器表!W10 -> 450000 | BA16: =機器表!X10 -> 176880 | BB16: =機器表!Y10 -> 0.7 | BC16: Ca | BF16: ④塗装工事 | BG16: 1 | BH16: 式 | BI16: 30000 | BJ16: 20000 | BL16: 0.8 | BO16: ④配管工事費 | BP16: 1 | BQ16: 式 | BR16: =ROUND(項目表!$E$3*標準項!BU16,-3) -> 28000 | BS16: =ROUND(項目表!$F$3*標準項!BU16,-3) -> 17000 | BU16: 0.58
A17: HK4030TEV | B17: w48 | C17: =C16+1 -> 13 | E17: =CONCATENATE("①",管材表!BO7," ",管材表!BP7) -> ①ﾁｬｯｷ弁 40A(ｽｲﾝｸﾞ) | F17: 1 | G17: =管材表!BQ7 -> 個 | H17: =管材表!BR7 -> 21200 | I17: =管材表!BS7 -> 13780 | J17: =管材表!BT7 -> 0.16 | K17: Cb | N17: ②掃除具ｾｯﾄ BHS650 | O17: 1 | P17: =機器表!EL58 -> ｾｯﾄ | Q17: =機器表!EM58 -> 12400 | R17: =機器表!EN58 -> 5220 | S17: =機器表!EO58 -> 0 | T17: Ca | W17: ②消耗品雑材 | X17: 1 | Y17: 式 | Z17: 20000 | AA17: 10000 | AE17: =CONCATENATE("①",管材表!AA5," ",管材表!AB5) -> ①外面被覆鋼管 25A | AF17: 16 | AG17: =管材表!AC5 -> m | AH17: =管材表!AD5 -> 3680 | AI17: =管材表!AE5 -> 2760 | AJ17: =管材表!AF5 -> 0.17 | AK17: Cb | AW17: ④同上搬入据付工事 | AX17: 1 | AY17: 式 | AZ17: =ROUND(項目表!$E$3*標準項!BC17,-3) -> 33000 | BA17: =ROUND(項目表!$F$3*標準項!BC17,-3) -> 21000 | BC17: 0.7 | BF17: ②消耗品雑材 | BG17: 1 | BH17: 式 | BI17: 30000 | BJ17: 20000 | BK17: 0 | BO17: ②消耗品雑材 | BP17: 1 | BQ17: 式 | BR17: 20000 | BS17: 10000
A18: HK5030TCV | B18: n70 | C18: =C17+1 -> 14 | E18: =CONCATENATE("①",管材表!DC3," ",管材表!DD3) -> ①Yｽﾄﾚｰﾅ 15A | F18: 1 | G18: =管材表!DE3 -> 個 | H18: =管材表!DF3 -> 6080 | I18: =管材表!DG3 -> 3950 | J18: =管材表!DH3 -> 0.08 | K18: Cb | N18: ②消耗品雑材 | O18: 1 | P18: 式 | Q18: 20000 | R18: 10000 | AE18: ①ﾌﾚｷｼﾞｮｲﾝﾄ(U) 25A*300L | AF18: 1 | AG18: 本 | AH18: =管材表!DV5 -> 5700 | AI18: =管材表!DW5 -> 2620 | AJ18: =管材表!DX5 -> 0.14 | AK18: Cb | AN18: NGP109TQ-J | AW18: =CONCATENATE("③",電材表!Q18," ",電材表!R18) -> ③感震器 BES-100 | AX18: 1 | AY18: =電材表!S18 -> 個 | AZ18: =電材表!T18 -> 20100 | BA18: =電材表!U18 -> 5580 | BB18: =電材表!V18 -> 0 | BC18: Cc
A19: HK5030TEV | B19: w70 | C19: =C18+1 -> 15 | E19: ①配管継手類 | F19: 1 | G19: 式 | H19: 5000 | I19: 3000 | J19: 0 | AE19: =CONCATENATE("①",管材表!CM8," ",管材表!CN8) -> ①ﾏﾚｰﾌﾞﾙ弁 50A | AF19: 1 | AG19: =管材表!CO8 -> 個 | AH19: =管材表!CP8 -> 41100 | AI19: =管材表!CQ8 -> 26720 | AJ19: =管材表!CR8 -> 0.18 | AK19: Cb | AN19: ○グリーンパッケージ NGP109TQ-J | AO19: 1 | AP19: =機器表!DF4 -> ｾｯﾄ | AQ19: =機器表!DG4 -> 1357000 | AR19: =機器表!DH4 -> 746140 | AS19: =機器表!DI4 -> 2.9 | AT19: Ca | AW19: ○煙突ｾｯﾄ BEP-KA 1203 | AX19: 1 | AY19: =機器表!EL7 -> ｾｯﾄ | AZ19: =機器表!EM7 -> 60400 | BA19: =機器表!EN7 -> 20760 | BB19: =機器表!EO7 -> 0.5 | BC19: Ca
A20: HK6030TCV | B20: n89 | C20: =C19+1 -> 16 | E20: ④配管工事費 | F20: 1 | G20: 式 | H20: =ROUND(項目表!$E$3*標準項!K20,-3) -> 116000 | I20: =ROUND(項目表!$F$3*標準項!K20,-3) -> 72000 | K20: 2.44 | AE20: =CONCATENATE("①",管材表!CM5," ",管材表!CN5) -> ①ﾏﾚｰﾌﾞﾙ弁 25A | AF20: 3 | AG20: =管材表!CO5 -> 個 | AH20: =管材表!CP5 -> 17500 | AI20: =管材表!CQ5 -> 11380 | AJ20: =管材表!CR5 -> 0.12 | AK20: Cb | AN20: （室内機・室外機 子機セット） | AS20: 0 | AW20: ○煙突直管 φ120 | AX20: 1 | AY20: =機器表!EL24 -> 本 | AZ20: =機器表!EM24 -> 8470 | BA20: =機器表!EN24 -> 2090 | BB20: =機器表!EO24 -> 0.1 | BC20: Ca | BO20: CG-554T2
A21: HK6030TEV | B21: w89 | C21: =C20+1 -> 17 | E21: ④配管塗装工事 | F21: 1 | G21: 式 | H21: 5000 | I21: 3000 | K21: 0.12 | AE21: ①注油口 50A | AF21: 1 | AG21: 個 | AH21: =管材表!FB10 -> 15000 | AI21: =管材表!FC10 -> 10000 | AK21: Cb | AN21: ④同上搬入据付工事 | AO21: 1 | AP21: 式 | AQ21: 165000 | AR21: 88000 | AS21: 0 | AW21: ○煙突ｴﾋﾞﾏｶﾞﾘ φ120 | AX21: 1 | AY21: =機器表!EL36 -> 個 | AZ21: =機器表!EM36 -> 6490 | BA21: =機器表!EN36 -> 1360 | BB21: =機器表!EO36 -> 0.1 | BC21: Ca | BO21: ○グロウエア CG-554T2 | BP21: 1 | BQ21: =機器表!V22 -> 台 | BR21: =機器表!W22 -> 413000 | BS21: =機器表!X22 -> 177140 | BT21: =機器表!Y22 -> 0.7 | BU21: Ca
A22: HK8030GCV | B22: n108 | C22: =C21+1 -> 18 | E22: ②消耗品雑材 | F22: 1 | G22: 式 | H22: 15000 | I22: 7500 | J22: 0 | AE22: ①配管継手類 | AF22: 1 | AG22: 式 | AH22: 9000 | AI22: 5000 | AN22: ④冷媒配管工事費 10mまで | AO22: 1 | AP22: 式 | AQ22: 200000 | AR22: 100000 | AS22: 0 | AW22: ②煙突支持金具 | AX22: 1 | AY22: 個 | AZ22: 15000 | BA22: 10000 | BB22: 0 | BF22: エロフィン配管（50A) | BO22: ④同上搬入据付工事 | BP22: 1 | BQ22: 式 | BR22: =ROUND(項目表!$E$3*標準項!BU22,-3) -> 33000 | BS22: =ROUND(項目表!$F$3*標準項!BU22,-3) -> 21000 | BU22: 0.7
A23: ---小型温風機--- | AE23: ②配管支持具 | AF23: 1 | AG23: 式 | AH23: 15000 | AI23: 8000 | AN23: ④同上配管断熱・防食ﾃｰﾌﾟ工事 | AO23: 1 | AP23: 式 | AQ23: 9600 | AR23: 6000 | AS23: 0 | AW23: ④同上煙突取付工事 | AX23: 1 | AY23: 式 | AZ23: =ROUND(項目表!$E$3*BC23,-3) -> 36000 | BA23: =ROUND(項目表!$F$3*標準項!BC23,-3) -> 22000 | BC23: 0.75 | BF23: ○ｴﾛﾌｨﾝﾁｭｰﾌﾞ 50A 32F 2750L | BG23: 96 | BH23: 本 | BI23: =機器表!BS52 -> 80000 | BJ23: =機器表!BT52 -> 32000 | BK23: 0.47 | BL23: Ca | BO23: =CONCATENATE("③",電材表!Q10," ",電材表!R10) -> ③CO2ｺﾝﾄﾛｰﾗ CGC-600SET14 | BP23: 1 | BQ23: =電材表!S10 -> 台 | BR23: =電材表!T10 -> 155000 | BS23: =電材表!U10 -> 89490 | BT23: =電材表!V10 -> 0 | BU23: Cc
A24: KA-125E | B24: aw3 | C24: 19 | N24: HK3030TCV | W24: HK3030TEV | AE24: ④配管工事費 | AF24: 1 | AG24: 式 | AH24: =ROUND(項目表!$E$3*標準項!AK24,-3) -> 162000 | AI24: =ROUND(項目表!$F$3*標準項!AK24,-3) -> 101000 | AK24: 3.42 | AN24: ④ドレーン配管工事 3mまで | AO24: 1 | AP24: 式 | AQ24: 6000 | AR24: 3000 | AS24: 0 | AW24: ④煙道断熱工事 | AX24: 1 | AY24: 式 | AZ24: 15000 | BA24: 10000 | BB24: 0 | BF24: ④ｴﾛﾌｨﾝ取付工事 | BG24: 1 | BH24: 式 | BI24: =ROUND(項目表!$E$3*BL24,-3) -> 428000 | BJ24: =ROUND(項目表!$F$3*BL24,-3) -> 265000 | BL24: 9.02 | BO24: =CONCATENATE("③",電材表!I9," ",電材表!J9) -> ③室温ｾﾝｻｰｾｯﾄ TS-102P | BP24: 1 | BQ24: =電材表!K9 -> 個 | BR24: =電材表!L9 -> 18100 | BS24: =電材表!M9 -> 2530 | BT24: =電材表!N9 -> 0 | BU24: Cc
A25: KA-205E | B25: aw16 | C25: =C24+1 -> 20 | N25: ○ﾊｳｽｶｵﾝｷ HK3030TCV | O25: 1 | P25: =機器表!N6 -> 台 | Q25: =機器表!O6 -> 1129000 | R25: =機器表!P6 -> 490810 | S25: =機器表!Q6 -> 1.45 | T25: Ca | W25: ○ﾊｳｽｶｵﾝｷ HK3030TEV | X25: 1 | Y25: =機器表!N7 -> 台 | Z25: =機器表!O7 -> 1141000 | AA25: =機器表!P7 -> 509220 | AB25: =機器表!Q7 -> 1.45 | AC25: Ca | AE25: ②消耗品雑材 | AF25: 1 | AG25: 式 | AH25: 12000 | AI25: 5000 | AN25: ④ｱﾙﾐﾌﾚｷﾀﾞｸﾄ取付 φ225 | AO25: 1 | AP25: 式 | AQ25: 6000 | AR25: 3000 | AW25: ②消耗品雑材 | AX25: 1 | AY25: 式 | AZ25: 15000 | BA25: 7500 | BB25: 0 | BF25: ○ｴﾛﾌｨﾝ支持金具 2段1列 | BG25: 48 | BH25: 本 | BI25: =機器表!GA4 -> 22000 | BJ25: =機器表!GB4 -> 11000 | BK25: 0.15 | BL25: Ca | BO25: =CONCATENATE("③",電材表!Q19," ",電材表!R19) -> ③不完全燃焼警報器 SG-35 | BP25: 1 | BQ25: =電材表!S19 -> 個 | BR25: =電材表!T19 -> 85800 | BS25: =電材表!U19 -> 31120 | BT25: =電材表!V19 -> 0 | BU25: Cc
A26: KA-325TE | B26: aw29 | C26: =C25+1 -> 21 | E26: HB-407TGA | N26: ④同上搬入据付工事 | O26: 1 | P26: 式 | Q26: =ROUND(項目表!$E$3*標準項!T26,-3) -> 69000 | R26: =ROUND(項目表!$F$3*標準項!T26,-3) -> 43000 | T26: 1.45 | W26: ④同上搬入据付工事 | X26: 1 | Y26: 式 | Z26: =ROUND(項目表!$E$3*標準項!AC26,-3) -> 69000 | AA26: =ROUND(項目表!$F$3*標準項!AC26,-3) -> 43000 | AC26: 1.45 | AN26: ①ｱﾙﾐﾌﾚｷﾀﾞｸﾄ φ225×4000L | AO26: 3 | AP26: =機器表!FJ3 -> 本 | AQ26: =機器表!FK3 -> 11600 | AR26: =機器表!FL3 -> 2710 | AS26: =機器表!FM3 -> 0 | AT26: Ca | BF26: ④同上取付工事 | BG26: 1 | BH26: 式 | BI26: =ROUND(項目表!$E$3*BL26,-3) -> 245000 | BJ26: =ROUND(項目表!$F$3*BL26,-3) -> 152000 | BL26: 5.16 | BO26: =CONCATENATE("③",電材表!Q18," ",電材表!R18) -> ③感震器 BES-100 | BP26: 1 | BQ26: =電材表!S18 -> 個 | BR26: =電材表!T18 -> 20100 | BS26: =電材表!U18 -> 5580 | BT26: =電材表!V18 -> 0 | BU26: Cc
A27: KA-405TE | B27: aw42 | C27: =C26+1 -> 22 | E27: =CONCATENATE("○",機器表!AB7," ",機器表!AC7) -> ○ﾊｳｽﾎﾞｲﾗ HB-407TGA | F27: 1 | G27: =機器表!AD7 -> 台 | H27: =機器表!AE7 -> 944000 | I27: =機器表!AF7 -> 458400 | J27: =機器表!AG7 -> 1.15 | K27: Ca | N27: =CONCATENATE("③",電材表!Q18," ",電材表!R18) -> ③感震器 BES-100 | O27: 1 | P27: =電材表!S18 -> 個 | Q27: =電材表!T18 -> 20100 | R27: =電材表!U18 -> 5580 | S27: =電材表!V18 -> 0 | T27: Cc | W27: =CONCATENATE("③",電材表!Q18," ",電材表!R18) -> ③感震器 BES-100 | X27: 1 | Y27: =電材表!S18 -> 個 | Z27: =電材表!T18 -> 20100 | AA27: =電材表!U18 -> 5580 | AB27: =電材表!V18 -> 0 | AC27: Cc | AE27: BOT-10000 | AN27: ①ﾌｨﾙﾀﾄﾞﾗｲﾔ | AO27: 1 | AP27: 個 | AQ27: =機器表!DG10 -> 15000 | AR27: =機器表!DH10 -> 9010 | AS27: 0 | AT27: Ca | BF27: =CONCATENATE("①",管材表!DK15," ",管材表!DL15) -> ①電動ﾎﾞｰﾙ弁(3方) 50A | BG27: 1 | BH27: =管材表!DM15 -> 個 | BI27: =管材表!DN15 -> 85300 | BJ27: =管材表!DO15 -> 55450 | BK27: =管材表!DP15 -> 0.18 | BL27: Cb | BO27: ④同上取付工事 | BP27: 1 | BQ27: 式 | BR27: 11000 | BS27: 7000
A28: KA-125 | B28: aw55 | C28: =C27+1 -> 23 | E28: ④同上搬入据付工事 | F28: 1 | G28: 式 | H28: =ROUND(項目表!$E$3*標準項!K28,-3) -> 55000 | I28: =ROUND(項目表!$F$3*標準項!K28,-3) -> 34000 | K28: 1.15 | N28: ○煙室ｾｯﾄ ES- 2330 | O28: 1 | P28: =機器表!EL15 -> ｾｯﾄ | Q28: =機器表!EM15 -> 119000 | R28: =機器表!EN15 -> 35870 | S28: =機器表!EO15 -> 0.5 | T28: Ca | W28: ○煙室ｾｯﾄ ES- 2330 | X28: 1 | Y28: =機器表!EL15 -> ｾｯﾄ | Z28: =機器表!EM15 -> 119000 | AA28: =機器表!EN15 -> 35870 | AB28: =機器表!EO15 -> 0.5 | AC28: Ca | AE28: ○ｵｲﾙﾀﾝｸ BOT-10000 | AF28: 1 | AG28: =機器表!ED9 -> 基 | AH28: =機器表!EE9 -> 1980000 | AI28: =機器表!EF9 -> 1230000 | AJ28: =機器表!EG9 -> 3.5 | AK28: Ca | AN28: ②消耗品雑材 | AO28: 1 | AP28: 式 | AQ28: 30000 | AR28: 15000 | AS28: 0 | AW28: KA-325TE | BF28: =CONCATENATE("①",管材表!K8," ",管材表!L8) -> ①SGP鋼管(白) 50A | BG28: 52 | BH28: =管材表!M8 -> m | BI28: =管材表!N8 -> 9480 | BJ28: =管材表!O8 -> 5020 | BK28: =管材表!P8 -> 0.29 | BL28: Cb | BO28: ○ｵｲﾙﾀﾝｸ BOT-200 | BP28: 1 | BQ28: =機器表!ED4 -> 基 | BR28: =機器表!EE4 -> 84000 | BS28: =機器表!EF4 -> 26080 | BT28: =機器表!EG4 -> 0.2 | BU28: Ca
A29: KA-205 | B29: aw70 | C29: =C28+1 -> 24 | E29: =CONCATENATE("③",電材表!Q18," ",電材表!R18) -> ③感震器 BES-100 | F29: 1 | G29: =電材表!S18 -> 個 | H29: =電材表!T18 -> 20100 | I29: =電材表!U18 -> 5580 | J29: =電材表!V18 -> 0 | K29: Cc | N29: ④同上取付工事 | O29: 1 | P29: 式 | Q29: =ROUND(項目表!$E$3*標準項!T29,-3) -> 24000 | R29: =ROUND(項目表!$F$3*標準項!T29,-3) -> 15000 | T29: =S28 -> 0.5 | W29: ④同上取付工事 | X29: 1 | Y29: 式 | Z29: =ROUND(項目表!$E$3*標準項!AC29,-3) -> 24000 | AA29: =ROUND(項目表!$F$3*標準項!AC29,-3) -> 15000 | AC29: =AB28 -> 0.5 | AE29: ④同上搬入据付工事 | AF29: 1 | AG29: 式 | AH29: =ROUND(項目表!$E$3*標準項!AK29,-3) -> 130000 | AI29: =ROUND(項目表!$F$3*標準項!AK29,-3) -> 80000 | AK29: 2.73 | AW29: ○小型温風機 KA-325TE | AX29: 1 | AY29: =機器表!V12 -> 台 | AZ29: =機器表!W12 -> 596000 | BA29: =機器表!X12 -> 228490 | BB29: =機器表!Y11 -> 0.9 | BC29: Ca | BF29: =CONCATENATE("①",管材表!BG8," ",管材表!BH8) -> ①ｹﾞｰﾄ弁 50A | BG29: 6 | BH29: =管材表!BI8 -> 個 | BI29: =管材表!BJ8 -> 39100 | BJ29: =管材表!BK8 -> 25420 | BK29: =管材表!BL8 -> 0.18 | BL29: Cb | BO29: ④同上組立工事 | BP29: 1 | BQ29: 式 | BR29: =ROUND(項目表!$E$3*標準項!BU29,-3) -> 10000 | BS29: =ROUND(項目表!$F$3*標準項!BU29,-3) -> 6000 | BU29: =BT28 -> 0.2
A30: KA-325T | B30: aw85 | C30: =C29+1 -> 25 | E30: =CONCATENATE("○",機器表!EJ6," ",機器表!EK6) -> ○煙突ｾｯﾄ BEP-HB1201 | F30: 1 | G30: =機器表!EL6 -> ｾｯﾄ | H30: =機器表!EM6 -> 65700 | I30: =機器表!EN6 -> 23160 | J30: =機器表!EO6 -> 0.5 | K30: Ca | N30: ○煙突ｾｯﾄ BEP-20T 1504 | O30: 1 | P30: =機器表!EL9 -> ｾｯﾄ | Q30: =機器表!EM9 -> 72800 | R30: =機器表!EN9 -> 23890 | S30: =機器表!EO9 -> 0.7 | T30: Ca | W30: ○煙突ｾｯﾄ BEP-20T 1504 | X30: 1 | Y30: =機器表!EL9 -> ｾｯﾄ | Z30: =機器表!EM9 -> 72800 | AA30: =機器表!EN9 -> 23890 | AB30: =機器表!EO9 -> 0.7 | AC30: Ca | AE30: ④タンク塗装工事 | AF30: 1 | AG30: 式 | AH30: 30000 | AI30: 20000 | AN30: EHP61×1基 | AW30: ④同上搬入据付工事 | AX30: 1 | AY30: 式 | AZ30: =ROUND(項目表!$E$3*標準項!BC30,-3) -> 43000 | BA30: =ROUND(項目表!$F$3*標準項!BC30,-3) -> 26000 | BC30: 0.9 | BF30: =CONCATENATE("①",管材表!BG3," ",管材表!BH3) -> ①ｹﾞｰﾄ弁 15A | BG30: 16 | BH30: =管材表!BI3 -> 個 | BI30: =管材表!BJ3 -> 6510 | BJ30: =管材表!BK3 -> 4230 | BK30: =管材表!BL3 -> 0.08 | BL30: Cb | BO30: ④同上搬入据付工事 | BP30: 1 | BQ30: 式 | BR30: =ROUND(項目表!$E$3*標準項!BU30,-3) -> 10000 | BS30: =ROUND(項目表!$F$3*標準項!BU30,-3) -> 6000 | BU30: =BT28 -> 0.2
A31: KA-405T | B31: aw100 | C31: =C30+1 -> 26 | E31: =CONCATENATE("○",機器表!EJ24," ",機器表!EK24) -> ○煙突直管 φ120 | F31: 1 | G31: =機器表!EL24 -> 本 | H31: =機器表!EM24 -> 8470 | I31: =機器表!EN24 -> 2090 | J31: =機器表!EO24 -> 0.1 | K31: Ca | N31: ○煙突直管 φ150 | O31: 2 | P31: =機器表!EL25 -> 本 | Q31: =機器表!EM25 -> 9930 | R31: =機器表!EN25 -> 2290 | S31: =機器表!EO25 -> 0.1 | T31: Ca | W31: ○煙突直管 φ150 | X31: 2 | Y31: =機器表!EL25 -> 本 | Z31: =機器表!EM25 -> 9930 | AA31: =機器表!EN25 -> 2290 | AB31: =機器表!EO25 -> 0.1 | AC31: Ca | AE31: =CONCATENATE("①",管材表!K9," ",管材表!L9) -> ①SGP鋼管(白) 65A | AF31: 4 | AG31: =管材表!M9 -> m | AH31: =管材表!N9 -> 13540 | AI31: =管材表!O9 -> 7180 | AJ31: =管材表!P9 -> 0.37 | AK31: Cb | AN31: ○誰でもﾋｰﾎﾟﾝ EHP61 | AO31: 1 | AP31: =機器表!DF12 -> ｾｯﾄ | AQ31: =機器表!DG12 -> 597000 | AR31: =機器表!DH12 -> - | AS31: =機器表!DI12 -> 1.6 | AT31: Ca | AW31: =CONCATENATE("③",電材表!Q18," ",電材表!R18) -> ③感震器 BES-100 | AX31: 1 | AY31: =電材表!S18 -> 個 | AZ31: =電材表!T18 -> 20100 | BA31: =電材表!U18 -> 5580 | BB31: =電材表!V18 -> 0 | BC31: Cc | BF31: ①空気抜弁(逆止弁付） 15A(AF-9H) | BG31: 16 | BH31: 個 | BI31: =管材表!ET12 -> 36100 | BJ31: =管材表!EU12 -> 28880 | BK31: 0.08 | BL31: Cb | BO31: ①油配管ｾｯﾄ BOP-805M | BP31: 1 | BQ31: =管材表!FA6 -> 個 | BR31: =管材表!FB6 -> 11800 | BS31: =管材表!FC6 -> 4430 | BT31: =管材表!FD6 -> 0.3 | BU31: Cb
A32: ---ｸﾞﾘｰﾝﾊﾟｯｹｰｼﾞ --- | E32: =CONCATENATE("○",機器表!EJ36," ",機器表!EK36) -> ○煙突ｴﾋﾞﾏｶﾞﾘ φ120 | F32: 1 | G32: =機器表!EL36 -> 個 | H32: =機器表!EM36 -> 6490 | I32: =機器表!EN36 -> 1360 | J32: =機器表!EO36 -> 0.1 | K32: Ca | N32: ○煙道ｴﾙﾎﾞ φ150 | O32: 1 | P32: =機器表!EL38 -> 個 | Q32: =機器表!EM38 -> 7210 | R32: =機器表!EN38 -> 1560 | S32: =機器表!EO38 -> 0.1 | T32: Ca | W32: ○煙道ｴﾙﾎﾞ φ150 | X32: 1 | Y32: =機器表!EL38 -> 個 | Z32: =機器表!EM38 -> 7210 | AA32: =機器表!EN38 -> 1560 | AB32: =機器表!EO38 -> 0.1 | AC32: Ca | AE32: =CONCATENATE("①",管材表!AA7," ",管材表!AB7) -> ①外面被覆鋼管 40A | AF32: 20 | AG32: =管材表!AC7 -> m | AH32: =管材表!AD7 -> 5180 | AI32: =管材表!AE7 -> 3890 | AJ32: =管材表!AF7 -> 0.23 | AN32: （室内機・室外機・操作盤セット） | AS32: 0 | AW32: ○煙突ｾｯﾄ BEP-KA 1203 | AX32: 1 | AY32: =機器表!EL7 -> ｾｯﾄ | AZ32: =機器表!EM7 -> 60400 | BA32: =機器表!EN7 -> 20760 | BB32: =機器表!EO7 -> 0.5 | BC32: Ca | BF32: ①配管継手類 | BG32: 1 | BH32: 式 | BI32: 180000 | BJ32: 120000 | BK32: 0 | BO32: ①逃し管ｾｯﾄ BOP-EP8M | BP32: 1 | BQ32: =管材表!FA8 -> 個 | BR32: =管材表!FB8 -> 18000 | BS32: =管材表!FC8 -> 4600 | BT32: =管材表!FD8 -> 0.2 | BU32: Cb
A33: NGP109TQX-J | B33: an3 | C33: 27 | E33: ②煙突支持金具 | F33: 1 | G33: 式 | H33: 18000 | I33: 12000 | J33: 0 | N33: ②煙突支持金具 | O33: 1 | P33: 個 | Q33: 25000 | R33: 14000 | W33: ②煙突支持金具 | X33: 1 | Y33: 個 | Z33: 25000 | AA33: 14000 | AE33: =CONCATENATE("①",管材表!CM11," ",管材表!CN11) -> ①ﾏﾚｰﾌﾞﾙ弁 65A(ﾌﾗﾝｼﾞ) | AF33: 1 | AG33: =管材表!CO11 -> 個 | AH33: =管材表!CP11 -> 112000 | AI33: =管材表!CQ11 -> 72800 | AJ33: =管材表!CR11 -> 0.32 | AK33: Cb | AN33: ④EHP用ﾊｲﾌﾞﾘｯﾄﾞ制御基板ｾｯﾄ EHP-HCS | AO33: 1 | AP33: =機器表!DF19 -> 式 | AQ33: =機器表!DG19 -> 71900 | AR33: =機器表!DH19 -> 4500 | AS33: =機器表!DI19 -> 0 | AT33: Ca | AW33: ○煙突直管 φ120 | AX33: 1 | AY33: =機器表!EL24 -> 本 | AZ33: =機器表!EM24 -> 8470 | BA33: =機器表!EN24 -> 2090 | BB33: =機器表!EO24 -> 0.1 | BC33: Ca | BF33: ④配管工事費 | BG33: 1 | BH33: 式 | BI33: =ROUND(項目表!$E$3*BL33,-3) -> 431000 | BJ33: =ROUND(項目表!$F$3*BL33,-3) -> 267000 | BL33: 9.07 | BO33: =CONCATENATE("①",管材表!CM3," ",管材表!CN3) -> ①ﾏﾚｰﾌﾞﾙ弁 15A | BP33: 1 | BQ33: =管材表!CO3 -> 個 | BR33: =管材表!CP3 -> 12200 | BS33: =管材表!CQ3 -> 7930 | BT33: =管材表!CR3 -> 0.08 | BU33: Cb
A34: NGP109TQ-J | B34: an19 | C34: =C33+1 -> 28 | E34: ④煙道・煙突取付工事 | F34: 1 | G34: 式 | H34: =ROUND(項目表!$E$3*標準項!K34,-3) -> 33000 | I34: =ROUND(項目表!$F$3*標準項!K34,-3) -> 21000 | K34: 0.7 | N34: ④煙道・煙突取付工事 | O34: 1 | P34: 式 | Q34: =ROUND(項目表!$E$3*標準項!T34,-3) -> 43000 | R34: =ROUND(項目表!$F$3*標準項!T34,-3) -> 26000 | T34: 0.9 | W34: ④煙道・煙突取付工事 | X34: 1 | Y34: 式 | Z34: =ROUND(項目表!$E$3*標準項!AC34,-3) -> 43000 | AA34: =ROUND(項目表!$F$3*標準項!AC34,-3) -> 26000 | AC34: 0.9 | AE34: =CONCATENATE("①",管材表!CM7," ",管材表!CN7) -> ①ﾏﾚｰﾌﾞﾙ弁 40A | AF34: 2 | AG34: =管材表!CO7 -> 個 | AH34: =管材表!CP7 -> 29200 | AI34: =管材表!CQ7 -> 18980 | AJ34: =管材表!CR7 -> 0.16 | AK34: Cb | AN34: ④同上搬入据付工事 | AO34: 1 | AP34: 式 | AQ34: 100000 | AR34: 50000 | AS34: 0 | AW34: ○煙突ｴﾋﾞﾏｶﾞﾘ φ120 | AX34: 1 | AY34: =機器表!EL36 -> 個 | AZ34: =機器表!EM36 -> 6490 | BA34: =機器表!EN36 -> 1360 | BB34: =機器表!EO36 -> 0.1 | BC34: Ca | BF34: ④埋設部防蝕工事 | BG34: 4 | BH34: 式 | BI34: 9000 | BJ34: 5000 | BL34: 0.2 | BO34: ④配管工事費 | BP34: 1 | BQ34: 式 | BR34: =ROUND(項目表!$E$3*標準項!BU34,-3) -> 28000 | BS34: =ROUND(項目表!$F$3*標準項!BU34,-3) -> 17000 | BU34: 0.58
A35: 誰でもﾋｰﾎﾟﾝ（1台） | B35: an31 | C35: =C34+1 -> 29 | E35: ④煙道断熱工事 ﾛｯｸｳｰﾙ | F35: 1 | G35: 式 | H35: 15000 | I35: 10000 | J35: 0 | N35: ④煙道断熱工事 | O35: 1 | P35: ｾｯﾄ | Q35: 20000 | R35: 13000 | S35: 0.1 | T35: Ca | W35: ④煙道断熱工事 | X35: 1 | Y35: ｾｯﾄ | Z35: 20000 | AA35: 13000 | AB35: 0.1 | AC35: Ca | AE35: ①ﾌﾚｷｼﾞｮｲﾝﾄ(F) 65A*500L | AF35: 1 | AG35: 本 | AH35: =管材表!DV22 -> 26000 | AI35: =管材表!DW22 -> 6760 | AJ35: 0.37 | AK35: Cb | AN35: ④冷媒配管工事費 10mまで | AO35: 1 | AP35: 式 | AQ35: 150000 | AR35: 70000 | AS35: 0 | AW35: ②煙突支持金具 | AX35: 1 | AY35: 個 | AZ35: 15000 | BA35: 10000 | BB35: 0 | BF35: ④塗装工事 | BG35: 1 | BH35: 式 | BI35: 45000 | BJ35: 30000 | BL35: 1.2 | BO35: ②消耗品雑材 | BP35: 1 | BQ35: 式 | BR35: 20000 | BS35: 10000
A36: 誰でもﾋｰﾎﾟﾝ（2台） | B36: an44 | C36: =C35+1 -> 30 | E36: =CONCATENATE("①",管材表!K7," ",管材表!L7) -> ①SGP鋼管(白) 40A | F36: 4 | G36: =管材表!M7 -> m | H36: =管材表!N7 -> 6910 | I36: =管材表!O7 -> 3660 | J36: =管材表!P7 -> 0.23 | K36: Cb | N36: ○ﾊﾟﾜｰﾀﾞｸﾄ 折幅900×50m | O36: 1 | P36: =機器表!ET15 -> 本 | Q36: =機器表!EU15 -> 21600 | R36: =機器表!EV15 -> 10650 | S36: =機器表!EW15 -> 0 | T36: Ca | W36: ○ﾊﾟﾜｰﾀﾞｸﾄ 折幅475×200m(0.07) | X36: 1 | Y36: =機器表!ET18 -> 本 | Z36: =機器表!EU18 -> 29800 | AA36: =機器表!EV18 -> 14900 | AB36: =機器表!EW18 -> 0 | AC36: Ca | AE36: ①ﾌﾚｷｼﾞｮｲﾝﾄ(F) 40A*500L | AF36: 1 | AG36: 本 | AH36: =管材表!DV20 -> 18000 | AI36: =管材表!DW20 -> 4680 | AJ36: 0.18 | AK36: Cb | AN36: ④同上配管断熱・防食ﾃｰﾌﾟ工事 | AO36: 1 | AP36: 式 | AQ36: 9600 | AR36: 6000 | AS36: 0 | AW36: ④同上煙突取付工事 | AX36: 1 | AY36: 式 | AZ36: =ROUND(項目表!$E$3*BC36,-3) -> 36000 | BA36: =ROUND(項目表!$F$3*標準項!BC36,-3) -> 22000 | BC36: 0.75 | BF36: ②消耗品雑材 | BG36: 1 | BH36: 式 | BI36: 50000 | BJ36: 25000 | BK36: 0
A37: ---ｸﾞﾛｳｴｱ--- | E37: =CONCATENATE("①",管材表!K5," ",管材表!L5) -> ①SGP鋼管(白) 25A | F37: 4 | G37: =管材表!M5 -> m | H37: =管材表!N5 -> 4540 | I37: =管材表!O5 -> 2400 | J37: =管材表!P5 -> 0.17 | K37: Cb | N37: ○ﾊﾟﾜｰﾀﾞｸﾄ 折幅475×200m(0.07) | O37: 2 | P37: =機器表!ET18 -> 本 | Q37: =機器表!EU18 -> 29800 | R37: =機器表!EV18 -> 14900 | S37: =機器表!EW18 -> 0 | T37: Ca | W37: ④吹出口筒 φ225×300L | X37: 2 | Y37: 本 | Z37: 6300 | AA37: 1000 | AE37: ①注油口 65A | AF37: 1 | AG37: 個 | AH37: 15000 | AI37: 10000 | AK37: Cb | AN37: ④ドレーン配管工事 3mまで | AO37: 1 | AP37: 式 | AQ37: 6000 | AR37: 3000 | AS37: 0 | AW37: ④煙道断熱工事 | AX37: 1 | AY37: 式 | AZ37: 15000 | BA37: 10000 | BB37: 0
A38: CG-254S2 | B38: bo3 | C38: 31 | E38: =CONCATENATE("①",管材表!K3," ",管材表!L3) -> ①SGP鋼管(白) 15A | F38: 4 | G38: =管材表!M3 -> m | H38: =管材表!N3 -> 2650 | I38: =管材表!O3 -> 1410 | J38: =管材表!P3 -> 0.12 | K38: Cb | N38: ○ﾀﾞｸﾄｺﾈｸﾀｰ DC-301 | O38: 10 | P38: =機器表!ET49 -> ｾｯﾄ | Q38: =機器表!EU49 -> 2370 | R38: =機器表!EV49 -> 700 | S38: =機器表!EW49 -> 0 | T38: Ca | W38: ②掃除具ｾｯﾄ BHS650 | X38: 1 | Y38: =機器表!EL58 -> ｾｯﾄ | Z38: =機器表!EM58 -> 12400 | AA38: =機器表!EN58 -> 5220 | AB38: =機器表!EO58 -> 0 | AC38: Ca | AE38: ①配管継手類 | AF38: 1 | AG38: 式 | AH38: 30000 | AI38: 20000 | AN38: ④省ｴﾈﾊｲﾌﾞﾘｯﾄﾞ基板取付工事 | AO38: 1 | AP38: 式 | AQ38: 5000 | AR38: 2500 | AS38: 0 | AW38: ②消耗品雑材 | AX38: 1 | AY38: 式 | AZ38: 15000 | BA38: 7500 | BB38: 0 | BO38: CG-854T2
A39: CG-554T2 | B39: bo21 | C39: =C38+1 -> 32 | E39: =CONCATENATE("①",管材表!BG7," ",管材表!BH7) -> ①ｹﾞｰﾄ弁 40A | F39: 2 | G39: =管材表!BI7 -> 個 | H39: =管材表!BJ7 -> 26700 | I39: =管材表!BK7 -> 17360 | J39: =管材表!BL7 -> 0.16 | K39: Cb | N39: ②掃除具ｾｯﾄ BHS650 | O39: 1 | P39: =機器表!EL58 -> ｾｯﾄ | Q39: =機器表!EM58 -> 12400 | R39: =機器表!EN58 -> 5220 | S39: =機器表!EO58 -> 0 | T39: Ca | W39: ②消耗品雑材 | X39: 1 | Y39: 式 | Z39: 20000 | AA39: 10000 | AE39: ④配管工事費 | AF39: 1 | AG39: 式 | AH39: =ROUND(項目表!$E$3*標準項!AK39,-3) -> 225000 | AI39: =ROUND(項目表!$F$3*標準項!AK39,-3) -> 139000 | AK39: 4.73 | AN39: ②消耗品雑材 | AO39: 1 | AP39: 式 | AQ39: 30000 | AR39: 15000 | AS39: 0 | BO39: ○グロウエア CG-854T2 | BP39: 1 | BQ39: =機器表!V18 -> 台 | BR39: =機器表!W23 -> 537000 | BS39: =機器表!X23 -> 240490 | BT39: =機器表!Y23 -> 0.9 | BU39: Ca
A40: CG-854T2 | B40: bo39 | C40: =C39+1 -> 33 | E40: =CONCATENATE("①",管材表!BG5," ",管材表!BH5) -> ①ｹﾞｰﾄ弁 25A | F40: 1 | G40: =管材表!BI5 -> 個 | H40: =管材表!BJ5 -> 11900 | I40: =管材表!BK5 -> 7740 | J40: =管材表!BL5 -> 0.12 | K40: Cb | N40: ②消耗品雑材 | O40: 1 | P40: 式 | Q40: 20000 | R40: 10000 | AE40: ②配管支持具 | AF40: 1 | AG40: 式 | AH40: 30000 | AI40: 20000 | BO40: ④同上搬入据付工事 | BP40: 1 | BQ40: 式 | BR40: =ROUND(項目表!$E$3*標準項!BU40,-3) -> 43000 | BS40: =ROUND(項目表!$F$3*標準項!BU40,-3) -> 26000 | BU40: 0.9
A41: ---ｸﾞﾘｰﾝｿｰﾗ --- | E41: =CONCATENATE("①",管材表!BG3," ",管材表!BH3) -> ①ｹﾞｰﾄ弁 15A | F41: 1 | G41: =管材表!BI3 -> 個 | H41: =管材表!BJ3 -> 6510 | I41: =管材表!BK3 -> 4230 | J41: =管材表!BL3 -> 0.08 | K41: Cb | AE41: ④タンク塗装工事 | AF41: 1 | AG41: 式 | AH41: =ROUND(項目表!$E$3*AK41,-3) -> 67000 | AI41: =ROUND(項目表!$F$3*標準項!AK41,-3) -> 41000 | AK41: 1.4 | AW41: KA-405TE | BO41: =CONCATENATE("③",電材表!Q10," ",電材表!R10) -> ③CO2ｺﾝﾄﾛｰﾗ CGC-600SET14 | BP41: 1 | BQ41: =電材表!S10 -> 台 | BR41: =電材表!T10 -> 155000 | BS41: =電材表!U10 -> 89490 | BT41: =電材表!V10 -> 0 | BU41: Cc
A42: RHE-134E | B42: bf97 | C42: 34 | E42: =CONCATENATE("①",管材表!BO7," ",管材表!BP7) -> ①ﾁｬｯｷ弁 40A(ｽｲﾝｸﾞ) | F42: 1 | G42: =管材表!BQ7 -> 個 | H42: =管材表!BR7 -> 21200 | I42: =管材表!BS7 -> 13780 | J42: =管材表!BT7 -> 0.16 | K42: Cb | AE42: ②消耗品雑材 | AF42: 1 | AG42: 式 | AH42: 30000 | AI42: 20000 | AW42: ○小型温風機 KA- 405TE | AX42: 1 | AY42: =機器表!V13 -> 台 | AZ42: =機器表!W13 -> 692000 | BA42: =機器表!X13 -> 259200 | BB42: =機器表!Y13 -> 1 | BC42: Ca | BF42: エロフィン配管（65A) | BO42: =CONCATENATE("③",電材表!I9," ",電材表!J9) -> ③室温ｾﾝｻｰｾｯﾄ TS-102P | BP42: 1 | BQ42: =電材表!K9 -> 個 | BR42: =電材表!L9 -> 18100 | BS42: =電材表!M9 -> 2530 | BT42: =電材表!N9 -> 0 | BU42: Cc
A43: ---循環扇 --- | E43: =CONCATENATE("①",管材表!DC3," ",管材表!DD3) -> ①Yｽﾄﾚｰﾅ 15A | F43: 1 | G43: =管材表!DE3 -> 個 | H43: =管材表!DF3 -> 6080 | I43: =管材表!DG3 -> 3950 | J43: =管材表!DH3 -> 0.08 | K43: Cb | AN43: EHP61×2基 | AW43: ④同上搬入据付工事 | AX43: 1 | AY43: 式 | AZ43: =ROUND(項目表!$E$3*標準項!BC43,-3) -> 48000 | BA43: =ROUND(項目表!$F$3*標準項!BC43,-3) -> 29000 | BC43: 1 | BF43: ○ｴﾛﾌｨﾝﾁｭｰﾌﾞ 65A 32F 2750L | BG43: 60 | BH43: 本 | BI43: =機器表!BS70 -> 93000 | BJ43: =機器表!BT70 -> 37000 | BK43: 0.61 | BL43: Ca | BO43: =CONCATENATE("③",電材表!Q19," ",電材表!R19) -> ③不完全燃焼警報器 SG-35 | BP43: 1 | BQ43: =電材表!S19 -> 個 | BR43: =電材表!T19 -> 85800 | BS43: =電材表!U19 -> 31120 | BT43: =電材表!V19 -> 0 | BU43: Cc
A44: FAN-400T | B44: aw116 | C44: 35 | E44: ①フレキシブルホース3/8B1500L | F44: 1 | G44: 本 | H44: =管材表!FB9 -> 15500 | I44: =管材表!FC9 -> 2920 | J44: 0.1 | K44: Cb | AE44: BOT-20000 | AN44: ○誰でもﾋｰﾎﾟﾝ EHP61 | AO44: 2 | AP44: =機器表!DF12 -> ｾｯﾄ | AQ44: =機器表!DG12 -> 597000 | AR44: =機器表!DH12 -> - | AS44: =機器表!DI12 -> 1.6 | AT44: Ca | AW44: =CONCATENATE("③",電材表!Q18," ",電材表!R18) -> ③感震器 BES-100 | AX44: 1 | AY44: =電材表!S18 -> 個 | AZ44: =電材表!T18 -> 20100 | BA44: =電材表!U18 -> 5580 | BB44: =電材表!V18 -> 0 | BC44: Cc | BF44: ○ｴﾛﾌｨﾝﾁｭｰﾌﾞ 65A 32F 2000L | BG44: 8 | BH44: 本 | BI44: =機器表!BS71 -> 85000 | BJ44: =機器表!BT71 -> 34000 | BK44: 0.44 | BL44: Ca | BO44: =CONCATENATE("③",電材表!Q18," ",電材表!R18) -> ③感震器 BES-100 | BP44: 1 | BQ44: =電材表!S18 -> 個 | BR44: =電材表!T18 -> 20100 | BS44: =電材表!U18 -> 5580 | BT44: =電材表!V18 -> 0 | BU44: Cc
A45: ---ｵｲﾙ関係 --- | E45: ①配管継手類 | F45: 1 | G45: 式 | H45: 5000 | I45: 3000 | J45: 0 | AE45: ○ｵｲﾙﾀﾝｸ BOT-20000 | AF45: 1 | AG45: =機器表!ED11 -> 基 | AH45: =機器表!EE11 -> 2600000 | AI45: =機器表!EF11 -> 1613000 | AJ45: =機器表!EG11 -> 5.1 | AK45: Ca | AN45: （室内機・室外機・操作盤セット） | AS45: 0 | AW45: ○煙突ｾｯﾄ BEP-HB 1201 | AX45: 1 | AY45: =機器表!EL6 -> ｾｯﾄ | AZ45: =機器表!EM6 -> 65700 | BA45: =機器表!EN6 -> 23160 | BB45: =機器表!EO6 -> 0.5 | BC45: Ca | BF45: ④ｴﾛﾌｨﾝ取付工事 | BG45: 1 | BH45: 式 | BI45: =ROUND(項目表!$E$3*BL45,-3) -> 341000 | BJ45: =ROUND(項目表!$F$3*BL45,-3) -> 211000 | BL45: 7.17 | BO45: ④同上取付工事 | BP45: 1 | BQ45: 式 | BR45: 11000 | BS45: 7000
A46: BOT- 200 ｵｲﾙﾀﾝｸ | B46: ae137 | C46: 36 | E46: ④配管工事費 | F46: 1 | G46: 式 | H46: =ROUND(項目表!$E$3*標準項!K46,-3) -> 117000 | I46: =ROUND(項目表!$F$3*標準項!K46,-3) -> 73000 | K46: 2.47 | AE46: ④同上搬入据付工事 | AF46: 1 | AG46: 式 | AH46: =ROUND(項目表!$E$3*標準項!AK46,-3) -> 242000 | AI46: =ROUND(項目表!$F$3*標準項!AK46,-3) -> 150000 | AK46: 5.1 | AN46: ④EHP用ﾊｲﾌﾞﾘｯﾄﾞ制御基板ｾｯﾄ EHP-HCS | AO46: 1 | AP46: =機器表!DF15 -> 面 | AQ46: =機器表!DG19 -> 71900 | AR46: =機器表!DH19 -> 4500 | AS46: =機器表!DI15 -> 1.6 | AT46: Ca | AW46: ○煙突直管 φ120 | AX46: 1 | AY46: =機器表!EL24 -> 本 | AZ46: =機器表!EM24 -> 8470 | BA46: =機器表!EN24 -> 2090 | BB46: =機器表!EO24 -> 0.1 | BC46: Ca | BF46: ○ｴﾛﾌｨﾝ支持金具 2段1列 | BG46: 40 | BH46: 本 | BI46: =機器表!GA4 -> 22000 | BJ46: =機器表!GB4 -> 11000 | BK46: 0.15 | BL46: Ca | BO46: ○ｵｲﾙﾀﾝｸ BOT-200 | BP46: 1 | BQ46: =機器表!ED4 -> 基 | BR46: =機器表!EE4 -> 84000 | BS46: =機器表!EF4 -> 26080 | BT46: =機器表!EG4 -> 0.2 | BU46: Ca
A47: BOT- 490 ｵｲﾙﾀﾝｸ | B47: ae3 | C47: =C46+1 -> 37 | E47: ④配管塗装工事 | F47: 1 | G47: =項目表!G3 -> 式 | H47: 5000 | I47: 3000 | K47: 0.12 | N47: HK4030TCV | W47: HK4030TEV | AE47: ④タンク塗装工事 | AF47: 1 | AG47: 式 | AH47: 60000 | AI47: 40000 | AN47: ④同上搬入据付工事 | AO47: 2 | AP47: 式 | AQ47: 100000 | AR47: 50000 | AS47: 0 | AW47: ○煙突ｴﾋﾞﾏｶﾞﾘ φ120 | AX47: 1 | AY47: =機器表!EL36 -> 個 | AZ47: =機器表!EM36 -> 6490 | BA47: =機器表!EN36 -> 1360 | BB47: =機器表!EO36 -> 0.1 | BC47: Ca | BF47: ④同上取付工事 | BG47: 1 | BH47: 式 | BI47: =ROUND(項目表!$E$3*BL47,-3) -> 188000 | BJ47: =ROUND(項目表!$F$3*BL47,-3) -> 116000 | BL47: 3.96 | BO47: ④同上組立工事 | BP47: 1 | BQ47: 式 | BR47: =ROUND(項目表!$E$3*標準項!BU47,-3) -> 10000 | BS47: =ROUND(項目表!$F$3*標準項!BU47,-3) -> 6000 | BU47: =BT46 -> 0.2
A48: BOT- 900 ｵｲﾙﾀﾝｸ | B48: ae172 | C48: =C47+1 -> 38 | E48: ②消耗品雑材 | F48: 1 | G48: 式 | H48: 15000 | I48: 7500 | J48: 0 | N48: ○ﾊｳｽｶｵﾝｷ HK4030TCV | O48: 1 | P48: =機器表!N10 -> 台 | Q48: =機器表!O10 -> 1424000 | R48: =機器表!P10 -> 593740 | S48: =機器表!Q10 -> 1.7 | T48: Ca | W48: ○ﾊｳｽｶｵﾝｷ HK4030TEV | X48: 1 | Y48: =機器表!N11 -> 台 | Z48: =機器表!O11 -> 1478000 | AA48: =機器表!P11 -> 620960 | AB48: =機器表!Q11 -> 1.7 | AC48: Ca | AE48: =CONCATENATE("①",管材表!K9," ",管材表!L9) -> ①SGP鋼管(白) 65A | AF48: 4 | AG48: =管材表!M9 -> m | AH48: =管材表!N9 -> 13540 | AI48: =管材表!O9 -> 7180 | AJ48: =管材表!P9 -> 0.37 | AK48: Cb | AN48: ④冷媒配管工事費 10mまで | AO48: 2 | AP48: 式 | AQ48: 150000 | AR48: 70000 | AS48: 0 | AW48: ②煙突支持金具 | AX48: 1 | AY48: 個 | AZ48: 15000 | BA48: 10000 | BB48: 0 | BF48: =CONCATENATE("①",管材表!DK15," ",管材表!DL15) -> ①電動ﾎﾞｰﾙ弁(3方) 50A | BG48: 1 | BH48: =管材表!DM15 -> 個 | BI48: =管材表!DN15 -> 85300 | BJ48: =管材表!DO15 -> 55450 | BK48: =管材表!DP15 -> 0.18 | BL48: Cb | BO48: ④同上搬入据付工事 | BP48: 1 | BQ48: 式 | BR48: =ROUND(項目表!$E$3*標準項!BU48,-3) -> 10000 | BS48: =ROUND(項目表!$F$3*標準項!BU48,-3) -> 6000 | BU48: =BT46 -> 0.2
A49: BOT- 1900 ｵｲﾙﾀﾝｸ | B49: ae13 | C49: =C48+1 -> 39 | N49: ④同上搬入据付工事 | O49: 1 | P49: 式 | Q49: =ROUND(項目表!$E$3*標準項!T49,-3) -> 78000 | R49: =ROUND(項目表!$F$3*標準項!T49,-3) -> 49000 | T49: 1.65 | W49: ④同上搬入据付工事 | X49: 1 | Y49: 式 | Z49: =ROUND(項目表!$E$3*標準項!AC49,-3) -> 78000 | AA49: =ROUND(項目表!$F$3*標準項!AC49,-3) -> 49000 | AC49: 1.65 | AE49: =CONCATENATE("①",管材表!AA7," ",管材表!AB7) -> ①外面被覆鋼管 40A | AF49: 20 | AG49: =管材表!AC7 -> m | AH49: =管材表!AD7 -> 5180 | AI49: =管材表!AE7 -> 3890 | AJ49: =管材表!AF7 -> 0.23 | AK49: Cb | AN49: ④同上配管断熱・防食ﾃｰﾌﾟ工事 | AO49: 2 | AP49: 式 | AQ49: 9600 | AR49: 6000 | AS49: 0 | AW49: ④同上煙突取付工事 | AX49: 1 | AY49: 式 | AZ49: =ROUND(項目表!$E$3*BC49,-3) -> 36000 | BA49: =ROUND(項目表!$F$3*標準項!BC49,-3) -> 22000 | BC49: 0.75 | BF49: =CONCATENATE("①",管材表!K9," ",管材表!L9) -> ①SGP鋼管(白) 65A | BG49: 40 | BH49: =管材表!M9 -> m | BI49: =管材表!N9 -> 13540 | BJ49: =管材表!O9 -> 7180 | BK49: =管材表!P9 -> 0.37 | BL49: Cb | BO49: ①油配管ｾｯﾄ BOP-805M | BP49: 1 | BQ49: =管材表!FA6 -> 個 | BR49: =管材表!FB6 -> 11800 | BS49: =管材表!FC6 -> 4430 | BT49: =管材表!FD6 -> 0.3 | BU49: Cb
A50: BOT-10000 ｵｲﾙﾀﾝｸ | B50: ae28 | C50: =C49+1 -> 40 | N50: =CONCATENATE("③",電材表!Q18," ",電材表!R18) -> ③感震器 BES-100 | O50: 1 | P50: =電材表!S18 -> 個 | Q50: =電材表!T18 -> 20100 | R50: =電材表!U18 -> 5580 | S50: =電材表!V18 -> 0 | T50: Cc | W50: =CONCATENATE("③",電材表!Q18," ",電材表!R18) -> ③感震器 BES-100 | X50: 1 | Y50: =電材表!S18 -> 個 | Z50: =電材表!T18 -> 20100 | AA50: =電材表!U18 -> 5580 | AB50: =電材表!V18 -> 0 | AC50: Cc | AE50: =CONCATENATE("①",管材表!CM11," ",管材表!CN11) -> ①ﾏﾚｰﾌﾞﾙ弁 65A(ﾌﾗﾝｼﾞ) | AF50: 1 | AG50: =管材表!CO11 -> 個 | AH50: =管材表!CP11 -> 112000 | AI50: =管材表!CQ11 -> 72800 | AJ50: =管材表!CR11 -> 0.32 | AK50: Cb | AN50: ④ドレーン配管工事 3mまで | AO50: 2 | AP50: 式 | AQ50: 6000 | AR50: 3000 | AS50: 0 | AW50: ④煙道断熱工事 | AX50: 1 | AY50: 式 | AZ50: 15000 | BA50: 10000 | BB50: 0 | BF50: =CONCATENATE("①",管材表!K8," ",管材表!L8) -> ①SGP鋼管(白) 50A | BG50: 10 | BH50: =管材表!M8 -> m | BI50: =管材表!N8 -> 9480 | BJ50: =管材表!O8 -> 5020 | BK50: =管材表!P8 -> 0.29 | BL50: Cb | BO50: ①逃し管ｾｯﾄ BOP-EP8M | BP50: 1 | BQ50: =管材表!FA8 -> 個 | BR50: =管材表!FB8 -> 18000 | BS50: =管材表!FC8 -> 4600 | BT50: =管材表!FD8 -> 0.2 | BU50: Cb
A51: BOT-20000 ｵｲﾙﾀﾝｸ | B51: ae45 | C51: =C50+1 -> 41 | N51: ○煙室ｾｯﾄ ES- 4030 | O51: 1 | P51: =機器表!EL16 -> ｾｯﾄ | Q51: =機器表!EM16 -> 126000 | R51: =機器表!EN16 -> 40000 | S51: =機器表!EO16 -> 0.5 | T51: Ca | W51: ○煙室ｾｯﾄ ES- 4030 | X51: 1 | Y51: =機器表!EL16 -> ｾｯﾄ | Z51: =機器表!EM16 -> 126000 | AA51: =機器表!EN16 -> 40000 | AB51: =機器表!EO16 -> 0.5 | AC51: Ca | AE51: =CONCATENATE("①",管材表!CM8," ",管材表!CN8) -> ①ﾏﾚｰﾌﾞﾙ弁 50A | AF51: 2 | AG51: =管材表!CO8 -> 個 | AH51: =管材表!CP8 -> 41100 | AI51: =管材表!CQ8 -> 26720 | AJ51: =管材表!CR8 -> 0.18 | AN51: ④省ｴﾈﾊｲﾌﾞﾘｯﾄﾞ基板取付工事 | AO51: 1 | AP51: 式 | AQ51: 5000 | AR51: 2500 | AS51: 0 | AW51: ②消耗品雑材 | AX51: 1 | AY51: 式 | AZ51: 15000 | BA51: 7500 | BB51: 0 | BF51: =CONCATENATE("①",管材表!BG8," ",管材表!BH8) -> ①ｹﾞｰﾄ弁 50A | BG51: 2 | BH51: =管材表!BI8 -> 個 | BI51: =管材表!BJ8 -> 39100 | BJ51: =管材表!BK8 -> 25420 | BK51: =管材表!BL8 -> 0.18 | BL51: Cb | BO51: =CONCATENATE("①",管材表!CM3," ",管材表!CN3) -> ①ﾏﾚｰﾌﾞﾙ弁 15A | BP51: 1 | BQ51: =管材表!CO3 -> 個 | BR51: =管材表!CP3 -> 12200 | BS51: =管材表!CQ3 -> 7930 | BT51: =管材表!CR3 -> 0.08 | BU51: Cb
A52: 少量危険物 | B52: ae91 | C52: =C51+1 -> 42 | E52: HB-807TGA | N52: ④同上取付工事 | O52: 1 | P52: 式 | Q52: =ROUND(項目表!$E$3*標準項!T52,-3) -> 24000 | R52: =ROUND(項目表!$F$3*標準項!T52,-3) -> 15000 | T52: =S51 -> 0.5 | W52: ④同上取付工事 | X52: 1 | Y52: 式 | Z52: =ROUND(項目表!$E$3*標準項!AC52,-3) -> 24000 | AA52: =ROUND(項目表!$F$3*標準項!AC52,-3) -> 15000 | AC52: =AB51 -> 0.5 | AE52: ①ﾌﾚｷｼﾞｮｲﾝﾄ(F) 65A*500L | AF52: 1 | AG52: 本 | AH52: =管材表!DV22 -> 26000 | AI52: =管材表!DW22 -> 6760 | AJ52: 0.37 | AK52: Cb | AN52: ②消耗品雑材 | AO52: 1 | AP52: 式 | AQ52: 30000 | AR52: 15000 | AS52: 0 | BF52: =CONCATENATE("①",管材表!BG3," ",管材表!BH3) -> ①ｹﾞｰﾄ弁 15A | BG52: 4 | BH52: =管材表!BI3 -> 個 | BI52: =管材表!BJ3 -> 6510 | BJ52: =管材表!BK3 -> 4230 | BK52: =管材表!BL3 -> 0.08 | BL52: Cb | BO52: ④配管工事費 | BP52: 1 | BQ52: 式 | BR52: =ROUND(項目表!$E$3*標準項!BU52,-3) -> 28000 | BS52: =ROUND(項目表!$F$3*標準項!BU52,-3) -> 17000 | BU52: 0.58
A53: 一般危険物 | B53: ae102 | C53: =C52+1 -> 43 | E53: =CONCATENATE("○",機器表!AB8," ",機器表!AC8) -> ○ﾊｳｽﾎﾞｲﾗ HB-807TGA5 | F53: 1 | G53: =機器表!AD8 -> 台 | H53: =機器表!AE8 -> 1511000 | I53: =機器表!AF8 -> 619670 | J53: =機器表!AG8 -> 1.6 | K53: Ca | N53: ○煙突ｾｯﾄ BEP-20T 2252 | O53: 1 | P53: =機器表!EL10 -> ｾｯﾄ | Q53: =機器表!EM10 -> 108400 | R53: =機器表!EN10 -> 37760 | S53: =機器表!EO10 -> 0.7 | T53: Ca | W53: ○煙突ｾｯﾄ BEP-20T 2252 | X53: 1 | Y53: =機器表!EL10 -> ｾｯﾄ | Z53: =機器表!EM10 -> 108400 | AA53: =機器表!EN10 -> 37760 | AB53: =機器表!EO10 -> 0.7 | AC53: Ca | AE53: ①ﾌﾚｷｼﾞｮｲﾝﾄ(F) 50A*500L | AF53: 1 | AG53: 本 | AH53: =管材表!DV21 -> 22700 | AI53: =管材表!DW21 -> 5900 | AJ53: 0.22 | AK53: Cb | BF53: ①空気抜弁(逆止弁付） 15A(AF-9H) | BG53: 4 | BH53: 個 | BI53: =管材表!ET12 -> 36100 | BJ53: =管材表!EU12 -> 28880 | BK53: 0.08 | BL53: Cb | BO53: ②消耗品雑材 | BP53: 1 | BQ53: 式 | BR53: 20000 | BS53: 10000
A54: 油配管_単独25A | B54: ae118 | C54: =C53+1 -> 44 | E54: ④同上搬入据付工事 | F54: 1 | G54: 式 | H54: =ROUND(項目表!$E$3*標準項!K54,-3) -> 75000 | I54: =ROUND(項目表!$F$3*標準項!K54,-3) -> 46000 | K54: 1.57 | N54: ○煙突直管 φ225 | O54: 2 | P54: =機器表!EL27 -> 本 | Q54: =機器表!EM27 -> 12600 | R54: =機器表!EN27 -> 3340 | S54: =機器表!EO27 -> 0.1 | T54: Ca | W54: ○煙突直管 φ225 | X54: 2 | Y54: =機器表!EL27 -> 本 | Z54: =機器表!EM27 -> 12600 | AA54: =機器表!EN27 -> 3340 | AB54: =機器表!EO27 -> 0.1 | AC54: Ca | AE54: ①注油口 65A | AF54: 1 | AG54: 個 | AH54: 15000 | AI54: 10000 | AK54: Cb | AW54: KA-125 | BF54: ①配管継手類 | BG54: 1 | BH54: 式 | BI54: 131400 | BJ54: 87600 | BK54: 0
A55: 油配管_集中25A | B55: ae128 | C55: =C54+1 -> 45 | E55: =CONCATENATE("③",電材表!Q18," ",電材表!R18) -> ③感震器 BES-100 | F55: 1 | G55: =電材表!S18 -> 個 | H55: =電材表!T18 -> 20100 | I55: =電材表!U18 -> 5580 | J55: =電材表!V18 -> 0 | K55: Cc | N55: ○煙道ｴﾙﾎﾞ φ225 | O55: 1 | P55: =機器表!EL39 -> 個 | Q55: =機器表!EM39 -> 16000 | R55: =機器表!EN39 -> 2820 | S55: =機器表!EO39 -> 0.1 | T55: Ca | W55: ○煙道ｴﾙﾎﾞ φ225 | X55: 1 | Y55: =機器表!EL39 -> 個 | Z55: =機器表!EM39 -> 16000 | AA55: =機器表!EN39 -> 2820 | AB55: =機器表!EO39 -> 0.1 | AC55: Ca | AE55: ①配管継手類 | AF55: 1 | AG55: 式 | AH55: 30000 | AI55: 20000 | AN55: ｱｸﾞﾘﾈｯﾄ 警報のみ | AW55: ○小型温風機 KA- 125 | AX55: 1 | AY55: =機器表!V3 -> 台 | AZ55: =機器表!W3 -> 331000 | BA55: =機器表!X3 -> 139730 | BB55: =機器表!Y3 -> 0.52 | BC55: Ca | BF55: ④配管工事費 | BG55: 1 | BH55: 式 | BI55: 296000 | BJ55: 197000 | BL55: 7.89
A56: BOT-490(防油堤付) | B56: ae189 | C56: =C55+1 -> 46 | E56: =CONCATENATE("○",機器表!EJ5," ",機器表!EK5) -> ○煙突ｾｯﾄ BEP-3P2252網付 | F56: 1 | G56: =機器表!EL5 -> ｾｯﾄ | H56: =機器表!EM5 -> 72800 | I56: =機器表!EN5 -> 23470 | J56: =機器表!EO5 -> 0.7 | K56: Ca | N56: ②煙突支持金具 | O56: 1 | P56: 個 | Q56: 25000 | R56: 14000 | W56: ②煙突支持金具 | X56: 1 | Y56: 個 | Z56: 25000 | AA56: 14000 | AE56: ④配管工事費 | AF56: 1 | AG56: 式 | AH56: =ROUND(項目表!$E$3*標準項!AK56,-3) -> 227000 | AI56: =ROUND(項目表!$F$3*標準項!AK56,-3) -> 141000 | AK56: 4.78 | AN56: ○ANｱﾄﾞﾊﾞﾝｽ AN-BOX ABX-1000A | AO56: 1 | AP56: =電材表!K39 -> 台 | AQ56: =電材表!L39 -> 406000 | AR56: =電材表!M39 -> 188780 | AS56: =電材表!N39 -> 0 | AT56: Cc | AW56: ④同上搬入据付工事 | AX56: 1 | AY56: 式 | AZ56: =ROUND(項目表!$E$3*標準項!BC56,-3) -> 25000 | BA56: =ROUND(項目表!$F$3*標準項!BC56,-3) -> 15000 | BC56: 0.52 | BF56: ④埋設部防蝕工事 | BG56: 1 | BH56: 式 | BI56: 8000 | BJ56: 5000 | BL56: 0.2
A57: KS1-399SZ(防油堤付) | B57: ae205 | C57: =C56+1 -> 47 | E57: =CONCATENATE("○",機器表!EJ27," ",機器表!EK27) -> ○煙突直管 φ225 | F57: 1 | G57: =機器表!EL27 -> 本 | H57: =機器表!EM27 -> 12600 | I57: =機器表!EN27 -> 3340 | J57: =機器表!EO27 -> 0.1 | K57: Ca | N57: ④煙道・煙突取付工事 | O57: 1 | P57: 式 | Q57: =ROUND(項目表!$E$3*標準項!T57,-3) -> 43000 | R57: =ROUND(項目表!$F$3*標準項!T57,-3) -> 26000 | T57: 0.9 | W57: ④煙道・煙突取付工事 | X57: 1 | Y57: 式 | Z57: =ROUND(項目表!$E$3*標準項!AC57,-3) -> 43000 | AA57: =ROUND(項目表!$F$3*標準項!AC57,-3) -> 26000 | AC57: 0.9 | AE57: ②配管支持具 | AF57: 1 | AG57: 式 | AH57: 50000 | AI57: 30000 | AN57: 〇AN-BOX用警報入力ﾕﾆｯﾄ AAL-1000 | AO57: 1 | AP57: 台 | AQ57: =電材表!L41 -> 57500 | AR57: =電材表!M41 -> 12330 | AS57: 0 | AT57: Cc | AW57: =CONCATENATE("③",電材表!Q18," ",電材表!R18) -> ③感震器 BES-100 | AX57: 1 | AY57: =電材表!S18 -> 個 | AZ57: =電材表!T18 -> 20100 | BA57: =電材表!U18 -> 5580 | BB57: =電材表!V18 -> 0 | BC57: Cc | BF57: ④塗装工事 | BG57: 1 | BH57: 式 | BI57: 30000 | BJ57: 15000 | BL57: 0.6
A58: KS2-490SJ(防油堤付) | B58: ae221 | C58: =C57+1 -> 48 | E58: =CONCATENATE("○",機器表!EJ39," ",機器表!EK39) -> ○煙道ｴﾙﾎﾞ φ225 | F58: 3 | G58: =機器表!EL39 -> 個 | H58: =機器表!EM39 -> 16000 | I58: =機器表!EN39 -> 2820 | J58: =機器表!EO39 -> 0.1 | K58: Ca | N58: ④煙道断熱工事 | O58: 1 | P58: ｾｯﾄ | Q58: 35000 | R58: 18000 | S58: 0.1 | T58: Ca | W58: ④煙道断熱工事 | X58: 1 | Y58: ｾｯﾄ | Z58: 35000 | AA58: 18000 | AB58: 0.1 | AC58: Ca | AE58: ○ﾛｰﾘｰｱｰｽ RE-SS | AF58: 1 | AG58: 式 | AH58: 21000 | AI58: 15000 | AN58: ④同上取付工事（ﾍﾞﾆﾔ込） | AO58: 1 | AP58: 式 | AQ58: 30000 | AR58: 15000 | AW58: ○煙突ｾｯﾄ BEP-KA 1203 | AX58: 1 | AY58: =機器表!EL7 -> ｾｯﾄ | AZ58: =機器表!EM7 -> 60400 | BA58: =機器表!EN7 -> 20760 | BB58: =機器表!EO7 -> 0.5 | BC58: Ca | BF58: ②消耗品雑材 | BG58: 1 | BH58: 式 | BI58: 50000 | BJ58: 30000 | BK58: 0
